{
  "type": "Feature",
  "properties": {
    "gn:admin1_code":"00",
    "gn:asciiname":"Turkestan",
    "gn:country_code":"UZ",
    "gn:dem":366,
    "gn:feature_class":"P",
    "gn:feature_code":"PPL",
    "gn:name":"Turkestan",
    "gn:population":0,
    "gn:timezone":"Asia/Samarkand",
    "iso:country":"UZ",
    "wof:name":"Turkestan",
    "wof:placetype":"locality"
},
  "geometry": {"coordinates":[65.59999999999999,40.13333],"type":"Point"}
}