{
  "type": "Feature",
  "properties": {
    "gn:admin1_code":"07",
    "gn:asciiname":"Bobodug`i",
    "gn:country_code":"UZ",
    "gn:dem":294,
    "gn:feature_class":"P",
    "gn:feature_code":"PPL",
    "gn:name":"Bobodug\u2018i",
    "gn:population":0,
    "gn:timezone":"Asia/Samarkand",
    "iso:country":"UZ",
    "name:und_x_variant":[
        "Bava-dogi",
        "Bobo-Dogy"
    ],
    "name:uzb_x_preferred":[
        "Bobodug\u2018i"
    ],
    "wof:name":"Bobodug`i",
    "wof:placetype":"locality"
},
  "geometry": {"coordinates":[64.99906999999999,40.16558],"type":"Point"}
}