{
  "type": "Feature",
  "properties": {
    "gn:admin1_code":"03",
    "gn:asciiname":"Katta-Oqtepa",
    "gn:country_code":"UZ",
    "gn:dem":382,
    "gn:feature_class":"P",
    "gn:feature_code":"PPL",
    "gn:name":"Katta-Oqtepa",
    "gn:population":0,
    "gn:timezone":"Asia/Tashkent",
    "iso:country":"UZ",
    "name:eng_x_preferred":[
        "Katta-Oqtepa"
    ],
    "name:und_x_variant":[
        "Kattaaktepa"
    ],
    "wof:name":"Katta-Oqtepa",
    "wof:placetype":"locality"
},
  "geometry": {"coordinates":[70.96382,40.63807],"type":"Point"}
}