{
  "type": "Feature",
  "properties": {
    "gn:admin1_code":"01",
    "gn:asciiname":"Qorabuloq",
    "gn:country_code":"UZ",
    "gn:dem":624,
    "gn:feature_class":"P",
    "gn:feature_code":"PPL",
    "gn:name":"Qorabuloq",
    "gn:population":0,
    "gn:timezone":"Asia/Tashkent",
    "iso:country":"UZ",
    "name:uzb_x_preferred":[
        "Qorabuloq"
    ],
    "wof:name":"Qorabuloq",
    "wof:placetype":"locality"
},
  "geometry": {"coordinates":[72.47750000000001,40.66501],"type":"Point"}
}