{
  "type": "Feature",
  "properties": {
    "gn:admin1_code":"07",
    "gn:admin3_code":"1538232.0",
    "gn:asciiname":"Karmana Shahri",
    "gn:country_code":"UZ",
    "gn:dem":350,
    "gn:feature_class":"P",
    "gn:feature_code":"PPLA2",
    "gn:name":"Karmana Shahri",
    "gn:population":0,
    "gn:timezone":"Asia/Samarkand",
    "iso:country":"UZ",
    "name:und_x_variant":[
        "Gorod Karmana",
        "Karmana Shahri"
    ],
    "wof:name":"Karmana Shahri",
    "wof:placetype":"locality"
},
  "geometry": {"coordinates":[65.37545,40.13782],"type":"Point"}
}