{
  "type": "Feature",
  "properties": {
    "gn:admin1_code":"06",
    "gn:asciiname":"Xodikent",
    "gn:country_code":"UZ",
    "gn:dem":1065,
    "gn:feature_class":"P",
    "gn:feature_code":"PPL",
    "gn:name":"Xodikent",
    "gn:population":0,
    "gn:timezone":"Asia/Tashkent",
    "iso:country":"UZ",
    "name:eng_x_preferred":[
        "Xadikent"
    ],
    "name:uzb_x_preferred":[
        "Xodikent"
    ],
    "wof:name":"Xodikent",
    "wof:placetype":"locality"
},
  "geometry": {"coordinates":[71.69412,41.36099],"type":"Point"}
}