{
  "type": "Feature",
  "properties": {
    "gn:admin1_code":"00",
    "gn:asciiname":"Sergali",
    "gn:cc2":"UZ",
    "gn:country_code":"UZ",
    "gn:dem":371,
    "gn:feature_class":"P",
    "gn:feature_code":"PPL",
    "gn:name":"Sergali",
    "gn:population":0,
    "gn:timezone":"Asia/Samarkand",
    "iso:country":"UZ",
    "name:und_x_variant":[
        "Sergaliakar",
        "Sergali"
    ],
    "wof:name":"Sergali",
    "wof:placetype":"locality"
},
  "geometry": {"coordinates":[68.40000000000001,40.16667],"type":"Point"}
}