{
  "type": "Feature",
  "properties": {
    "gn:admin1_code":"00",
    "gn:asciiname":"Yulguk-Say",
    "gn:country_code":"UZ",
    "gn:dem":437,
    "gn:feature_class":"P",
    "gn:feature_code":"PPL",
    "gn:name":"Yulguk-Say",
    "gn:population":0,
    "gn:timezone":"Asia/Samarkand",
    "iso:country":"UZ",
    "wof:name":"Yulguk-Say",
    "wof:placetype":"locality"
},
  "geometry": {"coordinates":[65.46666999999999,39.86667],"type":"Point"}
}