{
  "type": "Feature",
  "properties": {
    "gn:admin1_code":"06",
    "gn:asciiname":"Ko`lbuqon",
    "gn:country_code":"UZ",
    "gn:dem":814,
    "gn:feature_class":"P",
    "gn:feature_code":"PPL",
    "gn:name":"Ko\u2018lbuqon",
    "gn:population":0,
    "gn:timezone":"Asia/Tashkent",
    "iso:country":"UZ",
    "name:uzb_x_preferred":[
        "Kulbukan"
    ],
    "name:uzb_x_variant":[
        "Ko\u2018lbuqon"
    ],
    "wof:name":"Ko`lbuqon",
    "wof:placetype":"locality"
},
  "geometry": {"coordinates":[71.81013,41.25828],"type":"Point"}
}