{
  "type": "Feature",
  "properties": {
    "gn:admin1_code":"06",
    "gn:asciiname":"Nayman",
    "gn:country_code":"UZ",
    "gn:dem":372,
    "gn:feature_class":"P",
    "gn:feature_code":"PPL",
    "gn:name":"Nayman",
    "gn:population":0,
    "gn:timezone":"Asia/Tashkent",
    "iso:country":"UZ",
    "name:und_x_variant":[
        "Naiman",
        "Nayman"
    ],
    "wof:name":"Nayman",
    "wof:placetype":"locality"
},
  "geometry": {"coordinates":[71.03031999999997,40.75843],"type":"Point"}
}