{
  "type": "Feature",
  "properties": {
    "gn:admin1_code":"06",
    "gn:asciiname":"Nayman",
    "gn:country_code":"UZ",
    "gn:dem":372,
    "gn:feature_class":"P",
    "gn:feature_code":"PPL",
    "gn:name":"Nayman",
    "gn:population":0,
    "gn:timezone":"Asia/Tashkent",
    "iso:country":"UZ",
    "name:ceb_x_preferred":[
        "Nayman"
    ],
    "name:kir_x_preferred":[
        "\u041d\u0430\u0439\u043c\u0430\u043d"
    ],
    "name:rus_x_preferred":[
        "\u041d\u0430\u0439\u043c\u0430\u043d"
    ],
    "name:swe_x_preferred":[
        "Nayman"
    ],
    "name:ukr_x_preferred":[
        "\u041d\u0430\u0439\u043c\u0430\u043d"
    ],
    "name:und_x_variant":[
        "Naiman"
    ],
    "name:uzb_x_preferred":[
        "Nayman"
    ],
    "wof:name":"Nayman",
    "wof:placetype":"locality"
},
  "geometry": {"coordinates":[71.03031999999997,40.75843],"type":"Point"}
}