{
  "type": "Feature",
  "properties": {
    "gn:admin1_code":"01",
    "gn:asciiname":"Vahim",
    "gn:country_code":"UZ",
    "gn:dem":447,
    "gn:feature_class":"P",
    "gn:feature_code":"PPL",
    "gn:name":"Vahim",
    "gn:population":0,
    "gn:timezone":"Asia/Tashkent",
    "iso:country":"UZ",
    "name:rus_x_preferred":[
        "\u0412\u0430\u0445\u044b\u043c"
    ],
    "name:und_x_variant":[
        "Vakhym"
    ],
    "name:uzb_x_preferred":[
        "Vaxim"
    ],
    "name:uzb_x_variant":[
        "Vahim"
    ],
    "wof:name":"Vahim",
    "wof:placetype":"locality"
},
  "geometry": {"coordinates":[72.04955,40.74108],"type":"Point"}
}