{
  "type": "Feature",
  "properties": {
    "gn:admin1_code":"03",
    "gn:asciiname":"Qizil-Askar",
    "gn:country_code":"UZ",
    "gn:dem":886,
    "gn:feature_class":"P",
    "gn:feature_code":"PPL",
    "gn:name":"Qizil-Askar",
    "gn:population":0,
    "gn:timezone":"Asia/Tashkent",
    "iso:country":"UZ",
    "name:und_x_variant":[
        "Kizil-Askar"
    ],
    "name:uzb_x_preferred":[
        "Qizil-Askar"
    ],
    "wof:name":"Qizil-Askar",
    "wof:placetype":"locality"
},
  "geometry": {"coordinates":[71.78789,40.19123],"type":"Point"}
}