{
  "type": "Feature",
  "properties": {
    "gn:admin1_code":"10",
    "gn:asciiname":"Qushrabot",
    "gn:cc2":"UZ",
    "gn:country_code":"UZ",
    "gn:dem":738,
    "gn:feature_class":"P",
    "gn:feature_code":"PPL",
    "gn:name":"Q\u016dshrabot",
    "gn:population":0,
    "gn:timezone":"Asia/Samarkand",
    "iso:country":"UZ",
    "name:und_x_variant":[
        "Koshrabad",
        "Q\u016dshrabot"
    ],
    "wof:name":"Qushrabot",
    "wof:placetype":"locality"
},
  "geometry": {"coordinates":[66.65472,40.23611],"type":"Point"}
}