{
  "type": "Feature",
  "properties": {
    "gn:admin1_code":"00",
    "gn:asciiname":"Chagatay",
    "gn:cc2":"UZ",
    "gn:country_code":"UZ",
    "gn:dem":785,
    "gn:feature_class":"P",
    "gn:feature_code":"PPL",
    "gn:name":"Chagatay",
    "gn:population":0,
    "gn:timezone":"Asia/Samarkand",
    "iso:country":"UZ",
    "name:und_x_variant":[
        "Kul\u2019-Ata",
        "Chagatay"
    ],
    "wof:name":"Chagatay",
    "wof:placetype":"locality"
},
  "geometry": {"coordinates":[66.41667,40.18333],"type":"Point"}
}