{
  "type": "Feature",
  "properties": {
    "gn:admin1_code":"01",
    "gn:asciiname":"Beshkapa",
    "gn:country_code":"UZ",
    "gn:dem":557,
    "gn:feature_class":"P",
    "gn:feature_code":"PPL",
    "gn:name":"Beshkapa",
    "gn:population":0,
    "gn:timezone":"Asia/Tashkent",
    "iso:country":"UZ",
    "name:rus_x_preferred":[
        "\u0411\u0435\u0448\u043a\u0430\u043f\u0430"
    ],
    "wof:name":"Beshkapa",
    "wof:placetype":"locality"
},
  "geometry": {"coordinates":[72.33371,40.58763],"type":"Point"}
}