{
  "type": "Feature",
  "properties": {
    "gn:admin1_code":"00",
    "gn:asciiname":"Yam",
    "gn:cc2":"UZ",
    "gn:country_code":"UZ",
    "gn:dem":381,
    "gn:feature_class":"P",
    "gn:feature_code":"PPL",
    "gn:name":"Yam",
    "gn:population":0,
    "gn:timezone":"Asia/Samarkand",
    "iso:country":"UZ",
    "name:und_x_variant":[
        "Udarnik",
        "Yam"
    ],
    "wof:name":"Yam",
    "wof:placetype":"locality"
},
  "geometry": {"coordinates":[68.18333,40.11667],"type":"Point"}
}