{
  "type": "Feature",
  "properties": {
    "gn:admin1_code":"00",
    "gn:asciiname":"Yam",
    "gn:cc2":"UZ",
    "gn:country_code":"UZ",
    "gn:dem":381,
    "gn:feature_class":"P",
    "gn:feature_code":"PPL",
    "gn:name":"Yam",
    "gn:population":0,
    "gn:timezone":"Asia/Samarkand",
    "iso:country":"UZ",
    "name:cat_x_preferred":[
        "Yam"
    ],
    "name:ceb_x_preferred":[
        "Yam"
    ],
    "name:fas_x_preferred":[
        "\u06cc\u0645"
    ],
    "name:jpn_x_preferred":[
        "\u30e4\u30e0"
    ],
    "name:spa_x_preferred":[
        "Yam"
    ],
    "name:swe_x_preferred":[
        "Yam"
    ],
    "name:tgl_x_preferred":[
        "Yam"
    ],
    "name:tur_x_preferred":[
        "Yam"
    ],
    "name:und_x_variant":[
        "Udarnik"
    ],
    "wof:name":"Yam",
    "wof:placetype":"locality"
},
  "geometry": {"coordinates":[68.18333,40.11667],"type":"Point"}
}