{
  "type": "Feature",
  "properties": {
    "gn:admin1_code":"03",
    "gn:asciiname":"Amirobod",
    "gn:country_code":"UZ",
    "gn:dem":414,
    "gn:feature_class":"P",
    "gn:feature_code":"PPL",
    "gn:name":"Amirobod",
    "gn:population":0,
    "gn:timezone":"Asia/Tashkent",
    "iso:country":"UZ",
    "name:und_x_variant":[
        "Amirabad"
    ],
    "name:uzb_x_preferred":[
        "Amirobod"
    ],
    "wof:name":"Amirobod",
    "wof:placetype":"locality"
},
  "geometry": {"coordinates":[71.20612,40.4846],"type":"Point"}
}