{
  "type": "Feature",
  "properties": {
    "gn:admin1_code":"01",
    "gn:asciiname":"Yakkatut",
    "gn:country_code":"UZ",
    "gn:dem":437,
    "gn:feature_class":"P",
    "gn:feature_code":"PPL",
    "gn:name":"Yakkatut",
    "gn:population":0,
    "gn:timezone":"Asia/Tashkent",
    "iso:country":"UZ",
    "wof:name":"Yakkatut",
    "wof:placetype":"locality"
},
  "geometry": {"coordinates":[72.16722,40.86046],"type":"Point"}
}