{
  "type": "Feature",
  "properties": {
    "gn:admin1_code":"00",
    "gn:asciiname":"Pinen",
    "gn:country_code":"UZ",
    "gn:dem":1690,
    "gn:feature_class":"P",
    "gn:feature_code":"PPL",
    "gn:name":"Pin\u00ebn",
    "gn:population":0,
    "gn:timezone":"Asia/Dushanbe",
    "iso:country":"UZ",
    "wof:name":"Pinen",
    "wof:placetype":"locality"
},
  "geometry": {"coordinates":[68.51666999999999,39.21667],"type":"Point"}
}