{
  "type": "Feature",
  "properties": {
    "gn:admin1_code":"01",
    "gn:asciiname":"Qoraqo`rg`on",
    "gn:country_code":"UZ",
    "gn:dem":595,
    "gn:feature_class":"P",
    "gn:feature_code":"PPL",
    "gn:name":"Qoraqo\u2018rg\u2018on",
    "gn:population":0,
    "gn:timezone":"Asia/Tashkent",
    "iso:country":"UZ",
    "name:rus_x_preferred":[
        "\u041a\u0443\u0440\u0430\u043a\u0443\u0440\u0433\u0430\u043d"
    ],
    "name:und_x_variant":[
        "Kurakurgan"
    ],
    "name:uzb_x_preferred":[
        "Qoraqo\u2018rg\u2018on"
    ],
    "wof:name":"Qoraqo`rg`on",
    "wof:placetype":"locality"
},
  "geometry": {"coordinates":[72.36150000000001,40.55908],"type":"Point"}
}