{
  "type": "Feature",
  "properties": {
    "gn:admin1_code":"06",
    "gn:asciiname":"Dumar",
    "gn:country_code":"UZ",
    "gn:dem":435,
    "gn:feature_class":"P",
    "gn:feature_code":"PPL",
    "gn:name":"Dumar",
    "gn:population":0,
    "gn:timezone":"Asia/Tashkent",
    "iso:country":"UZ",
    "name:uzb_x_preferred":[
        "Dumar"
    ],
    "wof:name":"Dumar",
    "wof:placetype":"locality"
},
  "geometry": {"coordinates":[72.04404,40.94024],"type":"Point"}
}