{
  "type": "Feature",
  "properties": {
    "gn:admin1_code":"06",
    "gn:asciiname":"Bo`stonobod",
    "gn:country_code":"UZ",
    "gn:dem":779,
    "gn:feature_class":"P",
    "gn:feature_code":"PPL",
    "gn:name":"Bo\u2018stonobod",
    "gn:population":0,
    "gn:timezone":"Asia/Tashkent",
    "iso:country":"UZ",
    "name:eng_x_preferred":[
        "Bo\u2018stonobod"
    ],
    "wof:name":"Bo`stonobod",
    "wof:placetype":"locality"
},
  "geometry": {"coordinates":[71.51634,41.11418],"type":"Point"}
}