{
  "type": "Feature",
  "properties": {
    "gn:admin1_code":"08",
    "gn:asciiname":"Mayda",
    "gn:country_code":"UZ",
    "gn:dem":486,
    "gn:feature_class":"P",
    "gn:feature_code":"PPL",
    "gn:name":"Mayda",
    "gn:population":0,
    "gn:timezone":"Asia/Samarkand",
    "iso:country":"UZ",
    "name:und_x_variant":[
        "Maydan"
    ],
    "wof:name":"Mayda",
    "wof:placetype":"locality"
},
  "geometry": {"coordinates":[66.34636,39.00764],"type":"Point"}
}