{
  "type": "Feature",
  "properties": {
    "gn:admin1_code":"16",
    "gn:asciiname":"O`zbekiston",
    "gn:country_code":"UZ",
    "gn:dem":292,
    "gn:feature_class":"P",
    "gn:feature_code":"PPL",
    "gn:name":"O\u2018zbekiston",
    "gn:population":0,
    "gn:timezone":"Asia/Tashkent",
    "iso:country":"UZ",
    "name:uzb_x_preferred":[
        "O\u2018zbekiston"
    ],
    "wof:name":"O`zbekiston",
    "wof:placetype":"locality"
},
  "geometry": {"coordinates":[69.00246,40.41418],"type":"Point"}
}