{
  "type": "Feature",
  "properties": {
    "gn:admin1_code":"07",
    "gn:asciiname":"Shirinobod",
    "gn:country_code":"UZ",
    "gn:dem":429,
    "gn:feature_class":"P",
    "gn:feature_code":"PPL",
    "gn:name":"Shirinobod",
    "gn:population":0,
    "gn:timezone":"Asia/Samarkand",
    "iso:country":"UZ",
    "wof:name":"Shirinobod",
    "wof:placetype":"locality"
},
  "geometry": {"coordinates":[66.00286,40.03736],"type":"Point"}
}