{
  "type": "Feature",
  "properties": {
    "gn:admin1_code":"08",
    "gn:asciiname":"Baqirchi",
    "gn:country_code":"UZ",
    "gn:dem":1565,
    "gn:feature_class":"P",
    "gn:feature_code":"PPL",
    "gn:name":"Baqirchi",
    "gn:population":0,
    "gn:timezone":"Asia/Samarkand",
    "iso:country":"UZ",
    "wof:name":"Baqirchi",
    "wof:placetype":"locality"
},
  "geometry": {"coordinates":[66.99536999999999,38.60009],"type":"Point"}
}