{
  "type": "Feature",
  "properties": {
    "gn:admin1_code":"01",
    "gn:asciiname":"Uyshunchek",
    "gn:country_code":"UZ",
    "gn:dem":462,
    "gn:feature_class":"P",
    "gn:feature_code":"PPL",
    "gn:name":"Uyshunchek",
    "gn:population":0,
    "gn:timezone":"Asia/Tashkent",
    "iso:country":"UZ",
    "name:rus_x_preferred":[
        "\u0423\u0439\u0448\u0443\u043d\u0447\u0435\u043a"
    ],
    "name:uzb_x_preferred":[
        "Uyshunchek"
    ],
    "wof:name":"Uyshunchek",
    "wof:placetype":"locality"
},
  "geometry": {"coordinates":[72.26439000000001,40.79568],"type":"Point"}
}