{
  "type": "Feature",
  "properties": {
    "gn:admin1_code":"00",
    "gn:asciiname":"Maybulak",
    "gn:cc2":"UZ",
    "gn:country_code":"UZ",
    "gn:dem":601,
    "gn:feature_class":"P",
    "gn:feature_code":"PPL",
    "gn:name":"Maybulak",
    "gn:population":0,
    "gn:timezone":"Asia/Samarkand",
    "iso:country":"UZ",
    "name:und_x_variant":[
        "Maybul",
        "Maybulak"
    ],
    "wof:name":"Maybulak",
    "wof:placetype":"locality"
},
  "geometry": {"coordinates":[66.33333,40.11667],"type":"Point"}
}