{
  "type": "Feature",
  "properties": {
    "iso:country":"UZ",
    "name:ast_x_preferred":[
        "Muborak"
    ],
    "name:azb_x_preferred":[
        "\u0645\u0648\u0628\u0627\u0631\u06a9"
    ],
    "name:aze_x_preferred":[
        "M\u00fcbar\u0259k"
    ],
    "name:bul_x_preferred":[
        "\u041c\u0443\u0431\u043e\u0440\u0430\u043a"
    ],
    "name:ceb_x_preferred":[
        "Muborak"
    ],
    "name:eng_x_preferred":[
        "Muborak"
    ],
    "name:fas_x_preferred":[
        "\u0645\u0628\u0627\u0631\u06a9"
    ],
    "name:hsb_x_preferred":[
        "Muborak"
    ],
    "name:jpn_x_preferred":[
        "\u30e0\u30d0\u30ec\u30af"
    ],
    "name:kik_x_preferred":[
        "Muborak"
    ],
    "name:kor_x_preferred":[
        "\ubb34\ubc14\ub808\ud06c"
    ],
    "name:lit_x_preferred":[
        "Mubarekas"
    ],
    "name:nld_x_preferred":[
        "Muborak"
    ],
    "name:pol_x_preferred":[
        "Muborak"
    ],
    "name:rus_x_preferred":[
        "\u041c\u0443\u0431\u0430\u0440\u0435\u043a"
    ],
    "name:rus_x_variant":[
        "\u041c\u0443\u0431\u043e\u0440\u0430\u043a"
    ],
    "name:spa_x_preferred":[
        "Muborak"
    ],
    "name:tat_x_preferred":[
        "\u041c\u04e9\u0431\u0430\u0440\u04d9\u043a"
    ],
    "name:tur_x_preferred":[
        "Mubarek"
    ],
    "name:ukr_x_preferred":[
        "\u041c\u0443\u0431\u0430\u0440\u0435\u043a"
    ],
    "name:urd_x_preferred":[
        "\u0645\u0628\u0627\u0631\u06a9\u060c \u0627\u0632\u0628\u06a9\u0633\u062a\u0627\u0646"
    ],
    "name:urd_x_variant":[
        "\u0645\u0628\u0627\u0631\u06a9"
    ],
    "name:uzb_x_preferred":[
        "Muborak"
    ],
    "name:vie_x_preferred":[
        "Muborak"
    ],
    "qs:gn_country":"UZ",
    "qs:gn_fcode":"PPL",
    "qs:gn_pop":29180,
    "qs:name":"Muborak",
    "qs:name_adm0":"Uzbekistan",
    "qs:name_adm1":"Qashqadaryo",
    "qs:photos":0,
    "qs:photos_1k":0,
    "qs:photos_9k":0,
    "qs:photos_9r":0,
    "qs:photos_all":0,
    "qs:photos_sr":0,
    "qs:placetype":"Town",
    "qs:pop_sr":"7",
    "qs:woe_adm0":23424980,
    "wd:wordcount":423,
    "wof:name":"Muborak",
    "wof:placetype":"locality",
    "wof:population":29180
},
  "geometry": {"coordinates":[65.15278000000001,39.25528],"type":"Point"}
}