{
  "type": "Feature",
  "properties": {
    "gn:admin1_code":"12",
    "gn:asciiname":"Khomrau",
    "gn:country_code":"UZ",
    "gn:dem":1309,
    "gn:feature_class":"P",
    "gn:feature_code":"PPL",
    "gn:name":"Khomrau",
    "gn:population":0,
    "gn:timezone":"Asia/Samarkand",
    "iso:country":"UZ",
    "wof:name":"Khomrau",
    "wof:placetype":"locality"
},
  "geometry": {"coordinates":[67.89514,38.56587],"type":"Point"}
}