{
  "type": "Feature",
  "properties": {
    "gn:admin1_code":"16",
    "gn:asciiname":"Beshbuloq",
    "gn:country_code":"UZ",
    "gn:dem":274,
    "gn:feature_class":"P",
    "gn:feature_code":"PPL",
    "gn:name":"Beshbuloq",
    "gn:population":0,
    "gn:timezone":"Asia/Tashkent",
    "iso:country":"UZ",
    "name:und_x_variant":[
        "Nadezhdinskiy",
        "Nadezhdinskoye",
        "Krupskoy",
        "Krupskoi",
        "Imeni Krupskoy"
    ],
    "name:uzb_x_preferred":[
        "Beshbuloq"
    ],
    "wof:name":"Beshbuloq",
    "wof:placetype":"locality"
},
  "geometry": {"coordinates":[69.00749999999999,40.58806],"type":"Point"}
}