{
  "type": "Feature",
  "properties": {
    "gn:admin1_code":"00",
    "gn:asciiname":"Kuducha",
    "gn:country_code":"UZ",
    "gn:dem":600,
    "gn:feature_class":"P",
    "gn:feature_code":"PPL",
    "gn:name":"Kuducha",
    "gn:population":0,
    "gn:timezone":"Asia/Samarkand",
    "iso:country":"UZ",
    "wof:name":"Kuducha",
    "wof:placetype":"locality"
},
  "geometry": {"coordinates":[68.26666999999999,39.95],"type":"Point"}
}