{
  "type": "Feature",
  "properties": {
    "gn:admin1_code":"03",
    "gn:asciiname":"Qumqishloq",
    "gn:country_code":"UZ",
    "gn:dem":411,
    "gn:feature_class":"P",
    "gn:feature_code":"PPL",
    "gn:name":"Qumqishloq",
    "gn:population":0,
    "gn:timezone":"Asia/Tashkent",
    "iso:country":"UZ",
    "name:und_x_variant":[
        "Kumkishlak"
    ],
    "name:uzb_x_preferred":[
        "Qumqishloq"
    ],
    "wof:name":"Qumqishloq",
    "wof:placetype":"locality"
},
  "geometry": {"coordinates":[71.6908,40.69386],"type":"Point"}
}