{
  "type": "Feature",
  "properties": {
    "gn:admin1_code":"00",
    "gn:asciiname":"Ishakchi",
    "gn:country_code":"UZ",
    "gn:dem":187,
    "gn:feature_class":"P",
    "gn:feature_code":"PPL",
    "gn:name":"Ishakchi",
    "gn:population":0,
    "gn:timezone":"Asia/Samarkand",
    "iso:country":"UZ",
    "wof:name":"Ishakchi",
    "wof:placetype":"locality"
},
  "geometry": {"coordinates":[63.91667,39.33333],"type":"Point"}
}