{
  "type": "Feature",
  "properties": {
    "gn:admin1_code":"08",
    "gn:asciiname":"Qizilchorva",
    "gn:country_code":"UZ",
    "gn:dem":611,
    "gn:feature_class":"P",
    "gn:feature_code":"PPL",
    "gn:name":"Qizilchorva",
    "gn:population":0,
    "gn:timezone":"Asia/Samarkand",
    "iso:country":"UZ",
    "name:und_x_variant":[
        "Kyzyl-Chaura"
    ],
    "wof:name":"Qizilchorva",
    "wof:placetype":"locality"
},
  "geometry": {"coordinates":[66.54543000000001,39.20819],"type":"Point"}
}