{
  "type": "Feature",
  "properties": {
    "gn:admin1_code":"06",
    "gn:asciiname":"Xo`jaqo`rg`oncha",
    "gn:country_code":"UZ",
    "gn:dem":426,
    "gn:feature_class":"P",
    "gn:feature_code":"PPL",
    "gn:name":"Xo\u2018jaqo\u2018rg\u2018oncha",
    "gn:population":0,
    "gn:timezone":"Asia/Tashkent",
    "iso:country":"UZ",
    "name:eng_x_preferred":[
        "Xo\u2018jaqo\u2018rg\u2018oncha"
    ],
    "wof:name":"Xo`jaqo`rg`oncha",
    "wof:placetype":"locality"
},
  "geometry": {"coordinates":[71.92438,40.93915],"type":"Point"}
}