{
  "type": "Feature",
  "properties": {
    "gn:admin1_code":"00",
    "gn:asciiname":"Bagizagan",
    "gn:cc2":"UZ",
    "gn:country_code":"UZ",
    "gn:dem":762,
    "gn:feature_class":"P",
    "gn:feature_code":"PPL",
    "gn:name":"Bagizagan",
    "gn:population":0,
    "gn:timezone":"Asia/Samarkand",
    "iso:country":"UZ",
    "name:und_x_variant":[
        "Bogi-zagan",
        "Bagizagan"
    ],
    "wof:name":"Bagizagan",
    "wof:placetype":"locality"
},
  "geometry": {"coordinates":[67.16667,39.58333],"type":"Point"}
}