{
  "type": "Feature",
  "properties": {
    "gn:admin1_code":"00",
    "gn:asciiname":"Chardara",
    "gn:country_code":"UZ",
    "gn:dem":223,
    "gn:feature_class":"P",
    "gn:feature_code":"PPL",
    "gn:name":"Chardara",
    "gn:population":0,
    "gn:timezone":"Asia/Samarkand",
    "iso:country":"UZ",
    "wof:name":"Chardara",
    "wof:placetype":"locality"
},
  "geometry": {"coordinates":[64.46666999999999,40.45],"type":"Point"}
}