{
  "type": "Feature",
  "properties": {
    "gn:admin1_code":"06",
    "gn:asciiname":"Chek-Yaydak",
    "gn:country_code":"UZ",
    "gn:dem":452,
    "gn:feature_class":"P",
    "gn:feature_code":"PPL",
    "gn:name":"Chek-Yaydak",
    "gn:population":0,
    "gn:timezone":"Asia/Tashkent",
    "iso:country":"UZ",
    "wof:name":"Chek-Yaydak",
    "wof:placetype":"locality"
},
  "geometry": {"coordinates":[72.09943,40.96858],"type":"Point"}
}