{
  "type": "Feature",
  "properties": {
    "gn:admin1_code":"03",
    "gn:asciiname":"Jilva",
    "gn:country_code":"UZ",
    "gn:dem":385,
    "gn:feature_class":"P",
    "gn:feature_code":"PPL",
    "gn:name":"Jilva",
    "gn:population":0,
    "gn:timezone":"Asia/Tashkent",
    "iso:country":"UZ",
    "name:uzb_x_preferred":[
        "Jilva"
    ],
    "wof:name":"Jilva",
    "wof:placetype":"locality"
},
  "geometry": {"coordinates":[71.02885000000001,40.66317],"type":"Point"}
}