{
  "type": "Feature",
  "properties": {
    "gn:admin1_code":"01",
    "gn:asciiname":"Bo`ston",
    "gn:country_code":"UZ",
    "gn:dem":594,
    "gn:feature_class":"P",
    "gn:feature_code":"PPL",
    "gn:name":"Bo\u2018ston",
    "gn:population":0,
    "gn:timezone":"Asia/Tashkent",
    "iso:country":"UZ",
    "name:rus_x_preferred":[
        "\u0411\u0443\u0441\u0442\u0430\u043d"
    ],
    "name:und_x_variant":[
        "Bustan"
    ],
    "name:uzb_x_preferred":[
        "Bo\u2018ston"
    ],
    "wof:name":"Bo`ston",
    "wof:placetype":"locality"
},
  "geometry": {"coordinates":[72.42695999999999,40.6193],"type":"Point"}
}