{
  "type": "Feature",
  "properties": {
    "gn:admin1_code":"03",
    "gn:asciiname":"Khodzha",
    "gn:country_code":"UZ",
    "gn:dem":422,
    "gn:feature_class":"P",
    "gn:feature_code":"PPL",
    "gn:name":"Khodzha",
    "gn:population":0,
    "gn:timezone":"Asia/Tashkent",
    "iso:country":"UZ",
    "wof:name":"Khodzha",
    "wof:placetype":"locality"
},
  "geometry": {"coordinates":[71.18333,40.46667],"type":"Point"}
}