{
  "type": "Feature",
  "properties": {
    "gn:admin1_code":"03",
    "gn:asciiname":"Yoyilma",
    "gn:country_code":"UZ",
    "gn:dem":605,
    "gn:feature_class":"P",
    "gn:feature_code":"PPL",
    "gn:name":"Yoyilma",
    "gn:population":0,
    "gn:timezone":"Asia/Tashkent",
    "iso:country":"UZ",
    "name:rus_x_preferred":[
        "Yayil\u2019ma"
    ],
    "name:uzb_x_preferred":[
        "Yoyilma"
    ],
    "wof:name":"Yoyilma",
    "wof:placetype":"locality"
},
  "geometry": {"coordinates":[71.07719,40.35737],"type":"Point"}
}