{
  "type": "Feature",
  "properties": {
    "gn:admin1_code":"01",
    "gn:asciiname":"Jiyanbek",
    "gn:country_code":"UZ",
    "gn:dem":446,
    "gn:feature_class":"P",
    "gn:feature_code":"PPL",
    "gn:name":"Jiyanbek",
    "gn:population":0,
    "gn:timezone":"Asia/Tashkent",
    "iso:country":"UZ",
    "name:rus_x_preferred":[
        "\u0414\u0436\u0438\u044f\u043d\u0431\u0435\u043a"
    ],
    "name:und_x_variant":[
        "Dzhiyanbek"
    ],
    "name:uzb_x_preferred":[
        "Jiyanbek"
    ],
    "wof:name":"Jiyanbek",
    "wof:placetype":"locality"
},
  "geometry": {"coordinates":[72.0902,40.76606],"type":"Point"}
}