{
  "type": "Feature",
  "properties": {
    "gn:admin1_code":"03",
    "gn:asciiname":"Kattaqishloq",
    "gn:country_code":"UZ",
    "gn:dem":472,
    "gn:feature_class":"P",
    "gn:feature_code":"PPL",
    "gn:name":"Kattaqishloq",
    "gn:population":0,
    "gn:timezone":"Asia/Tashkent",
    "iso:country":"UZ",
    "name:und_x_variant":[
        "Kattakishlak"
    ],
    "name:uzb_x_preferred":[
        "Kattaqishloq"
    ],
    "wof:name":"Kattaqishloq",
    "wof:placetype":"locality"
},
  "geometry": {"coordinates":[71.99172,40.53006],"type":"Point"}
}