{
  "type": "Feature",
  "properties": {
    "gn:admin1_code":"00",
    "gn:asciiname":"Verkhniy Mussabazar",
    "gn:cc2":"UZ",
    "gn:country_code":"UZ",
    "gn:dem":1762,
    "gn:feature_class":"P",
    "gn:feature_code":"PPL",
    "gn:name":"Verkhniy Mussabazar",
    "gn:population":0,
    "gn:timezone":"Asia/Dushanbe",
    "iso:country":"UZ",
    "name:und_x_variant":[
        "Mussa-Bazar",
        "Mussa-Bashi",
        "Verkhniy Mussabazar"
    ],
    "wof:name":"Verkhniy Mussabazar",
    "wof:placetype":"locality"
},
  "geometry": {"coordinates":[67.45,39.25],"type":"Point"}
}