{
  "type": "Feature",
  "properties": {
    "gn:admin1_code":"03",
    "gn:asciiname":"Sarimozor",
    "gn:country_code":"UZ",
    "gn:dem":497,
    "gn:feature_class":"P",
    "gn:feature_code":"PPL",
    "gn:name":"Sarimozor",
    "gn:population":0,
    "gn:timezone":"Asia/Tashkent",
    "iso:country":"UZ",
    "name:uzb_x_preferred":[
        "Sarimozor"
    ],
    "wof:name":"Sarimozor",
    "wof:placetype":"locality"
},
  "geometry": {"coordinates":[71.69358000000003,40.43948],"type":"Point"}
}