{
  "type": "Feature",
  "properties": {
    "gn:admin1_code":"16",
    "gn:asciiname":"Nurota",
    "gn:country_code":"UZ",
    "gn:dem":269,
    "gn:feature_class":"P",
    "gn:feature_code":"PPL",
    "gn:name":"Nurota",
    "gn:population":0,
    "gn:timezone":"Asia/Tashkent",
    "iso:country":"UZ",
    "name:ceb_x_preferred":[
        "Nurota"
    ],
    "name:deu_x_preferred":[
        "Nurota"
    ],
    "name:fas_x_preferred":[
        "\u0646\u0648\u0631\u0627\u062a\u0627"
    ],
    "name:fra_x_preferred":[
        "Nourata"
    ],
    "name:hsb_x_preferred":[
        "Nurota"
    ],
    "name:ita_x_preferred":[
        "Nurota"
    ],
    "name:jpn_x_preferred":[
        "\u30cc\u30e9\u30bf"
    ],
    "name:kik_x_preferred":[
        "Nurata"
    ],
    "name:lit_x_preferred":[
        "Nurata"
    ],
    "name:mlg_x_preferred":[
        "Nurata"
    ],
    "name:pol_x_preferred":[
        "Nurota"
    ],
    "name:rus_x_preferred":[
        "\u041d\u0443\u0440\u0430\u0442\u0430"
    ],
    "name:spa_x_preferred":[
        "Nurota"
    ],
    "name:tat_x_preferred":[
        "\u041d\u0443\u0440\u0430\u0442\u0430"
    ],
    "name:tur_x_preferred":[
        "N\u00fcrata"
    ],
    "name:ukr_x_preferred":[
        "\u041d\u0443\u0440\u0430\u0442\u0430"
    ],
    "name:und_x_variant":[
        "Nurati"
    ],
    "name:urd_x_preferred":[
        "\u0646\u0648\u0631\u0648\u062a\u0627"
    ],
    "name:uzb_x_preferred":[
        "Nurota"
    ],
    "name:zho_x_preferred":[
        "\u52aa\u7f85\u5854"
    ],
    "wof:name":"Nurota",
    "wof:placetype":"locality"
},
  "geometry": {"coordinates":[68.77468,40.72974],"type":"Point"}
}