{
  "type": "Feature",
  "properties": {
    "gn:admin1_code":"00",
    "gn:asciiname":"Kursapay",
    "gn:cc2":"UZ",
    "gn:country_code":"UZ",
    "gn:dem":902,
    "gn:feature_class":"P",
    "gn:feature_code":"PPL",
    "gn:name":"Kursapay",
    "gn:population":0,
    "gn:timezone":"Asia/Samarkand",
    "iso:country":"UZ",
    "name:und_x_variant":[
        "Kul\u2019-Safar",
        "Kur-Sapar",
        "Kursapay"
    ],
    "wof:name":"Kursapay",
    "wof:placetype":"locality"
},
  "geometry": {"coordinates":[66.95,40.15],"type":"Point"}
}