{
  "type": "Feature",
  "properties": {
    "gn:admin1_code":"00",
    "gn:asciiname":"Kiyat-Khodzha",
    "gn:country_code":"UZ",
    "gn:dem":222,
    "gn:feature_class":"P",
    "gn:feature_code":"PPL",
    "gn:name":"Kiyat-Khodzha",
    "gn:population":0,
    "gn:timezone":"Asia/Samarkand",
    "iso:country":"UZ",
    "wof:name":"Kiyat-Khodzha",
    "wof:placetype":"locality"
},
  "geometry": {"coordinates":[64.25,40.05],"type":"Point"}
}