{
  "type": "Feature",
  "properties": {
    "gn:admin1_code":"09",
    "gn:asciiname":"Guliston",
    "gn:country_code":"UZ",
    "gn:dem":69,
    "gn:feature_class":"P",
    "gn:feature_code":"PPL",
    "gn:name":"Guliston",
    "gn:population":0,
    "gn:timezone":"Asia/Samarkand",
    "iso:country":"UZ",
    "wof:name":"Guliston",
    "wof:placetype":"locality"
},
  "geometry": {"coordinates":[59.11102,42.67248],"type":"Point"}
}