{
  "type": "Feature",
  "properties": {
    "gn:admin1_code":"07",
    "gn:asciiname":"Tog`aymurod",
    "gn:country_code":"UZ",
    "gn:dem":251,
    "gn:feature_class":"P",
    "gn:feature_code":"PPL",
    "gn:name":"Tog\u2018aymurod",
    "gn:population":0,
    "gn:timezone":"Asia/Samarkand",
    "iso:country":"UZ",
    "wof:name":"Tog`aymurod",
    "wof:placetype":"locality"
},
  "geometry": {"coordinates":[66.11537,40.87593],"type":"Point"}
}