{
  "type": "Feature",
  "properties": {
    "gn:admin1_code":"03",
    "gn:asciiname":"Xojiota",
    "gn:country_code":"UZ",
    "gn:dem":459,
    "gn:feature_class":"P",
    "gn:feature_code":"PPL",
    "gn:name":"Xojiota",
    "gn:population":0,
    "gn:timezone":"Asia/Tashkent",
    "iso:country":"UZ",
    "name:uzb_x_preferred":[
        "Xojiota"
    ],
    "wof:name":"Xojiota",
    "wof:placetype":"locality"
},
  "geometry": {"coordinates":[71.84362,40.56227],"type":"Point"}
}