{
  "type": "Feature",
  "properties": {
    "gn:admin1_code":"07",
    "gn:asciiname":"Chuqurquduq",
    "gn:country_code":"UZ",
    "gn:dem":271,
    "gn:feature_class":"P",
    "gn:feature_code":"PPL",
    "gn:name":"Chuqurquduq",
    "gn:population":0,
    "gn:timezone":"Asia/Samarkand",
    "iso:country":"UZ",
    "name:und_x_variant":[
        "Kolodets Chukurkuduk 1-y (Pervyy)",
        "Kolodets Chukurkuduk Pervyy",
        "Chuqurquduq"
    ],
    "wof:name":"Chuqurquduq",
    "wof:placetype":"locality"
},
  "geometry": {"coordinates":[66.68770000000001,40.81736],"type":"Point"}
}