{
  "type": "Feature",
  "properties": {
    "gn:admin1_code":"12",
    "gn:asciiname":"Chinar",
    "gn:cc2":"UZ",
    "gn:country_code":"UZ",
    "gn:dem":540,
    "gn:feature_class":"P",
    "gn:feature_code":"PPL",
    "gn:name":"Chinar",
    "gn:population":0,
    "gn:timezone":"Asia/Samarkand",
    "iso:country":"UZ",
    "name:und_x_variant":[
        "Kosh-Chinar",
        "Chinar"
    ],
    "wof:name":"Chinar",
    "wof:placetype":"locality"
},
  "geometry": {"coordinates":[68.05944000000001,38.33056],"type":"Point"}
}