{
  "type": "Feature",
  "properties": {
    "gn:admin1_code":"16",
    "gn:asciiname":"Musamuhammedov",
    "gn:country_code":"UZ",
    "gn:dem":272,
    "gn:feature_class":"P",
    "gn:feature_code":"PPL",
    "gn:name":"Musamuhammedov",
    "gn:population":0,
    "gn:timezone":"Asia/Tashkent",
    "iso:country":"UZ",
    "name:uzb_x_preferred":[
        "Musamuhammedov"
    ],
    "wof:name":"Musamuhammedov",
    "wof:placetype":"locality"
},
  "geometry": {"coordinates":[68.42955000000001,40.49218],"type":"Point"}
}