{
  "type": "Feature",
  "properties": {
    "gn:admin1_code":"01",
    "gn:asciiname":"Uyg`ur",
    "gn:country_code":"UZ",
    "gn:dem":531,
    "gn:feature_class":"P",
    "gn:feature_code":"PPL",
    "gn:name":"Uyg\u2018ur",
    "gn:population":0,
    "gn:timezone":"Asia/Tashkent",
    "iso:country":"UZ",
    "name:uzb_x_preferred":[
        "Uyg\u2018ur"
    ],
    "wof:name":"Uyg`ur",
    "wof:placetype":"locality"
},
  "geometry": {"coordinates":[72.54043,40.92054],"type":"Point"}
}