{
  "type": "Feature",
  "properties": {
    "gn:admin1_code":"01",
    "gn:asciiname":"To`g`risuv",
    "gn:country_code":"UZ",
    "gn:dem":596,
    "gn:feature_class":"P",
    "gn:feature_code":"PPL",
    "gn:name":"To\u2018g\u2018risuv",
    "gn:population":0,
    "gn:timezone":"Asia/Tashkent",
    "iso:country":"UZ",
    "name:rus_x_preferred":[
        "\u0422\u0443\u0433\u0440\u0438\u0441\u0443"
    ],
    "name:und_x_variant":[
        "Tugrisu"
    ],
    "name:uzb_x_preferred":[
        "To\u2018g\u2018risuv"
    ],
    "name:uzb_x_variant":[
        "Tugrisuv"
    ],
    "wof:name":"To`g`risuv",
    "wof:placetype":"locality"
},
  "geometry": {"coordinates":[72.43053,40.63621],"type":"Point"}
}