{
  "type": "Feature",
  "properties": {
    "gn:admin1_code":"06",
    "gn:asciiname":"Pagdi Qishloq",
    "gn:country_code":"UZ",
    "gn:dem":1518,
    "gn:feature_class":"P",
    "gn:feature_code":"PPL",
    "gn:name":"Pagdi Qishloq",
    "gn:population":0,
    "gn:timezone":"Asia/Tashkent",
    "iso:country":"UZ",
    "name:eng_x_preferred":[
        "Pagdi Qishloq"
    ],
    "wof:name":"Pagdi Qishloq",
    "wof:placetype":"locality"
},
  "geometry": {"coordinates":[70.81780000000001,41.01241],"type":"Point"}
}