{
  "type": "Feature",
  "properties": {
    "gn:admin1_code":"01",
    "gn:asciiname":"Moygir",
    "gn:country_code":"UZ",
    "gn:dem":452,
    "gn:feature_class":"P",
    "gn:feature_code":"PPL",
    "gn:name":"Moygir",
    "gn:population":0,
    "gn:timezone":"Asia/Tashkent",
    "iso:country":"UZ",
    "name:rus_x_preferred":[
        "\u041c\u0430\u0439\u0433\u0438\u0440"
    ],
    "name:und_x_variant":[
        "Maygyr"
    ],
    "name:uzb_x_preferred":[
        "Moygir"
    ],
    "wof:name":"Moygir",
    "wof:placetype":"locality"
},
  "geometry": {"coordinates":[72.24813,40.85489000000001],"type":"Point"}
}