{
  "type": "Feature",
  "properties": {
    "gn:admin1_code":"01",
    "gn:asciiname":"Safarobod",
    "gn:country_code":"UZ",
    "gn:dem":432,
    "gn:feature_class":"P",
    "gn:feature_code":"PPL",
    "gn:name":"Safarobod",
    "gn:population":0,
    "gn:timezone":"Asia/Tashkent",
    "iso:country":"UZ",
    "name:rus_x_preferred":[
        "\u0421\u0430\u0444\u0430\u0440\u0430\u0431\u0430\u0434"
    ],
    "name:und_x_variant":[
        "Safarabad"
    ],
    "name:uzb_x_preferred":[
        "Safarobod"
    ],
    "wof:name":"Safarobod",
    "wof:placetype":"locality"
},
  "geometry": {"coordinates":[72.00864,40.83416],"type":"Point"}
}