{
  "type": "Feature",
  "properties": {
    "gn:admin1_code":"03",
    "gn:asciiname":"Muyon",
    "gn:country_code":"UZ",
    "gn:dem":766,
    "gn:feature_class":"P",
    "gn:feature_code":"PPL",
    "gn:name":"Muyon",
    "gn:population":0,
    "gn:timezone":"Asia/Tashkent",
    "iso:country":"UZ",
    "name:und_x_variant":[
        "Muyan"
    ],
    "name:uzb_x_preferred":[
        "Mo\u2018yon"
    ],
    "name:uzb_x_variant":[
        "Muyon"
    ],
    "wof:name":"Muyon",
    "wof:placetype":"locality"
},
  "geometry": {"coordinates":[71.95471999999999,40.32139],"type":"Point"}
}