{
  "type": "Feature",
  "properties": {
    "gn:admin1_code":"07",
    "gn:asciiname":"Shardarok",
    "gn:country_code":"UZ",
    "gn:dem":844,
    "gn:feature_class":"P",
    "gn:feature_code":"PPL",
    "gn:name":"Shardarok",
    "gn:population":0,
    "gn:timezone":"Asia/Samarkand",
    "iso:country":"UZ",
    "wof:name":"Shardarok",
    "wof:placetype":"locality"
},
  "geometry": {"coordinates":[65.90324,40.33313],"type":"Point"}
}