{
  "type": "Feature",
  "properties": {
    "gn:admin1_code":"00",
    "gn:asciiname":"Uab",
    "gn:country_code":"UZ",
    "gn:dem":867,
    "gn:feature_class":"P",
    "gn:feature_code":"PPL",
    "gn:name":"Uab",
    "gn:population":0,
    "gn:timezone":"Asia/Samarkand",
    "iso:country":"UZ",
    "wof:name":"Uab",
    "wof:placetype":"locality"
},
  "geometry": {"coordinates":[67.93333,39.91667],"type":"Point"}
}