{
  "type": "Feature",
  "properties": {
    "gn:admin1_code":"06",
    "gn:asciiname":"Navkent",
    "gn:country_code":"UZ",
    "gn:dem":756,
    "gn:feature_class":"P",
    "gn:feature_code":"PPL",
    "gn:name":"Navkent",
    "gn:population":0,
    "gn:timezone":"Asia/Tashkent",
    "iso:country":"UZ",
    "name:und_x_variant":[
        "Novkent"
    ],
    "wof:name":"Navkent",
    "wof:placetype":"locality"
},
  "geometry": {"coordinates":[71.70137,41.20226],"type":"Point"}
}