{
  "type": "Feature",
  "properties": {
    "gn:admin1_code":"03",
    "gn:asciiname":"Yangiyo`l",
    "gn:country_code":"UZ",
    "gn:dem":611,
    "gn:feature_class":"P",
    "gn:feature_code":"PPL",
    "gn:name":"Yangiyo\u2018l",
    "gn:population":0,
    "gn:timezone":"Asia/Tashkent",
    "iso:country":"UZ",
    "name:rus_x_preferred":[
        "Yangiyul\u2019"
    ],
    "name:und_x_variant":[
        "Kurgantepa"
    ],
    "name:uzb_x_preferred":[
        "Yangiyo\u2018l"
    ],
    "wof:name":"Yangiyo`l",
    "wof:placetype":"locality"
},
  "geometry": {"coordinates":[71.486,40.28083],"type":"Point"}
}