{
  "type": "Feature",
  "properties": {
    "gn:admin1_code":"00",
    "gn:asciiname":"Tyl'-Gran-Kata",
    "gn:country_code":"UZ",
    "gn:dem":626,
    "gn:feature_class":"P",
    "gn:feature_code":"PPL",
    "gn:name":"Tyl\u2019-Gran-Kata",
    "gn:population":0,
    "gn:timezone":"Asia/Samarkand",
    "iso:country":"UZ",
    "name:rus_x_preferred":[
        "Tyl\u2019-Gran-Kata"
    ],
    "wof:name":"Tyl'-Gran-Kata",
    "wof:placetype":"locality"
},
  "geometry": {"coordinates":[67.90000000000001,38.43333],"type":"Point"}
}