{
  "type": "Feature",
  "properties": {
    "gn:admin1_code":"13",
    "gn:asciiname":"Kum",
    "gn:cc2":"UZ",
    "gn:country_code":"UZ",
    "gn:dem":426,
    "gn:feature_class":"P",
    "gn:feature_code":"PPL",
    "gn:name":"Kum",
    "gn:population":0,
    "gn:timezone":"Asia/Tashkent",
    "iso:country":"UZ",
    "name:ceb_x_preferred":[
        "Kum"
    ],
    "name:deu_x_preferred":[
        "Kum"
    ],
    "name:hun_x_preferred":[
        "Kum"
    ],
    "name:kat_x_preferred":[
        "\u10d9\u10e3\u10db\u10d8"
    ],
    "name:swe_x_preferred":[
        "Kum"
    ],
    "name:und_x_variant":[
        "Kun"
    ],
    "wof:name":"Kum",
    "wof:placetype":"locality"
},
  "geometry": {"coordinates":[69.34999999999999,41.21667],"type":"Point"}
}