{
  "type": "Feature",
  "properties": {
    "gn:admin1_code":"00",
    "gn:asciiname":"Farish",
    "gn:country_code":"UZ",
    "gn:dem":502,
    "gn:feature_class":"P",
    "gn:feature_code":"PPL",
    "gn:name":"Farish",
    "gn:population":0,
    "gn:timezone":"Asia/Samarkand",
    "iso:country":"UZ",
    "name:rus_x_preferred":[
        "\u0424\u0435\u0440\u0438\u0448"
    ],
    "wof:name":"Farish",
    "wof:placetype":"locality"
},
  "geometry": {"coordinates":[66.86667,40.58333],"type":"Point"}
}