{
  "type": "Feature",
  "properties": {
    "gn:admin1_code":"00",
    "gn:asciiname":"Kyzylsay",
    "gn:cc2":"UZ",
    "gn:country_code":"UZ",
    "gn:dem":619,
    "gn:feature_class":"P",
    "gn:feature_code":"PPL",
    "gn:name":"Kyzylsay",
    "gn:population":0,
    "gn:timezone":"Asia/Samarkand",
    "iso:country":"UZ",
    "name:und_x_variant":[
        "Kzyl-Say",
        "Kyzylsay"
    ],
    "wof:name":"Kyzylsay",
    "wof:placetype":"locality"
},
  "geometry": {"coordinates":[68.33333,39.95],"type":"Point"}
}