{
  "type": "Feature",
  "properties": {
    "gn:admin1_code":"12",
    "gn:asciiname":"Umyr",
    "gn:country_code":"UZ",
    "gn:dem":579,
    "gn:feature_class":"P",
    "gn:feature_code":"PPL",
    "gn:name":"Umyr",
    "gn:population":0,
    "gn:timezone":"Asia/Samarkand",
    "iso:country":"UZ",
    "wof:name":"Umyr",
    "wof:placetype":"locality"
},
  "geometry": {"coordinates":[68.03028,38.40528],"type":"Point"}
}