{
  "type": "Feature",
  "properties": {
    "gn:admin1_code":"08",
    "gn:asciiname":"Sovbog`",
    "gn:country_code":"UZ",
    "gn:dem":475,
    "gn:feature_class":"P",
    "gn:feature_code":"PPL",
    "gn:name":"Sovbog\u2018",
    "gn:population":0,
    "gn:timezone":"Asia/Samarkand",
    "iso:country":"UZ",
    "name:und_x_variant":[
        "Saubag",
        "Savbag",
        "Sovbog\u2018"
    ],
    "wof:name":"Sovbog`",
    "wof:placetype":"locality"
},
  "geometry": {"coordinates":[66.17527,38.68301],"type":"Point"}
}