{
  "type": "Feature",
  "properties": {
    "gn:admin1_code":"09",
    "gn:asciiname":"Qorasiyrak",
    "gn:country_code":"UZ",
    "gn:dem":66,
    "gn:feature_class":"P",
    "gn:feature_code":"PPL",
    "gn:name":"Qorasiyrak",
    "gn:population":0,
    "gn:timezone":"Asia/Samarkand",
    "iso:country":"UZ",
    "wof:name":"Qorasiyrak",
    "wof:placetype":"locality"
},
  "geometry": {"coordinates":[59.63448,42.80409],"type":"Point"}
}