{
  "type": "Feature",
  "properties": {
    "gn:admin1_code":"03",
    "gn:asciiname":"Navkat",
    "gn:country_code":"UZ",
    "gn:dem":808,
    "gn:feature_class":"P",
    "gn:feature_code":"PPL",
    "gn:name":"Navkat",
    "gn:population":0,
    "gn:timezone":"Asia/Tashkent",
    "iso:country":"UZ",
    "name:und_x_variant":[
        "Nowqat"
    ],
    "name:uzb_x_preferred":[
        "Novkent"
    ],
    "wof:name":"Navkat",
    "wof:placetype":"locality"
},
  "geometry": {"coordinates":[71.75456,40.23031],"type":"Point"}
}