{
  "type": "Feature",
  "properties": {
    "gn:admin1_code":"03",
    "gn:asciiname":"So`pilar",
    "gn:country_code":"UZ",
    "gn:dem":474,
    "gn:feature_class":"P",
    "gn:feature_code":"PPL",
    "gn:name":"So\u2018pilar",
    "gn:population":0,
    "gn:timezone":"Asia/Tashkent",
    "iso:country":"UZ",
    "name:und_x_variant":[
        "Supilar"
    ],
    "name:uzb_x_preferred":[
        "So\u2018pilar"
    ],
    "wof:name":"So`pilar",
    "wof:placetype":"locality"
},
  "geometry": {"coordinates":[71.76607,40.50947],"type":"Point"}
}