{
  "type": "Feature",
  "properties": {
    "gn:admin1_code":"07",
    "gn:asciiname":"Ushtepa",
    "gn:country_code":"UZ",
    "gn:dem":242,
    "gn:feature_class":"P",
    "gn:feature_code":"PPL",
    "gn:name":"Ushtepa",
    "gn:population":0,
    "gn:timezone":"Asia/Samarkand",
    "iso:country":"UZ",
    "name:und_x_variant":[
        "Uchtepa"
    ],
    "wof:name":"Ushtepa",
    "wof:placetype":"locality"
},
  "geometry": {"coordinates":[66.12276,41.53361],"type":"Point"}
}