{
  "type": "Feature",
  "properties": {
    "gn:admin1_code":"08",
    "gn:asciiname":"Lagandi",
    "gn:country_code":"UZ",
    "gn:dem":355,
    "gn:feature_class":"P",
    "gn:feature_code":"PPL",
    "gn:name":"Lagandi",
    "gn:population":0,
    "gn:timezone":"Asia/Samarkand",
    "iso:country":"UZ",
    "name:und_x_variant":[
        "Lyagandy"
    ],
    "wof:name":"Lagandi",
    "wof:placetype":"locality"
},
  "geometry": {"coordinates":[65.63079,38.87188],"type":"Point"}
}