{
  "type": "Feature",
  "properties": {
    "gn:admin1_code":"08",
    "gn:asciiname":"Esaboy",
    "gn:country_code":"UZ",
    "gn:dem":445,
    "gn:feature_class":"P",
    "gn:feature_code":"PPL",
    "gn:name":"Esaboy",
    "gn:population":0,
    "gn:timezone":"Asia/Samarkand",
    "iso:country":"UZ",
    "wof:name":"Esaboy",
    "wof:placetype":"locality"
},
  "geometry": {"coordinates":[66.24134000000001,38.89734],"type":"Point"}
}