{
  "type": "Feature",
  "properties": {
    "gn:admin1_code":"03",
    "gn:asciiname":"Qorabaki",
    "gn:country_code":"UZ",
    "gn:dem":388,
    "gn:feature_class":"P",
    "gn:feature_code":"PPL",
    "gn:name":"Qorabaki",
    "gn:population":0,
    "gn:timezone":"Asia/Tashkent",
    "iso:country":"UZ",
    "name:uzb_x_preferred":[
        "Qorabaki"
    ],
    "wof:name":"Qorabaki",
    "wof:placetype":"locality"
},
  "geometry": {"coordinates":[70.50440999999999,40.41149],"type":"Point"}
}