{
  "type": "Feature",
  "properties": {
    "gn:admin1_code":"01",
    "gn:asciiname":"Mekhnat",
    "gn:country_code":"UZ",
    "gn:dem":504,
    "gn:feature_class":"P",
    "gn:feature_code":"PPL",
    "gn:name":"Mekhnat",
    "gn:population":0,
    "gn:timezone":"Asia/Tashkent",
    "iso:country":"UZ",
    "name:rus_x_preferred":[
        "\u041c\u0435\u0445\u043d\u0430\u0442"
    ],
    "wof:name":"Mekhnat",
    "wof:placetype":"locality"
},
  "geometry": {"coordinates":[72.42424,40.84336],"type":"Point"}
}