{
  "type": "Feature",
  "properties": {
    "gn:admin1_code":"08",
    "gn:asciiname":"Dehqonobod",
    "gn:country_code":"UZ",
    "gn:dem":830,
    "gn:feature_class":"P",
    "gn:feature_code":"PPL",
    "gn:name":"Dehqonobod",
    "gn:population":0,
    "gn:timezone":"Asia/Samarkand",
    "iso:country":"UZ",
    "name:ckb_x_preferred":[
        "\u062f\u06ce\u06be\u0642\u0627\u0646\u0627\u0628\u0627\u062f"
    ],
    "name:fas_x_preferred":[
        "\u062f\u0647\u0642\u0627\u0646\u200c\u0622\u0628\u0627\u062f"
    ],
    "name:kik_x_preferred":[
        "Dehqonobod"
    ],
    "name:und_x_variant":[
        "Dekhkanabad",
        "Dehqonobod"
    ],
    "wof:name":"Dehqonobod",
    "wof:placetype":"locality"
},
  "geometry": {"coordinates":[66.49424,38.34752],"type":"Point"}
}