{
  "type": "Feature",
  "properties": {
    "gn:admin1_code":"08",
    "gn:asciiname":"Dehqonobod",
    "gn:country_code":"UZ",
    "gn:dem":830,
    "gn:feature_class":"P",
    "gn:feature_code":"PPL",
    "gn:name":"Dehqonobod",
    "gn:population":0,
    "gn:timezone":"Asia/Samarkand",
    "iso:country":"UZ",
    "name:und_x_variant":[
        "Dekhkanabad",
        "Dehqonobod"
    ],
    "wof:name":"Dehqonobod",
    "wof:placetype":"locality"
},
  "geometry": {"coordinates":[66.49424,38.34752],"type":"Point"}
}