{
  "type": "Feature",
  "properties": {
    "gn:admin1_code":"01",
    "gn:asciiname":"Arg`in",
    "gn:country_code":"UZ",
    "gn:dem":487,
    "gn:feature_class":"P",
    "gn:feature_code":"PPL",
    "gn:name":"Arg\u2018in",
    "gn:population":0,
    "gn:timezone":"Asia/Tashkent",
    "iso:country":"UZ",
    "name:rus_x_preferred":[
        "\u0410\u0440\u0433\u044b\u043d"
    ],
    "name:und_x_variant":[
        "Argyn"
    ],
    "name:uzb_x_preferred":[
        "Arg\u2018in"
    ],
    "wof:name":"Arg`in",
    "wof:placetype":"locality"
},
  "geometry": {"coordinates":[72.20466,40.66093],"type":"Point"}
}