{
  "type": "Feature",
  "properties": {
    "gn:admin1_code":"01",
    "gn:asciiname":"Obodon",
    "gn:country_code":"UZ",
    "gn:dem":712,
    "gn:feature_class":"P",
    "gn:feature_code":"PPL",
    "gn:name":"Obodon",
    "gn:population":0,
    "gn:timezone":"Asia/Tashkent",
    "iso:country":"UZ",
    "name:uzb_x_preferred":[
        "Obodon"
    ],
    "wof:name":"Obodon",
    "wof:placetype":"locality"
},
  "geometry": {"coordinates":[72.67125,40.6989],"type":"Point"}
}