{
  "type": "Feature",
  "properties": {
    "gn:admin1_code":"00",
    "gn:asciiname":"Karakuduk",
    "gn:country_code":"UZ",
    "gn:dem":741,
    "gn:feature_class":"P",
    "gn:feature_code":"PPL",
    "gn:name":"Karakuduk",
    "gn:population":0,
    "gn:timezone":"Asia/Samarkand",
    "iso:country":"UZ",
    "wof:name":"Karakuduk",
    "wof:placetype":"locality"
},
  "geometry": {"coordinates":[67.23333000000001,40.11667],"type":"Point"}
}