{
  "type": "Feature",
  "properties": {
    "gn:admin1_code":"12",
    "gn:asciiname":"Qo`rg`oncha",
    "gn:country_code":"UZ",
    "gn:dem":1456,
    "gn:feature_class":"P",
    "gn:feature_code":"PPL",
    "gn:name":"Qo\u2018rg\u2018oncha",
    "gn:population":0,
    "gn:timezone":"Asia/Samarkand",
    "iso:country":"UZ",
    "name:und_x_variant":[
        "Kurgancha"
    ],
    "name:uzb_x_preferred":[
        "Qo\u2018rg\u2018oncha"
    ],
    "wof:name":"Qo`rg`oncha",
    "wof:placetype":"locality"
},
  "geometry": {"coordinates":[67.43139000000001,38.37694000000001],"type":"Point"}
}