{
  "type": "Feature",
  "properties": {
    "gn:admin1_code":"08",
    "gn:asciiname":"Qorabayir",
    "gn:country_code":"UZ",
    "gn:dem":355,
    "gn:feature_class":"P",
    "gn:feature_code":"PPL",
    "gn:name":"Qorabayir",
    "gn:population":0,
    "gn:timezone":"Asia/Samarkand",
    "iso:country":"UZ",
    "name:und_x_variant":[
        "Karabair"
    ],
    "wof:name":"Qorabayir",
    "wof:placetype":"locality"
},
  "geometry": {"coordinates":[65.74292,39.1939],"type":"Point"}
}