{
  "type": "Feature",
  "properties": {
    "gn:admin1_code":"01",
    "gn:asciiname":"Oqtom",
    "gn:country_code":"UZ",
    "gn:dem":410,
    "gn:feature_class":"P",
    "gn:feature_code":"PPL",
    "gn:name":"Oqtom",
    "gn:population":0,
    "gn:timezone":"Asia/Tashkent",
    "iso:country":"UZ",
    "name:uzb_x_preferred":[
        "Oqtom"
    ],
    "wof:name":"Oqtom",
    "wof:placetype":"locality"
},
  "geometry": {"coordinates":[71.77186999999998,40.77985],"type":"Point"}
}