{
  "type": "Feature",
  "properties": {
    "gn:admin1_code":"06",
    "gn:asciiname":"Kandibog` Qishloq",
    "gn:country_code":"UZ",
    "gn:dem":747,
    "gn:feature_class":"P",
    "gn:feature_code":"PPL",
    "gn:name":"Kandibog\u2018 Qishloq",
    "gn:population":0,
    "gn:timezone":"Asia/Tashkent",
    "iso:country":"UZ",
    "name:eng_x_preferred":[
        "Kandibog\u2018 Qishloq"
    ],
    "wof:name":"Kandibog` Qishloq",
    "wof:placetype":"locality"
},
  "geometry": {"coordinates":[70.87774,40.90473],"type":"Point"}
}