{
  "type": "Feature",
  "properties": {
    "gn:admin1_code":"01",
    "gn:asciiname":"Qoraqalpoq",
    "gn:country_code":"UZ",
    "gn:dem":470,
    "gn:feature_class":"P",
    "gn:feature_code":"PPL",
    "gn:name":"Qoraqalpoq",
    "gn:population":0,
    "gn:timezone":"Asia/Tashkent",
    "iso:country":"UZ",
    "name:und_x_variant":[
        "Karakalpak",
        "Chumbagish",
        "Qoraqalpoq"
    ],
    "wof:name":"Qoraqalpoq",
    "wof:placetype":"locality"
},
  "geometry": {"coordinates":[72.36055,40.86087],"type":"Point"}
}