{
  "type": "Feature",
  "properties": {
    "gn:admin1_code":"09",
    "gn:asciiname":"Qo`ng`irot Shahri",
    "gn:country_code":"UZ",
    "gn:dem":62,
    "gn:feature_class":"P",
    "gn:feature_code":"PPLA2",
    "gn:name":"Qo\u2018ng\u2018irot Shahri",
    "gn:population":0,
    "gn:timezone":"Asia/Samarkand",
    "iso:country":"UZ",
    "name:und_x_variant":[
        "Gorod Kungrad",
        "Q\u016dnghirot Shahri"
    ],
    "name:uzb_x_preferred":[
        "Qo\u2018ng\u2018irot Shahri"
    ],
    "wof:name":"Qo`ng`irot Shahri",
    "wof:placetype":"locality"
},
  "geometry": {"coordinates":[58.84596,43.05207],"type":"Point"}
}