{
  "type": "Feature",
  "properties": {
    "gn:admin1_code":"16",
    "gn:asciiname":"Tamirli",
    "gn:country_code":"UZ",
    "gn:dem":302,
    "gn:feature_class":"P",
    "gn:feature_code":"PPL",
    "gn:name":"Tamirli",
    "gn:population":0,
    "gn:timezone":"Asia/Tashkent",
    "iso:country":"UZ",
    "name:uzb_x_preferred":[
        "Tamirli"
    ],
    "wof:name":"Tamirli",
    "wof:placetype":"locality"
},
  "geometry": {"coordinates":[68.88928,40.30333],"type":"Point"}
}