{
  "type": "Feature",
  "properties": {
    "gn:admin1_code":"09",
    "gn:asciiname":"Jeinsayot",
    "gn:country_code":"UZ",
    "gn:dem":61,
    "gn:feature_class":"P",
    "gn:feature_code":"PPL",
    "gn:name":"Jeinsayot",
    "gn:population":0,
    "gn:timezone":"Asia/Samarkand",
    "iso:country":"UZ",
    "wof:name":"Jeinsayot",
    "wof:placetype":"locality"
},
  "geometry": {"coordinates":[58.95222,43.12169],"type":"Point"}
}