{
  "type": "Feature",
  "properties": {
    "gn:admin1_code":"01",
    "gn:asciiname":"Burbash",
    "gn:country_code":"UZ",
    "gn:dem":597,
    "gn:feature_class":"P",
    "gn:feature_code":"PPL",
    "gn:name":"Burbash",
    "gn:population":0,
    "gn:timezone":"Asia/Tashkent",
    "iso:country":"UZ",
    "name:uzb_x_preferred":[
        "Burbash"
    ],
    "wof:name":"Burbash",
    "wof:placetype":"locality"
},
  "geometry": {"coordinates":[72.38115999999999,40.56744000000001],"type":"Point"}
}