{
  "type": "Feature",
  "properties": {
    "gn:admin1_code":"14",
    "gn:asciiname":"Do`stlik",
    "gn:country_code":"UZ",
    "gn:dem":289,
    "gn:feature_class":"P",
    "gn:feature_code":"PPL",
    "gn:name":"Do\u2018stlik",
    "gn:population":0,
    "gn:timezone":"Asia/Tashkent",
    "iso:country":"UZ",
    "name:uzb_x_preferred":[
        "Do\u2018stlik"
    ],
    "wof:name":"Do`stlik",
    "wof:placetype":"locality"
},
  "geometry": {"coordinates":[68.92304,40.77304],"type":"Point"}
}