{
  "type": "Feature",
  "properties": {
    "gn:admin1_code":"15",
    "gn:asciiname":"Qahramon",
    "gn:country_code":"UZ",
    "gn:dem":272,
    "gn:feature_class":"P",
    "gn:feature_code":"PPL",
    "gn:name":"Qahramon",
    "gn:population":0,
    "gn:timezone":"Asia/Tashkent",
    "iso:country":"UZ",
    "name:uzb_x_preferred":[
        "Qahramon"
    ],
    "wof:name":"Qahramon",
    "wof:placetype":"locality"
},
  "geometry": {"coordinates":[68.10807,40.53464],"type":"Point"}
}