{
  "type": "Feature",
  "properties": {
    "gn:admin1_code":"09",
    "gn:asciiname":"Bo`zchi",
    "gn:country_code":"UZ",
    "gn:dem":88,
    "gn:feature_class":"P",
    "gn:feature_code":"PPL",
    "gn:name":"Bo\u2018zchi",
    "gn:population":0,
    "gn:timezone":"Asia/Samarkand",
    "iso:country":"UZ",
    "name:uzb_x_preferred":[
        "Bo\u2018zchi"
    ],
    "wof:name":"Bo`zchi",
    "wof:placetype":"locality"
},
  "geometry": {"coordinates":[60.1786,42.12618],"type":"Point"}
}