{
  "type": "Feature",
  "properties": {
    "gn:admin1_code":"03",
    "gn:asciiname":"Kakir",
    "gn:country_code":"UZ",
    "gn:dem":377,
    "gn:feature_class":"P",
    "gn:feature_code":"PPL",
    "gn:name":"Kakir",
    "gn:population":0,
    "gn:timezone":"Asia/Tashkent",
    "iso:country":"UZ",
    "name:eng_x_preferred":[
        "Qaqir"
    ],
    "name:uzb_x_preferred":[
        "Kakir"
    ],
    "wof:name":"Kakir",
    "wof:placetype":"locality"
},
  "geometry": {"coordinates":[70.87820000000001,40.66841],"type":"Point"}
}