{
  "type": "Feature",
  "properties": {
    "gn:admin1_code":"16",
    "gn:asciiname":"Chorvador",
    "gn:country_code":"UZ",
    "gn:dem":266,
    "gn:feature_class":"P",
    "gn:feature_code":"PPL",
    "gn:name":"Chorvador",
    "gn:population":0,
    "gn:timezone":"Asia/Tashkent",
    "iso:country":"UZ",
    "name:uzb_x_preferred":[
        "Chorvador"
    ],
    "wof:name":"Chorvador",
    "wof:placetype":"locality"
},
  "geometry": {"coordinates":[68.65014000000001,40.74627],"type":"Point"}
}