{
  "type": "Feature",
  "properties": {
    "gn:admin1_code":"09",
    "gn:asciiname":"Chakcha",
    "gn:country_code":"UZ",
    "gn:dem":84,
    "gn:feature_class":"P",
    "gn:feature_code":"PPL",
    "gn:name":"Chakcha",
    "gn:population":0,
    "gn:timezone":"Asia/Samarkand",
    "iso:country":"UZ",
    "wof:name":"Chakcha",
    "wof:placetype":"locality"
},
  "geometry": {"coordinates":[60.08989,42.19985],"type":"Point"}
}