{
  "type": "Feature",
  "properties": {
    "gn:admin1_code":"03",
    "gn:asciiname":"Archa",
    "gn:country_code":"UZ",
    "gn:dem":679,
    "gn:feature_class":"P",
    "gn:feature_code":"PPL",
    "gn:name":"Archa",
    "gn:population":0,
    "gn:timezone":"Asia/Tashkent",
    "iso:country":"UZ",
    "name:uzb_x_preferred":[
        "Archa"
    ],
    "wof:name":"Archa",
    "wof:placetype":"locality"
},
  "geometry": {"coordinates":[71.58017,40.25912],"type":"Point"}
}