{
  "type": "Feature",
  "properties": {
    "gn:admin1_code":"01",
    "gn:asciiname":"Guliston",
    "gn:country_code":"UZ",
    "gn:dem":425,
    "gn:feature_class":"P",
    "gn:feature_code":"PPL",
    "gn:name":"Guliston",
    "gn:population":0,
    "gn:timezone":"Asia/Tashkent",
    "iso:country":"UZ",
    "name:ara_x_preferred":[
        "\u0643\u0648\u0644\u0633\u062a\u0627\u0646"
    ],
    "name:azb_x_preferred":[
        "\u06af\u0648\u0644\u06cc\u0633\u062a\u0627\u0646"
    ],
    "name:bak_x_preferred":[
        "\u0413\u04e9\u043b\u0441\u0442\u0430\u043d"
    ],
    "name:bel_x_preferred":[
        "\u0413\u0443\u043b\u0456\u0441\u0442\u0430\u043d"
    ],
    "name:bul_x_preferred":[
        "\u0413\u0443\u043b\u0438\u0441\u0442\u0430\u043d"
    ],
    "name:ceb_x_preferred":[
        "Guliston"
    ],
    "name:ckb_x_preferred":[
        "\u06af\u0648\u06b5\u0633\u062a\u0627\u0646"
    ],
    "name:deu_x_preferred":[
        "Guliston"
    ],
    "name:epo_x_preferred":[
        "Gulistano"
    ],
    "name:fas_x_preferred":[
        "\u06af\u0644\u0633\u062a\u0627\u0646"
    ],
    "name:fin_x_preferred":[
        "Guliston"
    ],
    "name:fra_x_preferred":[
        "Goulistan"
    ],
    "name:hin_x_preferred":[
        "\u0917\u0941\u0932\u093f\u0938\u094d\u0924\u094b\u0928"
    ],
    "name:hsb_x_preferred":[
        "Guliston"
    ],
    "name:hye_x_preferred":[
        "\u0533\u0578\u0582\u056c\u056b\u057d\u057f\u0561\u0576"
    ],
    "name:ita_x_preferred":[
        "Gulistan"
    ],
    "name:jpn_x_preferred":[
        "\u30b0\u30ea\u30b9\u30bf\u30f3"
    ],
    "name:kaa_x_preferred":[
        "Gu'listan"
    ],
    "name:kik_x_preferred":[
        "Guliston"
    ],
    "name:kor_x_preferred":[
        "\uad74\ub9ac\uc2a4\ud0c4"
    ],
    "name:lit_x_preferred":[
        "Gulistanas"
    ],
    "name:nld_x_preferred":[
        "Guliston"
    ],
    "name:pan_x_preferred":[
        "\u0a17\u0a41\u0a32\u0a40\u0a38\u0a24\u0a4b\u0a28"
    ],
    "name:pol_x_preferred":[
        "Guliston"
    ],
    "name:ron_x_preferred":[
        "Gulistan"
    ],
    "name:rus_x_preferred":[
        "\u0413\u0443\u043b\u0438\u0441\u0442\u0430\u043d"
    ],
    "name:spa_x_preferred":[
        "Guliston"
    ],
    "name:tat_x_preferred":[
        "\u0413\u04e9\u043b\u0441\u0442\u0430\u043d"
    ],
    "name:tgk_x_preferred":[
        "\u0413\u0443\u043b\u0438\u0441\u0442\u043e\u043d"
    ],
    "name:tuk_x_preferred":[
        "G\u00fclistan"
    ],
    "name:tur_x_preferred":[
        "G\u00fclistan"
    ],
    "name:ukr_x_preferred":[
        "\u0490\u0443\u043b\u0456\u0441\u0442\u0430\u043d"
    ],
    "name:urd_x_preferred":[
        "\u06af\u0644\u0633\u062a\u0627\u0646"
    ],
    "name:uzb_x_preferred":[
        "Guliston"
    ],
    "name:war_x_preferred":[
        "Guliston"
    ],
    "name:zho_x_preferred":[
        "\u53e4\u5229\u65af\u5766"
    ],
    "wof:name":"Guliston",
    "wof:placetype":"locality"
},
  "geometry": {"coordinates":[71.9192,40.74924],"type":"Point"}
}