{
  "type": "Feature",
  "properties": {
    "gn:admin1_code":"08",
    "gn:asciiname":"Boygundi",
    "gn:country_code":"UZ",
    "gn:dem":357,
    "gn:feature_class":"P",
    "gn:feature_code":"PPL",
    "gn:name":"Boygundi",
    "gn:population":0,
    "gn:timezone":"Asia/Samarkand",
    "iso:country":"UZ",
    "name:eng_x_preferred":[
        "Boygundi"
    ],
    "wof:name":"Boygundi",
    "wof:placetype":"locality"
},
  "geometry": {"coordinates":[65.66289999999999,38.99885],"type":"Point"}
}