{
  "type": "Feature",
  "properties": {
    "gn:admin1_code":"00",
    "gn:asciiname":"Qarsh",
    "gn:country_code":"UZ",
    "gn:dem":1670,
    "gn:feature_class":"P",
    "gn:feature_code":"PPL",
    "gn:name":"Qarsh",
    "gn:population":0,
    "gn:timezone":"Asia/Samarkand",
    "iso:country":"UZ",
    "name:und_x_variant":[
        "Karish",
        "Karsh"
    ],
    "name:uzb_x_preferred":[
        "Qarsh"
    ],
    "wof:name":"Qarsh",
    "wof:placetype":"locality"
},
  "geometry": {"coordinates":[67.74285,38.66922],"type":"Point"}
}