{
  "type": "Feature",
  "properties": {
    "gn:admin1_code":"16",
    "gn:asciiname":"Sardoba",
    "gn:cc2":"UZ",
    "gn:country_code":"UZ",
    "gn:dem":267,
    "gn:feature_class":"P",
    "gn:feature_code":"PPL",
    "gn:name":"Sardoba",
    "gn:population":0,
    "gn:timezone":"Asia/Tashkent",
    "iso:country":"UZ",
    "name:und_x_variant":[
        "Mirzarabad",
        "Sardoba"
    ],
    "wof:name":"Sardoba",
    "wof:placetype":"locality"
},
  "geometry": {"coordinates":[68.41916999999999,40.54167],"type":"Point"}
}