{
  "type": "Feature",
  "properties": {
    "gn:admin1_code":"03",
    "gn:asciiname":"Katta-Amirobod",
    "gn:country_code":"UZ",
    "gn:dem":387,
    "gn:feature_class":"P",
    "gn:feature_code":"PPL",
    "gn:name":"Katta-Amirobod",
    "gn:population":0,
    "gn:timezone":"Asia/Tashkent",
    "iso:country":"UZ",
    "name:uzb_x_preferred":[
        "Katta-Amirobod"
    ],
    "wof:name":"Katta-Amirobod",
    "wof:placetype":"locality"
},
  "geometry": {"coordinates":[70.88114,40.58781],"type":"Point"}
}