{
  "type": "Feature",
  "properties": {
    "gn:admin1_code":"06",
    "gn:asciiname":"Sho`rbuloq",
    "gn:country_code":"UZ",
    "gn:dem":575,
    "gn:feature_class":"P",
    "gn:feature_code":"PPL",
    "gn:name":"Sho\u2018rbuloq",
    "gn:population":0,
    "gn:timezone":"Asia/Tashkent",
    "iso:country":"UZ",
    "name:eng_x_preferred":[
        "Sho\u2018rbuloq"
    ],
    "wof:name":"Sho`rbuloq",
    "wof:placetype":"locality"
},
  "geometry": {"coordinates":[71.87642,41.12124],"type":"Point"}
}