{
  "type": "Feature",
  "properties": {
    "gn:admin1_code":"12",
    "gn:asciiname":"Bokaty",
    "gn:country_code":"UZ",
    "gn:dem":974,
    "gn:feature_class":"P",
    "gn:feature_code":"PPL",
    "gn:name":"Bokaty",
    "gn:population":0,
    "gn:timezone":"Asia/Samarkand",
    "iso:country":"UZ",
    "wof:name":"Bokaty",
    "wof:placetype":"locality"
},
  "geometry": {"coordinates":[67.08161,38.1176],"type":"Point"}
}