{
  "type": "Feature",
  "properties": {
    "gn:admin1_code":"01",
    "gn:asciiname":"Qizilto`qay",
    "gn:country_code":"UZ",
    "gn:dem":669,
    "gn:feature_class":"P",
    "gn:feature_code":"PPL",
    "gn:name":"Qizilto\u2018qay",
    "gn:population":0,
    "gn:timezone":"Asia/Tashkent",
    "iso:country":"UZ",
    "name:uzb_x_preferred":[
        "Qizilto\u2018qay"
    ],
    "wof:name":"Qizilto`qay",
    "wof:placetype":"locality"
},
  "geometry": {"coordinates":[72.82895000000001,40.83757],"type":"Point"}
}