{
  "type": "Feature",
  "properties": {
    "gn:admin1_code":"09",
    "gn:asciiname":"Qiyot",
    "gn:country_code":"UZ",
    "gn:dem":62,
    "gn:feature_class":"P",
    "gn:feature_code":"PPL",
    "gn:name":"Qiyot",
    "gn:population":0,
    "gn:timezone":"Asia/Samarkand",
    "iso:country":"UZ",
    "wof:name":"Qiyot",
    "wof:placetype":"locality"
},
  "geometry": {"coordinates":[58.7815,42.69573],"type":"Point"}
}