{
  "type": "Feature",
  "properties": {
    "gn:admin1_code":"16",
    "gn:asciiname":"Dehqonobod",
    "gn:country_code":"UZ",
    "gn:dem":276,
    "gn:feature_class":"P",
    "gn:feature_code":"PPL",
    "gn:name":"Dehqonobod",
    "gn:population":0,
    "gn:timezone":"Asia/Tashkent",
    "iso:country":"UZ",
    "name:und_x_variant":[
        "Dekhkanabad"
    ],
    "name:uzb_x_preferred":[
        "Dehqonobod"
    ],
    "wof:name":"Dehqonobod",
    "wof:placetype":"locality"
},
  "geometry": {"coordinates":[68.81438,40.44625],"type":"Point"}
}