{
  "type": "Feature",
  "properties": {
    "gn:admin1_code":"12",
    "gn:asciiname":"Hisorak",
    "gn:country_code":"UZ",
    "gn:dem":808,
    "gn:feature_class":"P",
    "gn:feature_code":"PPL",
    "gn:name":"Hisorak",
    "gn:population":0,
    "gn:timezone":"Asia/Samarkand",
    "iso:country":"UZ",
    "name:und_x_variant":[
        "Gisarak",
        "Xisorak"
    ],
    "name:uzb_x_preferred":[
        "Hisorak"
    ],
    "wof:name":"Hisorak",
    "wof:placetype":"locality"
},
  "geometry": {"coordinates":[67.80254000000001,38.57462],"type":"Point"}
}