{
  "type": "Feature",
  "properties": {
    "gn:admin1_code":"08",
    "gn:asciiname":"Gurati-2",
    "gn:country_code":"UZ",
    "gn:dem":1287,
    "gn:feature_class":"P",
    "gn:feature_code":"PPL",
    "gn:name":"Gurati-2",
    "gn:population":0,
    "gn:timezone":"Asia/Samarkand",
    "iso:country":"UZ",
    "name:und_x_variant":[
        "Guraty"
    ],
    "wof:name":"Gurati-2",
    "wof:placetype":"locality"
},
  "geometry": {"coordinates":[66.78678000000001,38.40451],"type":"Point"}
}