{
  "type": "Feature",
  "properties": {
    "gn:admin1_code":"07",
    "gn:asciiname":"Khanaka",
    "gn:country_code":"UZ",
    "gn:dem":645,
    "gn:feature_class":"P",
    "gn:feature_code":"PPL",
    "gn:name":"Khanaka",
    "gn:population":0,
    "gn:timezone":"Asia/Samarkand",
    "iso:country":"UZ",
    "wof:name":"Khanaka",
    "wof:placetype":"locality"
},
  "geometry": {"coordinates":[65.93333,40.21667],"type":"Point"}
}