{
  "type": "Feature",
  "properties": {
    "gn:admin1_code":"00",
    "gn:asciiname":"Balgauz",
    "gn:country_code":"UZ",
    "gn:dem":905,
    "gn:feature_class":"P",
    "gn:feature_code":"PPL",
    "gn:name":"Balgauz",
    "gn:population":0,
    "gn:timezone":"Asia/Tashkent",
    "iso:country":"UZ",
    "wof:name":"Balgauz",
    "wof:placetype":"locality"
},
  "geometry": {"coordinates":[68.78333000000001,39.93333],"type":"Point"}
}