{
  "type": "Feature",
  "properties": {
    "gn:admin1_code":"06",
    "gn:asciiname":"Sirmak",
    "gn:country_code":"UZ",
    "gn:dem":438,
    "gn:feature_class":"P",
    "gn:feature_code":"PPL",
    "gn:name":"Sirmak",
    "gn:population":0,
    "gn:timezone":"Asia/Tashkent",
    "iso:country":"UZ",
    "name:eng_x_preferred":[
        "Sirmak"
    ],
    "name:und_x_variant":[
        "Syrmak"
    ],
    "name:uzb_x_preferred":[
        "Sirmak"
    ],
    "name:uzb_x_variant":[
        "Sirmoq"
    ],
    "wof:name":"Sirmak",
    "wof:placetype":"locality"
},
  "geometry": {"coordinates":[72.08298000000001,40.92747],"type":"Point"}
}