{
  "type": "Feature",
  "properties": {
    "gn:admin1_code":"08",
    "gn:asciiname":"Boyqo`rg`on",
    "gn:country_code":"UZ",
    "gn:dem":851,
    "gn:feature_class":"P",
    "gn:feature_code":"PPL",
    "gn:name":"Boyqo\u2018rg\u2018on",
    "gn:population":0,
    "gn:timezone":"Asia/Samarkand",
    "iso:country":"UZ",
    "name:und_x_variant":[
        "Boyqo\u2018rg\u2018on",
        "Baykurgan"
    ],
    "wof:name":"Boyqo`rg`on",
    "wof:placetype":"locality"
},
  "geometry": {"coordinates":[66.65198000000001,38.57661],"type":"Point"}
}