{
  "type": "Feature",
  "properties": {
    "gn:admin1_code":"08",
    "gn:asciiname":"Dzhity-Kuduk",
    "gn:country_code":"UZ",
    "gn:dem":488,
    "gn:feature_class":"P",
    "gn:feature_code":"PPL",
    "gn:name":"Dzhity-Kuduk",
    "gn:population":0,
    "gn:timezone":"Asia/Samarkand",
    "iso:country":"UZ",
    "wof:name":"Dzhity-Kuduk",
    "wof:placetype":"locality"
},
  "geometry": {"coordinates":[66.33333,39.03333],"type":"Point"}
}