{
  "type": "Feature",
  "properties": {
    "gn:admin1_code":"08",
    "gn:asciiname":"Aymak",
    "gn:country_code":"UZ",
    "gn:dem":508,
    "gn:feature_class":"P",
    "gn:feature_code":"PPL",
    "gn:name":"Aymak",
    "gn:population":0,
    "gn:timezone":"Asia/Samarkand",
    "iso:country":"UZ",
    "wof:name":"Aymak",
    "wof:placetype":"locality"
},
  "geometry": {"coordinates":[66.48361,38.99556],"type":"Point"}
}