{
  "type": "Feature",
  "properties": {
    "gn:admin1_code":"10",
    "gn:asciiname":"Nurdum",
    "gn:country_code":"UZ",
    "gn:dem":522,
    "gn:feature_class":"P",
    "gn:feature_code":"PPL",
    "gn:name":"Nurdum",
    "gn:population":0,
    "gn:timezone":"Asia/Samarkand",
    "iso:country":"UZ",
    "wof:name":"Nurdum",
    "wof:placetype":"locality"
},
  "geometry": {"coordinates":[66.28528,39.70528],"type":"Point"}
}