{
  "type": "Feature",
  "properties": {
    "gn:admin1_code":"16",
    "gn:asciiname":"Qarapchi",
    "gn:country_code":"UZ",
    "gn:dem":273,
    "gn:feature_class":"P",
    "gn:feature_code":"PPL",
    "gn:name":"Qarapchi",
    "gn:population":0,
    "gn:timezone":"Asia/Tashkent",
    "iso:country":"UZ",
    "name:uzb_x_preferred":[
        "Qarapchi"
    ],
    "wof:name":"Qarapchi",
    "wof:placetype":"locality"
},
  "geometry": {"coordinates":[68.80939000000001,40.47561],"type":"Point"}
}