{
  "type": "Feature",
  "properties": {
    "gn:admin1_code":"03",
    "gn:asciiname":"Chekkuprik",
    "gn:country_code":"UZ",
    "gn:dem":387,
    "gn:feature_class":"P",
    "gn:feature_code":"PPL",
    "gn:name":"Chekkuprik",
    "gn:population":0,
    "gn:timezone":"Asia/Tashkent",
    "iso:country":"UZ",
    "name:uzb_x_preferred":[
        "Chekkuprik"
    ],
    "wof:name":"Chekkuprik",
    "wof:placetype":"locality"
},
  "geometry": {"coordinates":[70.71287,40.46437],"type":"Point"}
}