{
  "type": "Feature",
  "properties": {
    "gn:admin1_code":"03",
    "gn:asciiname":"Chimyon",
    "gn:country_code":"UZ",
    "gn:dem":683,
    "gn:feature_class":"P",
    "gn:feature_code":"PPL",
    "gn:name":"Chimyon",
    "gn:population":0,
    "gn:timezone":"Asia/Tashkent",
    "iso:country":"UZ",
    "name:pol_x_preferred":[
        "Chimyon"
    ],
    "name:rus_x_preferred":[
        "\u0427\u0438\u043c\u0438\u043e\u043d"
    ],
    "name:und_x_variant":[
        "Chimion"
    ],
    "name:uzb_x_preferred":[
        "Chimyon"
    ],
    "wof:name":"Chimyon",
    "wof:placetype":"locality"
},
  "geometry": {"coordinates":[71.51550999999998,40.25502],"type":"Point"}
}