{
  "type": "Feature",
  "properties": {
    "gn:admin1_code":"00",
    "gn:asciiname":"Khasokar",
    "gn:cc2":"UZ",
    "gn:country_code":"UZ",
    "gn:dem":211,
    "gn:feature_class":"P",
    "gn:feature_code":"PPL",
    "gn:name":"Khasokar",
    "gn:population":0,
    "gn:timezone":"Asia/Samarkand",
    "iso:country":"UZ",
    "name:und_x_variant":[
        "Khosakaran",
        "Chassakar",
        "Khasokar"
    ],
    "wof:name":"Khasokar",
    "wof:placetype":"locality"
},
  "geometry": {"coordinates":[64.16667,39.68333],"type":"Point"}
}