{
  "type": "Feature",
  "properties": {
    "gn:admin1_code":"15",
    "gn:admin2_code":"Zomin",
    "gn:asciiname":"Yam",
    "gn:cc2":"UZ",
    "gn:country_code":"UZ",
    "gn:dem":473,
    "gn:feature_class":"P",
    "gn:feature_code":"PPL",
    "gn:name":"Yam",
    "gn:population":0,
    "gn:timezone":"Asia/Samarkand",
    "iso:country":"UZ",
    "name:und_x_variant":[
        "Imeni Akhurbabayeva",
        "Yam"
    ],
    "wof:name":"Yam",
    "wof:placetype":"locality"
},
  "geometry": {"coordinates":[68.52278000000001,40.03278],"type":"Point"}
}