{
  "type": "Feature",
  "properties": {
    "gn:admin1_code":"09",
    "gn:asciiname":"Uch Gujum",
    "gn:country_code":"UZ",
    "gn:dem":104,
    "gn:feature_class":"P",
    "gn:feature_code":"PPL",
    "gn:name":"Uch Gujum",
    "gn:population":0,
    "gn:timezone":"Asia/Samarkand",
    "iso:country":"UZ",
    "wof:name":"Uch Gujum",
    "wof:placetype":"locality"
},
  "geometry": {"coordinates":[61.06415,41.51226],"type":"Point"}
}