{
  "type": "Feature",
  "properties": {
    "gn:admin1_code":"00",
    "gn:asciiname":"Kuz-Guzar",
    "gn:country_code":"UZ",
    "gn:dem":661,
    "gn:feature_class":"P",
    "gn:feature_code":"PPL",
    "gn:name":"Kuz-Guzar",
    "gn:population":0,
    "gn:timezone":"Asia/Samarkand",
    "iso:country":"UZ",
    "wof:name":"Kuz-Guzar",
    "wof:placetype":"locality"
},
  "geometry": {"coordinates":[67.01666999999999,39.86667],"type":"Point"}
}