{
  "type": "Feature",
  "properties": {
    "gn:admin1_code":"07",
    "gn:asciiname":"Dovriqo`rg`on",
    "gn:country_code":"UZ",
    "gn:dem":323,
    "gn:feature_class":"P",
    "gn:feature_code":"PPL",
    "gn:name":"Dovriqo\u2018rg\u2018on",
    "gn:population":0,
    "gn:timezone":"Asia/Samarkand",
    "iso:country":"UZ",
    "wof:name":"Dovriqo`rg`on",
    "wof:placetype":"locality"
},
  "geometry": {"coordinates":[65.25286,40.18508],"type":"Point"}
}