{
  "type": "Feature",
  "properties": {
    "gn:admin1_code":"14",
    "gn:asciiname":"Mamut",
    "gn:country_code":"UZ",
    "gn:dem":274,
    "gn:feature_class":"P",
    "gn:feature_code":"PPL",
    "gn:name":"Mamut",
    "gn:population":0,
    "gn:timezone":"Asia/Tashkent",
    "iso:country":"UZ",
    "name:uzb_x_preferred":[
        "Mamut"
    ],
    "wof:name":"Mamut",
    "wof:placetype":"locality"
},
  "geometry": {"coordinates":[68.91519,40.80707],"type":"Point"}
}