{
  "type": "Feature",
  "properties": {
    "gn:admin1_code":"03",
    "gn:asciiname":"Xo`jaqishloq",
    "gn:country_code":"UZ",
    "gn:dem":372,
    "gn:feature_class":"P",
    "gn:feature_code":"PPL",
    "gn:name":"Xo\u2018jaqishloq",
    "gn:population":0,
    "gn:timezone":"Asia/Tashkent",
    "iso:country":"UZ",
    "name:und_x_variant":[
        "Khodzha",
        "Khodzhakishlak",
        "Xo\u2018jaqishloq"
    ],
    "wof:name":"Xo`jaqishloq",
    "wof:placetype":"locality"
},
  "geometry": {"coordinates":[70.92448,40.72792000000001],"type":"Point"}
}