{
  "type": "Feature",
  "properties": {
    "gn:admin1_code":"10",
    "gn:asciiname":"Bashkuduk",
    "gn:country_code":"UZ",
    "gn:dem":610,
    "gn:feature_class":"P",
    "gn:feature_code":"PPL",
    "gn:name":"Bashkuduk",
    "gn:population":0,
    "gn:timezone":"Asia/Samarkand",
    "iso:country":"UZ",
    "wof:name":"Bashkuduk",
    "wof:placetype":"locality"
},
  "geometry": {"coordinates":[66.44833,39.63917],"type":"Point"}
}