{
  "type": "Feature",
  "properties": {
    "gn:admin1_code":"07",
    "gn:asciiname":"Shariqti",
    "gn:country_code":"UZ",
    "gn:dem":324,
    "gn:feature_class":"P",
    "gn:feature_code":"PPL",
    "gn:name":"Shariqti",
    "gn:population":0,
    "gn:timezone":"Asia/Samarkand",
    "iso:country":"UZ",
    "name:und_x_variant":[
        "Sharikdy",
        "Sharykty",
        "Shariqti"
    ],
    "wof:name":"Shariqti",
    "wof:placetype":"locality"
},
  "geometry": {"coordinates":[64.77788000000001,41.50977],"type":"Point"}
}