{
  "type": "Feature",
  "properties": {
    "gn:admin1_code":"12",
    "gn:asciiname":"Eski Termiz",
    "gn:country_code":"UZ",
    "gn:dem":304,
    "gn:feature_class":"P",
    "gn:feature_code":"PPL",
    "gn:name":"Eski Termiz",
    "gn:population":0,
    "gn:timezone":"Asia/Samarkand",
    "iso:country":"UZ",
    "name:uzb_x_preferred":[
        "Eski Termiz"
    ],
    "wof:name":"Eski Termiz",
    "wof:placetype":"locality"
},
  "geometry": {"coordinates":[67.23636999999999,37.26931],"type":"Point"}
}