{
  "type": "Feature",
  "properties": {
    "gn:admin1_code":"06",
    "gn:asciiname":"Sho`ro",
    "gn:country_code":"UZ",
    "gn:dem":435,
    "gn:feature_class":"P",
    "gn:feature_code":"PPL",
    "gn:name":"Sho\u2018ro",
    "gn:population":0,
    "gn:timezone":"Asia/Tashkent",
    "iso:country":"UZ",
    "name:und_x_variant":[
        "Leninabad",
        "Shura"
    ],
    "name:uzb_x_preferred":[
        "Sho\u2018ro"
    ],
    "wof:name":"Sho`ro",
    "wof:placetype":"locality"
},
  "geometry": {"coordinates":[72.04822,40.92145],"type":"Point"}
}