{
  "type": "Feature",
  "properties": {
    "gn:admin1_code":"09",
    "gn:asciiname":"Qorabayli",
    "gn:country_code":"UZ",
    "gn:dem":68,
    "gn:feature_class":"P",
    "gn:feature_code":"PPL",
    "gn:name":"Qorabayli",
    "gn:population":0,
    "gn:timezone":"Asia/Samarkand",
    "iso:country":"UZ",
    "wof:name":"Qorabayli",
    "wof:placetype":"locality"
},
  "geometry": {"coordinates":[59.15856,42.59284],"type":"Point"}
}