{
  "type": "Feature",
  "properties": {
    "gn:admin1_code":"03",
    "gn:asciiname":"Chinobod",
    "gn:country_code":"UZ",
    "gn:dem":378,
    "gn:feature_class":"P",
    "gn:feature_code":"PPL",
    "gn:name":"Chinobod",
    "gn:population":0,
    "gn:timezone":"Asia/Tashkent",
    "iso:country":"UZ",
    "name:uzb_x_preferred":[
        "Chinobod"
    ],
    "wof:name":"Chinobod",
    "wof:placetype":"locality"
},
  "geometry": {"coordinates":[70.7764,40.53208],"type":"Point"}
}