{
  "type": "Feature",
  "properties": {
    "gn:admin1_code":"08",
    "gn:asciiname":"Qorqo`ng`irot",
    "gn:country_code":"UZ",
    "gn:dem":363,
    "gn:feature_class":"P",
    "gn:feature_code":"PPL",
    "gn:name":"Qorqo\u2018ng\u2018irot",
    "gn:population":0,
    "gn:timezone":"Asia/Samarkand",
    "iso:country":"UZ",
    "name:eng_x_preferred":[
        "Qorqo\u2018ng\u2018irot"
    ],
    "wof:name":"Qorqo`ng`irot",
    "wof:placetype":"locality"
},
  "geometry": {"coordinates":[65.69221999999999,38.90637],"type":"Point"}
}