{
  "type": "Feature",
  "properties": {
    "gn:admin1_code":"01",
    "gn:asciiname":"Barraj",
    "gn:country_code":"UZ",
    "gn:dem":552,
    "gn:feature_class":"P",
    "gn:feature_code":"PPL",
    "gn:name":"Barraj",
    "gn:population":0,
    "gn:timezone":"Asia/Tashkent",
    "iso:country":"UZ",
    "name:rus_x_preferred":[
        "\u041a\u044b\u0437\u044b\u043b\u0430\u044f\u043a"
    ],
    "name:und_x_variant":[
        "Kyzylayak"
    ],
    "name:uzb_x_preferred":[
        "Barraj"
    ],
    "name:uzb_x_variant":[
        "Qiziloyoq"
    ],
    "wof:name":"Barraj",
    "wof:placetype":"locality"
},
  "geometry": {"coordinates":[72.55386999999997,40.88649],"type":"Point"}
}