{
  "type": "Feature",
  "properties": {
    "gn:admin1_code":"00",
    "gn:asciiname":"Shaytan",
    "gn:country_code":"UZ",
    "gn:dem":524,
    "gn:feature_class":"P",
    "gn:feature_code":"PPL",
    "gn:name":"Shaytan",
    "gn:population":0,
    "gn:timezone":"Asia/Samarkand",
    "iso:country":"UZ",
    "wof:name":"Shaytan",
    "wof:placetype":"locality"
},
  "geometry": {"coordinates":[67.83583,38.1975],"type":"Point"}
}