{
  "type": "Feature",
  "properties": {
    "gn:admin1_code":"06",
    "gn:asciiname":"Yangiobod",
    "gn:country_code":"UZ",
    "gn:dem":414,
    "gn:feature_class":"P",
    "gn:feature_code":"PPL",
    "gn:name":"Yangiobod",
    "gn:population":0,
    "gn:timezone":"Asia/Tashkent",
    "iso:country":"UZ",
    "name:eng_x_preferred":[
        "Yangiobod"
    ],
    "wof:name":"Yangiobod",
    "wof:placetype":"locality"
},
  "geometry": {"coordinates":[71.01130000000001,40.84084],"type":"Point"}
}