{
  "type": "Feature",
  "properties": {
    "gn:admin1_code":"09",
    "gn:asciiname":"Birleshik",
    "gn:country_code":"UZ",
    "gn:dem":66,
    "gn:feature_class":"P",
    "gn:feature_code":"PPL",
    "gn:name":"Birleshik",
    "gn:population":0,
    "gn:timezone":"Asia/Samarkand",
    "iso:country":"UZ",
    "wof:name":"Birleshik",
    "wof:placetype":"locality"
},
  "geometry": {"coordinates":[59.12589000000001,42.55512],"type":"Point"}
}