{
  "type": "Feature",
  "properties": {
    "gn:admin1_code":"07",
    "gn:asciiname":"Yunus",
    "gn:country_code":"UZ",
    "gn:dem":279,
    "gn:feature_class":"P",
    "gn:feature_code":"PPL",
    "gn:name":"Yunus",
    "gn:population":0,
    "gn:timezone":"Asia/Samarkand",
    "iso:country":"UZ",
    "wof:name":"Yunus",
    "wof:placetype":"locality"
},
  "geometry": {"coordinates":[65.28333000000001,41.13333],"type":"Point"}
}