{
  "type": "Feature",
  "properties": {
    "gn:admin1_code":"03",
    "gn:asciiname":"Yuqori-Valik",
    "gn:country_code":"UZ",
    "gn:dem":678,
    "gn:feature_class":"P",
    "gn:feature_code":"PPL",
    "gn:name":"Yuqori-Valik",
    "gn:population":0,
    "gn:timezone":"Asia/Tashkent",
    "iso:country":"UZ",
    "name:uzb_x_preferred":[
        "Yuqori-Valik"
    ],
    "wof:name":"Yuqori-Valik",
    "wof:placetype":"locality"
},
  "geometry": {"coordinates":[72.00870999999999,40.3808],"type":"Point"}
}