{
  "type": "Feature",
  "properties": {
    "gn:admin1_code":"00",
    "gn:asciiname":"Ravat",
    "gn:country_code":"UZ",
    "gn:dem":660,
    "gn:feature_class":"P",
    "gn:feature_code":"PPL",
    "gn:name":"Ravat",
    "gn:population":0,
    "gn:timezone":"Asia/Samarkand",
    "iso:country":"UZ",
    "name:kir_x_preferred":[
        "\u0420\u0430\u0432\u0430\u0442"
    ],
    "name:uzb_x_preferred":[
        "Ravot"
    ],
    "wof:name":"Ravat",
    "wof:placetype":"locality"
},
  "geometry": {"coordinates":[67.98333000000001,39.95],"type":"Point"}
}