{
  "type": "Feature",
  "properties": {
    "gn:admin1_code":"14",
    "gn:asciiname":"Yo`ldosh Oxunboboyev",
    "gn:country_code":"UZ",
    "gn:dem":352,
    "gn:feature_class":"P",
    "gn:feature_code":"PPL",
    "gn:name":"Yo\u2018ldosh Oxunboboyev",
    "gn:population":0,
    "gn:timezone":"Asia/Tashkent",
    "iso:country":"UZ",
    "name:uzb_x_preferred":[
        "Yo\u2018ldosh Oxunboboyev"
    ],
    "wof:name":"Yo`ldosh Oxunboboyev",
    "wof:placetype":"locality"
},
  "geometry": {"coordinates":[69.17489,40.94562],"type":"Point"}
}