{
  "type": "Feature",
  "properties": {
    "gn:admin1_code":"14",
    "gn:asciiname":"G`ayrat",
    "gn:country_code":"UZ",
    "gn:dem":300,
    "gn:feature_class":"P",
    "gn:feature_code":"PPL",
    "gn:name":"G\u2018ayrat",
    "gn:population":0,
    "gn:timezone":"Asia/Tashkent",
    "iso:country":"UZ",
    "name:und_x_variant":[
        "Kayrak",
        "Gayrat"
    ],
    "name:uzb_x_preferred":[
        "G\u2018ayrat"
    ],
    "wof:name":"G`ayrat",
    "wof:placetype":"locality"
},
  "geometry": {"coordinates":[68.78305999999999,41.03806],"type":"Point"}
}