{
  "type": "Feature",
  "properties": {
    "gn:admin1_code":"03",
    "gn:asciiname":"Birinchi Tekelik",
    "gn:country_code":"UZ",
    "gn:dem":411,
    "gn:feature_class":"P",
    "gn:feature_code":"PPL",
    "gn:name":"Birinchi Tekelik",
    "gn:population":0,
    "gn:timezone":"Asia/Tashkent",
    "iso:country":"UZ",
    "name:und_x_variant":[
        "Tekelik Pervyy"
    ],
    "name:uzb_x_preferred":[
        "Birinchi Tekelik"
    ],
    "name:uzb_x_variant":[
        "Takalik Bir"
    ],
    "wof:name":"Birinchi Tekelik",
    "wof:placetype":"locality"
},
  "geometry": {"coordinates":[71.66293,40.69178],"type":"Point"}
}