{
  "type": "Feature",
  "properties": {
    "gn:admin1_code":"14",
    "gn:asciiname":"Koshchi",
    "gn:cc2":"UZ",
    "gn:country_code":"UZ",
    "gn:dem":296,
    "gn:feature_class":"P",
    "gn:feature_code":"PPL",
    "gn:name":"Koshchi",
    "gn:population":0,
    "gn:timezone":"Asia/Tashkent",
    "iso:country":"UZ",
    "name:und_x_variant":[
        "Kushchi",
        "Koshchi"
    ],
    "wof:name":"Koshchi",
    "wof:placetype":"locality"
},
  "geometry": {"coordinates":[69.30722,40.31111],"type":"Point"}
}