{
  "type": "Feature",
  "properties": {
    "gn:admin1_code":"16",
    "gn:asciiname":"Uch Qahramon",
    "gn:country_code":"UZ",
    "gn:dem":280,
    "gn:feature_class":"P",
    "gn:feature_code":"PPL",
    "gn:name":"Uch Qahramon",
    "gn:population":0,
    "gn:timezone":"Asia/Tashkent",
    "iso:country":"UZ",
    "name:uzb_x_preferred":[
        "Uch Qahramon"
    ],
    "wof:name":"Uch Qahramon",
    "wof:placetype":"locality"
},
  "geometry": {"coordinates":[69.03648000000001,40.4716],"type":"Point"}
}