{
  "type": "Feature",
  "properties": {
    "gn:admin1_code":"08",
    "gn:asciiname":"Ching`iroq",
    "gn:country_code":"UZ",
    "gn:dem":1866,
    "gn:feature_class":"P",
    "gn:feature_code":"PPL",
    "gn:name":"Ching\u2018iroq",
    "gn:population":0,
    "gn:timezone":"Asia/Samarkand",
    "iso:country":"UZ",
    "name:und_x_variant":[
        "Ching\u2018iroq",
        "Chingurak"
    ],
    "wof:name":"Ching`iroq",
    "wof:placetype":"locality"
},
  "geometry": {"coordinates":[67.26430999999999,39.0398],"type":"Point"}
}