{
  "type": "Feature",
  "properties": {
    "gn:admin1_code":"00",
    "gn:asciiname":"Kara-Tyube",
    "gn:country_code":"UZ",
    "gn:dem":220,
    "gn:feature_class":"P",
    "gn:feature_code":"PPL",
    "gn:name":"Kara-Tyube",
    "gn:population":0,
    "gn:timezone":"Asia/Samarkand",
    "iso:country":"UZ",
    "wof:name":"Kara-Tyube",
    "wof:placetype":"locality"
},
  "geometry": {"coordinates":[64.23333000000001,40.08333],"type":"Point"}
}