{
  "type": "Feature",
  "properties": {
    "iso:country":"UZ",
    "name:ara_x_preferred":[
        "\u0645\u0631\u062d\u0645\u062a"
    ],
    "name:azb_x_preferred":[
        "\u0645\u0631\u062d\u0645\u062a"
    ],
    "name:bul_x_preferred":[
        "\u041c\u0430\u0440\u0445\u0430\u043c\u0430\u0442"
    ],
    "name:ceb_x_preferred":[
        "Marhamat"
    ],
    "name:deu_x_preferred":[
        "Marhamat"
    ],
    "name:eng_x_preferred":[
        "Marhamat"
    ],
    "name:fas_x_preferred":[
        "\u0645\u0631\u062d\u0645\u062a"
    ],
    "name:hsb_x_preferred":[
        "Marhamat"
    ],
    "name:ita_x_preferred":[
        "Marhamat"
    ],
    "name:jpn_x_preferred":[
        "\u30de\u30eb\u30cf\u30de\u30c8"
    ],
    "name:kaz_x_preferred":[
        "\u041c\u0430\u0440\u0445\u0430\u043c\u0430\u0442"
    ],
    "name:kik_x_preferred":[
        "Marhamat"
    ],
    "name:lit_x_preferred":[
        "Marhamatas"
    ],
    "name:nld_x_preferred":[
        "Marhamat"
    ],
    "name:pnb_x_preferred":[
        "\u0645\u0631\u062d\u0645\u062a"
    ],
    "name:pol_x_preferred":[
        "Marhamat"
    ],
    "name:rus_x_preferred":[
        "\u041c\u0430\u0440\u0445\u0430\u043c\u0430\u0442"
    ],
    "name:spa_x_preferred":[
        "Marhamat"
    ],
    "name:tat_x_preferred":[
        "\u041c\u04d9\u0440\u0445\u04d9\u043c\u04d9\u0442"
    ],
    "name:tur_x_preferred":[
        "Merhamet"
    ],
    "name:ukr_x_preferred":[
        "\u041c\u0430\u0440\u0445\u0430\u043c\u0430\u0442"
    ],
    "name:und_x_variant":[
        "Markhamat Pervyy"
    ],
    "name:urd_x_preferred":[
        "\u0645\u0631\u062d\u0645\u062a"
    ],
    "name:uzb_x_preferred":[
        "Marhamat"
    ],
    "qs:gn_country":"UZ",
    "qs:gn_fcode":"PPL",
    "qs:gn_pop":14646,
    "qs:name":"Marhamat",
    "qs:name_adm0":"Uzbekistan",
    "qs:name_adm1":"Andijon",
    "qs:photos":0,
    "qs:photos_1k":0,
    "qs:photos_9k":0,
    "qs:photos_9r":0,
    "qs:photos_all":0,
    "qs:photos_sr":0,
    "qs:placetype":"Town",
    "qs:pop_sr":"6",
    "qs:woe_adm0":23424980,
    "wd:wordcount":35,
    "wof:name":"Marhamat",
    "wof:placetype":"locality",
    "wof:population":14646
},
  "geometry": {"coordinates":[72.31388,40.48048],"type":"Point"}
}