{
  "type": "Feature",
  "properties": {
    "gn:admin1_code":"14",
    "gn:asciiname":"Evalak",
    "gn:cc2":"UZ",
    "gn:country_code":"UZ",
    "gn:dem":525,
    "gn:feature_class":"P",
    "gn:feature_code":"PPL",
    "gn:name":"Evalak",
    "gn:population":0,
    "gn:timezone":"Asia/Tashkent",
    "iso:country":"UZ",
    "name:und_x_variant":[
        "Yubelek",
        "Ivalek",
        "Evalak"
    ],
    "wof:name":"Evalak",
    "wof:placetype":"locality"
},
  "geometry": {"coordinates":[69.595,40.87917],"type":"Point"}
}