{
  "type": "Feature",
  "properties": {
    "gn:admin1_code":"06",
    "gn:asciiname":"Tuman",
    "gn:country_code":"UZ",
    "gn:dem":410,
    "gn:feature_class":"P",
    "gn:feature_code":"PPL",
    "gn:name":"Tuman",
    "gn:population":0,
    "gn:timezone":"Asia/Tashkent",
    "iso:country":"UZ",
    "name:cat_x_preferred":[
        "Tuman"
    ],
    "name:ceb_x_preferred":[
        "Tuman"
    ],
    "name:deu_x_preferred":[
        "Tuman"
    ],
    "name:eng_x_preferred":[
        "Tuman"
    ],
    "name:rus_x_preferred":[
        "\u0422\u0443\u043c\u0430\u043d"
    ],
    "name:ukr_x_preferred":[
        "\u0422\u0443\u043c\u0430\u043d"
    ],
    "name:uzb_x_preferred":[
        "Tuman"
    ],
    "wof:name":"Tuman",
    "wof:placetype":"locality"
},
  "geometry": {"coordinates":[71.80814000000002,40.92336],"type":"Point"}
}