{
  "type": "Feature",
  "properties": {
    "gn:admin1_code":"00",
    "gn:asciiname":"Vasil'kara",
    "gn:country_code":"UZ",
    "gn:dem":377,
    "gn:feature_class":"P",
    "gn:feature_code":"PPL",
    "gn:name":"Vasil\u2019kara",
    "gn:population":0,
    "gn:timezone":"Asia/Tashkent",
    "iso:country":"UZ",
    "name:rus_x_preferred":[
        "Vasil\u2019kara"
    ],
    "wof:name":"Vasil'kara",
    "wof:placetype":"locality"
},
  "geometry": {"coordinates":[69.25,40.86667],"type":"Point"}
}