{
  "type": "Feature",
  "properties": {
    "gn:admin1_code":"00",
    "gn:asciiname":"Yangi-Mazar",
    "gn:country_code":"UZ",
    "gn:dem":207,
    "gn:feature_class":"P",
    "gn:feature_code":"PPL",
    "gn:name":"Yangi-Mazar",
    "gn:population":0,
    "gn:timezone":"Asia/Samarkand",
    "iso:country":"UZ",
    "wof:name":"Yangi-Mazar",
    "wof:placetype":"locality"
},
  "geometry": {"coordinates":[63.98333,39.61667],"type":"Point"}
}