{
  "type": "Feature",
  "properties": {
    "gn:admin1_code":"08",
    "gn:asciiname":"Balhiyoq",
    "gn:country_code":"UZ",
    "gn:dem":319,
    "gn:feature_class":"P",
    "gn:feature_code":"PPL",
    "gn:name":"Balhiyoq",
    "gn:population":0,
    "gn:timezone":"Asia/Samarkand",
    "iso:country":"UZ",
    "name:eng_x_preferred":[
        "Balhiyoq"
    ],
    "wof:name":"Balhiyoq",
    "wof:placetype":"locality"
},
  "geometry": {"coordinates":[65.45194000000001,38.6432],"type":"Point"}
}