{
  "type": "Feature",
  "properties": {
    "gn:admin1_code":"15",
    "gn:asciiname":"Uchastok Kuktash",
    "gn:country_code":"UZ",
    "gn:dem":249,
    "gn:feature_class":"P",
    "gn:feature_code":"PPL",
    "gn:name":"Uchastok Kuktash",
    "gn:population":0,
    "gn:timezone":"Asia/Tashkent",
    "iso:country":"UZ",
    "wof:name":"Uchastok Kuktash",
    "wof:placetype":"locality"
},
  "geometry": {"coordinates":[67.97028,41.07056],"type":"Point"}
}