{
  "type": "Feature",
  "properties": {
    "gn:admin1_code":"06",
    "gn:asciiname":"Naymancha",
    "gn:country_code":"UZ",
    "gn:dem":455,
    "gn:feature_class":"P",
    "gn:feature_code":"PPL",
    "gn:name":"Naymancha",
    "gn:population":0,
    "gn:timezone":"Asia/Tashkent",
    "iso:country":"UZ",
    "name:eng_x_preferred":[
        "Naymancha"
    ],
    "wof:name":"Naymancha",
    "wof:placetype":"locality"
},
  "geometry": {"coordinates":[71.41511,40.92832],"type":"Point"}
}