{
  "type": "Feature",
  "properties": {
    "gn:admin1_code":"03",
    "gn:asciiname":"Tadzhikkishlak",
    "gn:country_code":"UZ",
    "gn:dem":485,
    "gn:feature_class":"P",
    "gn:feature_code":"PPL",
    "gn:name":"Tadzhikkishlak",
    "gn:population":0,
    "gn:timezone":"Asia/Tashkent",
    "iso:country":"UZ",
    "name:rus_x_preferred":[
        "\u0422\u0430\u0434\u0436\u0438\u043a\u043a\u0438\u0448\u043b\u0430\u043a"
    ],
    "wof:name":"Tadzhikkishlak",
    "wof:placetype":"locality"
},
  "geometry": {"coordinates":[72.02878,40.51519],"type":"Point"}
}