{
  "type": "Feature",
  "properties": {
    "gn:admin1_code":"08",
    "gn:asciiname":"Olposh Buloq",
    "gn:country_code":"UZ",
    "gn:dem":1652,
    "gn:feature_class":"P",
    "gn:feature_code":"PPL",
    "gn:name":"Olposh Buloq",
    "gn:population":0,
    "gn:timezone":"Asia/Samarkand",
    "iso:country":"UZ",
    "wof:name":"Olposh Buloq",
    "wof:placetype":"locality"
},
  "geometry": {"coordinates":[66.97601,39.27021],"type":"Point"}
}