{
  "type": "Feature",
  "properties": {
    "gn:admin1_code":"00",
    "gn:asciiname":"Sipata",
    "gn:cc2":"UZ",
    "gn:country_code":"UZ",
    "gn:dem":209,
    "gn:feature_class":"P",
    "gn:feature_code":"PPL",
    "gn:name":"Sipata",
    "gn:population":0,
    "gn:timezone":"Asia/Samarkand",
    "iso:country":"UZ",
    "name:und_x_variant":[
        "Sepatta",
        "Sipata"
    ],
    "wof:name":"Sipata",
    "wof:placetype":"locality"
},
  "geometry": {"coordinates":[64.09999999999999,39.71667],"type":"Point"}
}