{
  "type": "Feature",
  "properties": {
    "gn:admin1_code":"12",
    "gn:asciiname":"Yuqori Machay",
    "gn:cc2":"UZ",
    "gn:country_code":"UZ",
    "gn:dem":1338,
    "gn:feature_class":"P",
    "gn:feature_code":"PPL",
    "gn:name":"Yuqori Machay",
    "gn:population":0,
    "gn:timezone":"Asia/Samarkand",
    "iso:country":"UZ",
    "name:und_x_variant":[
        "Yukary-Machay",
        "Machay",
        "Yunary-Makay",
        "Yuqori Machay"
    ],
    "wof:name":"Yuqori Machay",
    "wof:placetype":"locality"
},
  "geometry": {"coordinates":[67.07889,38.33611],"type":"Point"}
}