{
  "type": "Feature",
  "properties": {
    "gn:admin1_code":"08",
    "gn:asciiname":"Xalqobod",
    "gn:country_code":"UZ",
    "gn:dem":498,
    "gn:feature_class":"P",
    "gn:feature_code":"PPL",
    "gn:name":"Xalqobod",
    "gn:population":0,
    "gn:timezone":"Asia/Samarkand",
    "iso:country":"UZ",
    "name:und_x_variant":[
        "Khalkabad"
    ],
    "wof:name":"Xalqobod",
    "wof:placetype":"locality"
},
  "geometry": {"coordinates":[66.31659999999999,38.66216],"type":"Point"}
}