{
  "type": "Feature",
  "properties": {
    "gn:admin1_code":"06",
    "gn:asciiname":"Qizilovul",
    "gn:country_code":"UZ",
    "gn:dem":451,
    "gn:feature_class":"P",
    "gn:feature_code":"PPL",
    "gn:name":"Qizilovul",
    "gn:population":0,
    "gn:timezone":"Asia/Tashkent",
    "iso:country":"UZ",
    "name:und_x_variant":[
        "Chapkul\u2019",
        "Kyzylaul"
    ],
    "name:uzb_x_preferred":[
        "Qizilovul"
    ],
    "name:uzb_x_variant":[
        "Qiziltov"
    ],
    "wof:name":"Qizilovul",
    "wof:placetype":"locality"
},
  "geometry": {"coordinates":[72.06693,40.9843],"type":"Point"}
}