{
  "type": "Feature",
  "properties": {
    "gn:admin1_code":"08",
    "gn:admin2_code":"Beshkent",
    "gn:asciiname":"Kurgancha",
    "gn:country_code":"UZ",
    "gn:dem":374,
    "gn:feature_class":"P",
    "gn:feature_code":"PPL",
    "gn:name":"Kurgancha",
    "gn:population":0,
    "gn:timezone":"Asia/Samarkand",
    "iso:country":"UZ",
    "wof:name":"Kurgancha",
    "wof:placetype":"locality"
},
  "geometry": {"coordinates":[65.75095999999999,38.84429],"type":"Point"}
}