{
  "type": "Feature",
  "properties": {
    "gn:admin1_code":"06",
    "gn:asciiname":"Sho`ra",
    "gn:country_code":"UZ",
    "gn:dem":438,
    "gn:feature_class":"P",
    "gn:feature_code":"PPL",
    "gn:name":"Sho\u2018ra",
    "gn:population":0,
    "gn:timezone":"Asia/Tashkent",
    "iso:country":"UZ",
    "name:eng_x_preferred":[
        "Sho\u2018ra"
    ],
    "wof:name":"Sho`ra",
    "wof:placetype":"locality"
},
  "geometry": {"coordinates":[71.73139,41.01428],"type":"Point"}
}