{
  "type": "Feature",
  "properties": {
    "gn:admin1_code":"06",
    "gn:asciiname":"Chorkesar",
    "gn:country_code":"UZ",
    "gn:dem":1237,
    "gn:feature_class":"P",
    "gn:feature_code":"PPL",
    "gn:name":"Chorkesar",
    "gn:population":0,
    "gn:timezone":"Asia/Tashkent",
    "iso:country":"UZ",
    "name:eng_x_preferred":[
        "Chorkesar"
    ],
    "wof:name":"Chorkesar",
    "wof:placetype":"locality"
},
  "geometry": {"coordinates":[70.90541999999998,41.03502],"type":"Point"}
}