{
  "type": "Feature",
  "properties": {
    "gn:admin1_code":"01",
    "gn:asciiname":"Chaqqon-1",
    "gn:country_code":"UZ",
    "gn:dem":451,
    "gn:feature_class":"P",
    "gn:feature_code":"PPL",
    "gn:name":"Chaqqon-1",
    "gn:population":0,
    "gn:timezone":"Asia/Tashkent",
    "iso:country":"UZ",
    "name:rus_x_preferred":[
        "\u0427\u0430\u043a\u043a\u0430\u043d"
    ],
    "name:und_x_variant":[
        "Chakkan"
    ],
    "name:uzb_x_preferred":[
        "Chaqqon-1"
    ],
    "name:uzb_x_variant":[
        "Chaqqon",
        "Chaqqon-Birinchi"
    ],
    "wof:name":"Chaqqon-1",
    "wof:placetype":"locality"
},
  "geometry": {"coordinates":[72.24014,40.81492],"type":"Point"}
}