{
  "type": "Feature",
  "properties": {
    "gn:admin1_code":"12",
    "gn:asciiname":"Navbog`",
    "gn:country_code":"UZ",
    "gn:dem":390,
    "gn:feature_class":"P",
    "gn:feature_code":"PPL",
    "gn:name":"Navbog\u2018",
    "gn:population":0,
    "gn:timezone":"Asia/Samarkand",
    "iso:country":"UZ",
    "name:und_x_variant":[
        "Naubag"
    ],
    "name:uzb_x_preferred":[
        "Navbog\u2018"
    ],
    "wof:name":"Navbog`",
    "wof:placetype":"locality"
},
  "geometry": {"coordinates":[66.98793000000001,37.64531],"type":"Point"}
}