{
  "type": "Feature",
  "properties": {
    "gn:admin1_code":"07",
    "gn:asciiname":"Quruqquduq",
    "gn:country_code":"UZ",
    "gn:dem":223,
    "gn:feature_class":"P",
    "gn:feature_code":"PPL",
    "gn:name":"Quruqquduq",
    "gn:population":0,
    "gn:timezone":"Asia/Samarkand",
    "iso:country":"UZ",
    "wof:name":"Quruqquduq",
    "wof:placetype":"locality"
},
  "geometry": {"coordinates":[63.61351,42.85061],"type":"Point"}
}