{
  "type": "Feature",
  "properties": {
    "gn:admin1_code":"00",
    "gn:asciiname":"Bezergen",
    "gn:cc2":"UZ",
    "gn:country_code":"UZ",
    "gn:dem":131,
    "gn:feature_class":"P",
    "gn:feature_code":"PPL",
    "gn:name":"Bezergen",
    "gn:population":0,
    "gn:timezone":"Asia/Samarkand",
    "iso:country":"UZ",
    "name:und_x_variant":[
        "Bazargen-Tugay",
        "Bezergen"
    ],
    "wof:name":"Bezergen",
    "wof:placetype":"locality"
},
  "geometry": {"coordinates":[61.45,41.31667],"type":"Point"}
}