{
  "type": "Feature",
  "properties": {
    "gn:admin1_code":"03",
    "gn:asciiname":"Bogiston",
    "gn:country_code":"UZ",
    "gn:dem":529,
    "gn:feature_class":"P",
    "gn:feature_code":"PPL",
    "gn:name":"Bogiston",
    "gn:population":0,
    "gn:timezone":"Asia/Tashkent",
    "iso:country":"UZ",
    "name:uzb_x_preferred":[
        "Bogiston"
    ],
    "wof:name":"Bogiston",
    "wof:placetype":"locality"
},
  "geometry": {"coordinates":[71.21120999999999,40.35065],"type":"Point"}
}