{
  "type": "Feature",
  "properties": {
    "gn:admin1_code":"03",
    "gn:asciiname":"Tovush",
    "gn:country_code":"UZ",
    "gn:dem":445,
    "gn:feature_class":"P",
    "gn:feature_code":"PPL",
    "gn:name":"Tovush",
    "gn:population":0,
    "gn:timezone":"Asia/Tashkent",
    "iso:country":"UZ",
    "name:uzb_x_preferred":[
        "Tovush"
    ],
    "wof:name":"Tovush",
    "wof:placetype":"locality"
},
  "geometry": {"coordinates":[70.91119999999999,40.4735],"type":"Point"}
}