{
  "type": "Feature",
  "properties": {
    "gn:admin1_code":"08",
    "gn:asciiname":"Guvalak",
    "gn:country_code":"UZ",
    "gn:dem":375,
    "gn:feature_class":"P",
    "gn:feature_code":"PPL",
    "gn:name":"Guvalak",
    "gn:population":0,
    "gn:timezone":"Asia/Samarkand",
    "iso:country":"UZ",
    "name:und_x_variant":[
        "Gubalyak"
    ],
    "wof:name":"Guvalak",
    "wof:placetype":"locality"
},
  "geometry": {"coordinates":[65.78343000000001,39.04102],"type":"Point"}
}