{
  "type": "Feature",
  "properties": {
    "gn:admin1_code":"10",
    "gn:asciiname":"Tyubeli",
    "gn:country_code":"UZ",
    "gn:dem":849,
    "gn:feature_class":"P",
    "gn:feature_code":"PPL",
    "gn:name":"Tyubeli",
    "gn:population":0,
    "gn:timezone":"Asia/Samarkand",
    "iso:country":"UZ",
    "wof:name":"Tyubeli",
    "wof:placetype":"locality"
},
  "geometry": {"coordinates":[67.15083,39.96222],"type":"Point"}
}