{
  "type": "Feature",
  "properties": {
    "gn:admin1_code":"08",
    "gn:asciiname":"Chimqo`rg`on",
    "gn:country_code":"UZ",
    "gn:dem":464,
    "gn:feature_class":"P",
    "gn:feature_code":"PPL",
    "gn:name":"Chimqo\u2018rg\u2018on",
    "gn:population":0,
    "gn:timezone":"Asia/Samarkand",
    "iso:country":"UZ",
    "name:und_x_variant":[
        "Chimkurgan",
        "Chimk\u016drghon",
        "Chimqo\u2018rg\u2018on"
    ],
    "wof:name":"Chimqo`rg`on",
    "wof:placetype":"locality"
},
  "geometry": {"coordinates":[66.34269,38.93684],"type":"Point"}
}