{
  "type": "Feature",
  "properties": {
    "gn:admin1_code":"14",
    "gn:asciiname":"Uyali",
    "gn:country_code":"UZ",
    "gn:dem":318,
    "gn:feature_class":"P",
    "gn:feature_code":"PPL",
    "gn:name":"Uyali",
    "gn:population":0,
    "gn:timezone":"Asia/Tashkent",
    "iso:country":"UZ",
    "name:und_x_variant":[
        "Komarovka"
    ],
    "name:uzb_x_preferred":[
        "Uyali"
    ],
    "wof:name":"Uyali",
    "wof:placetype":"locality"
},
  "geometry": {"coordinates":[69.11221999999999,40.95611],"type":"Point"}
}