{
  "type": "Feature",
  "properties": {
    "gn:admin1_code":"09",
    "gn:asciiname":"Mevali",
    "gn:country_code":"UZ",
    "gn:dem":60,
    "gn:feature_class":"P",
    "gn:feature_code":"PPL",
    "gn:name":"Mevali",
    "gn:population":0,
    "gn:timezone":"Asia/Samarkand",
    "iso:country":"UZ",
    "wof:name":"Mevali",
    "wof:placetype":"locality"
},
  "geometry": {"coordinates":[60.31667,42.98333],"type":"Point"}
}