{
  "type": "Feature",
  "properties": {
    "gn:admin1_code":"06",
    "gn:asciiname":"Qozoqovul",
    "gn:country_code":"UZ",
    "gn:dem":763,
    "gn:feature_class":"P",
    "gn:feature_code":"PPL",
    "gn:name":"Qozoqovul",
    "gn:population":0,
    "gn:timezone":"Asia/Tashkent",
    "iso:country":"UZ",
    "name:eng_x_preferred":[
        "Qozoqovul"
    ],
    "wof:name":"Qozoqovul",
    "wof:placetype":"locality"
},
  "geometry": {"coordinates":[71.56411999999997,41.13673],"type":"Point"}
}