{
  "type": "Feature",
  "properties": {
    "gn:admin1_code":"03",
    "gn:asciiname":"O`qchi-Dasht",
    "gn:country_code":"UZ",
    "gn:dem":659,
    "gn:feature_class":"P",
    "gn:feature_code":"PPL",
    "gn:name":"O\u2018qchi-Dasht",
    "gn:population":0,
    "gn:timezone":"Asia/Tashkent",
    "iso:country":"UZ",
    "name:und_x_variant":[
        "Okhchi",
        "Ukchi"
    ],
    "name:uzb_x_preferred":[
        "O\u2018qchi-Dasht"
    ],
    "name:uzb_x_variant":[
        "O\u2018qchi"
    ],
    "wof:name":"O`qchi-Dasht",
    "wof:placetype":"locality"
},
  "geometry": {"coordinates":[70.99954,40.33491],"type":"Point"}
}