{
  "type": "Feature",
  "properties": {
    "gn:admin1_code":"00",
    "gn:asciiname":"Karasakal",
    "gn:country_code":"UZ",
    "gn:dem":262,
    "gn:feature_class":"P",
    "gn:feature_code":"PPL",
    "gn:name":"Karasakal",
    "gn:population":0,
    "gn:timezone":"Asia/Tashkent",
    "iso:country":"UZ",
    "wof:name":"Karasakal",
    "wof:placetype":"locality"
},
  "geometry": {"coordinates":[67.86667,40.98333],"type":"Point"}
}