{
  "type": "Feature",
  "properties": {
    "gn:admin1_code":"00",
    "gn:asciiname":"Kommuna",
    "gn:cc2":"UZ",
    "gn:country_code":"UZ",
    "gn:dem":217,
    "gn:feature_class":"P",
    "gn:feature_code":"PPL",
    "gn:name":"Kommuna",
    "gn:population":0,
    "gn:timezone":"Asia/Samarkand",
    "iso:country":"UZ",
    "name:aze_x_preferred":[
        "Bala \u00c7ayl\u0131"
    ],
    "name:ita_x_preferred":[
        "Kommuna"
    ],
    "name:kat_x_preferred":[
        "\u10d9\u10dd\u10db\u10e3\u10dc\u10d0"
    ],
    "name:msa_x_preferred":[
        "Kommuna"
    ],
    "name:und_x_variant":[
        "Kommura"
    ],
    "wof:name":"Kommuna",
    "wof:placetype":"locality"
},
  "geometry": {"coordinates":[64.26666999999999,39.81667],"type":"Point"}
}