{
  "type": "Feature",
  "properties": {
    "gn:admin1_code":"00",
    "gn:asciiname":"Shaytan-Kishlak",
    "gn:country_code":"UZ",
    "gn:dem":711,
    "gn:feature_class":"P",
    "gn:feature_code":"PPL",
    "gn:name":"Shaytan-Kishlak",
    "gn:population":0,
    "gn:timezone":"Asia/Samarkand",
    "iso:country":"UZ",
    "wof:name":"Shaytan-Kishlak",
    "wof:placetype":"locality"
},
  "geometry": {"coordinates":[68.07634,38.50618],"type":"Point"}
}