{
  "type": "Feature",
  "properties": {
    "gn:admin1_code":"01",
    "gn:asciiname":"To`rttol",
    "gn:country_code":"UZ",
    "gn:dem":419,
    "gn:feature_class":"P",
    "gn:feature_code":"PPL",
    "gn:name":"To\u2018rttol",
    "gn:population":0,
    "gn:timezone":"Asia/Tashkent",
    "iso:country":"UZ",
    "name:und_x_variant":[
        "Torttal"
    ],
    "name:uzb_x_preferred":[
        "To\u2018rttol"
    ],
    "wof:name":"To`rttol",
    "wof:placetype":"locality"
},
  "geometry": {"coordinates":[71.83474,40.77815],"type":"Point"}
}