{
  "type": "Feature",
  "properties": {
    "gn:admin1_code":"03",
    "gn:asciiname":"Soybo`yi",
    "gn:country_code":"UZ",
    "gn:dem":690,
    "gn:feature_class":"P",
    "gn:feature_code":"PPL",
    "gn:name":"Soybo\u2018yi",
    "gn:population":0,
    "gn:timezone":"Asia/Tashkent",
    "iso:country":"UZ",
    "name:und_x_variant":[
        "Leningrad"
    ],
    "name:uzb_x_preferred":[
        "Soybo\u2018yi"
    ],
    "wof:name":"Soybo`yi",
    "wof:placetype":"locality"
},
  "geometry": {"coordinates":[71.59456999999998,40.24538],"type":"Point"}
}