{
  "type": "Feature",
  "properties": {
    "gn:country":"UZ",
    "gn:fcode":"PPL",
    "gn:pop":32024,
    "iso:country":"UZ",
    "name:deu_x_preferred":[
        "Quvasoy"
    ],
    "name:eng_x_preferred":[
        "Quvasoy"
    ],
    "name:jpn_x_preferred":[
        "\u30af\u30f4\u30a1\u30b5\u30a4"
    ],
    "name:kik_x_preferred":[
        "Quvasoy"
    ],
    "name:lit_x_preferred":[
        "Kuvasajus"
    ],
    "name:nld_x_preferred":[
        "Quvasoy"
    ],
    "name:pol_x_preferred":[
        "Quvasoy"
    ],
    "name:rus_x_preferred":[
        "\u041a\u0443\u0432\u0430\u0441\u0430\u0439"
    ],
    "name:spa_x_preferred":[
        "Kuvasay"
    ],
    "name:unk_x_variant":[
        "Kuwassai"
    ],
    "name:urd_x_preferred":[
        "\u0642\u0648\u0648\u0627\u0633\u0648\u06cc"
    ],
    "name:uzb_x_preferred":[
        "Quvasoy"
    ],
    "qs:name":"Quvasoy",
    "qs:photos_9r":0,
    "qs:photos_sr":0,
    "qs:pop_sr":"7",
    "wd:wordcount":41,
    "wof:name":"Quvasoy",
    "wof:placetype":"locality",
    "wof:population":32024
},
  "geometry": {"coordinates":[71.97444,40.30222],"type":"Point"}
}