{
  "type": "Feature",
  "properties": {
    "gn:admin1_code":"03",
    "gn:asciiname":"Bo`ston",
    "gn:country_code":"UZ",
    "gn:dem":684,
    "gn:feature_class":"P",
    "gn:feature_code":"PPL",
    "gn:name":"Bo\u2018ston",
    "gn:population":0,
    "gn:timezone":"Asia/Tashkent",
    "iso:country":"UZ",
    "name:und_x_variant":[
        "Bustan"
    ],
    "name:uzb_x_preferred":[
        "Bo\u2018ston"
    ],
    "wof:name":"Bo`ston",
    "wof:placetype":"locality"
},
  "geometry": {"coordinates":[71.80633,40.28659],"type":"Point"}
}