{
  "type": "Feature",
  "properties": {
    "gn:admin1_code":"06",
    "gn:asciiname":"Sherbilak",
    "gn:country_code":"UZ",
    "gn:dem":757,
    "gn:feature_class":"P",
    "gn:feature_code":"PPL",
    "gn:name":"Sherbilak",
    "gn:population":0,
    "gn:timezone":"Asia/Tashkent",
    "iso:country":"UZ",
    "name:eng_x_preferred":[
        "Sho\u2018rbuloq"
    ],
    "name:uzb_x_preferred":[
        "Sherbilak"
    ],
    "wof:name":"Sherbilak",
    "wof:placetype":"locality"
},
  "geometry": {"coordinates":[71.37267,41.08526],"type":"Point"}
}