{
  "type": "Feature",
  "properties": {
    "gn:admin1_code":"08",
    "gn:asciiname":"Yuqori Yangi",
    "gn:country_code":"UZ",
    "gn:dem":513,
    "gn:feature_class":"P",
    "gn:feature_code":"PPL",
    "gn:name":"Yuqori Yangi",
    "gn:population":0,
    "gn:timezone":"Asia/Samarkand",
    "iso:country":"UZ",
    "wof:name":"Yuqori Yangi",
    "wof:placetype":"locality"
},
  "geometry": {"coordinates":[66.46675,38.89379],"type":"Point"}
}