{
  "type": "Feature",
  "properties": {
    "gn:admin1_code":"01",
    "gn:asciiname":"Eshonqishloq",
    "gn:country_code":"UZ",
    "gn:dem":464,
    "gn:feature_class":"P",
    "gn:feature_code":"PPL",
    "gn:name":"Eshonqishloq",
    "gn:population":0,
    "gn:timezone":"Asia/Tashkent",
    "iso:country":"UZ",
    "name:rus_x_preferred":[
        "\u042d\u0448\u0430\u043d"
    ],
    "name:und_x_variant":[
        "Eshan"
    ],
    "name:uzb_x_preferred":[
        "Eshon"
    ],
    "name:uzb_x_variant":[
        "Eshonqishloq"
    ],
    "wof:name":"Eshonqishloq",
    "wof:placetype":"locality"
},
  "geometry": {"coordinates":[72.09923000000001,40.67064],"type":"Point"}
}