{
  "type": "Feature",
  "properties": {
    "gn:admin1_code":"03",
    "gn:asciiname":"Beshtol",
    "gn:country_code":"UZ",
    "gn:dem":468,
    "gn:feature_class":"P",
    "gn:feature_code":"PPL",
    "gn:name":"Beshtol",
    "gn:population":0,
    "gn:timezone":"Asia/Tashkent",
    "iso:country":"UZ",
    "name:uzb_x_preferred":[
        "Beshtol"
    ],
    "wof:name":"Beshtol",
    "wof:placetype":"locality"
},
  "geometry": {"coordinates":[71.77070000000001,40.52474],"type":"Point"}
}