{
  "type": "Feature",
  "properties": {
    "gn:admin1_code":"07",
    "gn:asciiname":"Demisti",
    "gn:country_code":"UZ",
    "gn:dem":240,
    "gn:feature_class":"P",
    "gn:feature_code":"PPL",
    "gn:name":"Demisti",
    "gn:population":0,
    "gn:timezone":"Asia/Samarkand",
    "iso:country":"UZ",
    "wof:name":"Demisti",
    "wof:placetype":"locality"
},
  "geometry": {"coordinates":[64.63333,39.95],"type":"Point"}
}