{
  "type": "Feature",
  "properties": {
    "gn:admin1_code":"06",
    "gn:asciiname":"Qayirma",
    "gn:country_code":"UZ",
    "gn:dem":703,
    "gn:feature_class":"P",
    "gn:feature_code":"PPL",
    "gn:name":"Qayirma",
    "gn:population":0,
    "gn:timezone":"Asia/Tashkent",
    "iso:country":"UZ",
    "name:eng_x_preferred":[
        "Qayirma"
    ],
    "wof:name":"Qayirma",
    "wof:placetype":"locality"
},
  "geometry": {"coordinates":[71.27204999999999,41.03352],"type":"Point"}
}