{
  "type": "Feature",
  "properties": {
    "gn:admin1_code":"16",
    "gn:asciiname":"Qoraqishloq",
    "gn:country_code":"UZ",
    "gn:dem":284,
    "gn:feature_class":"P",
    "gn:feature_code":"PPL",
    "gn:name":"Qoraqishloq",
    "gn:population":0,
    "gn:timezone":"Asia/Tashkent",
    "iso:country":"UZ",
    "name:uzb_x_preferred":[
        "Qoraqishloq"
    ],
    "wof:name":"Qoraqishloq",
    "wof:placetype":"locality"
},
  "geometry": {"coordinates":[68.98718000000001,40.43542],"type":"Point"}
}