{
  "type": "Feature",
  "properties": {
    "gn:admin1_code":"14",
    "gn:asciiname":"Yangiyul Shahri",
    "gn:cc2":"UZ",
    "gn:country_code":"UZ",
    "gn:dem":353,
    "gn:feature_class":"P",
    "gn:feature_code":"PPL",
    "gn:name":"Yangiy\u016dl Shahri",
    "gn:population":0,
    "gn:timezone":"Asia/Tashkent",
    "iso:country":"UZ",
    "name:und_x_variant":[
        "Gorod Yangiyul\u2019",
        "Yangiy\u016dl Shahri"
    ],
    "wof:name":"Yangiyul Shahri",
    "wof:placetype":"locality"
},
  "geometry": {"coordinates":[69.05500000000001,41.11333],"type":"Point"}
}