{
  "type": "Feature",
  "properties": {
    "gn:admin1_code":"00",
    "gn:asciiname":"Baskunchi",
    "gn:cc2":"UZ",
    "gn:country_code":"UZ",
    "gn:dem":1051,
    "gn:feature_class":"P",
    "gn:feature_code":"PPL",
    "gn:name":"Baskunchi",
    "gn:population":0,
    "gn:timezone":"Asia/Urumqi",
    "iso:country":"UZ",
    "name:und_x_variant":[
        "Kyzyl Karaul",
        "Baskunchi"
    ],
    "wof:name":"Baskunchi",
    "wof:placetype":"locality"
},
  "geometry": {"coordinates":[80.38333,44.33333],"type":"Point"}
}