{
  "type": "Feature",
  "properties": {
    "gn:admin1_code":"01",
    "gn:asciiname":"Namuna",
    "gn:country_code":"UZ",
    "gn:dem":474,
    "gn:feature_class":"P",
    "gn:feature_code":"PPL",
    "gn:name":"Namuna",
    "gn:population":0,
    "gn:timezone":"Asia/Tashkent",
    "iso:country":"UZ",
    "name:uzb_x_preferred":[
        "Namuna"
    ],
    "wof:name":"Namuna",
    "wof:placetype":"locality"
},
  "geometry": {"coordinates":[72.19516,40.69441],"type":"Point"}
}