{
  "type": "Feature",
  "properties": {
    "gn:admin1_code":"12",
    "gn:asciiname":"Ozodbuxoro",
    "gn:country_code":"UZ",
    "gn:dem":316,
    "gn:feature_class":"P",
    "gn:feature_code":"PPL",
    "gn:name":"Ozodbuxoro",
    "gn:population":0,
    "gn:timezone":"Asia/Samarkand",
    "iso:country":"UZ",
    "name:uzb_x_preferred":[
        "Ozodbuxoro"
    ],
    "wof:name":"Ozodbuxoro",
    "wof:placetype":"locality"
},
  "geometry": {"coordinates":[67.06625,37.45499],"type":"Point"}
}