{
  "type": "Feature",
  "properties": {
    "gn:admin1_code":"01",
    "gn:asciiname":"Sariosiyo",
    "gn:country_code":"UZ",
    "gn:dem":449,
    "gn:feature_class":"P",
    "gn:feature_code":"PPL",
    "gn:name":"Sariosiyo",
    "gn:population":0,
    "gn:timezone":"Asia/Tashkent",
    "iso:country":"UZ",
    "name:uzb_x_preferred":[
        "Sariosiyo"
    ],
    "wof:name":"Sariosiyo",
    "wof:placetype":"locality"
},
  "geometry": {"coordinates":[72.04536,40.68535],"type":"Point"}
}