{
  "type": "Feature",
  "properties": {
    "gn:admin1_code":"00",
    "gn:asciiname":"Dzhuma-Bazar",
    "gn:country_code":"UZ",
    "gn:dem":191,
    "gn:feature_class":"P",
    "gn:feature_code":"PPL",
    "gn:name":"Dzhuma-Bazar",
    "gn:population":0,
    "gn:timezone":"Asia/Samarkand",
    "iso:country":"UZ",
    "wof:name":"Dzhuma-Bazar",
    "wof:placetype":"locality"
},
  "geometry": {"coordinates":[63.91667,39.41667],"type":"Point"}
}