{
  "type": "Feature",
  "properties": {
    "gn:admin1_code":"12",
    "gn:asciiname":"Qayran",
    "gn:country_code":"UZ",
    "gn:dem":328,
    "gn:feature_class":"P",
    "gn:feature_code":"PPL",
    "gn:name":"Qayran",
    "gn:population":0,
    "gn:timezone":"Asia/Samarkand",
    "iso:country":"UZ",
    "name:und_x_variant":[
        "Kayran"
    ],
    "name:uzb_x_preferred":[
        "Qayran"
    ],
    "wof:name":"Qayran",
    "wof:placetype":"locality"
},
  "geometry": {"coordinates":[67.20971999999999,37.46],"type":"Point"}
}