{
  "type": "Feature",
  "properties": {
    "gn:admin1_code":"16",
    "gn:asciiname":"Yangihayot",
    "gn:country_code":"UZ",
    "gn:dem":276,
    "gn:feature_class":"P",
    "gn:feature_code":"PPL",
    "gn:name":"Yangihayot",
    "gn:population":0,
    "gn:timezone":"Asia/Tashkent",
    "iso:country":"UZ",
    "name:uzb_x_preferred":[
        "Yangihayot"
    ],
    "wof:name":"Yangihayot",
    "wof:placetype":"locality"
},
  "geometry": {"coordinates":[68.92684,40.49306],"type":"Point"}
}