{
  "type": "Feature",
  "properties": {
    "gn:admin1_code":"16",
    "gn:asciiname":"Yangihayot",
    "gn:country_code":"UZ",
    "gn:dem":276,
    "gn:feature_class":"P",
    "gn:feature_code":"PPL",
    "gn:name":"Yangihayot",
    "gn:population":0,
    "gn:timezone":"Asia/Tashkent",
    "iso:country":"UZ",
    "name:fas_x_preferred":[
        "\u06cc\u0646\u06af\u06cc\u200c\u062d\u06cc\u0627\u062a"
    ],
    "name:msa_x_preferred":[
        "Yangihayot"
    ],
    "name:rus_x_preferred":[
        "\u0425\u0430\u0451\u0442\u0438\u043d\u0430\u0432"
    ],
    "name:tgk_x_preferred":[
        "\u042f\u043d\u0433\u0438\u04b3\u0430\u0451\u0442"
    ],
    "name:urd_x_preferred":[
        "\u06cc\u0646\u06af\u06be\u06d2\u0648\u0679"
    ],
    "name:uzb_x_preferred":[
        "Yangihayot"
    ],
    "wof:name":"Yangihayot",
    "wof:placetype":"locality"
},
  "geometry": {"coordinates":[68.92684,40.49306],"type":"Point"}
}