{
  "type": "Feature",
  "properties": {
    "gn:admin1_code":"00",
    "gn:asciiname":"Bakhmal",
    "gn:country_code":"UZ",
    "gn:dem":1365,
    "gn:feature_class":"P",
    "gn:feature_code":"PPL",
    "gn:name":"Bakhmal",
    "gn:population":0,
    "gn:timezone":"Asia/Samarkand",
    "iso:country":"UZ",
    "wof:name":"Bakhmal",
    "wof:placetype":"locality"
},
  "geometry": {"coordinates":[68.01666999999999,39.71667],"type":"Point"}
}