{
  "type": "Feature",
  "properties": {
    "gn:admin1_code":"03",
    "gn:asciiname":"Qorako`l",
    "gn:country_code":"UZ",
    "gn:dem":427,
    "gn:feature_class":"P",
    "gn:feature_code":"PPL",
    "gn:name":"Qorako\u2018l",
    "gn:population":0,
    "gn:timezone":"Asia/Tashkent",
    "iso:country":"UZ",
    "name:rus_x_preferred":[
        "Karakul\u2019"
    ],
    "name:uzb_x_preferred":[
        "Qorako\u2018l"
    ],
    "wof:name":"Qorako`l",
    "wof:placetype":"locality"
},
  "geometry": {"coordinates":[71.16922,40.47135],"type":"Point"}
}