{
  "type": "Feature",
  "properties": {
    "gn:admin1_code":"08",
    "gn:asciiname":"Jinichka",
    "gn:country_code":"UZ",
    "gn:dem":1339,
    "gn:feature_class":"P",
    "gn:feature_code":"PPL",
    "gn:name":"Jinichka",
    "gn:population":0,
    "gn:timezone":"Asia/Samarkand",
    "iso:country":"UZ",
    "name:und_x_variant":[
        "Dzhinichka"
    ],
    "wof:name":"Jinichka",
    "wof:placetype":"locality"
},
  "geometry": {"coordinates":[66.85754,38.31906],"type":"Point"}
}