{
  "type": "Feature",
  "properties": {
    "gn:admin1_code":"14",
    "gn:asciiname":"Pargos",
    "gn:country_code":"UZ",
    "gn:dem":659,
    "gn:feature_class":"P",
    "gn:feature_code":"PPL",
    "gn:name":"Pargos",
    "gn:population":0,
    "gn:timezone":"Asia/Tashkent",
    "iso:country":"UZ",
    "wof:name":"Pargos",
    "wof:placetype":"locality"
},
  "geometry": {"coordinates":[69.68333,41.55],"type":"Point"}
}