{
  "type": "Feature",
  "properties": {
    "gn:admin1_code":"01",
    "gn:asciiname":"Yangiturmush",
    "gn:country_code":"UZ",
    "gn:dem":533,
    "gn:feature_class":"P",
    "gn:feature_code":"PPL",
    "gn:name":"Yangiturmush",
    "gn:population":0,
    "gn:timezone":"Asia/Tashkent",
    "iso:country":"UZ",
    "name:rus_x_preferred":[
        "\u0411\u0430\u0433\u0430\u0440\u0430"
    ],
    "name:und_x_variant":[
        "Bagara"
    ],
    "name:uzb_x_preferred":[
        "Yangiturmush"
    ],
    "wof:name":"Yangiturmush",
    "wof:placetype":"locality"
},
  "geometry": {"coordinates":[72.28426999999998,40.98854],"type":"Point"}
}