{
  "type": "Feature",
  "properties": {
    "gn:admin1_code":"01",
    "gn:asciiname":"Aralxon",
    "gn:country_code":"UZ",
    "gn:dem":422,
    "gn:feature_class":"P",
    "gn:feature_code":"PPL",
    "gn:name":"Aralxon",
    "gn:population":0,
    "gn:timezone":"Asia/Tashkent",
    "iso:country":"UZ",
    "name:und_x_variant":[
        "Aralkhan"
    ],
    "name:uzb_x_preferred":[
        "Aralxon"
    ],
    "name:uzb_x_variant":[
        "Orolxon"
    ],
    "wof:name":"Aralxon",
    "wof:placetype":"locality"
},
  "geometry": {"coordinates":[71.89619999999999,40.83648],"type":"Point"}
}