{
  "type": "Feature",
  "properties": {
    "iso:country":"UZ",
    "name:bel_x_preferred":[
        "\u0411\u0435\u043a\u0430\u0431\u0430\u0434"
    ],
    "name:bul_x_preferred":[
        "\u0411\u0435\u043a\u043e\u0431\u043e\u0434"
    ],
    "name:ceb_x_preferred":[
        "Bekobod"
    ],
    "name:ckb_x_preferred":[
        "\u0628\u06ce\u06a9\u0627\u0628\u0627\u062f"
    ],
    "name:deu_x_preferred":[
        "Bekobod"
    ],
    "name:eng_x_preferred":[
        "Bekabad"
    ],
    "name:epo_x_preferred":[
        "Bekabad"
    ],
    "name:fas_x_preferred":[
        "\u0628\u06cc\u06a9\u200c\u0622\u0628\u0627\u062f\u060c \u0627\u0632\u0628\u06a9\u0633\u062a\u0627\u0646"
    ],
    "name:fas_x_variant":[
        "\u0628\u06cc\u06a9\u200c\u0622\u0628\u0627\u062f"
    ],
    "name:fra_x_preferred":[
        "Bekabad"
    ],
    "name:heb_x_preferred":[
        "\u05d1\u05e7\u05d1\u05d3"
    ],
    "name:hsb_x_preferred":[
        "Bekobod"
    ],
    "name:hun_x_preferred":[
        "Bekobod"
    ],
    "name:hye_x_preferred":[
        "\u0532\u0565\u056f\u0561\u0562\u0561\u0564"
    ],
    "name:ita_x_preferred":[
        "Bekobod"
    ],
    "name:jpn_x_preferred":[
        "\u30d9\u30ab\u30d0\u30fc\u30c9"
    ],
    "name:kaz_x_preferred":[
        "\u0411\u0435\u043a\u0430\u0431\u0430\u0434"
    ],
    "name:kik_x_preferred":[
        "Bekabad"
    ],
    "name:lit_x_preferred":[
        "Bekabadas"
    ],
    "name:nds_x_preferred":[
        "Bekobod"
    ],
    "name:nld_x_preferred":[
        "Bekabad"
    ],
    "name:nob_x_preferred":[
        "Bekabad"
    ],
    "name:nor_x_preferred":[
        "Bekabad"
    ],
    "name:pan_x_preferred":[
        "\u0a2c\u0a47\u0a15\u0a3e\u0a2c\u0a3e\u0a26"
    ],
    "name:pol_x_preferred":[
        "Bekobod"
    ],
    "name:rus_x_preferred":[
        "\u0411\u0435\u043a\u0430\u0431\u0430\u0434"
    ],
    "name:spa_x_preferred":[
        "Bekobod"
    ],
    "name:tat_x_preferred":[
        "\u0411\u04d9\u043a\u0430\u0431\u0430\u0434"
    ],
    "name:tgk_x_preferred":[
        "\u0411\u0435\u043a\u043e\u0431\u043e\u0434"
    ],
    "name:tgl_x_preferred":[
        "Bekobod"
    ],
    "name:tur_x_preferred":[
        "Bekabad"
    ],
    "name:ukr_x_preferred":[
        "\u0411\u0435\u043a\u0430\u0431\u0430\u0434"
    ],
    "name:und_x_variant":[
        "Begovat"
    ],
    "name:urd_x_preferred":[
        "\u0628\u06cc\u06a9 \u0622\u0628\u0627\u062f"
    ],
    "name:uzb_x_preferred":[
        "Bekobod"
    ],
    "name:vmf_x_preferred":[
        "Bekobod"
    ],
    "name:zho_x_preferred":[
        "\u8c9d\u79d1\u535a\u5fb7"
    ],
    "qs:gn_country":"UZ",
    "qs:gn_fcode":"PPL",
    "qs:gn_pop":86259,
    "qs:name":"Bekabad",
    "qs:name_adm0":"Uzbekistan",
    "qs:name_adm1":"Toshkent",
    "qs:photos":0,
    "qs:photos_1k":0,
    "qs:photos_9k":1,
    "qs:photos_9r":1,
    "qs:photos_all":1,
    "qs:photos_sr":0,
    "qs:placetype":"Town",
    "qs:pop_sr":"8",
    "qs:woe_adm0":23424980,
    "wd:wordcount":472,
    "wof:name":"Bekabad",
    "wof:placetype":"locality",
    "wof:population":86259
},
  "geometry": {"coordinates":[69.26972000000001,40.22083],"type":"Point"}
}