{
  "type": "Feature",
  "properties": {
    "gn:admin1_code":"00",
    "gn:asciiname":"Barlas",
    "gn:cc2":"UZ",
    "gn:country_code":"UZ",
    "gn:dem":552,
    "gn:feature_class":"P",
    "gn:feature_code":"PPL",
    "gn:name":"Barlas",
    "gn:population":0,
    "gn:timezone":"Asia/Samarkand",
    "iso:country":"UZ",
    "name:aze_x_preferred":[
        "Barlaslar"
    ],
    "name:bul_x_preferred":[
        "\u0411\u0430\u0440\u043b\u0430\u0441\u0438"
    ],
    "name:cat_x_preferred":[
        "Barles"
    ],
    "name:epo_x_preferred":[
        "Barlas"
    ],
    "name:fas_x_preferred":[
        "\u0628\u0631\u0644\u0627\u0633"
    ],
    "name:fra_x_preferred":[
        "Barlas"
    ],
    "name:ita_x_preferred":[
        "Barlas"
    ],
    "name:jpn_x_preferred":[
        "\u30d0\u30eb\u30e9\u30b9"
    ],
    "name:kaz_x_preferred":[
        "\u0411\u0430\u0440\u043b\u0430\u0441"
    ],
    "name:pnb_x_preferred":[
        "\u0628\u0631\u0644\u0627\u0633"
    ],
    "name:pol_x_preferred":[
        "Bar\u0142asowie"
    ],
    "name:rus_x_preferred":[
        "\u0411\u0430\u0440\u043b\u0430\u0441\u044b"
    ],
    "name:slv_x_preferred":[
        "Barlasi"
    ],
    "name:tam_x_preferred":[
        "\u0baa\u0bb0\u0bcd\u0bb2\u0bbe\u0bb8\u0bcd"
    ],
    "name:tgk_x_preferred":[
        "\u0411\u0430\u0440\u043b\u043e\u0441"
    ],
    "name:tur_x_preferred":[
        "Barlaslar"
    ],
    "name:uig_x_preferred":[
        "\u0628\u0627\u0631\u0644\u0627\u0633 \u0642\u06d5\u0628\u0649\u0644\u0649\u0633\u0649"
    ],
    "name:ukr_x_preferred":[
        "\u0411\u0430\u0440\u043b\u0430\u0441\u0438"
    ],
    "name:und_x_variant":[
        "Barlasch",
        "Barlas"
    ],
    "name:urd_x_preferred":[
        "\u0628\u0631\u0644\u0627\u0633"
    ],
    "name:uzb_x_preferred":[
        "Barlos"
    ],
    "name:zho_x_preferred":[
        "\u5df4\u9b6f\u524c\u601d\u6c0f"
    ],
    "wof:name":"Barlas",
    "wof:placetype":"locality"
},
  "geometry": {"coordinates":[66.61667,40.05],"type":"Point"}
}