{
  "type": "Feature",
  "properties": {
    "gn:admin1_code":"00",
    "gn:asciiname":"Barlas",
    "gn:cc2":"UZ",
    "gn:country_code":"UZ",
    "gn:dem":552,
    "gn:feature_class":"P",
    "gn:feature_code":"PPL",
    "gn:name":"Barlas",
    "gn:population":0,
    "gn:timezone":"Asia/Samarkand",
    "iso:country":"UZ",
    "name:und_x_variant":[
        "Barlasch",
        "Barlas"
    ],
    "wof:name":"Barlas",
    "wof:placetype":"locality"
},
  "geometry": {"coordinates":[66.61667,40.05],"type":"Point"}
}