{
  "type": "Feature",
  "properties": {
    "gn:admin1_code":"06",
    "gn:asciiname":"Sarqamish",
    "gn:country_code":"UZ",
    "gn:dem":782,
    "gn:feature_class":"P",
    "gn:feature_code":"PPL",
    "gn:name":"Sarqamish",
    "gn:population":0,
    "gn:timezone":"Asia/Tashkent",
    "iso:country":"UZ",
    "name:uzb_x_preferred":[
        "Sarqamish"
    ],
    "name:uzb_x_variant":[
        "Sarkamish"
    ],
    "wof:name":"Sarqamish",
    "wof:placetype":"locality"
},
  "geometry": {"coordinates":[71.09848000000002,41.04967],"type":"Point"}
}