{
  "type": "Feature",
  "properties": {
    "gn:admin1_code":"08",
    "gn:asciiname":"Chuqur",
    "gn:country_code":"UZ",
    "gn:dem":477,
    "gn:feature_class":"P",
    "gn:feature_code":"PPL",
    "gn:name":"Chuqur",
    "gn:population":0,
    "gn:timezone":"Asia/Samarkand",
    "iso:country":"UZ",
    "name:azb_x_preferred":[
        "\u0686\u0648\u0642\u0648\u0631"
    ],
    "name:fas_x_preferred":[
        "\u0686\u0648\u0642\u0648\u0631"
    ],
    "name:und_x_variant":[
        "Chukur"
    ],
    "wof:name":"Chuqur",
    "wof:placetype":"locality"
},
  "geometry": {"coordinates":[66.11623,38.62907],"type":"Point"}
}