{
  "type": "Feature",
  "properties": {
    "iso:country":"UZ",
    "name:ara_x_preferred":[
        "\u0642\u0631\u0629 \u0642\u0648\u0644"
    ],
    "name:arz_x_preferred":[
        "\u0642\u0631\u0629 \u0642\u0648\u0644"
    ],
    "name:azb_x_preferred":[
        "\u0642\u0627\u0631\u0627\u06af\u0624\u0644"
    ],
    "name:aze_x_preferred":[
        "Qarag\u00f6l"
    ],
    "name:bul_x_preferred":[
        "\u041a\u0430\u0440\u0430\u043a\u0443\u043b"
    ],
    "name:chv_x_preferred":[
        "\u0425\u0443\u0440\u0430 \u041a\u04f3\u043b\u0115"
    ],
    "name:deu_x_preferred":[
        "Karakul"
    ],
    "name:deu_x_variant":[
        "Qorako\u02bbl"
    ],
    "name:eng_x_preferred":[
        "Qorako\u2018l"
    ],
    "name:fas_x_preferred":[
        "\u0642\u0648\u0631\u0627\u0642\u0648\u06cc"
    ],
    "name:fra_x_preferred":[
        "Karakul"
    ],
    "name:fra_x_variant":[
        "Qorako\u2018l"
    ],
    "name:heb_x_preferred":[
        "\u05e7\u05e8\u05e7\u05d5\u05dc"
    ],
    "name:hsb_x_preferred":[
        "Qorako\u2018l"
    ],
    "name:hye_x_preferred":[
        "\u053f\u0561\u0580\u0561\u056f\u0578\u0582\u056c"
    ],
    "name:ita_x_preferred":[
        "Karakul"
    ],
    "name:ita_x_variant":[
        "Qorako'l"
    ],
    "name:jpn_x_preferred":[
        "\u30ab\u30e9\u30af\u30eb"
    ],
    "name:kaz_x_preferred":[
        "\u049a\u0430\u0440\u0430\u043a\u04e9\u043b"
    ],
    "name:kik_x_preferred":[
        "Qorako\u2018l"
    ],
    "name:lit_x_preferred":[
        "Karakulis"
    ],
    "name:nld_x_preferred":[
        "Qorako\u2018l"
    ],
    "name:pol_x_preferred":[
        "Qorako\u02bbl"
    ],
    "name:por_x_preferred":[
        "Qorako\u2018l"
    ],
    "name:ron_x_preferred":[
        "Karakul"
    ],
    "name:rus_x_preferred":[
        "\u041a\u0430\u0440\u0430\u043a\u0443\u043b\u044c"
    ],
    "name:spa_x_preferred":[
        "Qorako\u2018l"
    ],
    "name:srp_x_preferred":[
        "\u041a\u0430\u0440\u0430\u043a\u0443\u043b"
    ],
    "name:tat_x_preferred":[
        "\u041a\u0430\u0440\u0430\u043a\u04af\u043b"
    ],
    "name:tgk_x_preferred":[
        "\u049a\u0430\u0440\u0430\u043a\u04ef\u043b"
    ],
    "name:tuk_x_preferred":[
        "Garag\u00f6l"
    ],
    "name:tur_x_preferred":[
        "Karag\u00f6l"
    ],
    "name:ukr_x_preferred":[
        "\u041a\u0430\u0440\u0430\u043a\u0443\u043b\u044c"
    ],
    "name:und_x_variant":[
        "Qorak\u016dl"
    ],
    "name:urd_x_preferred":[
        "\u0642\u0631\u06c1 \u0642\u0648\u0644"
    ],
    "name:uzb_x_preferred":[
        "Qorako\u02bbl"
    ],
    "name:zho_x_preferred":[
        "\u5361\u62c9\u5eab\u723e"
    ],
    "qs:gn_country":"UZ",
    "qs:gn_fcode":"PPL",
    "qs:gn_pop":22487,
    "qs:name":"Karakul'",
    "qs:name_adm0":"Uzbekistan",
    "qs:name_adm1":"Bukhoro",
    "qs:photos":0,
    "qs:photos_1k":0,
    "qs:photos_9k":0,
    "qs:photos_9r":0,
    "qs:photos_all":0,
    "qs:photos_sr":0,
    "qs:placetype":"Town",
    "qs:pop_sr":"7",
    "qs:woe_adm0":23424980,
    "wd:wordcount":86,
    "wof:name":"Karakul'",
    "wof:placetype":"locality",
    "wof:population":22487
},
  "geometry": {"coordinates":[63.83333,39.53333],"type":"Point"}
}