{
  "type": "Feature",
  "properties": {
    "gn:admin1_code":"08",
    "gn:asciiname":"Zarbuloq",
    "gn:country_code":"UZ",
    "gn:dem":277,
    "gn:feature_class":"P",
    "gn:feature_code":"PPL",
    "gn:name":"Zarbuloq",
    "gn:population":0,
    "gn:timezone":"Asia/Samarkand",
    "iso:country":"UZ",
    "name:eng_x_preferred":[
        "Zarbuloq"
    ],
    "wof:name":"Zarbuloq",
    "wof:placetype":"locality"
},
  "geometry": {"coordinates":[65.17946999999999,39.44108],"type":"Point"}
}