{
  "type": "Feature",
  "properties": {
    "gn:admin1_code":"03",
    "gn:asciiname":"Tuman",
    "gn:country_code":"UZ",
    "gn:dem":398,
    "gn:feature_class":"P",
    "gn:feature_code":"PPL",
    "gn:name":"Tuman",
    "gn:population":0,
    "gn:timezone":"Asia/Tashkent",
    "iso:country":"UZ",
    "name:uzb_x_preferred":[
        "Tuman"
    ],
    "wof:name":"Tuman",
    "wof:placetype":"locality"
},
  "geometry": {"coordinates":[71.11256,40.58917],"type":"Point"}
}