{
  "type": "Feature",
  "properties": {
    "gn:admin1_code":"01",
    "gn:asciiname":"Shilagay",
    "gn:country_code":"UZ",
    "gn:dem":520,
    "gn:feature_class":"P",
    "gn:feature_code":"PPL",
    "gn:name":"Shilagay",
    "gn:population":0,
    "gn:timezone":"Asia/Tashkent",
    "iso:country":"UZ",
    "name:uzb_x_preferred":[
        "Shilagay"
    ],
    "wof:name":"Shilagay",
    "wof:placetype":"locality"
},
  "geometry": {"coordinates":[72.43482,40.98155],"type":"Point"}
}