{
  "type": "Feature",
  "properties": {
    "gn:admin1_code":"03",
    "gn:asciiname":"Dashtpandigan",
    "gn:country_code":"UZ",
    "gn:dem":450,
    "gn:feature_class":"P",
    "gn:feature_code":"PPL",
    "gn:name":"Dashtpandigan",
    "gn:population":0,
    "gn:timezone":"Asia/Tashkent",
    "iso:country":"UZ",
    "name:uzb_x_preferred":[
        "Dashtpandigan"
    ],
    "wof:name":"Dashtpandigan",
    "wof:placetype":"locality"
},
  "geometry": {"coordinates":[71.22036,40.38711],"type":"Point"}
}