{
  "type": "Feature",
  "properties": {
    "gn:admin1_code":"12",
    "gn:asciiname":"Xomkan",
    "gn:country_code":"UZ",
    "gn:dem":429,
    "gn:feature_class":"P",
    "gn:feature_code":"PPL",
    "gn:name":"Xomkan",
    "gn:population":0,
    "gn:timezone":"Asia/Samarkand",
    "iso:country":"UZ",
    "name:uzb_x_preferred":[
        "Xomkan"
    ],
    "wof:name":"Xomkan",
    "wof:placetype":"locality"
},
  "geometry": {"coordinates":[67.3472,37.78649],"type":"Point"}
}