{
  "type": "Feature",
  "properties": {
    "gn:admin1_code":"12",
    "gn:asciiname":"Xurvatan",
    "gn:country_code":"UZ",
    "gn:dem":1503,
    "gn:feature_class":"P",
    "gn:feature_code":"PPL",
    "gn:name":"Xurvatan",
    "gn:population":0,
    "gn:timezone":"Asia/Samarkand",
    "iso:country":"UZ",
    "name:und_x_variant":[
        "Khurnatan",
        "Khurvatan"
    ],
    "name:uzb_x_preferred":[
        "Xurvatan"
    ],
    "wof:name":"Xurvatan",
    "wof:placetype":"locality"
},
  "geometry": {"coordinates":[67.79694000000001,38.76111],"type":"Point"}
}