{
  "type": "Feature",
  "properties": {
    "gn:admin1_code":"06",
    "gn:asciiname":"Toshloq",
    "gn:country_code":"UZ",
    "gn:dem":519,
    "gn:feature_class":"P",
    "gn:feature_code":"PPL",
    "gn:name":"Toshloq",
    "gn:population":0,
    "gn:timezone":"Asia/Tashkent",
    "iso:country":"UZ",
    "name:ceb_x_preferred":[
        "Toshloq"
    ],
    "name:deu_x_preferred":[
        "Toshloq"
    ],
    "name:eng_x_preferred":[
        "Toshloq"
    ],
    "name:kik_x_preferred":[
        "Toshloq"
    ],
    "name:kir_x_preferred":[
        "Toshloq"
    ],
    "name:pol_x_preferred":[
        "Toshloq"
    ],
    "name:rus_x_preferred":[
        "\u0422\u0430\u0448\u043b\u0430\u043a"
    ],
    "name:tur_x_preferred":[
        "Ta\u015flak"
    ],
    "name:urd_x_preferred":[
        "\u062a\u0627\u0634\u0644\u0627\u0642"
    ],
    "name:uzb_x_preferred":[
        "Toshloq"
    ],
    "wof:name":"Toshloq",
    "wof:placetype":"locality"
},
  "geometry": {"coordinates":[71.96680000000001,41.09528],"type":"Point"}
}