{
  "type": "Feature",
  "properties": {
    "gn:admin1_code":"07",
    "gn:asciiname":"Tuzbulak",
    "gn:country_code":"UZ",
    "gn:dem":87,
    "gn:feature_class":"P",
    "gn:feature_code":"PPL",
    "gn:name":"Tuzbulak",
    "gn:population":0,
    "gn:timezone":"Asia/Samarkand",
    "iso:country":"UZ",
    "wof:name":"Tuzbulak",
    "wof:placetype":"locality"
},
  "geometry": {"coordinates":[63.38333000000001,41.88333],"type":"Point"}
}