{
  "type": "Feature",
  "properties": {
    "gn:admin1_code":"03",
    "gn:asciiname":"Dashtmahalla",
    "gn:country_code":"UZ",
    "gn:dem":451,
    "gn:feature_class":"P",
    "gn:feature_code":"PPL",
    "gn:name":"Dashtmahalla",
    "gn:population":0,
    "gn:timezone":"Asia/Tashkent",
    "iso:country":"UZ",
    "name:und_x_variant":[
        "Dasht"
    ],
    "name:uzb_x_preferred":[
        "Dashtmahalla"
    ],
    "wof:name":"Dashtmahalla",
    "wof:placetype":"locality"
},
  "geometry": {"coordinates":[70.84833,40.39867],"type":"Point"}
}