{
  "type": "Feature",
  "properties": {
    "gn:admin1_code":"09",
    "gn:asciiname":"Uten",
    "gn:country_code":"UZ",
    "gn:dem":66,
    "gn:feature_class":"P",
    "gn:feature_code":"PPL",
    "gn:name":"Uten",
    "gn:population":0,
    "gn:timezone":"Asia/Samarkand",
    "iso:country":"UZ",
    "wof:name":"Uten",
    "wof:placetype":"locality"
},
  "geometry": {"coordinates":[59.65565,42.85206],"type":"Point"}
}