{
  "type": "Feature",
  "properties": {
    "gn:admin1_code":"03",
    "gn:asciiname":"Jurgun",
    "gn:country_code":"UZ",
    "gn:dem":367,
    "gn:feature_class":"P",
    "gn:feature_code":"PPL",
    "gn:name":"Jurgun",
    "gn:population":0,
    "gn:timezone":"Asia/Tashkent",
    "iso:country":"UZ",
    "name:und_x_variant":[
        "Kapasaray",
        "Jurghun",
        "Jurg\u2018un"
    ],
    "name:uzb_x_preferred":[
        "Jurgun"
    ],
    "wof:name":"Jurgun",
    "wof:placetype":"locality"
},
  "geometry": {"coordinates":[70.76439000000001,40.65927],"type":"Point"}
}