{
  "type": "Feature",
  "properties": {
    "gn:admin1_code":"12",
    "gn:asciiname":"Yangiobod",
    "gn:country_code":"UZ",
    "gn:dem":567,
    "gn:feature_class":"P",
    "gn:feature_code":"PPL",
    "gn:name":"Yangiobod",
    "gn:population":0,
    "gn:timezone":"Asia/Samarkand",
    "iso:country":"UZ",
    "name:uzb_x_preferred":[
        "Yangiobod"
    ],
    "wof:name":"Yangiobod",
    "wof:placetype":"locality"
},
  "geometry": {"coordinates":[68.27468,37.98756],"type":"Point"}
}