{
  "type": "Feature",
  "properties": {
    "gn:admin1_code":"09",
    "gn:asciiname":"Qozoqovul",
    "gn:country_code":"UZ",
    "gn:dem":71,
    "gn:feature_class":"P",
    "gn:feature_code":"PPL",
    "gn:name":"Qozoqovul",
    "gn:population":0,
    "gn:timezone":"Asia/Samarkand",
    "iso:country":"UZ",
    "wof:name":"Qozoqovul",
    "wof:placetype":"locality"
},
  "geometry": {"coordinates":[59.71675,42.57592],"type":"Point"}
}