{
  "type": "Feature",
  "properties": {
    "gn:admin1_code":"06",
    "gn:asciiname":"To`da",
    "gn:country_code":"UZ",
    "gn:dem":413,
    "gn:feature_class":"P",
    "gn:feature_code":"PPL",
    "gn:name":"To\u2018da",
    "gn:population":0,
    "gn:timezone":"Asia/Tashkent",
    "iso:country":"UZ",
    "name:eng_x_preferred":[
        "To\u2018da"
    ],
    "wof:name":"To`da",
    "wof:placetype":"locality"
},
  "geometry": {"coordinates":[71.22354,40.87198],"type":"Point"}
}