{
  "type": "Feature",
  "properties": {
    "gn:admin1_code":"00",
    "gn:asciiname":"Kul'dzhoy-Bar",
    "gn:country_code":"UZ",
    "gn:dem":249,
    "gn:feature_class":"P",
    "gn:feature_code":"PPL",
    "gn:name":"Kul\u2019dzhoy-Bar",
    "gn:population":0,
    "gn:timezone":"Asia/Samarkand",
    "iso:country":"UZ",
    "name:rus_x_preferred":[
        "Kul\u2019dzhoy-Bar"
    ],
    "wof:name":"Kul'dzhoy-Bar",
    "wof:placetype":"locality"
},
  "geometry": {"coordinates":[64.58333,40.08333],"type":"Point"}
}