{
  "type": "Feature",
  "properties": {
    "gn:admin1_code":"12",
    "gn:asciiname":"Naushakhar",
    "gn:country_code":"UZ",
    "gn:dem":302,
    "gn:feature_class":"P",
    "gn:feature_code":"PPL",
    "gn:name":"Naushakhar",
    "gn:population":0,
    "gn:timezone":"Asia/Samarkand",
    "iso:country":"UZ",
    "wof:name":"Naushakhar",
    "wof:placetype":"locality"
},
  "geometry": {"coordinates":[67.09806,37.38222],"type":"Point"}
}