{
  "type": "Feature",
  "properties": {
    "gn:admin1_code":"03",
    "gn:asciiname":"Oltiqush",
    "gn:country_code":"UZ",
    "gn:dem":389,
    "gn:feature_class":"P",
    "gn:feature_code":"PPL",
    "gn:name":"Oltiqush",
    "gn:population":0,
    "gn:timezone":"Asia/Tashkent",
    "iso:country":"UZ",
    "name:uzb_x_preferred":[
        "Oltiqush"
    ],
    "wof:name":"Oltiqush",
    "wof:placetype":"locality"
},
  "geometry": {"coordinates":[70.89684,40.59592],"type":"Point"}
}