{
  "type": "Feature",
  "properties": {
    "gn:admin1_code":"01",
    "gn:asciiname":"Paynab",
    "gn:country_code":"UZ",
    "gn:dem":529,
    "gn:feature_class":"P",
    "gn:feature_code":"PPL",
    "gn:name":"Paynab",
    "gn:population":0,
    "gn:timezone":"Asia/Tashkent",
    "iso:country":"UZ",
    "name:uzb_x_preferred":[
        "Paynab"
    ],
    "wof:name":"Paynab",
    "wof:placetype":"locality"
},
  "geometry": {"coordinates":[72.53355000000001,40.92364],"type":"Point"}
}