{
  "type": "Feature",
  "properties": {
    "gn:admin1_code":"01",
    "gn:asciiname":"Cho`ntak",
    "gn:country_code":"UZ",
    "gn:dem":510,
    "gn:feature_class":"P",
    "gn:feature_code":"PPL",
    "gn:name":"Cho\u2018ntak",
    "gn:population":0,
    "gn:timezone":"Asia/Tashkent",
    "iso:country":"UZ",
    "name:rus_x_preferred":[
        "\u0427\u0443\u043d\u0442\u0430\u043a"
    ],
    "name:und_x_variant":[
        "Chuntak"
    ],
    "name:uzb_x_preferred":[
        "Cho\u2018ntak"
    ],
    "wof:name":"Cho`ntak",
    "wof:placetype":"locality"
},
  "geometry": {"coordinates":[72.25424,40.63644],"type":"Point"}
}