{
  "type": "Feature",
  "properties": {
    "gn:admin1_code":"07",
    "gn:asciiname":"Tutak",
    "gn:country_code":"UZ",
    "gn:dem":1029,
    "gn:feature_class":"P",
    "gn:feature_code":"PPL",
    "gn:name":"Tutak",
    "gn:population":0,
    "gn:timezone":"Asia/Samarkand",
    "iso:country":"UZ",
    "name:und_x_variant":[
        "Tutek"
    ],
    "wof:name":"Tutak",
    "wof:placetype":"locality"
},
  "geometry": {"coordinates":[65.98968000000001,40.42261],"type":"Point"}
}