{
  "type": "Feature",
  "properties": {
    "gn:admin1_code":"03",
    "gn:asciiname":"Yuqorimahalla",
    "gn:country_code":"UZ",
    "gn:dem":460,
    "gn:feature_class":"P",
    "gn:feature_code":"PPL",
    "gn:name":"Yuqorimahalla",
    "gn:population":0,
    "gn:timezone":"Asia/Tashkent",
    "iso:country":"UZ",
    "name:und_x_variant":[
        "Yukarymakhalla"
    ],
    "name:uzb_x_preferred":[
        "Yuqorimahalla"
    ],
    "wof:name":"Yuqorimahalla",
    "wof:placetype":"locality"
},
  "geometry": {"coordinates":[71.42663,40.37253],"type":"Point"}
}