{
  "type": "Feature",
  "properties": {
    "gn:admin1_code":"14",
    "gn:asciiname":"Kensay",
    "gn:country_code":"UZ",
    "gn:dem":504,
    "gn:feature_class":"P",
    "gn:feature_code":"PPL",
    "gn:name":"Kensay",
    "gn:population":0,
    "gn:timezone":"Asia/Tashkent",
    "iso:country":"UZ",
    "wof:name":"Kensay",
    "wof:placetype":"locality"
},
  "geometry": {"coordinates":[69.28556,41.42889],"type":"Point"}
}