{
  "type": "Feature",
  "properties": {
    "gn:admin1_code":"06",
    "gn:asciiname":"Balandko`prik",
    "gn:country_code":"UZ",
    "gn:dem":475,
    "gn:feature_class":"P",
    "gn:feature_code":"PPL",
    "gn:name":"Balandko\u2018prik",
    "gn:population":0,
    "gn:timezone":"Asia/Tashkent",
    "iso:country":"UZ",
    "name:eng_x_preferred":[
        "Balandko\u2018prik"
    ],
    "name:und_x_variant":[
        "Balandkuprik"
    ],
    "name:uzb_x_preferred":[
        "Balandko\u2018prik"
    ],
    "wof:name":"Balandko`prik",
    "wof:placetype":"locality"
},
  "geometry": {"coordinates":[72.12338000000003,41.03075],"type":"Point"}
}