{
  "type": "Feature",
  "properties": {
    "gn:admin1_code":"12",
    "gn:asciiname":"Oybarik",
    "gn:country_code":"UZ",
    "gn:dem":940,
    "gn:feature_class":"P",
    "gn:feature_code":"PPL",
    "gn:name":"Oybarik",
    "gn:population":0,
    "gn:timezone":"Asia/Samarkand",
    "iso:country":"UZ",
    "name:und_x_variant":[
        "Oy-Borik",
        "Oybarik"
    ],
    "wof:name":"Oybarik",
    "wof:placetype":"locality"
},
  "geometry": {"coordinates":[67.73517,38.33134],"type":"Point"}
}