{
  "type": "Feature",
  "properties": {
    "gn:admin1_code":"16",
    "gn:asciiname":"Usmonobod",
    "gn:country_code":"UZ",
    "gn:dem":284,
    "gn:feature_class":"P",
    "gn:feature_code":"PPL",
    "gn:name":"Usmonobod",
    "gn:population":0,
    "gn:timezone":"Asia/Tashkent",
    "iso:country":"UZ",
    "name:und_x_variant":[
        "Sovkhoz Imeni Rutskogo"
    ],
    "name:uzb_x_preferred":[
        "Usmonobod"
    ],
    "wof:name":"Usmonobod",
    "wof:placetype":"locality"
},
  "geometry": {"coordinates":[68.88696999999999,40.40595],"type":"Point"}
}