{
  "type": "Feature",
  "properties": {
    "gn:admin1_code":"07",
    "gn:asciiname":"Sarmych",
    "gn:country_code":"UZ",
    "gn:dem":657,
    "gn:feature_class":"P",
    "gn:feature_code":"PPL",
    "gn:name":"Sarmych",
    "gn:population":0,
    "gn:timezone":"Asia/Samarkand",
    "iso:country":"UZ",
    "name:und_x_variant":[
        "Sarmich",
        "Sarmych"
    ],
    "wof:name":"Sarmych",
    "wof:placetype":"locality"
},
  "geometry": {"coordinates":[65.59999999999999,40.28333],"type":"Point"}
}