{
  "type": "Feature",
  "properties": {
    "gn:admin1_code":"06",
    "gn:asciiname":"Axsi",
    "gn:country_code":"UZ",
    "gn:dem":425,
    "gn:feature_class":"P",
    "gn:feature_code":"PPL",
    "gn:name":"Axsi",
    "gn:population":0,
    "gn:timezone":"Asia/Tashkent",
    "iso:country":"UZ",
    "name:eng_x_preferred":[
        "Axsi"
    ],
    "name:und_x_variant":[
        "Akhsi"
    ],
    "wof:name":"Axsi",
    "wof:placetype":"locality"
},
  "geometry": {"coordinates":[71.85598,40.98196],"type":"Point"}
}