{
  "type": "Feature",
  "properties": {
    "gn:admin1_code":"00",
    "gn:asciiname":"Kukun",
    "gn:country_code":"UZ",
    "gn:dem":232,
    "gn:feature_class":"P",
    "gn:feature_code":"PPL",
    "gn:name":"Kukun",
    "gn:population":0,
    "gn:timezone":"Asia/Samarkand",
    "iso:country":"UZ",
    "wof:name":"Kukun",
    "wof:placetype":"locality"
},
  "geometry": {"coordinates":[64.46666999999999,39.98333],"type":"Point"}
}