{
  "type": "Feature",
  "properties": {
    "gn:country":"UZ",
    "gn:fcode":"PPL",
    "gn:population":11446,
    "iso:country":"UZ",
    "name:ara_x_preferred":[
        "\u063a\u0632\u0644\u064a"
    ],
    "name:aze_x_preferred":[
        "G\u0259zli"
    ],
    "name:deu_x_preferred":[
        "Gazli"
    ],
    "name:eng_x_preferred":[
        "Gazli"
    ],
    "name:fas_x_preferred":[
        "\u06af\u0627\u0632\u0644\u06cc"
    ],
    "name:hsb_x_preferred":[
        "Gazli"
    ],
    "name:jpn_x_preferred":[
        "\u30ac\u30ba\u30ea"
    ],
    "name:lit_x_preferred":[
        "Gazli"
    ],
    "name:nld_x_preferred":[
        "Gazli"
    ],
    "name:pol_x_preferred":[
        "Gazli"
    ],
    "name:rus_x_preferred":[
        "\u0413\u0430\u0437\u043b\u0438"
    ],
    "name:spa_x_preferred":[
        "Gazli"
    ],
    "name:tat_x_preferred":[
        "\u0413\u0430\u0437\u043b\u044b"
    ],
    "name:tgk_x_preferred":[
        "\u0413\u0430\u0437\u043b\u04e3"
    ],
    "name:ukr_x_preferred":[
        "\u0490\u0430\u0437\u043b\u0456"
    ],
    "name:uzb_x_preferred":[
        "Gazli"
    ],
    "qs_pg:aaroncc":"UZ",
    "qs_pg:gn_country":"UZ",
    "qs_pg:gn_fcode":"PPL",
    "qs_pg:gn_pop":11446,
    "qs_pg:name":"Gazli",
    "qs_pg:photos_9r":0,
    "qs_pg:photos_sr":0,
    "qs_pg:pop_sr":6,
    "qs_pg:qs_pg_placetype":"locality",
    "wof:name":"Gazli",
    "wof:placetype":"locality",
    "wof:population":11446
},
  "geometry": {"coordinates":[63.45,40.13333],"type":"Point"}
}