{
  "type": "Feature",
  "properties": {
    "gn:admin1_code":"14",
    "gn:asciiname":"Gul",
    "gn:country_code":"UZ",
    "gn:dem":264,
    "gn:feature_class":"P",
    "gn:feature_code":"PPL",
    "gn:name":"Gul",
    "gn:population":0,
    "gn:timezone":"Asia/Tashkent",
    "iso:country":"UZ",
    "name:aze_x_preferred":[
        "G\u00fcl"
    ],
    "name:ceb_x_preferred":[
        "Gul"
    ],
    "name:deu_x_preferred":[
        "Gul"
    ],
    "name:epo_x_preferred":[
        "Gul"
    ],
    "name:fas_x_preferred":[
        "\u06af\u0644"
    ],
    "name:rus_x_preferred":[
        "\u0413\u044e\u043b\u044c"
    ],
    "name:swe_x_preferred":[
        "Gul"
    ],
    "name:uzb_x_preferred":[
        "Gul"
    ],
    "wof:name":"Gul",
    "wof:placetype":"locality"
},
  "geometry": {"coordinates":[68.79314000000001,40.85099],"type":"Point"}
}