{
  "type": "Feature",
  "properties": {
    "gn:admin1_code":"01",
    "gn:asciiname":"Qaqirchek",
    "gn:country_code":"UZ",
    "gn:dem":426,
    "gn:feature_class":"P",
    "gn:feature_code":"PPL",
    "gn:name":"Qaqirchek",
    "gn:population":0,
    "gn:timezone":"Asia/Tashkent",
    "iso:country":"UZ",
    "name:uzb_x_preferred":[
        "Qaqirchek"
    ],
    "wof:name":"Qaqirchek",
    "wof:placetype":"locality"
},
  "geometry": {"coordinates":[71.89605,40.792],"type":"Point"}
}