{
  "type": "Feature",
  "properties": {
    "gn:admin1_code":"03",
    "gn:asciiname":"To`da",
    "gn:country_code":"UZ",
    "gn:dem":460,
    "gn:feature_class":"P",
    "gn:feature_code":"PPL",
    "gn:name":"To\u2018da",
    "gn:population":0,
    "gn:timezone":"Asia/Tashkent",
    "iso:country":"UZ",
    "name:und_x_variant":[
        "Tuda"
    ],
    "name:uzb_x_preferred":[
        "To\u2018da"
    ],
    "wof:name":"To`da",
    "wof:placetype":"locality"
},
  "geometry": {"coordinates":[71.30233,40.37236],"type":"Point"}
}