{
  "type": "Feature",
  "properties": {
    "gn:admin1_code":"01",
    "gn:asciiname":"Shurbulak",
    "gn:country_code":"UZ",
    "gn:dem":543,
    "gn:feature_class":"P",
    "gn:feature_code":"PPL",
    "gn:name":"Shurbulak",
    "gn:population":0,
    "gn:timezone":"Asia/Tashkent",
    "iso:country":"UZ",
    "name:rus_x_preferred":[
        "\u0428\u0443\u0440\u0431\u0443\u043b\u0430\u043a"
    ],
    "name:und_x_variant":[
        "\u0428\u0443\u0440\u0431\u0443\u043b\u0430\u043a"
    ],
    "wof:name":"Shurbulak",
    "wof:placetype":"locality"
},
  "geometry": {"coordinates":[72.37539,40.74544],"type":"Point"}
}