{
  "type": "Feature",
  "properties": {
    "gn:admin1_code":"14",
    "gn:asciiname":"Qoramozor",
    "gn:country_code":"UZ",
    "gn:dem":333,
    "gn:feature_class":"P",
    "gn:feature_code":"PPL",
    "gn:name":"Qoramozor",
    "gn:population":0,
    "gn:timezone":"Asia/Tashkent",
    "iso:country":"UZ",
    "name:uzb_x_preferred":[
        "Qoramozor"
    ],
    "wof:name":"Qoramozor",
    "wof:placetype":"locality"
},
  "geometry": {"coordinates":[69.15494,40.81108],"type":"Point"}
}