{
  "type": "Feature",
  "properties": {
    "gn:admin1_code":"08",
    "gn:asciiname":"Kichik Do`stberdi",
    "gn:country_code":"UZ",
    "gn:dem":499,
    "gn:feature_class":"P",
    "gn:feature_code":"PPL",
    "gn:name":"Kichik Do\u2018stberdi",
    "gn:population":0,
    "gn:timezone":"Asia/Samarkand",
    "iso:country":"UZ",
    "name:und_x_variant":[
        "Kichik Do\u2018stberdi",
        "Dos-Berdy"
    ],
    "wof:name":"Kichik Do`stberdi",
    "wof:placetype":"locality"
},
  "geometry": {"coordinates":[66.38379,38.99664],"type":"Point"}
}