{
  "type": "Feature",
  "properties": {
    "gn:admin1_code":"08",
    "gn:asciiname":"Duyul'",
    "gn:country_code":"UZ",
    "gn:dem":536,
    "gn:feature_class":"P",
    "gn:feature_code":"PPL",
    "gn:name":"Duyul\u2019",
    "gn:population":0,
    "gn:timezone":"Asia/Samarkand",
    "iso:country":"UZ",
    "name:rus_x_preferred":[
        "Duyul\u2019"
    ],
    "wof:name":"Duyul'",
    "wof:placetype":"locality"
},
  "geometry": {"coordinates":[66.56116999999999,38.91231],"type":"Point"}
}