{
  "type": "Feature",
  "properties": {
    "gn:admin1_code":"08",
    "gn:asciiname":"Beshterak",
    "gn:country_code":"UZ",
    "gn:dem":589,
    "gn:feature_class":"P",
    "gn:feature_code":"PPL",
    "gn:name":"Beshterak",
    "gn:population":0,
    "gn:timezone":"Asia/Samarkand",
    "iso:country":"UZ",
    "wof:name":"Beshterak",
    "wof:placetype":"locality"
},
  "geometry": {"coordinates":[66.76886999999999,39.11566],"type":"Point"}
}