{
  "type": "Feature",
  "properties": {
    "gn:admin1_code":"03",
    "gn:asciiname":"Qorakaltak",
    "gn:country_code":"UZ",
    "gn:dem":435,
    "gn:feature_class":"P",
    "gn:feature_code":"PPL",
    "gn:name":"Qorakaltak",
    "gn:population":0,
    "gn:timezone":"Asia/Tashkent",
    "iso:country":"UZ",
    "name:uzb_x_preferred":[
        "Qorakaltak"
    ],
    "wof:name":"Qorakaltak",
    "wof:placetype":"locality"
},
  "geometry": {"coordinates":[71.58967,40.53248],"type":"Point"}
}