{
  "type": "Feature",
  "properties": {
    "gn:admin1_code":"08",
    "gn:asciiname":"Darxon",
    "gn:country_code":"UZ",
    "gn:dem":1053,
    "gn:feature_class":"P",
    "gn:feature_code":"PPL",
    "gn:name":"Darxon",
    "gn:population":0,
    "gn:timezone":"Asia/Samarkand",
    "iso:country":"UZ",
    "name:deu_x_preferred":[
        "Darxon"
    ],
    "wof:name":"Darxon",
    "wof:placetype":"locality"
},
  "geometry": {"coordinates":[66.57987,38.50537],"type":"Point"}
}