{
  "type": "Feature",
  "properties": {
    "gn:admin1_code":"16",
    "gn:asciiname":"Petropavlovskiy",
    "gn:country_code":"UZ",
    "gn:dem":276,
    "gn:feature_class":"P",
    "gn:feature_code":"PPL",
    "gn:name":"Petropavlovskiy",
    "gn:population":0,
    "gn:timezone":"Asia/Tashkent",
    "iso:country":"UZ",
    "name:und_x_variant":[
        "Petropavlovski",
        "Petropavlovskiy"
    ],
    "wof:name":"Petropavlovskiy",
    "wof:placetype":"locality"
},
  "geometry": {"coordinates":[69.03333000000001,40.53333],"type":"Point"}
}