{
  "type": "Feature",
  "properties": {
    "gn:admin1_code":"07",
    "gn:asciiname":"Toshrabot",
    "gn:country_code":"UZ",
    "gn:dem":348,
    "gn:feature_class":"P",
    "gn:feature_code":"PPL",
    "gn:name":"Toshrabot",
    "gn:population":0,
    "gn:timezone":"Asia/Samarkand",
    "iso:country":"UZ",
    "wof:name":"Toshrabot",
    "wof:placetype":"locality"
},
  "geometry": {"coordinates":[65.39331,40.21129000000001],"type":"Point"}
}