{
  "type": "Feature",
  "properties": {
    "gn:admin1_code":"14",
    "gn:asciiname":"Yangi Isloxot",
    "gn:country_code":"UZ",
    "gn:dem":301,
    "gn:feature_class":"P",
    "gn:feature_code":"PPL",
    "gn:name":"Yangi Isloxot",
    "gn:population":0,
    "gn:timezone":"Asia/Tashkent",
    "iso:country":"UZ",
    "name:uzb_x_preferred":[
        "Yangi Isloxot"
    ],
    "wof:name":"Yangi Isloxot",
    "wof:placetype":"locality"
},
  "geometry": {"coordinates":[68.88829,40.96542],"type":"Point"}
}