{
  "type": "Feature",
  "properties": {
    "gn:admin1_code":"00",
    "gn:asciiname":"Turkmen",
    "gn:country_code":"UZ",
    "gn:dem":679,
    "gn:feature_class":"P",
    "gn:feature_code":"PPL",
    "gn:name":"Turkmen",
    "gn:population":0,
    "gn:timezone":"Asia/Samarkand",
    "iso:country":"UZ",
    "name:ara_x_preferred":[
        "\u062a\u0631\u0643\u0645\u0627\u0646"
    ],
    "name:fas_x_preferred":[
        "\u062a\u0631\u06a9\u0645\u0646"
    ],
    "name:fin_x_preferred":[
        "Turkmeeni"
    ],
    "name:ita_x_preferred":[
        "Turkmeno"
    ],
    "name:kor_x_preferred":[
        "\ud22c\ub974\ud06c\uba58"
    ],
    "name:kur_x_preferred":[
        "Turkmen"
    ],
    "name:mal_x_preferred":[
        "\u0d1f\u0d7c\u0d15\u0d4d\u0d2e\u0d46\u0d7b"
    ],
    "name:por_x_preferred":[
        "Turcomano"
    ],
    "name:spa_x_preferred":[
        "Turcomano"
    ],
    "name:zho_x_preferred":[
        "\u571f\u5e93\u66fc"
    ],
    "wof:name":"Turkmen",
    "wof:placetype":"locality"
},
  "geometry": {"coordinates":[66.81667,40.18333],"type":"Point"}
}