{
  "type": "Feature",
  "properties": {
    "gn:admin1_code":"08",
    "gn:admin2_code":"Beshkent",
    "gn:asciiname":"Uzunchavo",
    "gn:country_code":"UZ",
    "gn:dem":376,
    "gn:feature_class":"P",
    "gn:feature_code":"PPL",
    "gn:name":"Uzunchavo",
    "gn:population":0,
    "gn:timezone":"Asia/Samarkand",
    "iso:country":"UZ",
    "wof:name":"Uzunchavo",
    "wof:placetype":"locality"
},
  "geometry": {"coordinates":[65.79346,38.89391],"type":"Point"}
}