{
  "type": "Feature",
  "properties": {
    "gn:admin1_code":"08",
    "gn:asciiname":"Mudin",
    "gn:country_code":"UZ",
    "gn:dem":365,
    "gn:feature_class":"P",
    "gn:feature_code":"PPL",
    "gn:name":"Mudin",
    "gn:population":0,
    "gn:timezone":"Asia/Samarkand",
    "iso:country":"UZ",
    "wof:name":"Mudin",
    "wof:placetype":"locality"
},
  "geometry": {"coordinates":[65.69906999999999,38.9817],"type":"Point"}
}