{
  "type": "Feature",
  "properties": {
    "gn:admin1_code":"14",
    "gn:asciiname":"Dzhail'ma",
    "gn:country_code":"UZ",
    "gn:dem":632,
    "gn:feature_class":"P",
    "gn:feature_code":"PPL",
    "gn:name":"Dzhail\u2019ma",
    "gn:population":0,
    "gn:timezone":"Asia/Tashkent",
    "iso:country":"UZ",
    "name:rus_x_preferred":[
        "Dzhail\u2019ma"
    ],
    "wof:name":"Dzhail'ma",
    "wof:placetype":"locality"
},
  "geometry": {"coordinates":[69.65333000000001,41.33778],"type":"Point"}
}