{
  "type": "Feature",
  "properties": {
    "gn:admin1_code":"14",
    "gn:asciiname":"Yo`ltushgan",
    "gn:country_code":"UZ",
    "gn:dem":273,
    "gn:feature_class":"P",
    "gn:feature_code":"PPL",
    "gn:name":"Yo\u2018ltushgan",
    "gn:population":0,
    "gn:timezone":"Asia/Tashkent",
    "iso:country":"UZ",
    "name:uzb_x_preferred":[
        "Yo\u2018ltushgan"
    ],
    "wof:name":"Yo`ltushgan",
    "wof:placetype":"locality"
},
  "geometry": {"coordinates":[68.79673000000001,40.94324],"type":"Point"}
}