{
  "type": "Feature",
  "properties": {
    "gn:admin1_code":"06",
    "gn:asciiname":"Irvadan",
    "gn:country_code":"UZ",
    "gn:dem":440,
    "gn:feature_class":"P",
    "gn:feature_code":"PPL",
    "gn:name":"Irvadan",
    "gn:population":0,
    "gn:timezone":"Asia/Tashkent",
    "iso:country":"UZ",
    "name:uzb_x_preferred":[
        "Irvadan"
    ],
    "name:uzb_x_variant":[
        "Irvadon"
    ],
    "wof:name":"Irvadan",
    "wof:placetype":"locality"
},
  "geometry": {"coordinates":[71.62808000000003,40.98289000000001],"type":"Point"}
}