{
  "type": "Feature",
  "properties": {
    "gn:admin1_code":"00",
    "gn:asciiname":"Ravat",
    "gn:country_code":"UZ",
    "gn:dem":674,
    "gn:feature_class":"P",
    "gn:feature_code":"PPL",
    "gn:name":"Ravat",
    "gn:population":0,
    "gn:timezone":"Asia/Samarkand",
    "iso:country":"UZ",
    "wof:name":"Ravat",
    "wof:placetype":"locality"
},
  "geometry": {"coordinates":[66.21666999999999,40.46667],"type":"Point"}
}