{
  "type": "Feature",
  "properties": {
    "gn:admin1_code":"01",
    "gn:asciiname":"Namuna",
    "gn:country_code":"UZ",
    "gn:dem":711,
    "gn:feature_class":"P",
    "gn:feature_code":"PPL",
    "gn:name":"Namuna",
    "gn:population":0,
    "gn:timezone":"Asia/Tashkent",
    "iso:country":"UZ",
    "wof:name":"Namuna",
    "wof:placetype":"locality"
},
  "geometry": {"coordinates":[72.87778,40.78545],"type":"Point"}
}