{
  "type": "Feature",
  "properties": {
    "gn:admin1_code":"01",
    "gn:asciiname":"G`alaba",
    "gn:country_code":"UZ",
    "gn:dem":431,
    "gn:feature_class":"P",
    "gn:feature_code":"PPL",
    "gn:name":"G\u2018alaba",
    "gn:population":0,
    "gn:timezone":"Asia/Tashkent",
    "iso:country":"UZ",
    "name:rus_x_preferred":[
        "Kolkhoz Imeni Tel\u2019mana"
    ],
    "name:uzb_x_preferred":[
        "G\u2018alaba"
    ],
    "name:uzb_x_variant":[
        "Avangard"
    ],
    "wof:name":"G`alaba",
    "wof:placetype":"locality"
},
  "geometry": {"coordinates":[71.93574,40.73148],"type":"Point"}
}