{
  "type": "Feature",
  "properties": {
    "gn:admin1_code":"00",
    "gn:asciiname":"Bayburi",
    "gn:country_code":"UZ",
    "gn:dem":605,
    "gn:feature_class":"P",
    "gn:feature_code":"PPL",
    "gn:name":"Bayburi",
    "gn:population":0,
    "gn:timezone":"Asia/Samarkand",
    "iso:country":"UZ",
    "wof:name":"Bayburi",
    "wof:placetype":"locality"
},
  "geometry": {"coordinates":[67.95,38.43333],"type":"Point"}
}