{
  "type": "Feature",
  "properties": {
    "gn:admin1_code":"03",
    "gn:asciiname":"Taksonqovun",
    "gn:country_code":"UZ",
    "gn:dem":461,
    "gn:feature_class":"P",
    "gn:feature_code":"PPL",
    "gn:name":"Taksonqovun",
    "gn:population":0,
    "gn:timezone":"Asia/Tashkent",
    "iso:country":"UZ",
    "name:und_x_variant":[
        "Taksankavun"
    ],
    "name:uzb_x_preferred":[
        "Taksonqovun"
    ],
    "wof:name":"Taksonqovun",
    "wof:placetype":"locality"
},
  "geometry": {"coordinates":[71.00958,40.48155],"type":"Point"}
}