{
  "type": "Feature",
  "properties": {
    "gn:admin1_code":"16",
    "gn:asciiname":"Shirin",
    "gn:country_code":"UZ",
    "gn:dem":314,
    "gn:feature_class":"P",
    "gn:feature_code":"PPL",
    "gn:name":"Shirin",
    "gn:population":0,
    "gn:timezone":"Asia/Tashkent",
    "iso:country":"UZ",
    "name:azb_x_preferred":[
        "\u0634\u06cc\u0631\u06cc\u0646"
    ],
    "name:hsb_x_preferred":[
        "Shirin"
    ],
    "name:jpn_x_preferred":[
        "\u30b7\u30ea\u30f3"
    ],
    "name:pol_x_preferred":[
        "Shirin"
    ],
    "name:rus_x_preferred":[
        "\u0428\u0438\u0440\u0438\u043d"
    ],
    "name:spa_x_preferred":[
        "Shirin"
    ],
    "name:tat_x_preferred":[
        "\u0428\u0438\u0440\u0438\u043d"
    ],
    "name:tur_x_preferred":[
        "\u015eirin"
    ],
    "name:urd_x_preferred":[
        "\u0634\u06cc\u0631\u06cc\u0646"
    ],
    "name:uzb_x_preferred":[
        "Shirin"
    ],
    "wof:name":"Shirin",
    "wof:placetype":"locality"
},
  "geometry": {"coordinates":[69.14974000000001,40.22343],"type":"Point"}
}