{
  "type": "Feature",
  "properties": {
    "gn:admin1_code":"03",
    "gn:asciiname":"Do`ngsaroy",
    "gn:country_code":"UZ",
    "gn:dem":435,
    "gn:feature_class":"P",
    "gn:feature_code":"PPL",
    "gn:name":"Do\u2018ngsaroy",
    "gn:population":0,
    "gn:timezone":"Asia/Tashkent",
    "iso:country":"UZ",
    "name:uzb_x_preferred":[
        "Do\u2018ngsaroy"
    ],
    "wof:name":"Do`ngsaroy",
    "wof:placetype":"locality"
},
  "geometry": {"coordinates":[70.85034,40.43984],"type":"Point"}
}