{
  "type": "Feature",
  "properties": {
    "gn:admin1_code":"01",
    "gn:asciiname":"Sultan-Ayaya",
    "gn:country_code":"UZ",
    "gn:dem":469,
    "gn:feature_class":"P",
    "gn:feature_code":"PPL",
    "gn:name":"Sultan-Ayaya",
    "gn:population":0,
    "gn:timezone":"Asia/Tashkent",
    "iso:country":"UZ",
    "name:und_x_variant":[
        "Sultan-Ayak",
        "Sultan-Ayaya"
    ],
    "wof:name":"Sultan-Ayaya",
    "wof:placetype":"locality"
},
  "geometry": {"coordinates":[72.28333000000001,40.73333],"type":"Point"}
}