{
  "type": "Feature",
  "properties": {
    "gn:admin1_code":"12",
    "gn:asciiname":"Dunongi",
    "gn:country_code":"UZ",
    "gn:dem":1581,
    "gn:feature_class":"P",
    "gn:feature_code":"PPL",
    "gn:name":"Dunongi",
    "gn:population":0,
    "gn:timezone":"Asia/Samarkand",
    "iso:country":"UZ",
    "name:und_x_variant":[
        "Bakhcha"
    ],
    "name:uzb_x_preferred":[
        "Dunongi"
    ],
    "wof:name":"Dunongi",
    "wof:placetype":"locality"
},
  "geometry": {"coordinates":[67.44722,38.58667],"type":"Point"}
}