{
  "type": "Feature",
  "properties": {
    "gn:admin1_code":"12",
    "gn:asciiname":"Rabotak",
    "gn:country_code":"UZ",
    "gn:dem":387,
    "gn:feature_class":"P",
    "gn:feature_code":"PPL",
    "gn:name":"Rabotak",
    "gn:population":0,
    "gn:timezone":"Asia/Samarkand",
    "iso:country":"UZ",
    "name:und_x_variant":[
        "Rabatak"
    ],
    "name:uzb_x_preferred":[
        "Rabotak"
    ],
    "wof:name":"Rabotak",
    "wof:placetype":"locality"
},
  "geometry": {"coordinates":[67.13054,37.70609],"type":"Point"}
}