{
  "type": "Feature",
  "properties": {
    "gn:admin1_code":"01",
    "gn:asciiname":"To`rachek",
    "gn:country_code":"UZ",
    "gn:dem":641,
    "gn:feature_class":"P",
    "gn:feature_code":"PPL",
    "gn:name":"To\u2018rachek",
    "gn:population":0,
    "gn:timezone":"Asia/Tashkent",
    "iso:country":"UZ",
    "name:rus_x_preferred":[
        "\u0422\u0443\u0440\u0430\u0447\u0435\u043a"
    ],
    "name:und_x_variant":[
        "Turachek"
    ],
    "name:uzb_x_preferred":[
        "To\u2018rachek"
    ],
    "wof:name":"To`rachek",
    "wof:placetype":"locality"
},
  "geometry": {"coordinates":[72.57269000000002,40.7149],"type":"Point"}
}