{
  "type": "Feature",
  "properties": {
    "gn:admin1_code":"01",
    "gn:asciiname":"Chorvador",
    "gn:country_code":"UZ",
    "gn:dem":484,
    "gn:feature_class":"P",
    "gn:feature_code":"PPL",
    "gn:name":"Chorvador",
    "gn:population":0,
    "gn:timezone":"Asia/Tashkent",
    "iso:country":"UZ",
    "name:rus_x_preferred":[
        "\u0427\u0430\u0440\u0432\u0430\u0434\u0430\u0440"
    ],
    "name:und_x_variant":[
        "Charvadar"
    ],
    "name:uzb_x_preferred":[
        "Chorvador"
    ],
    "wof:name":"Chorvador",
    "wof:placetype":"locality"
},
  "geometry": {"coordinates":[72.29663000000002,40.92365],"type":"Point"}
}