{
  "type": "Feature",
  "properties": {
    "gn:admin1_code":"12",
    "gn:asciiname":"Oynabuloq",
    "gn:country_code":"UZ",
    "gn:dem":1567,
    "gn:feature_class":"P",
    "gn:feature_code":"PPL",
    "gn:name":"Oynabuloq",
    "gn:population":0,
    "gn:timezone":"Asia/Samarkand",
    "iso:country":"UZ",
    "name:und_x_variant":[
        "Ayna",
        "Ayna-Bulak",
        "Oynabuloq"
    ],
    "wof:name":"Oynabuloq",
    "wof:placetype":"locality"
},
  "geometry": {"coordinates":[66.96356,38.32304],"type":"Point"}
}