{
  "type": "Feature",
  "properties": {
    "gn:admin1_code":"03",
    "gn:asciiname":"Fedchenko",
    "gn:country_code":"UZ",
    "gn:dem":480,
    "gn:feature_class":"P",
    "gn:feature_code":"PPL",
    "gn:name":"Fedchenko",
    "gn:population":0,
    "gn:timezone":"Asia/Tashkent",
    "iso:country":"UZ",
    "name:ita_x_preferred":[
        "Fedchenko"
    ],
    "name:rus_x_preferred":[
        "\u0424\u0435\u0434\u0447\u0435\u043d\u043a\u043e"
    ],
    "name:ukr_x_preferred":[
        "\u0424\u0435\u0434\u0447\u0435\u043d\u043a\u043e"
    ],
    "wof:name":"Fedchenko",
    "wof:placetype":"locality"
},
  "geometry": {"coordinates":[72.07194,40.56028],"type":"Point"}
}