{
  "type": "Feature",
  "properties": {
    "gn:admin1_code":"08",
    "gn:asciiname":"Chashmaimiron",
    "gn:country_code":"UZ",
    "gn:dem":1469,
    "gn:feature_class":"P",
    "gn:feature_code":"PPL",
    "gn:name":"Chashmaimiron",
    "gn:population":0,
    "gn:timezone":"Asia/Samarkand",
    "iso:country":"UZ",
    "name:und_x_variant":[
        "Chashmamiran",
        "Chashmamiron",
        "Chashmaimiron"
    ],
    "wof:name":"Chashmaimiron",
    "wof:placetype":"locality"
},
  "geometry": {"coordinates":[66.96720999999999,38.40096],"type":"Point"}
}