{
  "type": "Feature",
  "properties": {
    "gn:admin1_code":"00",
    "gn:asciiname":"Chandyr",
    "gn:cc2":"UZ",
    "gn:country_code":"UZ",
    "gn:dem":234,
    "gn:feature_class":"P",
    "gn:feature_code":"PPL",
    "gn:name":"Chandyr",
    "gn:population":0,
    "gn:timezone":"Asia/Samarkand",
    "iso:country":"UZ",
    "name:und_x_variant":[
        "Chardyr",
        "Chandir",
        "Chandyr"
    ],
    "wof:name":"Chandyr",
    "wof:placetype":"locality"
},
  "geometry": {"coordinates":[64.45,40.08333],"type":"Point"}
}