{
  "type": "Feature",
  "properties": {
    "gn:admin1_code":"07",
    "gn:asciiname":"G`ishti",
    "gn:country_code":"UZ",
    "gn:dem":271,
    "gn:feature_class":"P",
    "gn:feature_code":"PPL",
    "gn:name":"G\u2018ishti",
    "gn:population":0,
    "gn:timezone":"Asia/Samarkand",
    "iso:country":"UZ",
    "wof:name":"G`ishti",
    "wof:placetype":"locality"
},
  "geometry": {"coordinates":[64.81434,40.09766],"type":"Point"}
}