{
  "type": "Feature",
  "properties": {
    "gn:admin1_code":"08",
    "gn:asciiname":"Qorqumdi",
    "gn:country_code":"UZ",
    "gn:dem":541,
    "gn:feature_class":"P",
    "gn:feature_code":"PPL",
    "gn:name":"Qorqumdi",
    "gn:population":0,
    "gn:timezone":"Asia/Samarkand",
    "iso:country":"UZ",
    "wof:name":"Qorqumdi",
    "wof:placetype":"locality"
},
  "geometry": {"coordinates":[66.28003000000001,38.60757],"type":"Point"}
}