{
  "type": "Feature",
  "properties": {
    "gn:admin1_code":"03",
    "gn:asciiname":"Vaxim",
    "gn:country_code":"UZ",
    "gn:dem":430,
    "gn:feature_class":"P",
    "gn:feature_code":"PPL",
    "gn:name":"Vaxim",
    "gn:population":0,
    "gn:timezone":"Asia/Tashkent",
    "iso:country":"UZ",
    "name:und_x_variant":[
        "Vakhim"
    ],
    "name:uzb_x_preferred":[
        "Vaxim"
    ],
    "wof:name":"Vaxim",
    "wof:placetype":"locality"
},
  "geometry": {"coordinates":[71.2373,40.40598],"type":"Point"}
}