{
  "type": "Feature",
  "properties": {
    "gn:admin1_code":"14",
    "gn:asciiname":"Nowomikhaylowka",
    "gn:cc2":"UZ",
    "gn:country_code":"UZ",
    "gn:dem":322,
    "gn:feature_class":"P",
    "gn:feature_code":"PPL",
    "gn:name":"Nowomikhaylowka",
    "gn:population":0,
    "gn:timezone":"Asia/Tashkent",
    "iso:country":"UZ",
    "name:und_x_variant":[
        "Novomikhaylovskiy",
        "Novo-Mikhaylovskoye",
        "Novomikhaylovka",
        "Nowomikhaylowka"
    ],
    "wof:name":"Nowomikhaylowka",
    "wof:placetype":"locality"
},
  "geometry": {"coordinates":[69.02722,41.03667],"type":"Point"}
}