{
  "type": "Feature",
  "properties": {
    "gn:admin1_code":"08",
    "gn:asciiname":"Kandzhigaly",
    "gn:country_code":"UZ",
    "gn:dem":742,
    "gn:feature_class":"P",
    "gn:feature_code":"PPL",
    "gn:name":"Kandzhigaly",
    "gn:population":0,
    "gn:timezone":"Asia/Samarkand",
    "iso:country":"UZ",
    "name:und_x_variant":[
        "Kaidzhigal\u2019",
        "Kandzhigaly"
    ],
    "wof:name":"Kandzhigaly",
    "wof:placetype":"locality"
},
  "geometry": {"coordinates":[66.66667,39.28333],"type":"Point"}
}