{
  "type": "Feature",
  "properties": {
    "gn:admin1_code":"06",
    "gn:asciiname":"Qorateri",
    "gn:country_code":"UZ",
    "gn:dem":423,
    "gn:feature_class":"P",
    "gn:feature_code":"PPL",
    "gn:name":"Qorateri",
    "gn:population":0,
    "gn:timezone":"Asia/Tashkent",
    "iso:country":"UZ",
    "name:eng_x_preferred":[
        "Qorateri"
    ],
    "name:und_x_variant":[
        "Karateri"
    ],
    "wof:name":"Qorateri",
    "wof:placetype":"locality"
},
  "geometry": {"coordinates":[71.93508,40.91582],"type":"Point"}
}