{
  "type": "Feature",
  "properties": {
    "gn:admin1_code":"08",
    "gn:asciiname":"Naukat",
    "gn:country_code":"UZ",
    "gn:dem":347,
    "gn:feature_class":"P",
    "gn:feature_code":"PPL",
    "gn:name":"Naukat",
    "gn:population":0,
    "gn:timezone":"Asia/Samarkand",
    "iso:country":"UZ",
    "wof:name":"Naukat",
    "wof:placetype":"locality"
},
  "geometry": {"coordinates":[65.56523,38.87611],"type":"Point"}
}