{
  "type": "Feature",
  "properties": {
    "gn:admin1_code":"00",
    "gn:asciiname":"Nauzandak",
    "gn:country_code":"UZ",
    "gn:dem":766,
    "gn:feature_class":"P",
    "gn:feature_code":"PPL",
    "gn:name":"Nauzandak",
    "gn:population":0,
    "gn:timezone":"Asia/Samarkand",
    "iso:country":"UZ",
    "wof:name":"Nauzandak",
    "wof:placetype":"locality"
},
  "geometry": {"coordinates":[67.16667,39.55],"type":"Point"}
}