{
  "type": "Feature",
  "properties": {
    "gn:admin1_code":"06",
    "gn:asciiname":"Madyor",
    "gn:country_code":"UZ",
    "gn:dem":389,
    "gn:feature_class":"P",
    "gn:feature_code":"PPL",
    "gn:name":"Madyor",
    "gn:population":0,
    "gn:timezone":"Asia/Tashkent",
    "iso:country":"UZ",
    "name:eng_x_preferred":[
        "Madyor"
    ],
    "wof:name":"Madyor",
    "wof:placetype":"locality"
},
  "geometry": {"coordinates":[71.43118,40.77069],"type":"Point"}
}