{
  "type": "Feature",
  "properties": {
    "gn:admin1_code":"00",
    "gn:asciiname":"Yangi-Rabat",
    "gn:country_code":"UZ",
    "gn:dem":222,
    "gn:feature_class":"P",
    "gn:feature_code":"PPL",
    "gn:name":"Yangi-Rabat",
    "gn:population":0,
    "gn:timezone":"Asia/Samarkand",
    "iso:country":"UZ",
    "wof:name":"Yangi-Rabat",
    "wof:placetype":"locality"
},
  "geometry": {"coordinates":[64.53333000000001,39.75],"type":"Point"}
}