{
  "type": "Feature",
  "properties": {
    "gn:admin1_code":"01",
    "gn:asciiname":"Qo`shtepa",
    "gn:country_code":"UZ",
    "gn:dem":684,
    "gn:feature_class":"P",
    "gn:feature_code":"PPL",
    "gn:name":"Qo\u2018shtepa",
    "gn:population":0,
    "gn:timezone":"Asia/Tashkent",
    "iso:country":"UZ",
    "name:rus_x_preferred":[
        "\u041a\u0443\u0448\u0442\u0435\u043f\u0430"
    ],
    "name:und_x_variant":[
        "Kushtepa"
    ],
    "name:uzb_x_preferred":[
        "Qo\u2018shtepa"
    ],
    "wof:name":"Qo`shtepa",
    "wof:placetype":"locality"
},
  "geometry": {"coordinates":[72.79425000000001,40.75056],"type":"Point"}
}