{
  "type": "Feature",
  "properties": {
    "gn:admin1_code":"07",
    "gn:asciiname":"Qizilcha",
    "gn:country_code":"UZ",
    "gn:dem":790,
    "gn:feature_class":"P",
    "gn:feature_code":"PPL",
    "gn:name":"Qizilcha",
    "gn:population":0,
    "gn:timezone":"Asia/Samarkand",
    "iso:country":"UZ",
    "name:und_x_variant":[
        "Koshrabad",
        "Qizilcha"
    ],
    "wof:name":"Qizilcha",
    "wof:placetype":"locality"
},
  "geometry": {"coordinates":[66.13670999999999,40.7107],"type":"Point"}
}