{
  "type": "Feature",
  "properties": {
    "gn:admin1_code":"00",
    "gn:asciiname":"Kumak",
    "gn:country_code":"UZ",
    "gn:dem":442,
    "gn:feature_class":"P",
    "gn:feature_code":"PPL",
    "gn:name":"Kumak",
    "gn:population":0,
    "gn:timezone":"Asia/Samarkand",
    "iso:country":"UZ",
    "wof:name":"Kumak",
    "wof:placetype":"locality"
},
  "geometry": {"coordinates":[66.11667,39.98333],"type":"Point"}
}