{
  "type": "Feature",
  "properties": {
    "gn:admin1_code":"00",
    "gn:asciiname":"Takanli",
    "gn:country_code":"UZ",
    "gn:dem":1175,
    "gn:feature_class":"P",
    "gn:feature_code":"PPL",
    "gn:name":"Takanli",
    "gn:population":0,
    "gn:timezone":"Asia/Samarkand",
    "iso:country":"UZ",
    "name:und_x_variant":[
        "Tykallik",
        "Tikanli",
        "Chakanli",
        "Takanli"
    ],
    "wof:name":"Takanli",
    "wof:placetype":"locality"
},
  "geometry": {"coordinates":[66.22766999999999,40.32156],"type":"Point"}
}