{
  "type": "Feature",
  "properties": {
    "gn:admin1_code":"12",
    "gn:asciiname":"Shaytan-Kishlak",
    "gn:country_code":"UZ",
    "gn:dem":633,
    "gn:feature_class":"P",
    "gn:feature_code":"PPL",
    "gn:name":"Shaytan-Kishlak",
    "gn:population":0,
    "gn:timezone":"Asia/Samarkand",
    "iso:country":"UZ",
    "wof:name":"Shaytan-Kishlak",
    "wof:placetype":"locality"
},
  "geometry": {"coordinates":[67.87314000000001,38.41522],"type":"Point"}
}