{
  "type": "Feature",
  "properties": {
    "gn:admin1_code":"08",
    "gn:asciiname":"Saroy",
    "gn:country_code":"UZ",
    "gn:dem":551,
    "gn:feature_class":"P",
    "gn:feature_code":"PPL",
    "gn:name":"Saroy",
    "gn:population":0,
    "gn:timezone":"Asia/Samarkand",
    "iso:country":"UZ",
    "wof:name":"Saroy",
    "wof:placetype":"locality"
},
  "geometry": {"coordinates":[66.66913000000001,39.04887],"type":"Point"}
}