{
  "type": "Feature",
  "properties": {
    "gn:admin1_code":"03",
    "gn:asciiname":"Povulg`on",
    "gn:country_code":"UZ",
    "gn:dem":471,
    "gn:feature_class":"P",
    "gn:feature_code":"PPL",
    "gn:name":"Povulg\u2018on",
    "gn:population":0,
    "gn:timezone":"Asia/Tashkent",
    "iso:country":"UZ",
    "name:und_x_variant":[
        "Paulgan"
    ],
    "name:uzb_x_preferred":[
        "Povulg\u2018on"
    ],
    "wof:name":"Povulg`on",
    "wof:placetype":"locality"
},
  "geometry": {"coordinates":[71.53089,40.37522],"type":"Point"}
}