{
  "type": "Feature",
  "properties": {
    "gn:admin1_code":"01",
    "gn:asciiname":"Yangiobod",
    "gn:country_code":"UZ",
    "gn:dem":462,
    "gn:feature_class":"P",
    "gn:feature_code":"PPL",
    "gn:name":"Yangiobod",
    "gn:population":0,
    "gn:timezone":"Asia/Tashkent",
    "iso:country":"UZ",
    "name:rus_x_preferred":[
        "\u042f\u043d\u0433\u0438\u0430\u0431\u0430\u0434"
    ],
    "name:und_x_variant":[
        "Yangiabad"
    ],
    "name:uzb_x_preferred":[
        "Yangiobod"
    ],
    "wof:name":"Yangiobod",
    "wof:placetype":"locality"
},
  "geometry": {"coordinates":[72.27249,40.90719],"type":"Point"}
}