{
  "type": "Feature",
  "properties": {
    "gn:admin1_code":"12",
    "gn:asciiname":"Bulakay",
    "gn:country_code":"UZ",
    "gn:dem":372,
    "gn:feature_class":"P",
    "gn:feature_code":"PPL",
    "gn:name":"Bulakay",
    "gn:population":0,
    "gn:timezone":"Asia/Samarkand",
    "iso:country":"UZ",
    "name:uzb_x_preferred":[
        "Bulakay"
    ],
    "wof:name":"Bulakay",
    "wof:placetype":"locality"
},
  "geometry": {"coordinates":[67.51286,37.59225],"type":"Point"}
}