{
  "type": "Feature",
  "properties": {
    "gn:admin1_code":"07",
    "gn:asciiname":"Toshquduq",
    "gn:country_code":"UZ",
    "gn:dem":202,
    "gn:feature_class":"P",
    "gn:feature_code":"PPL",
    "gn:name":"Toshquduq",
    "gn:population":0,
    "gn:timezone":"Asia/Tashkent",
    "iso:country":"UZ",
    "name:und_x_variant":[
        "Kolodets Tas-Kuduk"
    ],
    "wof:name":"Toshquduq",
    "wof:placetype":"locality"
},
  "geometry": {"coordinates":[65.44069,42.94938],"type":"Point"}
}