{
  "type": "Feature",
  "properties": {
    "gn:admin1_code":"08",
    "gn:asciiname":"Qishliq",
    "gn:country_code":"UZ",
    "gn:dem":571,
    "gn:feature_class":"P",
    "gn:feature_code":"PPL",
    "gn:name":"Qishliq",
    "gn:population":0,
    "gn:timezone":"Asia/Samarkand",
    "iso:country":"UZ",
    "name:und_x_variant":[
        "Chukur",
        "Kishlyk",
        "Qishliq"
    ],
    "wof:name":"Qishliq",
    "wof:placetype":"locality"
},
  "geometry": {"coordinates":[66.55376,38.78701],"type":"Point"}
}