{
  "type": "Feature",
  "properties": {
    "gn:admin1_code":"01",
    "gn:asciiname":"Qilichmozor",
    "gn:country_code":"UZ",
    "gn:dem":650,
    "gn:feature_class":"P",
    "gn:feature_code":"PPL",
    "gn:name":"Qilichmozor",
    "gn:population":0,
    "gn:timezone":"Asia/Tashkent",
    "iso:country":"UZ",
    "name:rus_x_preferred":[
        "\u041a\u044b\u0437\u044b\u043b\u043c\u0430\u0437\u0430\u0440"
    ],
    "name:und_x_variant":[
        "Kyzylmazar"
    ],
    "name:uzb_x_preferred":[
        "Qilichmozor"
    ],
    "wof:name":"Qilichmozor",
    "wof:placetype":"locality"
},
  "geometry": {"coordinates":[72.60765000000001,40.7378],"type":"Point"}
}