{
  "type": "Feature",
  "properties": {
    "gn:admin1_code":"03",
    "gn:asciiname":"Turklar",
    "gn:country_code":"UZ",
    "gn:dem":674,
    "gn:feature_class":"P",
    "gn:feature_code":"PPL",
    "gn:name":"Turklar",
    "gn:population":0,
    "gn:timezone":"Asia/Tashkent",
    "iso:country":"UZ",
    "wof:name":"Turklar",
    "wof:placetype":"locality"
},
  "geometry": {"coordinates":[71.98508000000002,40.374],"type":"Point"}
}