{
  "type": "Feature",
  "properties": {
    "gn:admin1_code":"09",
    "gn:asciiname":"Lotin",
    "gn:country_code":"UZ",
    "gn:dem":100,
    "gn:feature_class":"P",
    "gn:feature_code":"PPL",
    "gn:name":"Lotin",
    "gn:population":0,
    "gn:timezone":"Asia/Samarkand",
    "iso:country":"UZ",
    "wof:name":"Lotin",
    "wof:placetype":"locality"
},
  "geometry": {"coordinates":[61.13304,41.60751],"type":"Point"}
}