{
  "type": "Feature",
  "properties": {
    "gn:admin1_code":"00",
    "gn:asciiname":"Yangikishlak",
    "gn:cc2":"UZ",
    "gn:country_code":"UZ",
    "gn:dem":1306,
    "gn:feature_class":"P",
    "gn:feature_code":"PPL",
    "gn:name":"Yangikishlak",
    "gn:population":0,
    "gn:timezone":"Asia/Tashkent",
    "iso:country":"UZ",
    "name:rus_x_preferred":[
        "\u042f\u043d\u0433\u0438\u043a\u0438\u0448\u043b\u0430\u043a"
    ],
    "name:und_x_variant":[
        "Karanchitugay",
        "Yangikishlak"
    ],
    "wof:name":"Yangikishlak",
    "wof:placetype":"locality"
},
  "geometry": {"coordinates":[70.26666999999999,41.08333],"type":"Point"}
}