{
  "type": "Feature",
  "properties": {
    "gn:admin1_code":"01",
    "gn:asciiname":"Yangi-Baliqchi",
    "gn:country_code":"UZ",
    "gn:dem":397,
    "gn:feature_class":"P",
    "gn:feature_code":"PPL",
    "gn:name":"Yangi-Baliqchi",
    "gn:population":0,
    "gn:timezone":"Asia/Tashkent",
    "iso:country":"UZ",
    "name:uzb_x_preferred":[
        "Yangi-Baliqchi"
    ],
    "name:uzb_x_variant":[
        "Yangi-Bo\u2018liqchi"
    ],
    "wof:name":"Yangi-Baliqchi",
    "wof:placetype":"locality"
},
  "geometry": {"coordinates":[71.58955999999998,40.73797],"type":"Point"}
}