{
  "type": "Feature",
  "properties": {
    "gn:admin1_code":"03",
    "gn:asciiname":"Katta-Kenagas",
    "gn:country_code":"UZ",
    "gn:dem":431,
    "gn:feature_class":"P",
    "gn:feature_code":"PPL",
    "gn:name":"Katta-Kenagas",
    "gn:population":0,
    "gn:timezone":"Asia/Tashkent",
    "iso:country":"UZ",
    "name:uzb_x_preferred":[
        "Katta-Kenagas"
    ],
    "wof:name":"Katta-Kenagas",
    "wof:placetype":"locality"
},
  "geometry": {"coordinates":[71.08962,40.50535],"type":"Point"}
}