{
  "type": "Feature",
  "properties": {
    "gn:admin1_code":"02",
    "gn:asciiname":"Zimovki",
    "gn:country_code":"UZ",
    "gn:dem":255,
    "gn:feature_class":"P",
    "gn:feature_code":"PPL",
    "gn:name":"Zimovki",
    "gn:population":0,
    "gn:timezone":"Asia/Samarkand",
    "iso:country":"UZ",
    "wof:name":"Zimovki",
    "wof:placetype":"locality"
},
  "geometry": {"coordinates":[64.88333,39.41667],"type":"Point"}
}