{
  "type": "Feature",
  "properties": {
    "gn:admin1_code":"03",
    "gn:asciiname":"Katta Boybucha",
    "gn:country_code":"UZ",
    "gn:dem":377,
    "gn:feature_class":"P",
    "gn:feature_code":"PPL",
    "gn:name":"Katta Boybucha",
    "gn:population":0,
    "gn:timezone":"Asia/Tashkent",
    "iso:country":"UZ",
    "name:und_x_variant":[
        "Urgandzhi",
        "Kattabaybuchcha",
        "Kattabaybuncha"
    ],
    "name:uzb_x_preferred":[
        "Katta Boybucha"
    ],
    "wof:name":"Katta Boybucha",
    "wof:placetype":"locality"
},
  "geometry": {"coordinates":[70.92546999999998,40.68086],"type":"Point"}
}