{
  "type": "Feature",
  "properties": {
    "gn:admin1_code":"12",
    "gn:asciiname":"Tortulya",
    "gn:country_code":"UZ",
    "gn:dem":602,
    "gn:feature_class":"P",
    "gn:feature_code":"PPL",
    "gn:name":"Tortulya",
    "gn:population":0,
    "gn:timezone":"Asia/Samarkand",
    "iso:country":"UZ",
    "wof:name":"Tortulya",
    "wof:placetype":"locality"
},
  "geometry": {"coordinates":[67.88965999999999,38.38612],"type":"Point"}
}