{
  "type": "Feature",
  "properties": {
    "gn:admin1_code":"14",
    "gn:asciiname":"Karatepa",
    "gn:country_code":"UZ",
    "gn:dem":492,
    "gn:feature_class":"P",
    "gn:feature_code":"PPL",
    "gn:name":"Karatepa",
    "gn:population":0,
    "gn:timezone":"Asia/Tashkent",
    "iso:country":"UZ",
    "wof:name":"Karatepa",
    "wof:placetype":"locality"
},
  "geometry": {"coordinates":[69.51056,41.28417],"type":"Point"}
}