{
  "type": "Feature",
  "properties": {
    "gn:admin1_code":"01",
    "gn:asciiname":"Yulamatol",
    "gn:country_code":"UZ",
    "gn:dem":613,
    "gn:feature_class":"P",
    "gn:feature_code":"PPL",
    "gn:name":"Yulamatol",
    "gn:population":0,
    "gn:timezone":"Asia/Tashkent",
    "iso:country":"UZ",
    "name:rus_x_preferred":[
        "\u042e\u043b\u0430\u043c\u0430\u0442\u0430\u043b"
    ],
    "name:und_x_variant":[
        "Yulamatal"
    ],
    "name:uzb_x_preferred":[
        "Yulamatol"
    ],
    "wof:name":"Yulamatol",
    "wof:placetype":"locality"
},
  "geometry": {"coordinates":[72.39596999999998,40.55599],"type":"Point"}
}