{
  "type": "Feature",
  "properties": {
    "iso:country":"UZ",
    "name:azb_x_preferred":[
        "\u067e\u06cc\u0634\u0646\u0628\u0647"
    ],
    "name:eng_x_preferred":[
        "Paishanba"
    ],
    "name:kik_x_preferred":[
        "Payshanba"
    ],
    "name:nld_x_preferred":[
        "Paishanba"
    ],
    "name:pol_x_preferred":[
        "Payshanba"
    ],
    "name:rus_x_preferred":[
        "\u041f\u0430\u0439\u0448\u0430\u043d\u0431\u0430"
    ],
    "name:tur_x_preferred":[
        "Per\u015fembe"
    ],
    "name:unk_x_variant":[
        "Payshmba"
    ],
    "name:urd_x_preferred":[
        "\u067e\u06cc\u0634\u0646\u0628\u06c1"
    ],
    "name:uzb_x_preferred":[
        "Payshanba"
    ],
    "qs:gn_country":"UZ",
    "qs:gn_fcode":"PPL",
    "qs:gn_pop":24772,
    "qs:name":"Payshanba",
    "qs:name_adm0":"Uzbekistan",
    "qs:name_adm1":"Samarqand",
    "qs:photos":0,
    "qs:photos_1k":0,
    "qs:photos_9k":0,
    "qs:photos_9r":0,
    "qs:photos_all":0,
    "qs:photos_sr":0,
    "qs:placetype":"Town",
    "qs:pop_sr":"7",
    "qs:woe_adm0":23424980,
    "wd:wordcount":38,
    "wof:name":"Payshanba",
    "wof:placetype":"locality",
    "wof:population":24772
},
  "geometry": {"coordinates":[66.23694,40.00778],"type":"Point"}
}