{
  "type": "Feature",
  "properties": {
    "gn:admin1_code":"12",
    "gn:asciiname":"Besh-Takhta",
    "gn:country_code":"UZ",
    "gn:dem":1301,
    "gn:feature_class":"P",
    "gn:feature_code":"PPL",
    "gn:name":"Besh-Takhta",
    "gn:population":0,
    "gn:timezone":"Asia/Samarkand",
    "iso:country":"UZ",
    "wof:name":"Besh-Takhta",
    "wof:placetype":"locality"
},
  "geometry": {"coordinates":[67.51262,38.28509],"type":"Point"}
}