{
  "type": "Feature",
  "properties": {
    "gn:admin1_code":"08",
    "gn:asciiname":"Choygul",
    "gn:country_code":"UZ",
    "gn:dem":959,
    "gn:feature_class":"P",
    "gn:feature_code":"PPL",
    "gn:name":"Choygul",
    "gn:population":0,
    "gn:timezone":"Asia/Samarkand",
    "iso:country":"UZ",
    "name:und_x_variant":[
        "Ak-Kishlak",
        "Ishan-Kishlak",
        "Chaygul\u2019",
        "Choygul"
    ],
    "wof:name":"Choygul",
    "wof:placetype":"locality"
},
  "geometry": {"coordinates":[66.73860999999999,38.59958],"type":"Point"}
}