{
  "type": "Feature",
  "properties": {
    "gn:admin1_code":"15",
    "gn:admin2_code":"Yangiobod",
    "gn:asciiname":"Oyuoly",
    "gn:cc2":"UZ",
    "gn:country_code":"UZ",
    "gn:dem":1094,
    "gn:feature_class":"P",
    "gn:feature_code":"PPL",
    "gn:name":"Oyuoly",
    "gn:population":0,
    "gn:timezone":"Asia/Samarkand",
    "iso:country":"UZ",
    "name:und_x_variant":[
        "Uy-Uly",
        "Oyuoly"
    ],
    "wof:name":"Oyuoly",
    "wof:placetype":"locality"
},
  "geometry": {"coordinates":[68.685,39.89083],"type":"Point"}
}