{
  "type": "Feature",
  "properties": {
    "gn:admin1_code":"09",
    "gn:asciiname":"Qorajar",
    "gn:country_code":"UZ",
    "gn:dem":53,
    "gn:feature_class":"P",
    "gn:feature_code":"PPL",
    "gn:name":"Qorajar",
    "gn:population":0,
    "gn:timezone":"Asia/Samarkand",
    "iso:country":"UZ",
    "wof:name":"Qorajar",
    "wof:placetype":"locality"
},
  "geometry": {"coordinates":[58.79971,43.54584000000001],"type":"Point"}
}