{
  "type": "Feature",
  "properties": {
    "gn:admin1_code":"06",
    "gn:asciiname":"Gaznon",
    "gn:country_code":"UZ",
    "gn:dem":1043,
    "gn:feature_class":"P",
    "gn:feature_code":"PPL",
    "gn:name":"Gaznon",
    "gn:population":0,
    "gn:timezone":"Asia/Tashkent",
    "iso:country":"UZ",
    "name:eng_x_preferred":[
        "Gaznon"
    ],
    "wof:name":"Gaznon",
    "wof:placetype":"locality"
},
  "geometry": {"coordinates":[71.6691,41.34225],"type":"Point"}
}