{
  "type": "Feature",
  "properties": {
    "gn:admin1_code":"03",
    "gn:asciiname":"Mehnatrohat",
    "gn:country_code":"UZ",
    "gn:dem":388,
    "gn:feature_class":"P",
    "gn:feature_code":"PPL",
    "gn:name":"Mehnatrohat",
    "gn:population":0,
    "gn:timezone":"Asia/Tashkent",
    "iso:country":"UZ",
    "name:und_x_variant":[
        "Mikhnatrakhat"
    ],
    "name:uzb_x_preferred":[
        "Mehnatrohat"
    ],
    "wof:name":"Mehnatrohat",
    "wof:placetype":"locality"
},
  "geometry": {"coordinates":[71.00676,40.63066],"type":"Point"}
}