{
  "type": "Feature",
  "properties": {
    "gn:admin1_code":"01",
    "gn:asciiname":"Eshan",
    "gn:country_code":"UZ",
    "gn:dem":698,
    "gn:feature_class":"P",
    "gn:feature_code":"PPL",
    "gn:name":"Eshan",
    "gn:population":0,
    "gn:timezone":"Asia/Tashkent",
    "iso:country":"UZ",
    "name:rus_x_preferred":[
        "\u042d\u0448\u0430\u043d"
    ],
    "wof:name":"Eshan",
    "wof:placetype":"locality"
},
  "geometry": {"coordinates":[72.73966,40.73306],"type":"Point"}
}