{
  "type": "Feature",
  "properties": {
    "gn:admin1_code":"06",
    "gn:asciiname":"Toshkechuv",
    "gn:country_code":"UZ",
    "gn:dem":445,
    "gn:feature_class":"P",
    "gn:feature_code":"PPL",
    "gn:name":"Toshkechuv",
    "gn:population":0,
    "gn:timezone":"Asia/Tashkent",
    "iso:country":"UZ",
    "name:eng_x_preferred":[
        "Toshkechuv"
    ],
    "name:kir_x_preferred":[
        "Toshkechuv"
    ],
    "name:und_x_variant":[
        "Tashkechu"
    ],
    "wof:name":"Toshkechuv",
    "wof:placetype":"locality"
},
  "geometry": {"coordinates":[71.98264,41.00103],"type":"Point"}
}