{
  "type": "Feature",
  "properties": {
    "gn:admin1_code":"14",
    "gn:asciiname":"Saksonota",
    "gn:cc2":"UZ",
    "gn:country_code":"UZ",
    "gn:dem":564,
    "gn:feature_class":"P",
    "gn:feature_code":"PPL",
    "gn:name":"Saksonota",
    "gn:population":0,
    "gn:timezone":"Asia/Tashkent",
    "iso:country":"UZ",
    "name:und_x_variant":[
        "Saksan Ata",
        "Saksonota"
    ],
    "wof:name":"Saksonota",
    "wof:placetype":"locality"
},
  "geometry": {"coordinates":[69.58333,41.41667],"type":"Point"}
}