{
  "type": "Feature",
  "properties": {
    "gn:admin1_code":"08",
    "gn:asciiname":"Pashtan",
    "gn:country_code":"UZ",
    "gn:dem":357,
    "gn:feature_class":"P",
    "gn:feature_code":"PPL",
    "gn:name":"Pashtan",
    "gn:population":0,
    "gn:timezone":"Asia/Samarkand",
    "iso:country":"UZ",
    "name:und_x_variant":[
        "Loshtan",
        "Pashtan"
    ],
    "wof:name":"Pashtan",
    "wof:placetype":"locality"
},
  "geometry": {"coordinates":[65.61889000000001,38.92229],"type":"Point"}
}