{
  "type": "Feature",
  "properties": {
    "gn:admin1_code":"00",
    "gn:asciiname":"Rozhdestvenskiy",
    "gn:country_code":"UZ",
    "gn:dem":319,
    "gn:feature_class":"P",
    "gn:feature_code":"PPL",
    "gn:name":"Rozhdestvenskiy",
    "gn:population":0,
    "gn:timezone":"Asia/Tashkent",
    "iso:country":"UZ",
    "wof:name":"Rozhdestvenskiy",
    "wof:placetype":"locality"
},
  "geometry": {"coordinates":[69.05,41.01667],"type":"Point"}
}