{
  "type": "Feature",
  "properties": {
    "gn:admin1_code":"14",
    "gn:asciiname":"Qushqurghon",
    "gn:cc2":"UZ",
    "gn:country_code":"UZ",
    "gn:dem":610,
    "gn:feature_class":"P",
    "gn:feature_code":"PPL",
    "gn:name":"Q\u016dshq\u016drghon",
    "gn:population":0,
    "gn:timezone":"Asia/Tashkent",
    "iso:country":"UZ",
    "name:und_x_variant":[
        "Koshkurgan",
        "Q\u016dshq\u016drghon"
    ],
    "wof:name":"Qushqurghon",
    "wof:placetype":"locality"
},
  "geometry": {"coordinates":[69.63056,41.48361],"type":"Point"}
}