{
  "type": "Feature",
  "properties": {
    "gn:admin1_code":"03",
    "gn:asciiname":"Jangol",
    "gn:country_code":"UZ",
    "gn:dem":657,
    "gn:feature_class":"P",
    "gn:feature_code":"PPL",
    "gn:name":"Jangol",
    "gn:population":0,
    "gn:timezone":"Asia/Tashkent",
    "iso:country":"UZ",
    "name:und_x_variant":[
        "Dzhangal"
    ],
    "name:uzb_x_preferred":[
        "Jangol"
    ],
    "wof:name":"Jangol",
    "wof:placetype":"locality"
},
  "geometry": {"coordinates":[71.83920000000001,40.32575],"type":"Point"}
}