{
  "type": "Feature",
  "properties": {
    "gn:admin1_code":"06",
    "gn:asciiname":"Tolliovul",
    "gn:country_code":"UZ",
    "gn:dem":395,
    "gn:feature_class":"P",
    "gn:feature_code":"PPL",
    "gn:name":"Tolliovul",
    "gn:population":0,
    "gn:timezone":"Asia/Tashkent",
    "iso:country":"UZ",
    "name:eng_x_preferred":[
        "Tolovul"
    ],
    "name:und_x_variant":[
        "Otdeleniye Nomer Sovkhoz Namangan"
    ],
    "name:uzb_x_preferred":[
        "Tolliovul"
    ],
    "wof:name":"Tolliovul",
    "wof:placetype":"locality"
},
  "geometry": {"coordinates":[71.56206999999998,40.77991],"type":"Point"}
}