{
  "type": "Feature",
  "properties": {
    "gn:admin1_code":"09",
    "gn:asciiname":"Ko`kdaryo",
    "gn:country_code":"UZ",
    "gn:dem":60,
    "gn:feature_class":"P",
    "gn:feature_code":"PPL",
    "gn:name":"Ko\u2018kdaryo",
    "gn:population":0,
    "gn:timezone":"Asia/Samarkand",
    "iso:country":"UZ",
    "name:uzb_x_preferred":[
        "Ko\u2018kdaryo"
    ],
    "wof:name":"Ko`kdaryo",
    "wof:placetype":"locality"
},
  "geometry": {"coordinates":[58.78188000000001,43.09204],"type":"Point"}
}