{
  "type": "Feature",
  "properties": {
    "gn:admin1_code":"06",
    "gn:asciiname":"Yangishahar",
    "gn:country_code":"UZ",
    "gn:dem":715,
    "gn:feature_class":"P",
    "gn:feature_code":"PPL",
    "gn:name":"Yangishahar",
    "gn:population":0,
    "gn:timezone":"Asia/Tashkent",
    "iso:country":"UZ",
    "name:eng_x_preferred":[
        "Yangishahar"
    ],
    "wof:name":"Yangishahar",
    "wof:placetype":"locality"
},
  "geometry": {"coordinates":[71.66608000000002,41.15494],"type":"Point"}
}