{
  "type": "Feature",
  "properties": {
    "gn:admin1_code":"07",
    "gn:asciiname":"Charbak",
    "gn:country_code":"UZ",
    "gn:dem":243,
    "gn:feature_class":"P",
    "gn:feature_code":"PPL",
    "gn:name":"Charbak",
    "gn:population":0,
    "gn:timezone":"Asia/Samarkand",
    "iso:country":"UZ",
    "name:und_x_variant":[
        "Charbag",
        "Charbak"
    ],
    "wof:name":"Charbak",
    "wof:placetype":"locality"
},
  "geometry": {"coordinates":[64.6425,39.94194],"type":"Point"}
}