{
  "type": "Feature",
  "properties": {
    "gn:admin1_code":"12",
    "gn:asciiname":"Baymakli",
    "gn:cc2":"UZ",
    "gn:country_code":"UZ",
    "gn:dem":374,
    "gn:feature_class":"P",
    "gn:feature_code":"PPL",
    "gn:name":"Baymakli",
    "gn:population":0,
    "gn:timezone":"Asia/Samarkand",
    "iso:country":"UZ",
    "name:und_x_variant":[
        "Baymakhli",
        "Baymakli"
    ],
    "wof:name":"Baymakli",
    "wof:placetype":"locality"
},
  "geometry": {"coordinates":[67.50778000000001,37.63556],"type":"Point"}
}