{
  "type": "Feature",
  "properties": {
    "gn:admin1_code":"00",
    "gn:asciiname":"Changaly",
    "gn:country_code":"UZ",
    "gn:dem":705,
    "gn:feature_class":"P",
    "gn:feature_code":"PPL",
    "gn:name":"Changaly",
    "gn:population":0,
    "gn:timezone":"Asia/Samarkand",
    "iso:country":"UZ",
    "wof:name":"Changaly",
    "wof:placetype":"locality"
},
  "geometry": {"coordinates":[66.01666999999999,39.81667],"type":"Point"}
}