{
  "type": "Feature",
  "properties": {
    "gn:admin1_code":"00",
    "gn:asciiname":"Mikhin",
    "gn:country_code":"UZ",
    "gn:dem":956,
    "gn:feature_class":"P",
    "gn:feature_code":"PPL",
    "gn:name":"Mikhin",
    "gn:population":0,
    "gn:timezone":"Asia/Samarkand",
    "iso:country":"UZ",
    "wof:name":"Mikhin",
    "wof:placetype":"locality"
},
  "geometry": {"coordinates":[67.11667,40.38333],"type":"Point"}
}