{
  "type": "Feature",
  "properties": {
    "gn:admin1_code":"03",
    "gn:asciiname":"Chilan",
    "gn:country_code":"UZ",
    "gn:dem":482,
    "gn:feature_class":"P",
    "gn:feature_code":"PPL",
    "gn:name":"Chilan",
    "gn:population":0,
    "gn:timezone":"Asia/Tashkent",
    "iso:country":"UZ",
    "wof:name":"Chilan",
    "wof:placetype":"locality"
},
  "geometry": {"coordinates":[72.05284,40.53831],"type":"Point"}
}