{
  "type": "Feature",
  "properties": {
    "gn:admin1_code":"06",
    "gn:asciiname":"Shilvi",
    "gn:country_code":"UZ",
    "gn:dem":1141,
    "gn:feature_class":"P",
    "gn:feature_code":"PPL",
    "gn:name":"Shilvi",
    "gn:population":0,
    "gn:timezone":"Asia/Bishkek",
    "iso:country":"UZ",
    "name:eng_x_preferred":[
        "Shilba"
    ],
    "name:uzb_x_preferred":[
        "Shilvi"
    ],
    "wof:name":"Shilvi",
    "wof:placetype":"locality"
},
  "geometry": {"coordinates":[71.66786,41.39458],"type":"Point"}
}