{
  "type": "Feature",
  "properties": {
    "gn:admin1_code":"07",
    "gn:asciiname":"Sufiyan",
    "gn:country_code":"UZ",
    "gn:dem":262,
    "gn:feature_class":"P",
    "gn:feature_code":"PPL",
    "gn:name":"Sufiyan",
    "gn:population":0,
    "gn:timezone":"Asia/Samarkand",
    "iso:country":"UZ",
    "name:und_x_variant":[
        "Sefiyan",
        "Sufiyan"
    ],
    "wof:name":"Sufiyan",
    "wof:placetype":"locality"
},
  "geometry": {"coordinates":[64.78333000000001,40.06667],"type":"Point"}
}