{
  "type": "Feature",
  "properties": {
    "gn:admin1_code":"00",
    "gn:asciiname":"Tolya",
    "gn:cc2":"UZ",
    "gn:country_code":"UZ",
    "gn:dem":607,
    "gn:feature_class":"P",
    "gn:feature_code":"PPL",
    "gn:name":"Tolya",
    "gn:population":0,
    "gn:timezone":"Asia/Samarkand",
    "iso:country":"UZ",
    "name:und_x_variant":[
        "Tulya",
        "Tolya"
    ],
    "wof:name":"Tolya",
    "wof:placetype":"locality"
},
  "geometry": {"coordinates":[66.63333,40.06667],"type":"Point"}
}