{
  "type": "Feature",
  "properties": {
    "gn:admin1_code":"06",
    "gn:asciiname":"Alixon",
    "gn:country_code":"UZ",
    "gn:dem":745,
    "gn:feature_class":"P",
    "gn:feature_code":"PPL",
    "gn:name":"Alixon",
    "gn:population":0,
    "gn:timezone":"Asia/Tashkent",
    "iso:country":"UZ",
    "name:und_x_variant":[
        "Alikhan"
    ],
    "wof:name":"Alixon",
    "wof:placetype":"locality"
},
  "geometry": {"coordinates":[71.82026,41.22504],"type":"Point"}
}