{
  "type": "Feature",
  "properties": {
    "gn:admin1_code":"01",
    "gn:asciiname":"Oyim",
    "gn:country_code":"UZ",
    "gn:dem":631,
    "gn:feature_class":"P",
    "gn:feature_code":"PPL",
    "gn:name":"Oyim",
    "gn:population":0,
    "gn:timezone":"Asia/Tashkent",
    "iso:country":"UZ",
    "name:rus_x_preferred":[
        "\u0410\u0438\u043c"
    ],
    "name:ukr_x_preferred":[
        "\u0410\u0457\u043c"
    ],
    "name:und_x_variant":[
        "Aim",
        "Oyim"
    ],
    "name:uzb_x_preferred":[
        "Oyim"
    ],
    "wof:name":"Oyim",
    "wof:placetype":"locality"
},
  "geometry": {"coordinates":[72.74234,40.81955],"type":"Point"}
}