{
  "type": "Feature",
  "properties": {
    "gn:admin1_code":"03",
    "gn:asciiname":"Qoraqalpoq",
    "gn:country_code":"UZ",
    "gn:dem":385,
    "gn:feature_class":"P",
    "gn:feature_code":"PPL",
    "gn:name":"Qoraqalpoq",
    "gn:population":0,
    "gn:timezone":"Asia/Tashkent",
    "iso:country":"UZ",
    "name:uzb_x_preferred":[
        "Qoraqalpoq"
    ],
    "wof:name":"Qoraqalpoq",
    "wof:placetype":"locality"
},
  "geometry": {"coordinates":[70.90411999999998,40.62532],"type":"Point"}
}