{
  "type": "Feature",
  "properties": {
    "gn:admin1_code":"00",
    "gn:asciiname":"Agach-Dzhan",
    "gn:country_code":"UZ",
    "gn:dem":855,
    "gn:feature_class":"P",
    "gn:feature_code":"PPL",
    "gn:name":"Agach-Dzhan",
    "gn:population":0,
    "gn:timezone":"Asia/Samarkand",
    "iso:country":"UZ",
    "wof:name":"Agach-Dzhan",
    "wof:placetype":"locality"
},
  "geometry": {"coordinates":[67.81667,39.96667],"type":"Point"}
}