{
  "type": "Feature",
  "properties": {
    "gn:admin1_code":"03",
    "gn:asciiname":"To`liboy",
    "gn:country_code":"UZ",
    "gn:dem":399,
    "gn:feature_class":"P",
    "gn:feature_code":"PPL",
    "gn:name":"To\u2018liboy",
    "gn:population":0,
    "gn:timezone":"Asia/Tashkent",
    "iso:country":"UZ",
    "name:und_x_variant":[
        "Tulibay"
    ],
    "name:uzb_x_preferred":[
        "To\u2018liboy"
    ],
    "wof:name":"To`liboy",
    "wof:placetype":"locality"
},
  "geometry": {"coordinates":[70.95211,40.55943],"type":"Point"}
}