{
  "type": "Feature",
  "properties": {
    "gn:admin1_code":"09",
    "gn:asciiname":"Ageden",
    "gn:country_code":"UZ",
    "gn:dem":64,
    "gn:feature_class":"P",
    "gn:feature_code":"PPL",
    "gn:name":"Ageden",
    "gn:population":0,
    "gn:timezone":"Asia/Samarkand",
    "iso:country":"UZ",
    "wof:name":"Ageden",
    "wof:placetype":"locality"
},
  "geometry": {"coordinates":[59.34725,42.90813],"type":"Point"}
}