{
  "type": "Feature",
  "properties": {
    "gn:admin1_code":"12",
    "gn:asciiname":"Qarsaqli",
    "gn:country_code":"UZ",
    "gn:dem":407,
    "gn:feature_class":"P",
    "gn:feature_code":"PPL",
    "gn:name":"Qarsaqli",
    "gn:population":0,
    "gn:timezone":"Asia/Samarkand",
    "iso:country":"UZ",
    "name:uzb_x_preferred":[
        "Qarsaqli"
    ],
    "wof:name":"Qarsaqli",
    "wof:placetype":"locality"
},
  "geometry": {"coordinates":[67.64801999999999,37.80804000000001],"type":"Point"}
}