{
  "type": "Feature",
  "properties": {
    "gn:admin1_code":"08",
    "gn:asciiname":"Qumbang",
    "gn:country_code":"UZ",
    "gn:dem":316,
    "gn:feature_class":"P",
    "gn:feature_code":"PPL",
    "gn:name":"Qumbang",
    "gn:population":0,
    "gn:timezone":"Asia/Samarkand",
    "iso:country":"UZ",
    "name:eng_x_preferred":[
        "Qumbang"
    ],
    "wof:name":"Qumbang",
    "wof:placetype":"locality"
},
  "geometry": {"coordinates":[65.34092,38.87587],"type":"Point"}
}