{
  "type": "Feature",
  "properties": {
    "gn:admin1_code":"03",
    "gn:asciiname":"Sultanobod",
    "gn:country_code":"UZ",
    "gn:dem":500,
    "gn:feature_class":"P",
    "gn:feature_code":"PPL",
    "gn:name":"Sultanobod",
    "gn:population":0,
    "gn:timezone":"Asia/Tashkent",
    "iso:country":"UZ",
    "name:rus_x_preferred":[
        "\u0421\u0443\u043b\u0442\u0430\u043d\u0430\u0431\u0430\u0434"
    ],
    "name:und_x_variant":[
        "Suyatan-Abad",
        "Sultan-Abad",
        "Sultanabad"
    ],
    "name:uzb_x_preferred":[
        "Sultanobod"
    ],
    "name:uzb_x_variant":[
        "Sultonobod"
    ],
    "wof:name":"Sultanobod",
    "wof:placetype":"locality"
},
  "geometry": {"coordinates":[72.1525,40.56366],"type":"Point"}
}