{
  "type": "Feature",
  "properties": {
    "gn:admin1_code":"01",
    "gn:asciiname":"Yangiqishloq",
    "gn:country_code":"UZ",
    "gn:dem":589,
    "gn:feature_class":"P",
    "gn:feature_code":"PPL",
    "gn:name":"Yangiqishloq",
    "gn:population":0,
    "gn:timezone":"Asia/Tashkent",
    "iso:country":"UZ",
    "name:rus_x_preferred":[
        "\u042f\u043d\u0433\u0438\u043a\u0438\u0448\u043b\u0430\u043a"
    ],
    "name:und_x_variant":[
        "Yangikishlak"
    ],
    "name:uzb_x_preferred":[
        "Yangiqishloq"
    ],
    "wof:name":"Yangiqishloq",
    "wof:placetype":"locality"
},
  "geometry": {"coordinates":[72.25285,40.53196],"type":"Point"}
}