{
  "type": "Feature",
  "properties": {
    "gn:admin1_code":"00",
    "gn:asciiname":"Sangi-Sade",
    "gn:country_code":"UZ",
    "gn:dem":229,
    "gn:feature_class":"P",
    "gn:feature_code":"PPL",
    "gn:name":"Sangi-Sade",
    "gn:population":0,
    "gn:timezone":"Asia/Samarkand",
    "iso:country":"UZ",
    "wof:name":"Sangi-Sade",
    "wof:placetype":"locality"
},
  "geometry": {"coordinates":[64.48333000000001,39.85],"type":"Point"}
}