{
  "type": "Feature",
  "properties": {
    "gn:admin1_code":"08",
    "gn:asciiname":"Nishon",
    "gn:country_code":"UZ",
    "gn:dem":354,
    "gn:feature_class":"P",
    "gn:feature_code":"PPL",
    "gn:name":"Nishon",
    "gn:population":0,
    "gn:timezone":"Asia/Samarkand",
    "iso:country":"UZ",
    "name:und_x_variant":[
        "Nishan",
        "Nishon"
    ],
    "wof:name":"Nishon",
    "wof:placetype":"locality"
},
  "geometry": {"coordinates":[65.68734000000001,38.61896],"type":"Point"}
}