{
  "type": "Feature",
  "properties": {
    "gn:admin1_code":"14",
    "gn:asciiname":"Zakhar'yevskiy",
    "gn:country_code":"UZ",
    "gn:dem":338,
    "gn:feature_class":"P",
    "gn:feature_code":"PPL",
    "gn:name":"Zakhar'yevskiy",
    "gn:population":0,
    "gn:timezone":"Asia/Tashkent",
    "iso:country":"UZ",
    "wof:name":"Zakhar'yevskiy",
    "wof:placetype":"locality"
},
  "geometry": {"coordinates":[69.13333,41.05],"type":"Point"}
}