{
  "type": "Feature",
  "properties": {
    "gn:admin1_code":"12",
    "gn:asciiname":"Laykand",
    "gn:country_code":"UZ",
    "gn:dem":348,
    "gn:feature_class":"P",
    "gn:feature_code":"PPL",
    "gn:name":"Laykand",
    "gn:population":0,
    "gn:timezone":"Asia/Samarkand",
    "iso:country":"UZ",
    "wof:name":"Laykand",
    "wof:placetype":"locality"
},
  "geometry": {"coordinates":[67.38611,37.48139000000001],"type":"Point"}
}