{
  "type": "Feature",
  "properties": {
    "gn:admin1_code":"00",
    "gn:asciiname":"Khatab",
    "gn:country_code":"UZ",
    "gn:dem":636,
    "gn:feature_class":"P",
    "gn:feature_code":"PPL",
    "gn:name":"Khatab",
    "gn:population":0,
    "gn:timezone":"Asia/Samarkand",
    "iso:country":"UZ",
    "wof:name":"Khatab",
    "wof:placetype":"locality"
},
  "geometry": {"coordinates":[68.11667,39.93333],"type":"Point"}
}