{
  "type": "Feature",
  "properties": {
    "gn:admin1_code":"01",
    "gn:asciiname":"Oqqo`rg`on",
    "gn:country_code":"UZ",
    "gn:dem":420,
    "gn:feature_class":"P",
    "gn:feature_code":"PPL",
    "gn:name":"Oqqo\u2018rg\u2018on",
    "gn:population":0,
    "gn:timezone":"Asia/Tashkent",
    "iso:country":"UZ",
    "name:eng_x_preferred":[
        "Oqqo\u2018rg\u2018on"
    ],
    "name:und_x_variant":[
        "Chunkayma"
    ],
    "wof:name":"Oqqo`rg`on",
    "wof:placetype":"locality"
},
  "geometry": {"coordinates":[71.89726,40.90408],"type":"Point"}
}