{
  "type": "Feature",
  "properties": {
    "gn:admin1_code":"01",
    "gn:asciiname":"Mart",
    "gn:country_code":"UZ",
    "gn:dem":501,
    "gn:feature_class":"P",
    "gn:feature_code":"PPL",
    "gn:name":"Mart",
    "gn:population":0,
    "gn:timezone":"Asia/Tashkent",
    "iso:country":"UZ",
    "name:rus_x_preferred":[
        "\u041c\u0430\u0440\u0442"
    ],
    "name:uzb_x_preferred":[
        "Mart"
    ],
    "wof:name":"Mart",
    "wof:placetype":"locality"
},
  "geometry": {"coordinates":[72.41204,40.83972],"type":"Point"}
}