{
  "type": "Feature",
  "properties": {
    "gn:admin1_code":"00",
    "gn:asciiname":"Katta-Say",
    "gn:country_code":"UZ",
    "gn:dem":735,
    "gn:feature_class":"P",
    "gn:feature_code":"PPL",
    "gn:name":"Katta-Say",
    "gn:population":0,
    "gn:timezone":"Asia/Samarkand",
    "iso:country":"UZ",
    "wof:name":"Katta-Say",
    "wof:placetype":"locality"
},
  "geometry": {"coordinates":[65.95,39.73333],"type":"Point"}
}