{
  "type": "Feature",
  "properties": {
    "gn:admin1_code":"08",
    "gn:admin2_code":"Beshkent",
    "gn:asciiname":"Taxtapul",
    "gn:country_code":"UZ",
    "gn:dem":394,
    "gn:feature_class":"P",
    "gn:feature_code":"PPL",
    "gn:name":"Taxtapul",
    "gn:population":0,
    "gn:timezone":"Asia/Samarkand",
    "iso:country":"UZ",
    "name:und_x_variant":[
        "Takhtapul\u2019"
    ],
    "wof:name":"Taxtapul",
    "wof:placetype":"locality"
},
  "geometry": {"coordinates":[65.89179,38.84052],"type":"Point"}
}