{
  "type": "Feature",
  "properties": {
    "gn:admin1_code":"09",
    "gn:asciiname":"Dovutko`l",
    "gn:country_code":"UZ",
    "gn:dem":65,
    "gn:feature_class":"P",
    "gn:feature_code":"PPL",
    "gn:name":"Dovutko\u2018l",
    "gn:population":0,
    "gn:timezone":"Asia/Samarkand",
    "iso:country":"UZ",
    "name:und_x_variant":[
        "Dautkul\u2019"
    ],
    "name:uzb_x_preferred":[
        "Dovutko\u2018l"
    ],
    "wof:name":"Dovutko`l",
    "wof:placetype":"locality"
},
  "geometry": {"coordinates":[59.37197,42.86816],"type":"Point"}
}