{
  "type": "Feature",
  "properties": {
    "gn:admin1_code":"01",
    "gn:asciiname":"Otchopar",
    "gn:country_code":"UZ",
    "gn:dem":628,
    "gn:feature_class":"P",
    "gn:feature_code":"PPL",
    "gn:name":"Otchopar",
    "gn:population":0,
    "gn:timezone":"Asia/Tashkent",
    "iso:country":"UZ",
    "name:rus_x_preferred":[
        "\u0410\u0442\u0447\u0430\u043f\u0430\u0440"
    ],
    "name:und_x_variant":[
        "Atchapar"
    ],
    "name:uzb_x_preferred":[
        "Otchopar"
    ],
    "wof:name":"Otchopar",
    "wof:placetype":"locality"
},
  "geometry": {"coordinates":[72.51120999999998,40.78563],"type":"Point"}
}