{
  "type": "Feature",
  "properties": {
    "gn:admin1_code":"03",
    "gn:asciiname":"Qozaqovul",
    "gn:country_code":"UZ",
    "gn:dem":380,
    "gn:feature_class":"P",
    "gn:feature_code":"PPL",
    "gn:name":"Qozaqovul",
    "gn:population":0,
    "gn:timezone":"Asia/Tashkent",
    "iso:country":"UZ",
    "name:uzb_x_preferred":[
        "Qozaqovul"
    ],
    "wof:name":"Qozaqovul",
    "wof:placetype":"locality"
},
  "geometry": {"coordinates":[70.56264,40.45029],"type":"Point"}
}