{
  "type": "Feature",
  "properties": {
    "gn:admin1_code":"14",
    "gn:asciiname":"Chighiriq",
    "gn:cc2":"UZ",
    "gn:country_code":"UZ",
    "gn:dem":401,
    "gn:feature_class":"P",
    "gn:feature_code":"PPL",
    "gn:name":"Chighiriq",
    "gn:population":0,
    "gn:timezone":"Asia/Tashkent",
    "iso:country":"UZ",
    "name:und_x_variant":[
        "Chigirikskiy",
        "Chigirik",
        "Chighiriq"
    ],
    "wof:name":"Chighiriq",
    "wof:placetype":"locality"
},
  "geometry": {"coordinates":[69.36083000000001,41.0175],"type":"Point"}
}