{
  "type": "Feature",
  "properties": {
    "gn:admin1_code":"08",
    "gn:asciiname":"Achamayli",
    "gn:country_code":"UZ",
    "gn:dem":629,
    "gn:feature_class":"P",
    "gn:feature_code":"PPL",
    "gn:name":"Achamayli",
    "gn:population":0,
    "gn:timezone":"Asia/Samarkand",
    "iso:country":"UZ",
    "wof:name":"Achamayli",
    "wof:placetype":"locality"
},
  "geometry": {"coordinates":[66.83861,39.13294000000001],"type":"Point"}
}