{
  "type": "Feature",
  "properties": {
    "gn:admin1_code":"03",
    "gn:asciiname":"Yakkatutdasht",
    "gn:country_code":"UZ",
    "gn:dem":470,
    "gn:feature_class":"P",
    "gn:feature_code":"PPL",
    "gn:name":"Yakkatutdasht",
    "gn:population":0,
    "gn:timezone":"Asia/Tashkent",
    "iso:country":"UZ",
    "name:uzb_x_preferred":[
        "Yakkatutdasht"
    ],
    "wof:name":"Yakkatutdasht",
    "wof:placetype":"locality"
},
  "geometry": {"coordinates":[70.89360000000001,40.4284],"type":"Point"}
}