{
  "type": "Feature",
  "properties": {
    "gn:admin1_code":"08",
    "gn:asciiname":"Yuqori Uyshun",
    "gn:country_code":"UZ",
    "gn:dem":725,
    "gn:feature_class":"P",
    "gn:feature_code":"PPL",
    "gn:name":"Yuqori Uyshun",
    "gn:population":0,
    "gn:timezone":"Asia/Samarkand",
    "iso:country":"UZ",
    "wof:name":"Yuqori Uyshun",
    "wof:placetype":"locality"
},
  "geometry": {"coordinates":[66.48659000000001,39.30208],"type":"Point"}
}