{
  "type": "Feature",
  "properties": {
    "gn:admin1_code":"09",
    "gn:asciiname":"Nurmanbay",
    "gn:country_code":"UZ",
    "gn:dem":90,
    "gn:feature_class":"P",
    "gn:feature_code":"PPL",
    "gn:name":"Nurmanbay",
    "gn:population":0,
    "gn:timezone":"Asia/Samarkand",
    "iso:country":"UZ",
    "wof:name":"Nurmanbay",
    "wof:placetype":"locality"
},
  "geometry": {"coordinates":[60.55,41.88333],"type":"Point"}
}