{
  "type": "Feature",
  "properties": {
    "gn:admin1_code":"09",
    "gn:asciiname":"Ko`nchi",
    "gn:country_code":"UZ",
    "gn:dem":63,
    "gn:feature_class":"P",
    "gn:feature_code":"PPL",
    "gn:name":"Ko\u2018nchi",
    "gn:population":0,
    "gn:timezone":"Asia/Samarkand",
    "iso:country":"UZ",
    "name:und_x_variant":[
        "Yaby-Kichak",
        "Yabykipchak"
    ],
    "name:uzb_x_preferred":[
        "Ko\u2018nchi"
    ],
    "wof:name":"Ko`nchi",
    "wof:placetype":"locality"
},
  "geometry": {"coordinates":[59.7951,42.87887],"type":"Point"}
}