{
  "type": "Feature",
  "properties": {
    "gn:admin1_code":"10",
    "gn:asciiname":"Kuropatkino",
    "gn:cc2":"UZ",
    "gn:country_code":"UZ",
    "gn:dem":740,
    "gn:feature_class":"P",
    "gn:feature_code":"PPL",
    "gn:name":"Kuropatkino",
    "gn:population":0,
    "gn:timezone":"Asia/Samarkand",
    "iso:country":"UZ",
    "name:aze_x_preferred":[
        "Kuropatkino"
    ],
    "name:bel_x_preferred":[
        "\u041a\u0430\u043a\u0430\u0432\u0430\u0434\u0437\u043e\u0440"
    ],
    "name:hye_x_preferred":[
        "\u053f\u0561\u0584\u0561\u057e\u0561\u0571\u0578\u0580"
    ],
    "name:msa_x_preferred":[
        "Kuropatkino"
    ],
    "name:rus_x_preferred":[
        "\u041a\u0443\u0440\u043e\u043f\u0430\u0442\u043a\u0438\u043d\u043e"
    ],
    "name:ukr_x_preferred":[
        "\u041a\u0430\u043a\u0430\u0432\u0430\u0434\u0437\u043e\u0440"
    ],
    "name:und_x_variant":[
        "Kuropatkina",
        "Bogarnoye"
    ],
    "wof:name":"Kuropatkino",
    "wof:placetype":"locality"
},
  "geometry": {"coordinates":[67.45361,39.94],"type":"Point"}
}