{
  "type": "Feature",
  "properties": {
    "gn:admin1_code":"10",
    "gn:asciiname":"Kuropatkino",
    "gn:cc2":"UZ",
    "gn:country_code":"UZ",
    "gn:dem":740,
    "gn:feature_class":"P",
    "gn:feature_code":"PPL",
    "gn:name":"Kuropatkino",
    "gn:population":0,
    "gn:timezone":"Asia/Samarkand",
    "iso:country":"UZ",
    "name:und_x_variant":[
        "Kuropatkina",
        "Kuropatkino",
        "Bogarnoye"
    ],
    "wof:name":"Kuropatkino",
    "wof:placetype":"locality"
},
  "geometry": {"coordinates":[67.45361,39.94],"type":"Point"}
}