{
  "type": "Feature",
  "properties": {
    "gn:admin1_code":"06",
    "gn:asciiname":"Yoshlik",
    "gn:country_code":"UZ",
    "gn:dem":892,
    "gn:feature_class":"P",
    "gn:feature_code":"PPL",
    "gn:name":"Yoshlik",
    "gn:population":0,
    "gn:timezone":"Asia/Tashkent",
    "iso:country":"UZ",
    "name:eng_x_preferred":[
        "Yoshlik"
    ],
    "wof:name":"Yoshlik",
    "wof:placetype":"locality"
},
  "geometry": {"coordinates":[71.56425,41.18308],"type":"Point"}
}