{
  "type": "Feature",
  "properties": {
    "gn:admin1_code":"03",
    "gn:asciiname":"Yakkatut",
    "gn:country_code":"UZ",
    "gn:dem":455,
    "gn:feature_class":"P",
    "gn:feature_code":"PPL",
    "gn:name":"Yakkatut",
    "gn:population":0,
    "gn:timezone":"Asia/Tashkent",
    "iso:country":"UZ",
    "name:uzb_x_preferred":[
        "Yakkatut"
    ],
    "wof:name":"Yakkatut",
    "wof:placetype":"locality"
},
  "geometry": {"coordinates":[70.88639000000001,40.43833],"type":"Point"}
}