{
  "type": "Feature",
  "properties": {
    "gn:admin1_code":"08",
    "gn:asciiname":"Ozod",
    "gn:country_code":"UZ",
    "gn:dem":353,
    "gn:feature_class":"P",
    "gn:feature_code":"PPL",
    "gn:name":"Ozod",
    "gn:population":0,
    "gn:timezone":"Asia/Samarkand",
    "iso:country":"UZ",
    "name:und_x_variant":[
        "Azad"
    ],
    "wof:name":"Ozod",
    "wof:placetype":"locality"
},
  "geometry": {"coordinates":[65.55234,38.56226],"type":"Point"}
}