{
  "type": "Feature",
  "properties": {
    "gn:admin1_code":"00",
    "gn:asciiname":"Balasy",
    "gn:country_code":"UZ",
    "gn:dem":1143,
    "gn:feature_class":"P",
    "gn:feature_code":"PPL",
    "gn:name":"Balasy",
    "gn:population":0,
    "gn:timezone":"Asia/Samarkand",
    "iso:country":"UZ",
    "wof:name":"Balasy",
    "wof:placetype":"locality"
},
  "geometry": {"coordinates":[67.63333,39.71667],"type":"Point"}
}