{
  "type": "Feature",
  "properties": {
    "gn:admin1_code":"03",
    "gn:asciiname":"Jaloyir",
    "gn:country_code":"UZ",
    "gn:dem":383,
    "gn:feature_class":"P",
    "gn:feature_code":"PPL",
    "gn:name":"Jaloyir",
    "gn:population":0,
    "gn:timezone":"Asia/Tashkent",
    "iso:country":"UZ",
    "name:eng_x_preferred":[
        "Jaloir"
    ],
    "name:und_x_variant":[
        "Dzhalair"
    ],
    "name:uzb_x_preferred":[
        "Jaloyir"
    ],
    "wof:name":"Jaloyir",
    "wof:placetype":"locality"
},
  "geometry": {"coordinates":[70.97389,40.63801],"type":"Point"}
}