{
  "type": "Feature",
  "properties": {
    "gn:admin1_code":"00",
    "gn:asciiname":"Uraur",
    "gn:country_code":"UZ",
    "gn:dem":952,
    "gn:feature_class":"P",
    "gn:feature_code":"PPL",
    "gn:name":"Uraur",
    "gn:population":0,
    "gn:timezone":"Asia/Samarkand",
    "iso:country":"UZ",
    "wof:name":"Uraur",
    "wof:placetype":"locality"
},
  "geometry": {"coordinates":[68.16667,38.28333],"type":"Point"}
}