{
  "type": "Feature",
  "properties": {
    "gn:admin1_code":"03",
    "gn:asciiname":"Xonqishloq",
    "gn:country_code":"UZ",
    "gn:dem":386,
    "gn:feature_class":"P",
    "gn:feature_code":"PPL",
    "gn:name":"Xonqishloq",
    "gn:population":0,
    "gn:timezone":"Asia/Tashkent",
    "iso:country":"UZ",
    "name:uzb_x_preferred":[
        "Xonqishloq"
    ],
    "wof:name":"Xonqishloq",
    "wof:placetype":"locality"
},
  "geometry": {"coordinates":[71.00919,40.62694000000001],"type":"Point"}
}