{
  "type": "Feature",
  "properties": {
    "gn:admin1_code":"09",
    "gn:asciiname":"Kenagas",
    "gn:country_code":"UZ",
    "gn:dem":76,
    "gn:feature_class":"P",
    "gn:feature_code":"PPL",
    "gn:name":"Kenagas",
    "gn:population":0,
    "gn:timezone":"Asia/Samarkand",
    "iso:country":"UZ",
    "wof:name":"Kenagas",
    "wof:placetype":"locality"
},
  "geometry": {"coordinates":[59.53901,42.30446],"type":"Point"}
}