{
  "type": "Feature",
  "properties": {
    "gn:admin1_code":"01",
    "gn:asciiname":"To`rtko`l",
    "gn:country_code":"UZ",
    "gn:dem":446,
    "gn:feature_class":"P",
    "gn:feature_code":"PPL",
    "gn:name":"To\u2018rtko\u2018l",
    "gn:population":0,
    "gn:timezone":"Asia/Tashkent",
    "iso:country":"UZ",
    "name:rus_x_preferred":[
        "Turtkul\u2019"
    ],
    "name:und_x_variant":[
        "Dyurt-Kul\u2019",
        "Turtkul\u2019",
        "To\u2018rtko\u2018l"
    ],
    "name:uzb_x_preferred":[
        "To\u2018rtko\u2018l"
    ],
    "wof:name":"To`rtko`l",
    "wof:placetype":"locality"
},
  "geometry": {"coordinates":[72.19025000000001,40.88391],"type":"Point"}
}