{
  "type": "Feature",
  "properties": {
    "gn:admin1_code":"01",
    "gn:asciiname":"Botir",
    "gn:country_code":"UZ",
    "gn:dem":428,
    "gn:feature_class":"P",
    "gn:feature_code":"PPL",
    "gn:name":"Botir",
    "gn:population":0,
    "gn:timezone":"Asia/Tashkent",
    "iso:country":"UZ",
    "name:uzb_x_preferred":[
        "Botir"
    ],
    "wof:name":"Botir",
    "wof:placetype":"locality"
},
  "geometry": {"coordinates":[72.00516,40.87312],"type":"Point"}
}