{
  "type": "Feature",
  "properties": {
    "gn:admin1_code":"03",
    "gn:asciiname":"Jilgorodok",
    "gn:country_code":"UZ",
    "gn:dem":484,
    "gn:feature_class":"P",
    "gn:feature_code":"PPL",
    "gn:name":"Jilgorodok",
    "gn:population":0,
    "gn:timezone":"Asia/Tashkent",
    "iso:country":"UZ",
    "name:uzb_x_preferred":[
        "Jilgorodok"
    ],
    "wof:name":"Jilgorodok",
    "wof:placetype":"locality"
},
  "geometry": {"coordinates":[71.61509000000002,40.41163],"type":"Point"}
}