{
  "type": "Feature",
  "properties": {
    "gn:admin1_code":"03",
    "gn:asciiname":"Uymovut",
    "gn:country_code":"UZ",
    "gn:dem":371,
    "gn:feature_class":"P",
    "gn:feature_code":"PPL",
    "gn:name":"Uymovut",
    "gn:population":0,
    "gn:timezone":"Asia/Tashkent",
    "iso:country":"UZ",
    "name:eng_x_preferred":[
        "Uymovut"
    ],
    "wof:name":"Uymovut",
    "wof:placetype":"locality"
},
  "geometry": {"coordinates":[70.90428,40.72329000000001],"type":"Point"}
}