{
  "type": "Feature",
  "properties": {
    "gn:admin1_code":"01",
    "gn:asciiname":"Chavqon",
    "gn:country_code":"UZ",
    "gn:dem":502,
    "gn:feature_class":"P",
    "gn:feature_code":"PPL",
    "gn:name":"Chavqon",
    "gn:population":0,
    "gn:timezone":"Asia/Tashkent",
    "iso:country":"UZ",
    "name:rus_x_preferred":[
        "\u0427\u0430\u0432\u043a\u0430\u043d"
    ],
    "name:und_x_variant":[
        "Chavkan"
    ],
    "name:uzb_x_preferred":[
        "Chavqon"
    ],
    "wof:name":"Chavqon",
    "wof:placetype":"locality"
},
  "geometry": {"coordinates":[72.44382,40.88727],"type":"Point"}
}