{
  "type": "Feature",
  "properties": {
    "gn:admin1_code":"01",
    "gn:asciiname":"Xodirsho",
    "gn:country_code":"UZ",
    "gn:dem":735,
    "gn:feature_class":"P",
    "gn:feature_code":"PPL",
    "gn:name":"Xodirsho",
    "gn:population":0,
    "gn:timezone":"Asia/Tashkent",
    "iso:country":"UZ",
    "name:rus_x_preferred":[
        "\u0425\u0430\u0434\u044b\u0440\u0448\u0430"
    ],
    "name:und_x_variant":[
        "Khadyrsha"
    ],
    "name:uzb_x_preferred":[
        "Xodirsho"
    ],
    "name:uzb_x_variant":[
        "Xidirsho"
    ],
    "wof:name":"Xodirsho",
    "wof:placetype":"locality"
},
  "geometry": {"coordinates":[73.02663000000003,40.83646],"type":"Point"}
}