{
  "type": "Feature",
  "properties": {
    "gn:admin1_code":"06",
    "gn:asciiname":"Kaptol Qishloq",
    "gn:country_code":"UZ",
    "gn:dem":1531,
    "gn:feature_class":"P",
    "gn:feature_code":"PPL",
    "gn:name":"Kaptol Qishloq",
    "gn:population":0,
    "gn:timezone":"Asia/Tashkent",
    "iso:country":"UZ",
    "name:eng_x_preferred":[
        "Kaptol Qishloq"
    ],
    "wof:name":"Kaptol Qishloq",
    "wof:placetype":"locality"
},
  "geometry": {"coordinates":[70.79467,41.004],"type":"Point"}
}