{
  "type": "Feature",
  "properties": {
    "gn:admin1_code":"00",
    "gn:asciiname":"Tash-Kash",
    "gn:cc2":"UZ",
    "gn:country_code":"UZ",
    "gn:dem":223,
    "gn:feature_class":"P",
    "gn:feature_code":"PPL",
    "gn:name":"Tash-Kash",
    "gn:population":0,
    "gn:timezone":"Asia/Samarkand",
    "iso:country":"UZ",
    "name:und_x_variant":[
        "Arablya",
        "Tash-Kash"
    ],
    "wof:name":"Tash-Kash",
    "wof:placetype":"locality"
},
  "geometry": {"coordinates":[64.59999999999999,39.78333],"type":"Point"}
}