{
  "type": "Feature",
  "properties": {
    "gn:admin1_code":"08",
    "gn:asciiname":"Qumqishloq",
    "gn:country_code":"UZ",
    "gn:dem":581,
    "gn:feature_class":"P",
    "gn:feature_code":"PPL",
    "gn:name":"Qumqishloq",
    "gn:population":0,
    "gn:timezone":"Asia/Samarkand",
    "iso:country":"UZ",
    "wof:name":"Qumqishloq",
    "wof:placetype":"locality"
},
  "geometry": {"coordinates":[66.74885,39.05629],"type":"Point"}
}