{
  "type": "Feature",
  "properties": {
    "gn:admin1_code":"03",
    "gn:asciiname":"Jarqishloq",
    "gn:country_code":"UZ",
    "gn:dem":413,
    "gn:feature_class":"P",
    "gn:feature_code":"PPL",
    "gn:name":"Jarqishloq",
    "gn:population":0,
    "gn:timezone":"Asia/Tashkent",
    "iso:country":"UZ",
    "name:uzb_x_preferred":[
        "Jarqishloq"
    ],
    "wof:name":"Jarqishloq",
    "wof:placetype":"locality"
},
  "geometry": {"coordinates":[70.63911999999998,40.39167],"type":"Point"}
}