{
  "type": "Feature",
  "properties": {
    "gn:admin1_code":"08",
    "gn:asciiname":"Olaqo`yli",
    "gn:country_code":"UZ",
    "gn:dem":631,
    "gn:feature_class":"P",
    "gn:feature_code":"PPL",
    "gn:name":"Olaqo\u2018yli",
    "gn:population":0,
    "gn:timezone":"Asia/Samarkand",
    "iso:country":"UZ",
    "wof:name":"Olaqo`yli",
    "wof:placetype":"locality"
},
  "geometry": {"coordinates":[66.82084,39.1531],"type":"Point"}
}