{
  "type": "Feature",
  "properties": {
    "gn:admin1_code":"14",
    "gn:asciiname":"Hosildor",
    "gn:country_code":"UZ",
    "gn:dem":290,
    "gn:feature_class":"P",
    "gn:feature_code":"PPL",
    "gn:name":"Hosildor",
    "gn:population":0,
    "gn:timezone":"Asia/Tashkent",
    "iso:country":"UZ",
    "name:uzb_x_preferred":[
        "Hosildor"
    ],
    "wof:name":"Hosildor",
    "wof:placetype":"locality"
},
  "geometry": {"coordinates":[68.94351,40.72954],"type":"Point"}
}