{
  "type": "Feature",
  "properties": {
    "iso:country":"UZ",
    "name:rus_x_preferred":[
        "\u041a\u043e\u0441\u043e\u043d"
    ],
    "name:unk_x_variant":[
        "Kassan"
    ],
    "qs:gn_country":"UZ",
    "qs:gn_fcode":"PPL",
    "qs:gn_pop":59681,
    "qs:name":"Kasan",
    "qs:name_adm0":"Uzbekistan",
    "qs:name_adm1":"Qashqadaryo",
    "qs:photos":0,
    "qs:photos_1k":0,
    "qs:photos_9k":1,
    "qs:photos_9r":1,
    "qs:photos_all":3,
    "qs:photos_sr":0,
    "qs:placetype":"Town",
    "qs:pop_sr":"8",
    "qs:woe_adm0":23424980,
    "wd:wordcount":49,
    "wof:name":"Kasan",
    "wof:placetype":"locality",
    "wof:population":59681
},
  "geometry": {"coordinates":[65.58499999999999,39.0375],"type":"Point"}
}