{
  "type": "Feature",
  "properties": {
    "gn:admin1_code":"12",
    "gn:asciiname":"Qorashiq",
    "gn:country_code":"UZ",
    "gn:dem":566,
    "gn:feature_class":"P",
    "gn:feature_code":"PPL",
    "gn:name":"Qorashiq",
    "gn:population":0,
    "gn:timezone":"Asia/Samarkand",
    "iso:country":"UZ",
    "name:und_x_variant":[
        "Karashik",
        "Karashin",
        "Qorashiq"
    ],
    "wof:name":"Qorashiq",
    "wof:placetype":"locality"
},
  "geometry": {"coordinates":[68.02606999999999,38.39051],"type":"Point"}
}