{
  "type": "Feature",
  "properties": {
    "gn:admin1_code":"03",
    "gn:asciiname":"Ucholish",
    "gn:country_code":"UZ",
    "gn:dem":472,
    "gn:feature_class":"P",
    "gn:feature_code":"PPL",
    "gn:name":"Ucholish",
    "gn:population":0,
    "gn:timezone":"Asia/Tashkent",
    "iso:country":"UZ",
    "name:und_x_variant":[
        "Uchalish"
    ],
    "name:uzb_x_preferred":[
        "Ucholish"
    ],
    "wof:name":"Ucholish",
    "wof:placetype":"locality"
},
  "geometry": {"coordinates":[71.85233000000002,40.52845],"type":"Point"}
}