{
  "type": "Feature",
  "properties": {
    "gn:admin1_code":"00",
    "gn:asciiname":"Durmen",
    "gn:country_code":"UZ",
    "gn:dem":246,
    "gn:feature_class":"P",
    "gn:feature_code":"PPL",
    "gn:name":"Durmen",
    "gn:population":0,
    "gn:timezone":"Asia/Samarkand",
    "iso:country":"UZ",
    "wof:name":"Durmen",
    "wof:placetype":"locality"
},
  "geometry": {"coordinates":[64.56667,40.11667],"type":"Point"}
}