{
  "type": "Feature",
  "properties": {
    "gn:admin1_code":"00",
    "gn:asciiname":"Imeni Lenina",
    "gn:cc2":"UZ",
    "gn:country_code":"UZ",
    "gn:dem":90,
    "gn:feature_class":"P",
    "gn:feature_code":"PPL",
    "gn:name":"Imeni Lenina",
    "gn:population":0,
    "gn:timezone":"Asia/Samarkand",
    "iso:country":"UZ",
    "name:und_x_variant":[
        "Khayrabad",
        "Imeni Lenina"
    ],
    "wof:name":"Imeni Lenina",
    "wof:placetype":"locality"
},
  "geometry": {"coordinates":[60.15,41.48333],"type":"Point"}
}