{
  "type": "Feature",
  "properties": {
    "gn:admin1_code":"06",
    "gn:asciiname":"Kichik-Mirzaorol",
    "gn:country_code":"UZ",
    "gn:dem":373,
    "gn:feature_class":"P",
    "gn:feature_code":"PPL",
    "gn:name":"Kichik-Mirzaorol",
    "gn:population":0,
    "gn:timezone":"Asia/Tashkent",
    "iso:country":"UZ",
    "name:eng_x_preferred":[
        "Kichik-Mirzaorol"
    ],
    "wof:name":"Kichik-Mirzaorol",
    "wof:placetype":"locality"
},
  "geometry": {"coordinates":[71.09778,40.83194],"type":"Point"}
}