{
  "type": "Feature",
  "properties": {
    "gn:admin1_code":"01",
    "gn:asciiname":"Kirov",
    "gn:country_code":"UZ",
    "gn:dem":475,
    "gn:feature_class":"P",
    "gn:feature_code":"PPL",
    "gn:name":"Kirov",
    "gn:population":0,
    "gn:timezone":"Asia/Tashkent",
    "iso:country":"UZ",
    "name:ara_x_preferred":[
        "\u0643\u064a\u0631\u0648\u0641"
    ],
    "name:azb_x_preferred":[
        "\u06a9\u06cc\u0631\u0648\u0641"
    ],
    "name:aze_x_preferred":[
        "Kirov"
    ],
    "name:bel_x_preferred":[
        "\u041a\u0456\u0440\u0430\u045e"
    ],
    "name:bul_x_preferred":[
        "\u041a\u0438\u0440\u043e\u0432"
    ],
    "name:cat_x_preferred":[
        "K\u00edrov"
    ],
    "name:ceb_x_preferred":[
        "Kirov"
    ],
    "name:ces_x_preferred":[
        "Kirov"
    ],
    "name:che_x_preferred":[
        "\u041a\u0438\u0440\u043e\u0432"
    ],
    "name:deu_x_preferred":[
        "Kirow"
    ],
    "name:epo_x_preferred":[
        "Kirov"
    ],
    "name:fas_x_preferred":[
        "\u06a9\u06cc\u0631\u0648\u0641"
    ],
    "name:fin_x_preferred":[
        "Kirov"
    ],
    "name:fra_x_preferred":[
        "Kirov"
    ],
    "name:heb_x_preferred":[
        "\u05e7\u05d9\u05e8\u05d5\u05d1"
    ],
    "name:hin_x_preferred":[
        "\u0915\u093f\u0930\u094b\u0935"
    ],
    "name:hrv_x_preferred":[
        "Kirov"
    ],
    "name:hun_x_preferred":[
        "Kirov"
    ],
    "name:hye_x_preferred":[
        "\u053f\u056b\u0580\u0578\u057e"
    ],
    "name:ind_x_preferred":[
        "Kirov"
    ],
    "name:ita_x_preferred":[
        "Kirov"
    ],
    "name:kat_x_preferred":[
        "\u10d9\u10d8\u10e0\u10dd\u10d5\u10d8"
    ],
    "name:kir_x_preferred":[
        "\u041a\u0438\u0440\u043e\u0432"
    ],
    "name:kor_x_preferred":[
        "\ud0a4\ub85c\ud504"
    ],
    "name:lat_x_preferred":[
        "Kirov"
    ],
    "name:lit_x_preferred":[
        "Kirovas"
    ],
    "name:ltz_x_preferred":[
        "Kirow"
    ],
    "name:nds_x_preferred":[
        "Kirow"
    ],
    "name:nld_x_preferred":[
        "Kirov"
    ],
    "name:nno_x_preferred":[
        "Kirov"
    ],
    "name:nor_x_preferred":[
        "Kirov"
    ],
    "name:oss_x_preferred":[
        "\u041a\u0438\u0440\u043e\u0432"
    ],
    "name:pol_x_preferred":[
        "Kirow"
    ],
    "name:por_x_preferred":[
        "Kirov"
    ],
    "name:rus_x_preferred":[
        "\u041a\u0438\u0440\u043e\u0432"
    ],
    "name:sco_x_preferred":[
        "Kirov"
    ],
    "name:slk_x_preferred":[
        "Kirov"
    ],
    "name:spa_x_preferred":[
        "Kirov"
    ],
    "name:spa_x_variant":[
        "K\u00edrov"
    ],
    "name:swa_x_preferred":[
        "Kirov"
    ],
    "name:swe_x_preferred":[
        "Kirov"
    ],
    "name:tur_x_preferred":[
        "Kirov"
    ],
    "name:ukr_x_preferred":[
        "\u041a\u0456\u0440\u043e\u0432"
    ],
    "name:urd_x_preferred":[
        "\u06a9\u0627\u0626\u06cc\u0631\u0648\u0648"
    ],
    "name:vie_x_preferred":[
        "Kirov"
    ],
    "name:zho_x_preferred":[
        "\u57fa\u6d1b\u592b"
    ],
    "wof:name":"Kirov",
    "wof:placetype":"locality"
},
  "geometry": {"coordinates":[72.30459999999999,40.76872],"type":"Point"}
}