{
  "type": "Feature",
  "properties": {
    "gn:admin1_code":"01",
    "gn:asciiname":"Kirov",
    "gn:country_code":"UZ",
    "gn:dem":475,
    "gn:feature_class":"P",
    "gn:feature_code":"PPL",
    "gn:name":"Kirov",
    "gn:population":0,
    "gn:timezone":"Asia/Tashkent",
    "iso:country":"UZ",
    "name:rus_x_preferred":[
        "\u041a\u0438\u0440\u043e\u0432"
    ],
    "wof:name":"Kirov",
    "wof:placetype":"locality"
},
  "geometry": {"coordinates":[72.30459999999999,40.76872],"type":"Point"}
}