{
  "type": "Feature",
  "properties": {
    "iso:country":"UZ",
    "name:azb_x_preferred":[
        "\u0642\u0627\u0631\u0627\u0648\u0648\u0644 \u0628\u0627\u0632\u0627\u0631"
    ],
    "name:ceb_x_preferred":[
        "Qorovulbozor"
    ],
    "name:eng_x_preferred":[
        "Karaulbazar"
    ],
    "name:fra_x_preferred":[
        "Karaulbazar"
    ],
    "name:hsb_x_preferred":[
        "Qorovulbozor"
    ],
    "name:ita_x_preferred":[
        "Karaulbazar"
    ],
    "name:jpn_x_preferred":[
        "\u30ab\u30e9\u30a6\u30fc\u30eb\u30d0\u30b6\u30fc\u30eb"
    ],
    "name:kik_x_preferred":[
        "Qorovulbozor"
    ],
    "name:nld_x_preferred":[
        "Karaulbazar"
    ],
    "name:pol_x_preferred":[
        "Qorovulbozor"
    ],
    "name:rus_x_preferred":[
        "\u041a\u0430\u0440\u0430\u0443\u043b\u0431\u0430\u0437\u0430\u0440"
    ],
    "name:spa_x_preferred":[
        "Karaulbazar"
    ],
    "name:tat_x_preferred":[
        "\u041a\u0430\u0440\u0430\u0432\u044b\u043b\u0431\u0430\u0437\u0430\u0440"
    ],
    "name:tur_x_preferred":[
        "Karaulpazar"
    ],
    "name:ukr_x_preferred":[
        "\u041a\u0430\u0440\u0430\u0443\u043b\u0431\u0430\u0437\u0430\u0440"
    ],
    "name:urd_x_preferred":[
        "\u0642\u0627\u0631\u0627\u0648\u0648\u0644 \u0628\u0627\u0632\u0627\u0631"
    ],
    "name:uzb_x_preferred":[
        "Qorovulbozor"
    ],
    "qs:gn_country":"UZ",
    "qs:gn_fcode":"PPL",
    "qs:gn_pop":8618,
    "qs:name":"Qorovulbozor",
    "qs:name_adm0":"Uzbekistan",
    "qs:name_adm1":"Bukhoro",
    "qs:photos":0,
    "qs:photos_1k":0,
    "qs:photos_9k":0,
    "qs:photos_9r":0,
    "qs:photos_all":0,
    "qs:photos_sr":0,
    "qs:placetype":"Town",
    "qs:pop_sr":"5",
    "qs:woe_adm0":23424980,
    "wd:wordcount":30,
    "wof:name":"Qorovulbozor",
    "wof:placetype":"locality",
    "wof:population":8618
},
  "geometry": {"coordinates":[64.79361,39.50056],"type":"Point"}
}