{
  "type": "Feature",
  "properties": {
    "gn:admin1_code":"08",
    "gn:admin2_code":"Beshkent",
    "gn:asciiname":"Batash",
    "gn:country_code":"UZ",
    "gn:dem":371,
    "gn:feature_class":"P",
    "gn:feature_code":"PPL",
    "gn:name":"Batash",
    "gn:population":0,
    "gn:timezone":"Asia/Samarkand",
    "iso:country":"UZ",
    "name:spa_x_preferred":[
        "Sardoba Batash"
    ],
    "wof:name":"Batash",
    "wof:placetype":"locality"
},
  "geometry": {"coordinates":[65.74194,38.81694],"type":"Point"}
}