{
  "type": "Feature",
  "properties": {
    "gn:admin1_code":"14",
    "gn:asciiname":"O. Jo`rayev",
    "gn:country_code":"UZ",
    "gn:dem":324,
    "gn:feature_class":"P",
    "gn:feature_code":"PPL",
    "gn:name":"O. Jo\u2018rayev",
    "gn:population":0,
    "gn:timezone":"Asia/Tashkent",
    "iso:country":"UZ",
    "name:uzb_x_preferred":[
        "O. Jo\u2018rayev"
    ],
    "wof:name":"O. Jo`rayev",
    "wof:placetype":"locality"
},
  "geometry": {"coordinates":[69.16970000000001,40.77372],"type":"Point"}
}