{
  "type": "Feature",
  "properties": {
    "gn:admin1_code":"14",
    "gn:asciiname":"Yoshlik",
    "gn:country_code":"UZ",
    "gn:dem":287,
    "gn:feature_class":"P",
    "gn:feature_code":"PPL",
    "gn:name":"Yoshlik",
    "gn:population":0,
    "gn:timezone":"Asia/Tashkent",
    "iso:country":"UZ",
    "name:uzb_x_preferred":[
        "Yoshlik"
    ],
    "wof:name":"Yoshlik",
    "wof:placetype":"locality"
},
  "geometry": {"coordinates":[69.01097,40.83743],"type":"Point"}
}