{
  "type": "Feature",
  "properties": {
    "gn:admin1_code":"03",
    "gn:asciiname":"Xalqobod",
    "gn:country_code":"UZ",
    "gn:dem":383,
    "gn:feature_class":"P",
    "gn:feature_code":"PPL",
    "gn:name":"Xalqobod",
    "gn:population":0,
    "gn:timezone":"Asia/Tashkent",
    "iso:country":"UZ",
    "name:uzb_x_preferred":[
        "Xalqobod"
    ],
    "wof:name":"Xalqobod",
    "wof:placetype":"locality"
},
  "geometry": {"coordinates":[70.78237,40.51829],"type":"Point"}
}