{
  "type": "Feature",
  "properties": {
    "gn:admin1_code":"03",
    "gn:asciiname":"Tinchlik",
    "gn:country_code":"UZ",
    "gn:dem":434,
    "gn:feature_class":"P",
    "gn:feature_code":"PPL",
    "gn:name":"Tinchlik",
    "gn:population":0,
    "gn:timezone":"Asia/Tashkent",
    "iso:country":"UZ",
    "name:und_x_variant":[
        "Vodkhoz"
    ],
    "name:uzb_x_preferred":[
        "Tinchlik"
    ],
    "wof:name":"Tinchlik",
    "wof:placetype":"locality"
},
  "geometry": {"coordinates":[71.55089,40.47591],"type":"Point"}
}