{
  "type": "Feature",
  "properties": {
    "gn:admin1_code":"08",
    "gn:asciiname":"Past Uyshun",
    "gn:country_code":"UZ",
    "gn:dem":606,
    "gn:feature_class":"P",
    "gn:feature_code":"PPL",
    "gn:name":"Past Uyshun",
    "gn:population":0,
    "gn:timezone":"Asia/Samarkand",
    "iso:country":"UZ",
    "wof:name":"Past Uyshun",
    "wof:placetype":"locality"
},
  "geometry": {"coordinates":[66.48491999999999,39.24073],"type":"Point"}
}