{
  "type": "Feature",
  "properties": {
    "gn:admin1_code":"08",
    "gn:asciiname":"Qulchiyali",
    "gn:country_code":"UZ",
    "gn:dem":539,
    "gn:feature_class":"P",
    "gn:feature_code":"PPL",
    "gn:name":"Qulchiyali",
    "gn:population":0,
    "gn:timezone":"Asia/Samarkand",
    "iso:country":"UZ",
    "wof:name":"Qulchiyali",
    "wof:placetype":"locality"
},
  "geometry": {"coordinates":[66.41981,39.17301],"type":"Point"}
}