{
  "type": "Feature",
  "properties": {
    "gn:admin1_code":"10",
    "gn:asciiname":"Bazardzhay",
    "gn:cc2":"UZ",
    "gn:country_code":"UZ",
    "gn:dem":880,
    "gn:feature_class":"P",
    "gn:feature_code":"PPL",
    "gn:name":"Bazardzhay",
    "gn:population":0,
    "gn:timezone":"Asia/Samarkand",
    "iso:country":"UZ",
    "name:und_x_variant":[
        "Bazar-Dzhoy",
        "Kipchaksu",
        "Bazardzhay"
    ],
    "wof:name":"Bazardzhay",
    "wof:placetype":"locality"
},
  "geometry": {"coordinates":[67.23860999999999,39.97167],"type":"Point"}
}