{
  "type": "Feature",
  "properties": {
    "gn:admin1_code":"06",
    "gn:asciiname":"Qorashahar",
    "gn:country_code":"UZ",
    "gn:dem":379,
    "gn:feature_class":"P",
    "gn:feature_code":"PPL",
    "gn:name":"Qorashahar",
    "gn:population":0,
    "gn:timezone":"Asia/Tashkent",
    "iso:country":"UZ",
    "name:eng_x_preferred":[
        "Qorashahar"
    ],
    "wof:name":"Qorashahar",
    "wof:placetype":"locality"
},
  "geometry": {"coordinates":[71.2629,40.85359],"type":"Point"}
}