{
  "type": "Feature",
  "properties": {
    "gn:admin1_code":"08",
    "gn:asciiname":"Oqoltin",
    "gn:country_code":"UZ",
    "gn:dem":647,
    "gn:feature_class":"P",
    "gn:feature_code":"PPL",
    "gn:name":"Oqoltin",
    "gn:population":0,
    "gn:timezone":"Asia/Samarkand",
    "iso:country":"UZ",
    "wof:name":"Oqoltin",
    "wof:placetype":"locality"
},
  "geometry": {"coordinates":[66.53745000000001,39.25143],"type":"Point"}
}