{
  "type": "Feature",
  "properties": {
    "gn:admin1_code":"08",
    "gn:asciiname":"Oqoltin",
    "gn:country_code":"UZ",
    "gn:dem":647,
    "gn:feature_class":"P",
    "gn:feature_code":"PPL",
    "gn:name":"Oqoltin",
    "gn:population":0,
    "gn:timezone":"Asia/Samarkand",
    "iso:country":"UZ",
    "name:deu_x_preferred":[
        "Oqoltin"
    ],
    "name:ell_x_preferred":[
        "\u039f\u03ba\u03bf\u03bb\u03c4\u03af\u03bd"
    ],
    "name:kik_x_preferred":[
        "Oqoltin"
    ],
    "name:pnb_x_preferred":[
        "\u0622\u06a9\u0648\u0644\u062a\u06cc\u0646"
    ],
    "name:rus_x_preferred":[
        "\u0410\u043a\u0430\u043b\u0442\u044b\u043d"
    ],
    "name:tur_x_preferred":[
        "Akalt\u0131n"
    ],
    "name:ukr_x_preferred":[
        "\u0410\u043a\u0430\u043b\u0442\u0438\u043d"
    ],
    "name:urd_x_preferred":[
        "\u0627\u0642\u0648\u0644\u062a\u06cc\u0646"
    ],
    "name:uzb_x_preferred":[
        "Oqoltin"
    ],
    "wof:name":"Oqoltin",
    "wof:placetype":"locality"
},
  "geometry": {"coordinates":[66.53745000000001,39.25143],"type":"Point"}
}