{
  "type": "Feature",
  "properties": {
    "gn:admin1_code":"01",
    "gn:asciiname":"Damariq",
    "gn:country_code":"UZ",
    "gn:dem":504,
    "gn:feature_class":"P",
    "gn:feature_code":"PPL",
    "gn:name":"Damariq",
    "gn:population":0,
    "gn:timezone":"Asia/Tashkent",
    "iso:country":"UZ",
    "name:rus_x_preferred":[
        "\u0414\u0430\u043c\u0430\u0440\u044b\u043a"
    ],
    "name:und_x_variant":[
        "Damaryk"
    ],
    "name:uzb_x_preferred":[
        "Damariq"
    ],
    "wof:name":"Damariq",
    "wof:placetype":"locality"
},
  "geometry": {"coordinates":[72.36373,40.80067],"type":"Point"}
}