{
  "type": "Feature",
  "properties": {
    "gn:country":"UZ",
    "gn:fcode":"PPL",
    "gn:population":26950,
    "iso:country":"UZ",
    "name:ast_x_preferred":[
        "Shovot"
    ],
    "name:deu_x_preferred":[
        "Shovot"
    ],
    "name:eng_x_preferred":[
        "Shovot"
    ],
    "name:fas_x_preferred":[
        "\u0634\u0627\u0648\u0627\u062a"
    ],
    "name:fra_x_preferred":[
        "Shovot"
    ],
    "name:hun_x_preferred":[
        "Savat"
    ],
    "name:ita_x_preferred":[
        "Shovot"
    ],
    "name:jpn_x_preferred":[
        "\u30b7\u30e3\u30f4\u30a1\u30c8"
    ],
    "name:kik_x_preferred":[
        "Shovot"
    ],
    "name:nld_x_preferred":[
        "Shovot"
    ],
    "name:pol_x_preferred":[
        "Shovot"
    ],
    "name:rus_x_preferred":[
        "\u0428\u0430\u0432\u0430\u0442"
    ],
    "name:spa_x_preferred":[
        "Shovot"
    ],
    "name:tur_x_preferred":[
        "\u015eavat"
    ],
    "name:und_x_variant":[
        "Shavat"
    ],
    "name:urd_x_preferred":[
        "\u0634\u0627\u0648\u0627\u062a"
    ],
    "name:uzb_x_preferred":[
        "Shovot"
    ],
    "qs_pg:aaroncc":"UZ",
    "qs_pg:gn_country":"UZ",
    "qs_pg:gn_fcode":"PPL",
    "qs_pg:gn_pop":26950,
    "qs_pg:name":"Showot",
    "qs_pg:photos_9r":0,
    "qs_pg:photos_sr":0,
    "qs_pg:pop_sr":7,
    "qs_pg:qs_pg_placetype":"locality",
    "wof:name":"Showot",
    "wof:placetype":"locality",
    "wof:population":26950
},
  "geometry": {"coordinates":[60.3025,41.65583],"type":"Point"}
}