{
  "type": "Feature",
  "properties": {
    "gn:admin1_code":"14",
    "gn:asciiname":"Sewerniy Mayak",
    "gn:cc2":"UZ",
    "gn:country_code":"UZ",
    "gn:dem":424,
    "gn:feature_class":"P",
    "gn:feature_code":"PPL",
    "gn:name":"Sewerniy Mayak",
    "gn:population":0,
    "gn:timezone":"Asia/Tashkent",
    "iso:country":"UZ",
    "name:und_x_variant":[
        "Uchastok Severnyy Mayak",
        "Severnyy Mayak",
        "Sewerniy Mayak"
    ],
    "wof:name":"Sewerniy Mayak",
    "wof:placetype":"locality"
},
  "geometry": {"coordinates":[69.38778000000001,41.18861],"type":"Point"}
}