{
  "type": "Feature",
  "properties": {
    "gn:admin1_code":"08",
    "gn:asciiname":"Zamit",
    "gn:country_code":"UZ",
    "gn:dem":1311,
    "gn:feature_class":"P",
    "gn:feature_code":"PPL",
    "gn:name":"Zamit",
    "gn:population":0,
    "gn:timezone":"Asia/Samarkand",
    "iso:country":"UZ",
    "wof:name":"Zamit",
    "wof:placetype":"locality"
},
  "geometry": {"coordinates":[67.05126,38.85143],"type":"Point"}
}