{
  "type": "Feature",
  "properties": {
    "gn:admin1_code":"00",
    "gn:asciiname":"Peshku",
    "gn:cc2":"UZ",
    "gn:country_code":"UZ",
    "gn:dem":226,
    "gn:feature_class":"P",
    "gn:feature_code":"PPL",
    "gn:name":"Peshku",
    "gn:population":0,
    "gn:timezone":"Asia/Samarkand",
    "iso:country":"UZ",
    "name:und_x_variant":[
        "Peshkou",
        "Peshku"
    ],
    "wof:name":"Peshku",
    "wof:placetype":"locality"
},
  "geometry": {"coordinates":[64.33333,40.03333],"type":"Point"}
}