{
  "type": "Feature",
  "properties": {
    "gn:admin1_code":"12",
    "gn:asciiname":"Pistamazar",
    "gn:country_code":"UZ",
    "gn:dem":505,
    "gn:feature_class":"P",
    "gn:feature_code":"PPL",
    "gn:name":"Pistamazar",
    "gn:population":0,
    "gn:timezone":"Asia/Samarkand",
    "iso:country":"UZ",
    "name:und_x_variant":[
        "Pistmazar",
        "Psta-Mazar",
        "Pistamazar"
    ],
    "wof:name":"Pistamazar",
    "wof:placetype":"locality"
},
  "geometry": {"coordinates":[67.9426,38.27342],"type":"Point"}
}