{
  "type": "Feature",
  "properties": {
    "gn:admin1_code":"06",
    "gn:asciiname":"Kichik-Oyboq",
    "gn:country_code":"UZ",
    "gn:dem":440,
    "gn:feature_class":"P",
    "gn:feature_code":"PPL",
    "gn:name":"Kichik-Oyboq",
    "gn:population":0,
    "gn:timezone":"Asia/Tashkent",
    "iso:country":"UZ",
    "name:eng_x_preferred":[
        "Kichik-Oyboq"
    ],
    "name:und_x_variant":[
        "Kichik-Yaydak"
    ],
    "name:uzb_x_preferred":[
        "Kichik-Oyboq"
    ],
    "wof:name":"Kichik-Oyboq",
    "wof:placetype":"locality"
},
  "geometry": {"coordinates":[72.09614999999999,40.92761],"type":"Point"}
}