{
  "type": "Feature",
  "properties": {
    "gn:admin1_code":"08",
    "gn:asciiname":"Suvlik",
    "gn:country_code":"UZ",
    "gn:dem":491,
    "gn:feature_class":"P",
    "gn:feature_code":"PPL",
    "gn:name":"Suvlik",
    "gn:population":0,
    "gn:timezone":"Asia/Samarkand",
    "iso:country":"UZ",
    "name:und_x_variant":[
        "Suluk",
        "Sulak",
        "Suvlik"
    ],
    "wof:name":"Suvlik",
    "wof:placetype":"locality"
},
  "geometry": {"coordinates":[66.31152,39.13363],"type":"Point"}
}