{
  "type": "Feature",
  "properties": {
    "gn:admin1_code":"01",
    "gn:asciiname":"Chapayev",
    "gn:country_code":"UZ",
    "gn:dem":481,
    "gn:feature_class":"P",
    "gn:feature_code":"PPL",
    "gn:name":"Chapayev",
    "gn:population":0,
    "gn:timezone":"Asia/Tashkent",
    "iso:country":"UZ",
    "name:rus_x_preferred":[
        "\u0427\u0430\u043f\u0430\u0435\u0432"
    ],
    "wof:name":"Chapayev",
    "wof:placetype":"locality"
},
  "geometry": {"coordinates":[72.33214,40.92043],"type":"Point"}
}