{
  "type": "Feature",
  "properties": {
    "gn:admin1_code":"12",
    "gn:asciiname":"Sayrob",
    "gn:cc2":"UZ",
    "gn:country_code":"UZ",
    "gn:dem":1003,
    "gn:feature_class":"P",
    "gn:feature_code":"PPL",
    "gn:name":"Sayrob",
    "gn:population":0,
    "gn:timezone":"Asia/Samarkand",
    "iso:country":"UZ",
    "name:und_x_variant":[
        "Sairob",
        "Sayrob"
    ],
    "wof:name":"Sayrob",
    "wof:placetype":"locality"
},
  "geometry": {"coordinates":[66.96666999999999,38.07472],"type":"Point"}
}