{
  "type": "Feature",
  "properties": {
    "gn:admin1_code":"08",
    "gn:asciiname":"Xiyobon",
    "gn:country_code":"UZ",
    "gn:dem":756,
    "gn:feature_class":"P",
    "gn:feature_code":"PPL",
    "gn:name":"Xiyobon",
    "gn:population":0,
    "gn:timezone":"Asia/Samarkand",
    "iso:country":"UZ",
    "wof:name":"Xiyobon",
    "wof:placetype":"locality"
},
  "geometry": {"coordinates":[66.86667,38.93369000000001],"type":"Point"}
}