{
  "type": "Feature",
  "properties": {
    "gn:admin1_code":"03",
    "gn:asciiname":"Qashqar",
    "gn:country_code":"UZ",
    "gn:dem":440,
    "gn:feature_class":"P",
    "gn:feature_code":"PPL",
    "gn:name":"Qashqar",
    "gn:population":0,
    "gn:timezone":"Asia/Tashkent",
    "iso:country":"UZ",
    "name:uzb_x_preferred":[
        "Qashqar"
    ],
    "wof:name":"Qashqar",
    "wof:placetype":"locality"
},
  "geometry": {"coordinates":[70.88874,40.46643],"type":"Point"}
}