{
  "type": "Feature",
  "properties": {
    "gn:admin1_code":"16",
    "gn:asciiname":"Xalqobod",
    "gn:country_code":"UZ",
    "gn:dem":271,
    "gn:feature_class":"P",
    "gn:feature_code":"PPL",
    "gn:name":"Xalqobod",
    "gn:population":0,
    "gn:timezone":"Asia/Tashkent",
    "iso:country":"UZ",
    "name:uzb_x_preferred":[
        "Xalqobod"
    ],
    "wof:name":"Xalqobod",
    "wof:placetype":"locality"
},
  "geometry": {"coordinates":[68.74656,40.45275],"type":"Point"}
}