{
  "type": "Feature",
  "properties": {
    "gn:admin1_code":"01",
    "gn:asciiname":"Kamoltepa",
    "gn:country_code":"UZ",
    "gn:dem":446,
    "gn:feature_class":"P",
    "gn:feature_code":"PPL",
    "gn:name":"Kamoltepa",
    "gn:population":0,
    "gn:timezone":"Asia/Tashkent",
    "iso:country":"UZ",
    "name:uzb_x_preferred":[
        "Kamoltepa"
    ],
    "wof:name":"Kamoltepa",
    "wof:placetype":"locality"
},
  "geometry": {"coordinates":[71.99655,40.6771],"type":"Point"}
}