{
  "type": "Feature",
  "properties": {
    "gn:admin1_code":"16",
    "gn:asciiname":"Sobir Rahimov",
    "gn:country_code":"UZ",
    "gn:dem":289,
    "gn:feature_class":"P",
    "gn:feature_code":"PPL",
    "gn:name":"Sobir Rahimov",
    "gn:population":0,
    "gn:timezone":"Asia/Tashkent",
    "iso:country":"UZ",
    "name:uzb_x_preferred":[
        "Sobir Rahimov"
    ],
    "wof:name":"Sobir Rahimov",
    "wof:placetype":"locality"
},
  "geometry": {"coordinates":[68.94419000000001,40.37494],"type":"Point"}
}