{
  "type": "Feature",
  "properties": {
    "gn:admin1_code":"03",
    "gn:asciiname":"Koklen",
    "gn:country_code":"UZ",
    "gn:dem":730,
    "gn:feature_class":"P",
    "gn:feature_code":"PPL",
    "gn:name":"Koklen",
    "gn:population":0,
    "gn:timezone":"Asia/Tashkent",
    "iso:country":"UZ",
    "name:uzb_x_preferred":[
        "Koklen"
    ],
    "name:uzb_x_variant":[
        "Kokilon"
    ],
    "wof:name":"Koklen",
    "wof:placetype":"locality"
},
  "geometry": {"coordinates":[71.91091,40.30745],"type":"Point"}
}