{
  "type": "Feature",
  "properties": {
    "iso:country":"UZ",
    "name:ara_x_preferred":[
        "\u0633\u064a\u062d\u0648\u0646"
    ],
    "name:ceb_x_preferred":[
        "Sirdaryo"
    ],
    "name:deu_x_preferred":[
        "Sirdaryo"
    ],
    "name:eng_x_preferred":[
        "Sirdaryo"
    ],
    "name:fas_x_preferred":[
        "\u0633\u06cc\u0631\u062f\u0627\u0631\u06cc\u0648"
    ],
    "name:fra_x_preferred":[
        "Sirdaryo"
    ],
    "name:heb_x_preferred":[
        "\u05e1\u05d9\u05e8\u05d3\u05d0\u05e8\u05d9\u05d5"
    ],
    "name:hsb_x_preferred":[
        "Sirdaryo"
    ],
    "name:hun_x_preferred":[
        "Sirdaryo"
    ],
    "name:hye_x_preferred":[
        "\u054d\u056b\u0580\u0564\u0561\u0580\u0575\u0561"
    ],
    "name:ita_x_preferred":[
        "Syrdarya"
    ],
    "name:ita_x_variant":[
        "Sirdaryo"
    ],
    "name:jpn_x_preferred":[
        "\u30b7\u30eb\u30c0\u30ea\u30e4"
    ],
    "name:kik_x_preferred":[
        "Sirdaryo"
    ],
    "name:nld_x_preferred":[
        "Sirdaryo"
    ],
    "name:nob_x_preferred":[
        "Sirdaryo"
    ],
    "name:nor_x_preferred":[
        "Sirdaryo"
    ],
    "name:pol_x_preferred":[
        "Syrdaria"
    ],
    "name:pol_x_variant":[
        "Sirdaryo"
    ],
    "name:rus_x_preferred":[
        "\u0421\u044b\u0440\u0434\u0430\u0440\u044c\u044f"
    ],
    "name:rus_x_variant":[
        "\u0421\u044b\u0440\u0434\u0430\u0440\u044c\u0438\u043d\u0441\u043a\u0430\u044f"
    ],
    "name:spa_x_preferred":[
        "Sirdaryo"
    ],
    "name:tat_x_preferred":[
        "\u0421\u044b\u0440\u0434\u04d9\u0440\u044c\u044f"
    ],
    "name:tuk_x_preferred":[
        "Syrdarya"
    ],
    "name:tur_x_preferred":[
        "Sirderya"
    ],
    "name:ukr_x_preferred":[
        "\u0421\u0438\u0440\u0434\u0430\u0440'\u044f"
    ],
    "name:und_x_variant":[
        "Syr-Novorossliski"
    ],
    "name:urd_x_preferred":[
        "\u0633\u06cc\u0631\u062f\u0631\u06cc\u0627"
    ],
    "name:urd_x_variant":[
        "\u0633\u06cc\u0631\u062f\u0631\u06cc\u0648"
    ],
    "name:uzb_x_preferred":[
        "Sirdaryo"
    ],
    "name:vie_x_preferred":[
        "Sirdaryo"
    ],
    "name:zho_x_preferred":[
        "\u9521\u5c14\u8fbe\u5229\u4e9a"
    ],
    "qs:gn_country":"UZ",
    "qs:gn_fcode":"PPL",
    "qs:gn_pop":26816,
    "qs:name":"Sirdaryo",
    "qs:name_adm0":"Uzbekistan",
    "qs:name_adm1":"Sirdaryo",
    "qs:photos":0,
    "qs:photos_1k":0,
    "qs:photos_9k":1,
    "qs:photos_9r":1,
    "qs:photos_all":1,
    "qs:photos_sr":0,
    "qs:placetype":"Town",
    "qs:pop_sr":"7",
    "qs:woe_adm0":23424980,
    "wd:wordcount":35,
    "wof:name":"Sirdaryo",
    "wof:placetype":"locality",
    "wof:population":26816
},
  "geometry": {"coordinates":[68.66167,40.84361],"type":"Point"}
}