{
  "type": "Feature",
  "properties": {
    "gn:admin1_code":"07",
    "gn:asciiname":"Karagalyk",
    "gn:country_code":"UZ",
    "gn:dem":744,
    "gn:feature_class":"P",
    "gn:feature_code":"PPL",
    "gn:name":"Karagalyk",
    "gn:population":0,
    "gn:timezone":"Asia/Samarkand",
    "iso:country":"UZ",
    "name:und_x_variant":[
        "Urta-Kishlak",
        "Gum",
        "Karagalyk"
    ],
    "wof:name":"Karagalyk",
    "wof:placetype":"locality"
},
  "geometry": {"coordinates":[66.21666999999999,40.55],"type":"Point"}
}