{
  "type": "Feature",
  "properties": {
    "gn:admin1_code":"03",
    "gn:asciiname":"Shoximardonobod",
    "gn:country_code":"UZ",
    "gn:dem":744,
    "gn:feature_class":"P",
    "gn:feature_code":"PPL",
    "gn:name":"Shoximardonobod",
    "gn:population":0,
    "gn:timezone":"Asia/Tashkent",
    "iso:country":"UZ",
    "name:uzb_x_preferred":[
        "Shoximardonobod"
    ],
    "wof:name":"Shoximardonobod",
    "wof:placetype":"locality"
},
  "geometry": {"coordinates":[71.76036999999999,40.26291],"type":"Point"}
}