{
  "type": "Feature",
  "properties": {
    "gn:admin1_code":"03",
    "gn:asciiname":"Kanjirga",
    "gn:country_code":"UZ",
    "gn:dem":479,
    "gn:feature_class":"P",
    "gn:feature_code":"PPL",
    "gn:name":"Kanjirga",
    "gn:population":0,
    "gn:timezone":"Asia/Tashkent",
    "iso:country":"UZ",
    "name:uzb_x_preferred":[
        "Kanjirga"
    ],
    "wof:name":"Kanjirga",
    "wof:placetype":"locality"
},
  "geometry": {"coordinates":[71.80544999999999,40.50422],"type":"Point"}
}