{
  "type": "Feature",
  "properties": {
    "gn:admin1_code":"08",
    "gn:asciiname":"Kunya-Fazli",
    "gn:country_code":"UZ",
    "gn:dem":304,
    "gn:feature_class":"P",
    "gn:feature_code":"PPL",
    "gn:name":"Kunya-Fazli",
    "gn:population":0,
    "gn:timezone":"Asia/Samarkand",
    "iso:country":"UZ",
    "name:und_x_variant":[
        "Kunya-Fazil\u2019",
        "Kunya-Fazli"
    ],
    "wof:name":"Kunya-Fazli",
    "wof:placetype":"locality"
},
  "geometry": {"coordinates":[65.28381999999999,38.75907],"type":"Point"}
}