{
  "type": "Feature",
  "properties": {
    "gn:admin1_code":"16",
    "gn:asciiname":"Bolg`ali",
    "gn:country_code":"UZ",
    "gn:dem":291,
    "gn:feature_class":"P",
    "gn:feature_code":"PPL",
    "gn:name":"Bolg\u2018ali",
    "gn:population":0,
    "gn:timezone":"Asia/Tashkent",
    "iso:country":"UZ",
    "name:uzb_x_preferred":[
        "Bolg\u2018ali"
    ],
    "wof:name":"Bolg`ali",
    "wof:placetype":"locality"
},
  "geometry": {"coordinates":[68.99198,40.38274000000001],"type":"Point"}
}