{
  "type": "Feature",
  "properties": {
    "gn:admin1_code":"01",
    "gn:asciiname":"Boymahalla",
    "gn:country_code":"UZ",
    "gn:dem":579,
    "gn:feature_class":"P",
    "gn:feature_code":"PPL",
    "gn:name":"Boymahalla",
    "gn:population":0,
    "gn:timezone":"Asia/Tashkent",
    "iso:country":"UZ",
    "name:uzb_x_preferred":[
        "Boymahalla"
    ],
    "wof:name":"Boymahalla",
    "wof:placetype":"locality"
},
  "geometry": {"coordinates":[72.42899,40.73381],"type":"Point"}
}