{
  "type": "Feature",
  "properties": {
    "gn:admin1_code":"08",
    "gn:asciiname":"Uz",
    "gn:country_code":"UZ",
    "gn:dem":711,
    "gn:feature_class":"P",
    "gn:feature_code":"PPL",
    "gn:name":"Uz",
    "gn:population":0,
    "gn:timezone":"Asia/Samarkand",
    "iso:country":"UZ",
    "wof:name":"Uz",
    "wof:placetype":"locality"
},
  "geometry": {"coordinates":[66.85061999999999,38.9427],"type":"Point"}
}