{
  "type": "Feature",
  "properties": {
    "gn:admin1_code":"03",
    "gn:asciiname":"Sharqtongi",
    "gn:country_code":"UZ",
    "gn:dem":504,
    "gn:feature_class":"P",
    "gn:feature_code":"PPL",
    "gn:name":"Sharqtongi",
    "gn:population":0,
    "gn:timezone":"Asia/Tashkent",
    "iso:country":"UZ",
    "name:uzb_x_preferred":[
        "Sharqtongi"
    ],
    "wof:name":"Sharqtongi",
    "wof:placetype":"locality"
},
  "geometry": {"coordinates":[71.49025999999998,40.3624],"type":"Point"}
}