{
  "type": "Feature",
  "properties": {
    "gn:admin1_code":"01",
    "gn:asciiname":"Mingchinor",
    "gn:country_code":"UZ",
    "gn:dem":409,
    "gn:feature_class":"P",
    "gn:feature_code":"PPL",
    "gn:name":"Mingchinor",
    "gn:population":0,
    "gn:timezone":"Asia/Tashkent",
    "iso:country":"UZ",
    "name:und_x_variant":[
        "Sovkhoz Sto Let V.I. Lenina"
    ],
    "name:uzb_x_preferred":[
        "Mingchinor"
    ],
    "wof:name":"Mingchinor",
    "wof:placetype":"locality"
},
  "geometry": {"coordinates":[71.61638000000001,40.68697],"type":"Point"}
}