{
  "type": "Feature",
  "properties": {
    "gn:admin1_code":"03",
    "gn:asciiname":"Yangiobod",
    "gn:country_code":"UZ",
    "gn:dem":406,
    "gn:feature_class":"P",
    "gn:feature_code":"PPL",
    "gn:name":"Yangiobod",
    "gn:population":0,
    "gn:timezone":"Asia/Tashkent",
    "iso:country":"UZ",
    "name:und_x_variant":[
        "Yangiabad"
    ],
    "name:uzb_x_preferred":[
        "Yangiobod"
    ],
    "wof:name":"Yangiobod",
    "wof:placetype":"locality"
},
  "geometry": {"coordinates":[71.38268000000002,40.49536],"type":"Point"}
}