{
  "type": "Feature",
  "properties": {
    "gn:admin1_code":"07",
    "gn:asciiname":"Koskuduk",
    "gn:country_code":"UZ",
    "gn:dem":102,
    "gn:feature_class":"P",
    "gn:feature_code":"PPL",
    "gn:name":"Koskuduk",
    "gn:population":0,
    "gn:timezone":"Asia/Samarkand",
    "iso:country":"UZ",
    "wof:name":"Koskuduk",
    "wof:placetype":"locality"
},
  "geometry": {"coordinates":[63.28333000000001,41.71667],"type":"Point"}
}