{
  "type": "Feature",
  "properties": {
    "gn:admin1_code":"08",
    "gn:asciiname":"Kara-Sol'dy",
    "gn:country_code":"UZ",
    "gn:dem":582,
    "gn:feature_class":"P",
    "gn:feature_code":"PPL",
    "gn:name":"Kara-Sol\u2019dy",
    "gn:population":0,
    "gn:timezone":"Asia/Samarkand",
    "iso:country":"UZ",
    "name:rus_x_preferred":[
        "Kara-Sol\u2019dy"
    ],
    "wof:name":"Kara-Sol'dy",
    "wof:placetype":"locality"
},
  "geometry": {"coordinates":[66.73333000000001,39.01667],"type":"Point"}
}