{
  "type": "Feature",
  "properties": {
    "gn:admin1_code":"08",
    "gn:asciiname":"Bo`ztepa",
    "gn:country_code":"UZ",
    "gn:dem":1024,
    "gn:feature_class":"P",
    "gn:feature_code":"PPL",
    "gn:name":"Bo\u2018ztepa",
    "gn:population":0,
    "gn:timezone":"Asia/Samarkand",
    "iso:country":"UZ",
    "name:und_x_variant":[
        "Bo\u2018ztepa",
        "Buztepa"
    ],
    "wof:name":"Bo`ztepa",
    "wof:placetype":"locality"
},
  "geometry": {"coordinates":[66.48974,38.0408],"type":"Point"}
}