{
  "type": "Feature",
  "properties": {
    "gn:admin1_code":"14",
    "gn:asciiname":"Tavaksay",
    "gn:cc2":"UZ",
    "gn:country_code":"UZ",
    "gn:dem":665,
    "gn:feature_class":"P",
    "gn:feature_code":"PPL",
    "gn:name":"Tavaksay",
    "gn:population":0,
    "gn:timezone":"Asia/Tashkent",
    "iso:country":"UZ",
    "name:und_x_variant":[
        "Tavak",
        "Tavaksay"
    ],
    "wof:name":"Tavaksay",
    "wof:placetype":"locality"
},
  "geometry": {"coordinates":[69.68111,41.55417],"type":"Point"}
}