{
  "type": "Feature",
  "properties": {
    "gn:admin1_code":"10",
    "gn:asciiname":"Zartepa Qishloq",
    "gn:country_code":"UZ",
    "gn:dem":461,
    "gn:feature_class":"P",
    "gn:feature_code":"PPL",
    "gn:name":"Zartepa Qishloq",
    "gn:population":0,
    "gn:timezone":"Asia/Samarkand",
    "iso:country":"UZ",
    "name:eng_x_preferred":[
        "Zartepa Qishloq"
    ],
    "wof:name":"Zartepa Qishloq",
    "wof:placetype":"locality"
},
  "geometry": {"coordinates":[65.74727,39.66568],"type":"Point"}
}