{
  "type": "Feature",
  "properties": {
    "gn:admin1_code":"00",
    "gn:asciiname":"Dzhingil'dy",
    "gn:country_code":"UZ",
    "gn:dem":174,
    "gn:feature_class":"P",
    "gn:feature_code":"PPL",
    "gn:name":"Dzhingil\u2019dy",
    "gn:population":0,
    "gn:timezone":"Asia/Samarkand",
    "iso:country":"UZ",
    "name:rus_x_preferred":[
        "Dzhingil\u2019dy"
    ],
    "wof:name":"Dzhingil'dy",
    "wof:placetype":"locality"
},
  "geometry": {"coordinates":[62.58333,40.31667],"type":"Point"}
}