{
  "type": "Feature",
  "properties": {
    "gn:admin1_code":"09",
    "gn:asciiname":"Kampirtepa",
    "gn:country_code":"UZ",
    "gn:dem":71,
    "gn:feature_class":"P",
    "gn:feature_code":"PPL",
    "gn:name":"Kampirtepa",
    "gn:population":0,
    "gn:timezone":"Asia/Samarkand",
    "iso:country":"UZ",
    "wof:name":"Kampirtepa",
    "wof:placetype":"locality"
},
  "geometry": {"coordinates":[61.64332,42.9371],"type":"Point"}
}