{
  "type": "Feature",
  "properties": {
    "gn:admin1_code":"14",
    "gn:asciiname":"Dumaloq",
    "gn:cc2":"UZ",
    "gn:country_code":"UZ",
    "gn:dem":675,
    "gn:feature_class":"P",
    "gn:feature_code":"PPLL",
    "gn:name":"Dumaloq",
    "gn:population":0,
    "gn:timezone":"Asia/Tashkent",
    "iso:country":"UZ",
    "name:und_x_variant":[
        "Domalak",
        "Dumalak",
        "Dumaloq"
    ],
    "wof:name":"Dumaloq",
    "wof:placetype":"locality"
},
  "geometry": {"coordinates":[69.71389000000001,41.54111],"type":"Point"}
}