{
  "type": "Feature",
  "properties": {
    "gn:admin1_code":"00",
    "gn:asciiname":"Imeni Kalinina",
    "gn:country_code":"UZ",
    "gn:dem":598,
    "gn:feature_class":"P",
    "gn:feature_code":"PPL",
    "gn:name":"Imeni Kalinina",
    "gn:population":0,
    "gn:timezone":"Asia/Samarkand",
    "iso:country":"UZ",
    "name:kir_x_preferred":[
        "\u041a\u0430\u043b\u0438\u043d\u0438\u043d"
    ],
    "name:uzb_x_preferred":[
        "Kalinin"
    ],
    "wof:name":"Imeni Kalinina",
    "wof:placetype":"locality"
},
  "geometry": {"coordinates":[66.78333000000001,40.01667],"type":"Point"}
}