{
  "type": "Feature",
  "properties": {
    "gn:admin1_code":"08",
    "gn:asciiname":"Machan",
    "gn:country_code":"UZ",
    "gn:dem":392,
    "gn:feature_class":"P",
    "gn:feature_code":"PPL",
    "gn:name":"Machan",
    "gn:population":0,
    "gn:timezone":"Asia/Samarkand",
    "iso:country":"UZ",
    "wof:name":"Machan",
    "wof:placetype":"locality"
},
  "geometry": {"coordinates":[65.86709,39.19588],"type":"Point"}
}