{
  "type": "Feature",
  "properties": {
    "gn:admin1_code":"00",
    "gn:asciiname":"Goray-Topas",
    "gn:country_code":"UZ",
    "gn:dem":786,
    "gn:feature_class":"P",
    "gn:feature_code":"PPL",
    "gn:name":"Goray-Topas",
    "gn:population":0,
    "gn:timezone":"Asia/Samarkand",
    "iso:country":"UZ",
    "wof:name":"Goray-Topas",
    "wof:placetype":"locality"
},
  "geometry": {"coordinates":[66.90000000000001,40.16667],"type":"Point"}
}