{
  "type": "Feature",
  "properties": {
    "gn:admin1_code":"08",
    "gn:asciiname":"Chumych",
    "gn:country_code":"UZ",
    "gn:dem":585,
    "gn:feature_class":"P",
    "gn:feature_code":"PPL",
    "gn:name":"Chumych",
    "gn:population":0,
    "gn:timezone":"Asia/Samarkand",
    "iso:country":"UZ",
    "wof:name":"Chumych",
    "wof:placetype":"locality"
},
  "geometry": {"coordinates":[66.68333,38.96667],"type":"Point"}
}