{
  "type": "Feature",
  "properties": {
    "gn:admin1_code":"01",
    "gn:asciiname":"Alam",
    "gn:country_code":"UZ",
    "gn:dem":434,
    "gn:feature_class":"P",
    "gn:feature_code":"PPL",
    "gn:name":"Alam",
    "gn:population":0,
    "gn:timezone":"Asia/Tashkent",
    "iso:country":"UZ",
    "name:rus_x_preferred":[
        "Bol\u2019shevik"
    ],
    "name:rus_x_variant":[
        "\u0411\u043e\u043b\u044c\u0448\u0435\u0432\u0438\u043a"
    ],
    "name:uzb_x_preferred":[
        "Alam"
    ],
    "name:uzb_x_variant":[
        "A\u2018lam",
        "Olom"
    ],
    "wof:name":"Alam",
    "wof:placetype":"locality"
},
  "geometry": {"coordinates":[72.05844,40.84457],"type":"Point"}
}