{
  "type": "Feature",
  "properties": {
    "gn:admin1_code":"01",
    "gn:asciiname":"Bahrin",
    "gn:country_code":"UZ",
    "gn:dem":491,
    "gn:feature_class":"P",
    "gn:feature_code":"PPL",
    "gn:name":"Bahrin",
    "gn:population":0,
    "gn:timezone":"Asia/Tashkent",
    "iso:country":"UZ",
    "name:fas_x_preferred":[
        "\u0628\u062d\u0631\u06cc\u0646"
    ],
    "name:rus_x_preferred":[
        "\u0411\u0430\u0445\u0440\u0438\u043d"
    ],
    "name:und_x_variant":[
        "Bakhrin"
    ],
    "name:uzb_x_preferred":[
        "Bahrin"
    ],
    "name:uzb_x_variant":[
        "Baxrin"
    ],
    "wof:name":"Bahrin",
    "wof:placetype":"locality"
},
  "geometry": {"coordinates":[72.17074000000002,40.58988],"type":"Point"}
}