{
  "type": "Feature",
  "properties": {
    "gn:admin1_code":"01",
    "gn:asciiname":"Oktyabr'",
    "gn:country_code":"UZ",
    "gn:dem":683,
    "gn:feature_class":"P",
    "gn:feature_code":"PPL",
    "gn:name":"Oktyabr\u2019",
    "gn:population":0,
    "gn:timezone":"Asia/Tashkent",
    "iso:country":"UZ",
    "name:rus_x_preferred":[
        "Oktyabr\u2019"
    ],
    "name:rus_x_variant":[
        "\u041e\u043a\u0442\u044f\u0431\u0440\u044c"
    ],
    "wof:name":"Oktyabr'",
    "wof:placetype":"locality"
},
  "geometry": {"coordinates":[72.77625999999999,40.75278],"type":"Point"}
}