{
  "type": "Feature",
  "properties": {
    "gn:admin1_code":"08",
    "gn:asciiname":"Tudamaydan",
    "gn:country_code":"UZ",
    "gn:dem":1071,
    "gn:feature_class":"P",
    "gn:feature_code":"PPL",
    "gn:name":"Tudamaydan",
    "gn:population":0,
    "gn:timezone":"Asia/Samarkand",
    "iso:country":"UZ",
    "wof:name":"Tudamaydan",
    "wof:placetype":"locality"
},
  "geometry": {"coordinates":[67.09999999999999,38.98333],"type":"Point"}
}