{
  "type": "Feature",
  "properties": {
    "gn:admin1_code":"00",
    "gn:asciiname":"Yam-Bash",
    "gn:cc2":"UZ",
    "gn:country_code":"UZ",
    "gn:dem":690,
    "gn:feature_class":"P",
    "gn:feature_code":"PPL",
    "gn:name":"Yam-Bash",
    "gn:population":0,
    "gn:timezone":"Asia/Samarkand",
    "iso:country":"UZ",
    "name:und_x_variant":[
        "Kalya-Mulla",
        "Yam-Bash"
    ],
    "wof:name":"Yam-Bash",
    "wof:placetype":"locality"
},
  "geometry": {"coordinates":[66.28333000000001,40.18333],"type":"Point"}
}