{
  "type": "Feature",
  "properties": {
    "gn:admin1_code":"01",
    "gn:asciiname":"Shuvoqzor",
    "gn:country_code":"UZ",
    "gn:dem":488,
    "gn:feature_class":"P",
    "gn:feature_code":"PPL",
    "gn:name":"Shuvoqzor",
    "gn:population":0,
    "gn:timezone":"Asia/Tashkent",
    "iso:country":"UZ",
    "name:uzb_x_preferred":[
        "Shuvoqzor"
    ],
    "wof:name":"Shuvoqzor",
    "wof:placetype":"locality"
},
  "geometry": {"coordinates":[72.41983,40.91269000000001],"type":"Point"}
}