{
  "type": "Feature",
  "properties": {
    "gn:admin1_code":"16",
    "gn:asciiname":"Usmon Yusupov",
    "gn:country_code":"UZ",
    "gn:dem":267,
    "gn:feature_class":"P",
    "gn:feature_code":"PPL",
    "gn:name":"Usmon Yusupov",
    "gn:population":0,
    "gn:timezone":"Asia/Tashkent",
    "iso:country":"UZ",
    "name:uzb_x_preferred":[
        "Usmon Yusupov"
    ],
    "wof:name":"Usmon Yusupov",
    "wof:placetype":"locality"
},
  "geometry": {"coordinates":[68.6247,40.75544],"type":"Point"}
}