{
  "type": "Feature",
  "properties": {
    "gn:admin1_code":"01",
    "gn:asciiname":"Shaftolizor",
    "gn:country_code":"UZ",
    "gn:dem":423,
    "gn:feature_class":"P",
    "gn:feature_code":"PPL",
    "gn:name":"Shaftolizor",
    "gn:population":0,
    "gn:timezone":"Asia/Tashkent",
    "iso:country":"UZ",
    "name:und_x_variant":[
        "Moskva"
    ],
    "name:uzb_x_preferred":[
        "Shaftolizor"
    ],
    "wof:name":"Shaftolizor",
    "wof:placetype":"locality"
},
  "geometry": {"coordinates":[71.88993000000001,40.76826],"type":"Point"}
}