{
  "type": "Feature",
  "properties": {
    "gn:admin1_code":"07",
    "gn:asciiname":"Aldabergan",
    "gn:country_code":"UZ",
    "gn:dem":250,
    "gn:feature_class":"P",
    "gn:feature_code":"PPL",
    "gn:name":"Aldabergan",
    "gn:population":0,
    "gn:timezone":"Asia/Samarkand",
    "iso:country":"UZ",
    "wof:name":"Aldabergan",
    "wof:placetype":"locality"
},
  "geometry": {"coordinates":[65.58864,41.33586],"type":"Point"}
}