{
  "type": "Feature",
  "properties": {
    "gn:admin1_code":"00",
    "gn:asciiname":"Siyazy-Payan",
    "gn:country_code":"UZ",
    "gn:dem":228,
    "gn:feature_class":"P",
    "gn:feature_code":"PPL",
    "gn:name":"Siyazy-Payan",
    "gn:population":0,
    "gn:timezone":"Asia/Samarkand",
    "iso:country":"UZ",
    "wof:name":"Siyazy-Payan",
    "wof:placetype":"locality"
},
  "geometry": {"coordinates":[64.59999999999999,39.81667],"type":"Point"}
}