{
  "type": "Feature",
  "properties": {
    "gn:admin1_code":"08",
    "gn:asciiname":"Vari",
    "gn:country_code":"UZ",
    "gn:dem":295,
    "gn:feature_class":"P",
    "gn:feature_code":"PPL",
    "gn:name":"Vari",
    "gn:population":0,
    "gn:timezone":"Asia/Samarkand",
    "iso:country":"UZ",
    "name:ara_x_preferred":[
        "\u0641\u0627\u0631\u064a"
    ],
    "name:ceb_x_preferred":[
        "V\u00e1ri"
    ],
    "name:ell_x_preferred":[
        "\u0392\u03ac\u03c1\u03b7 \u0391\u03c4\u03c4\u03b9\u03ba\u03ae\u03c2"
    ],
    "name:eng_x_preferred":[
        "Vari"
    ],
    "name:fin_x_preferred":[
        "V\u00e1ri"
    ],
    "name:ita_x_preferred":[
        "Vari"
    ],
    "name:ron_x_preferred":[
        "Vari"
    ],
    "name:rus_x_preferred":[
        "\u0412\u0430\u0440\u0438"
    ],
    "name:tur_x_preferred":[
        "Vari"
    ],
    "name:urd_x_preferred":[
        "\u0648\u0627\u0631\u06cc"
    ],
    "wof:name":"Vari",
    "wof:placetype":"locality"
},
  "geometry": {"coordinates":[65.18722,38.71007],"type":"Point"}
}