{
  "type": "Feature",
  "properties": {
    "gn:admin1_code":"08",
    "gn:asciiname":"Vari",
    "gn:country_code":"UZ",
    "gn:dem":295,
    "gn:feature_class":"P",
    "gn:feature_code":"PPL",
    "gn:name":"Vari",
    "gn:population":0,
    "gn:timezone":"Asia/Samarkand",
    "iso:country":"UZ",
    "name:eng_x_preferred":[
        "Vari"
    ],
    "wof:name":"Vari",
    "wof:placetype":"locality"
},
  "geometry": {"coordinates":[65.18722,38.71007],"type":"Point"}
}