{
  "type": "Feature",
  "properties": {
    "gn:admin1_code":"01",
    "gn:asciiname":"Komintern",
    "gn:country_code":"UZ",
    "gn:dem":483,
    "gn:feature_class":"P",
    "gn:feature_code":"PPL",
    "gn:name":"Komintern",
    "gn:population":0,
    "gn:timezone":"Asia/Tashkent",
    "iso:country":"UZ",
    "name:rus_x_preferred":[
        "\u041a\u043e\u043c\u0438\u043d\u0442\u0435\u0440\u043d"
    ],
    "name:und_x_variant":[
        "Dzhalimbek",
        "Dzhalabek",
        "Komintern"
    ],
    "wof:name":"Komintern",
    "wof:placetype":"locality"
},
  "geometry": {"coordinates":[72.31376,40.74683],"type":"Point"}
}