{
  "type": "Feature",
  "properties": {
    "gn:admin1_code":"01",
    "gn:asciiname":"Komintern",
    "gn:country_code":"UZ",
    "gn:dem":483,
    "gn:feature_class":"P",
    "gn:feature_code":"PPL",
    "gn:name":"Komintern",
    "gn:population":0,
    "gn:timezone":"Asia/Tashkent",
    "iso:country":"UZ",
    "name:bel_x_preferred":[
        "\u041a\u0430\u043c\u0456\u043d\u0442\u044d\u0440\u043d"
    ],
    "name:ceb_x_preferred":[
        "Komintern"
    ],
    "name:deu_x_preferred":[
        "Komintern"
    ],
    "name:hye_x_preferred":[
        "\u053f\u0578\u0574\u056b\u0576\u057f\u0565\u0580\u0576"
    ],
    "name:kaz_x_preferred":[
        "\u041a\u043e\u043c\u0438\u043d\u0442\u0435\u0440\u043d"
    ],
    "name:pol_x_preferred":[
        "Komintern"
    ],
    "name:rus_x_preferred":[
        "\u041a\u043e\u043c\u0438\u043d\u0442\u0435\u0440\u043d"
    ],
    "name:spa_x_preferred":[
        "Komintern"
    ],
    "name:ukr_x_preferred":[
        "\u041a\u043e\u043c\u0456\u043d\u0442\u0435\u0440\u043d"
    ],
    "name:und_x_variant":[
        "Dzhalimbek",
        "Dzhalabek"
    ],
    "wof:name":"Komintern",
    "wof:placetype":"locality"
},
  "geometry": {"coordinates":[72.31376,40.74683],"type":"Point"}
}