{
  "type": "Feature",
  "properties": {
    "gn:admin1_code":"06",
    "gn:asciiname":"Mozorko`hna",
    "gn:country_code":"UZ",
    "gn:dem":437,
    "gn:feature_class":"P",
    "gn:feature_code":"PPL",
    "gn:name":"Mozorko\u2018hna",
    "gn:population":0,
    "gn:timezone":"Asia/Tashkent",
    "iso:country":"UZ",
    "name:eng_x_preferred":[
        "Mozorko\u2018hna"
    ],
    "wof:name":"Mozorko`hna",
    "wof:placetype":"locality"
},
  "geometry": {"coordinates":[71.46755999999998,40.92482],"type":"Point"}
}