{
  "type": "Feature",
  "properties": {
    "gn:admin1_code":"09",
    "gn:asciiname":"Kenes",
    "gn:country_code":"UZ",
    "gn:dem":59,
    "gn:feature_class":"P",
    "gn:feature_code":"PPL",
    "gn:name":"Kenes",
    "gn:population":0,
    "gn:timezone":"Asia/Samarkand",
    "iso:country":"UZ",
    "wof:name":"Kenes",
    "wof:placetype":"locality"
},
  "geometry": {"coordinates":[59.86555,43.05975],"type":"Point"}
}