{
  "type": "Feature",
  "properties": {
    "gn:admin1_code":"06",
    "gn:asciiname":"Kandigon",
    "gn:country_code":"UZ",
    "gn:dem":1665,
    "gn:feature_class":"P",
    "gn:feature_code":"PPL",
    "gn:name":"Kandigon",
    "gn:population":0,
    "gn:timezone":"Asia/Tashkent",
    "iso:country":"UZ",
    "name:uzb_x_preferred":[
        "Kandagan"
    ],
    "name:uzb_x_variant":[
        "Kandigon"
    ],
    "wof:name":"Kandigon",
    "wof:placetype":"locality"
},
  "geometry": {"coordinates":[70.71126,41.09014000000001],"type":"Point"}
}