{
  "type": "Feature",
  "properties": {
    "gn:admin1_code":"16",
    "gn:asciiname":"Choljivut",
    "gn:country_code":"UZ",
    "gn:dem":267,
    "gn:feature_class":"P",
    "gn:feature_code":"PPL",
    "gn:name":"Choljivut",
    "gn:population":0,
    "gn:timezone":"Asia/Tashkent",
    "iso:country":"UZ",
    "name:uzb_x_preferred":[
        "Choljivut"
    ],
    "wof:name":"Choljivut",
    "wof:placetype":"locality"
},
  "geometry": {"coordinates":[68.64482,40.47117],"type":"Point"}
}