{
  "type": "Feature",
  "properties": {
    "gn:admin1_code":"12",
    "gn:asciiname":"Angor",
    "gn:country_code":"UZ",
    "gn:dem":325,
    "gn:feature_class":"P",
    "gn:feature_code":"PPL",
    "gn:name":"Angor",
    "gn:population":0,
    "gn:timezone":"Asia/Samarkand",
    "iso:country":"UZ",
    "name:uzb_x_preferred":[
        "Angor"
    ],
    "wof:name":"Angor",
    "wof:placetype":"locality"
},
  "geometry": {"coordinates":[67.15056,37.46222],"type":"Point"}
}