{
  "type": "Feature",
  "properties": {
    "gn:admin1_code":"12",
    "gn:asciiname":"Daxanonjon",
    "gn:country_code":"UZ",
    "gn:dem":939,
    "gn:feature_class":"P",
    "gn:feature_code":"PPL",
    "gn:name":"Daxanonjon",
    "gn:population":0,
    "gn:timezone":"Asia/Samarkand",
    "iso:country":"UZ",
    "name:und_x_variant":[
        "Daganadzham"
    ],
    "name:uzb_x_preferred":[
        "Daxanonjon"
    ],
    "wof:name":"Daxanonjon",
    "wof:placetype":"locality"
},
  "geometry": {"coordinates":[67.05028,38.15722],"type":"Point"}
}