{
  "type": "Feature",
  "properties": {
    "gn:admin1_code":"08",
    "gn:asciiname":"Paxtaobod",
    "gn:country_code":"UZ",
    "gn:dem":510,
    "gn:feature_class":"P",
    "gn:feature_code":"PPL",
    "gn:name":"Paxtaobod",
    "gn:population":0,
    "gn:timezone":"Asia/Samarkand",
    "iso:country":"UZ",
    "wof:name":"Paxtaobod",
    "wof:placetype":"locality"
},
  "geometry": {"coordinates":[66.49061999999999,38.99197],"type":"Point"}
}