{
  "type": "Feature",
  "properties": {
    "gn:admin1_code":"08",
    "gn:asciiname":"Paxtaobod",
    "gn:country_code":"UZ",
    "gn:dem":510,
    "gn:feature_class":"P",
    "gn:feature_code":"PPL",
    "gn:name":"Paxtaobod",
    "gn:population":0,
    "gn:timezone":"Asia/Samarkand",
    "iso:country":"UZ",
    "name:azb_x_preferred":[
        "\u067e\u062e\u062a\u0647\u200c\u0622\u0628\u0627\u062f"
    ],
    "name:deu_x_preferred":[
        "Paxtaobod"
    ],
    "name:hsb_x_preferred":[
        "Paxtaobod"
    ],
    "name:ita_x_preferred":[
        "Pakhtaabad"
    ],
    "name:jpn_x_preferred":[
        "\u30d1\u30d5\u30bf\u30fc\u30d0\u30fc\u30c9"
    ],
    "name:kik_x_preferred":[
        "Paxtaobod"
    ],
    "name:lit_x_preferred":[
        "Pachtaabadas"
    ],
    "name:pol_x_preferred":[
        "Paxtaobod"
    ],
    "name:rus_x_preferred":[
        "\u041f\u0430\u0445\u0442\u0430\u0430\u0431\u0430\u0434"
    ],
    "name:spa_x_preferred":[
        "Paxtaobod"
    ],
    "name:tat_x_preferred":[
        "\u041f\u04d9\u0445\u0442\u04d9\u0430\u0431\u0430\u0434"
    ],
    "name:tur_x_preferred":[
        "Pahtaabad"
    ],
    "name:ukr_x_preferred":[
        "\u041f\u0430\u0445\u0442\u0430\u0430\u0431\u0430\u0434"
    ],
    "name:urd_x_preferred":[
        "\u067e\u062e\u062a\u06c1 \u0622\u0628\u0627\u062f"
    ],
    "name:uzb_x_preferred":[
        "Paxtaobod"
    ],
    "wof:name":"Paxtaobod",
    "wof:placetype":"locality"
},
  "geometry": {"coordinates":[66.49061999999999,38.99197],"type":"Point"}
}