{
  "type": "Feature",
  "properties": {
    "gn:admin1_code":"03",
    "gn:asciiname":"Samarqandbino",
    "gn:country_code":"UZ",
    "gn:dem":489,
    "gn:feature_class":"P",
    "gn:feature_code":"PPL",
    "gn:name":"Samarqandbino",
    "gn:population":0,
    "gn:timezone":"Asia/Tashkent",
    "iso:country":"UZ",
    "name:und_x_variant":[
        "Samarkandbina"
    ],
    "name:uzb_x_preferred":[
        "Samarqandbino"
    ],
    "wof:name":"Samarqandbino",
    "wof:placetype":"locality"
},
  "geometry": {"coordinates":[71.11357,40.43096],"type":"Point"}
}