{
  "type": "Feature",
  "properties": {
    "gn:admin1_code":"03",
    "gn:asciiname":"Qaraqchitol",
    "gn:country_code":"UZ",
    "gn:dem":408,
    "gn:feature_class":"P",
    "gn:feature_code":"PPL",
    "gn:name":"Qaraqchitol",
    "gn:population":0,
    "gn:timezone":"Asia/Tashkent",
    "iso:country":"UZ",
    "name:und_x_variant":[
        "Karachital"
    ],
    "name:uzb_x_preferred":[
        "Qaraqchitol"
    ],
    "wof:name":"Qaraqchitol",
    "wof:placetype":"locality"
},
  "geometry": {"coordinates":[71.19802,40.50874],"type":"Point"}
}