{
  "type": "Feature",
  "properties": {
    "gn:admin1_code":"00",
    "gn:asciiname":"Kiyat",
    "gn:country_code":"UZ",
    "gn:dem":533,
    "gn:feature_class":"P",
    "gn:feature_code":"PPL",
    "gn:name":"Kiyat",
    "gn:population":0,
    "gn:timezone":"Asia/Samarkand",
    "iso:country":"UZ",
    "wof:name":"Kiyat",
    "wof:placetype":"locality"
},
  "geometry": {"coordinates":[66.61667,39.96667],"type":"Point"}
}