{
  "type": "Feature",
  "properties": {
    "gn:admin1_code":"00",
    "gn:asciiname":"Gay-Bata",
    "gn:cc2":"UZ",
    "gn:country_code":"UZ",
    "gn:dem":1115,
    "gn:feature_class":"P",
    "gn:feature_code":"PPL",
    "gn:name":"Gay-Bata",
    "gn:population":0,
    "gn:timezone":"Asia/Samarkand",
    "iso:country":"UZ",
    "name:und_x_variant":[
        "Gay-Bota",
        "Gay-Bata"
    ],
    "wof:name":"Gay-Bata",
    "wof:placetype":"locality"
},
  "geometry": {"coordinates":[66.58333,40.41667],"type":"Point"}
}