{
  "type": "Feature",
  "properties": {
    "gn:admin1_code":"08",
    "gn:asciiname":"To`rtsari",
    "gn:country_code":"UZ",
    "gn:dem":427,
    "gn:feature_class":"P",
    "gn:feature_code":"PPL",
    "gn:name":"To\u2018rtsari",
    "gn:population":0,
    "gn:timezone":"Asia/Samarkand",
    "iso:country":"UZ",
    "wof:name":"To`rtsari",
    "wof:placetype":"locality"
},
  "geometry": {"coordinates":[66.07337,38.78],"type":"Point"}
}