{
  "type": "Feature",
  "properties": {
    "gn:admin1_code":"09",
    "gn:asciiname":"Sultan-Bay",
    "gn:country_code":"UZ",
    "gn:dem":85,
    "gn:feature_class":"P",
    "gn:feature_code":"PPL",
    "gn:name":"Sultan-Bay",
    "gn:population":0,
    "gn:timezone":"Asia/Samarkand",
    "iso:country":"UZ",
    "wof:name":"Sultan-Bay",
    "wof:placetype":"locality"
},
  "geometry": {"coordinates":[60.10361999999999,41.93722],"type":"Point"}
}