{
  "type": "Feature",
  "properties": {
    "gn:admin1_code":"03",
    "gn:asciiname":"G`alaba",
    "gn:country_code":"UZ",
    "gn:dem":380,
    "gn:feature_class":"P",
    "gn:feature_code":"PPL",
    "gn:name":"G\u2018alaba",
    "gn:population":0,
    "gn:timezone":"Asia/Tashkent",
    "iso:country":"UZ",
    "name:uzb_x_preferred":[
        "G\u2018alaba"
    ],
    "wof:name":"G`alaba",
    "wof:placetype":"locality"
},
  "geometry": {"coordinates":[70.8347,40.60209],"type":"Point"}
}