{
  "type": "Feature",
  "properties": {
    "gn:admin1_code":"06",
    "gn:asciiname":"Arab",
    "gn:country_code":"UZ",
    "gn:dem":1541,
    "gn:feature_class":"P",
    "gn:feature_code":"PPL",
    "gn:name":"Arab",
    "gn:population":0,
    "gn:timezone":"Asia/Tashkent",
    "iso:country":"UZ",
    "name:eng_x_preferred":[
        "Arab"
    ],
    "wof:name":"Arab",
    "wof:placetype":"locality"
},
  "geometry": {"coordinates":[70.93201999999999,41.18975],"type":"Point"}
}