{
  "type": "Feature",
  "properties": {
    "gn:admin1_code":"12",
    "gn:asciiname":"Yangiqurilish",
    "gn:country_code":"UZ",
    "gn:dem":514,
    "gn:feature_class":"P",
    "gn:feature_code":"PPL",
    "gn:name":"Yangiqurilish",
    "gn:population":0,
    "gn:timezone":"Asia/Samarkand",
    "iso:country":"UZ",
    "name:uzb_x_preferred":[
        "Yangiqurilish"
    ],
    "wof:name":"Yangiqurilish",
    "wof:placetype":"locality"
},
  "geometry": {"coordinates":[67.77131,38.1499],"type":"Point"}
}