{
  "type": "Feature",
  "properties": {
    "gn:admin1_code":"06",
    "gn:asciiname":"Yakatol",
    "gn:country_code":"UZ",
    "gn:dem":383,
    "gn:feature_class":"P",
    "gn:feature_code":"PPL",
    "gn:name":"Yakatol",
    "gn:population":0,
    "gn:timezone":"Asia/Tashkent",
    "iso:country":"UZ",
    "name:eng_x_preferred":[
        "Yakatol"
    ],
    "wof:name":"Yakatol",
    "wof:placetype":"locality"
},
  "geometry": {"coordinates":[71.34266,40.81578],"type":"Point"}
}