{
  "type": "Feature",
  "properties": {
    "gn:admin1_code":"12",
    "gn:asciiname":"Olatemir",
    "gn:country_code":"UZ",
    "gn:dem":477,
    "gn:feature_class":"P",
    "gn:feature_code":"PPL",
    "gn:name":"Olatemir",
    "gn:population":0,
    "gn:timezone":"Asia/Samarkand",
    "iso:country":"UZ",
    "name:und_x_variant":[
        "Alatemir"
    ],
    "name:uzb_x_preferred":[
        "Olatemir"
    ],
    "wof:name":"Olatemir",
    "wof:placetype":"locality"
},
  "geometry": {"coordinates":[67.80848,38.09847],"type":"Point"}
}