{
  "type": "Feature",
  "properties": {
    "iso:country":"UZ",
    "name:azb_x_preferred":[
        "\u067e\u062e\u062a\u0647\u200c\u06a9\u0627\u0631"
    ],
    "name:ckb_x_preferred":[
        "\u067e\u06d5\u062e\u062a\u06d5\u06a9\u0627\u0631"
    ],
    "name:dut_x_preferred":[
        "Paxtakor"
    ],
    "name:eng_x_preferred":[
        "Paxtakor"
    ],
    "name:fra_x_preferred":[
        "Pakhtakor"
    ],
    "name:fre_x_preferred":[
        "Pakhtakor"
    ],
    "name:ger_x_preferred":[
        "Paxtakor"
    ],
    "name:jpn_x_preferred":[
        "\u30d1\u30d5\u30bf\u30b3\u30fc\u30eb"
    ],
    "name:per_x_preferred":[
        "\u067e\u062e\u062a\u0647\u200c\u06a9\u0627\u0631"
    ],
    "name:pol_x_preferred":[
        "Paxtakor"
    ],
    "name:por_x_preferred":[
        "Paxtakor"
    ],
    "name:rus_x_preferred":[
        "\u041f\u0430\u0445\u0442\u0430\u043a\u043e\u0440"
    ],
    "name:spa_x_preferred":[
        "Pahtakor"
    ],
    "name:tur_x_preferred":[
        "Pahtakar"
    ],
    "name:unk_x_variant":[
        "Paxtakor"
    ],
    "name:urd_x_preferred":[
        "\u067e\u062e\u062a\u06c1 \u06a9\u0627\u0631\u060c \u0627\u0632\u0628\u06a9\u0633\u062a\u0627\u0646"
    ],
    "name:uzb_x_preferred":[
        "Paxtakor"
    ],
    "qs:gn_country":"UZ",
    "qs:gn_fcode":"PPL",
    "qs:gn_pop":21384,
    "qs:name":"Pakhtakor",
    "qs:name_adm0":"Uzbekistan",
    "qs:name_adm1":"Jizzakh",
    "qs:photos":0,
    "qs:photos_1k":0,
    "qs:photos_9k":1,
    "qs:photos_9r":3,
    "qs:photos_all":103,
    "qs:photos_sr":0,
    "qs:placetype":"Town",
    "qs:pop_sr":"7",
    "qs:woe_adm0":23424980,
    "wd:wordcount":102,
    "wof:name":"Pakhtakor",
    "wof:placetype":"locality",
    "wof:population":21384
},
  "geometry": {"coordinates":[67.95444000000001,40.31528],"type":"Point"}
}