{
  "type": "Feature",
  "properties": {
    "gn:admin1_code":"01",
    "gn:asciiname":"Arykbuyi",
    "gn:country_code":"UZ",
    "gn:dem":606,
    "gn:feature_class":"P",
    "gn:feature_code":"PPL",
    "gn:name":"Arykbuyi",
    "gn:population":0,
    "gn:timezone":"Asia/Tashkent",
    "iso:country":"UZ",
    "name:rus_x_preferred":[
        "\u0410\u0440\u044b\u043a\u0431\u0443\u0439\u0438"
    ],
    "wof:name":"Arykbuyi",
    "wof:placetype":"locality"
},
  "geometry": {"coordinates":[72.36835000000001,40.52172],"type":"Point"}
}