{
  "type": "Feature",
  "properties": {
    "gn:admin1_code":"15",
    "gn:asciiname":"Zarafshon",
    "gn:country_code":"UZ",
    "gn:dem":320,
    "gn:feature_class":"P",
    "gn:feature_code":"PPL",
    "gn:name":"Zarafshon",
    "gn:population":0,
    "gn:timezone":"Asia/Samarkand",
    "iso:country":"UZ",
    "name:ara_x_preferred":[
        "\u0632\u0631\u0627\u0641\u0634\u0648\u0646"
    ],
    "name:ben_x_preferred":[
        "\u099c\u09b0\u09be\u09ab\u09b6\u09cb\u09a8"
    ],
    "name:ell_x_preferred":[
        "\u0396\u03b1\u03c1\u03b1\u03c6\u03c3\u03cc\u03bd"
    ],
    "name:heb_x_preferred":[
        "\u05d6\u05e8\u05e4\u05e9\u05d5\u05df"
    ],
    "name:ind_x_preferred":[
        "Zarafshon"
    ],
    "name:swe_x_preferred":[
        "Zarafshon"
    ],
    "name:urd_x_preferred":[
        "\u0632\u0627\u0631\u0641\u0634\u0648\u0646"
    ],
    "name:uzb_x_preferred":[
        "Zarafshon"
    ],
    "name:vie_x_preferred":[
        "S\u00f4ng Zarafshon"
    ],
    "wof:name":"Zarafshon",
    "wof:placetype":"locality"
},
  "geometry": {"coordinates":[68.14993,40.23784],"type":"Point"}
}