{
  "type": "Feature",
  "properties": {
    "gn:admin1_code":"15",
    "gn:asciiname":"Zarafshon",
    "gn:country_code":"UZ",
    "gn:dem":320,
    "gn:feature_class":"P",
    "gn:feature_code":"PPL",
    "gn:name":"Zarafshon",
    "gn:population":0,
    "gn:timezone":"Asia/Samarkand",
    "iso:country":"UZ",
    "name:uzb_x_preferred":[
        "Zarafshon"
    ],
    "wof:name":"Zarafshon",
    "wof:placetype":"locality"
},
  "geometry": {"coordinates":[68.14993,40.23784000000001],"type":"Point"}
}