{
  "type": "Feature",
  "properties": {
    "gn:admin1_code":"03",
    "gn:asciiname":"Urganji",
    "gn:country_code":"UZ",
    "gn:dem":385,
    "gn:feature_class":"P",
    "gn:feature_code":"PPL",
    "gn:name":"Urganji",
    "gn:population":0,
    "gn:timezone":"Asia/Tashkent",
    "iso:country":"UZ",
    "name:eng_x_preferred":[
        "Urganji"
    ],
    "name:und_x_variant":[
        "Urgandzhi"
    ],
    "wof:name":"Urganji",
    "wof:placetype":"locality"
},
  "geometry": {"coordinates":[71.03069000000001,40.65408],"type":"Point"}
}