{
  "type": "Feature",
  "properties": {
    "gn:admin1_code":"00",
    "gn:asciiname":"Pirmast",
    "gn:country_code":"UZ",
    "gn:dem":243,
    "gn:feature_class":"P",
    "gn:feature_code":"PPL",
    "gn:name":"Pirmast",
    "gn:population":0,
    "gn:timezone":"Asia/Samarkand",
    "iso:country":"UZ",
    "wof:name":"Pirmast",
    "wof:placetype":"locality"
},
  "geometry": {"coordinates":[64.53333000000001,40.05],"type":"Point"}
}