{
  "type": "Feature",
  "properties": {
    "gn:admin1_code":"14",
    "gn:asciiname":"Khujakent",
    "gn:cc2":"UZ",
    "gn:country_code":"UZ",
    "gn:dem":781,
    "gn:feature_class":"P",
    "gn:feature_code":"PPL",
    "gn:name":"Kh\u016djakent",
    "gn:population":0,
    "gn:timezone":"Asia/Tashkent",
    "iso:country":"UZ",
    "name:und_x_variant":[
        "Khodzhikent",
        "Khodzhankent",
        "Kh\u016djakent"
    ],
    "wof:name":"Khujakent",
    "wof:placetype":"locality"
},
  "geometry": {"coordinates":[69.94806,41.63333],"type":"Point"}
}