{
  "type": "Feature",
  "properties": {
    "gn:admin1_code":"07",
    "gn:asciiname":"Boloqaraq",
    "gn:country_code":"UZ",
    "gn:dem":134,
    "gn:feature_class":"P",
    "gn:feature_code":"PPL",
    "gn:name":"Boloqaraq",
    "gn:population":0,
    "gn:timezone":"Asia/Samarkand",
    "iso:country":"UZ",
    "wof:name":"Boloqaraq",
    "wof:placetype":"locality"
},
  "geometry": {"coordinates":[64.38318000000001,41.01796],"type":"Point"}
}