{
  "type": "Feature",
  "properties": {
    "gn:admin1_code":"01",
    "gn:asciiname":"To`payil",
    "gn:country_code":"UZ",
    "gn:dem":630,
    "gn:feature_class":"P",
    "gn:feature_code":"PPL",
    "gn:name":"To\u2018payil",
    "gn:population":0,
    "gn:timezone":"Asia/Tashkent",
    "iso:country":"UZ",
    "name:rus_x_preferred":[
        "\u0422\u0443\u043b\u0430\u0439\u0438\u043b"
    ],
    "name:und_x_variant":[
        "Tulayil"
    ],
    "name:uzb_x_preferred":[
        "To\u2018payil"
    ],
    "wof:name":"To`payil",
    "wof:placetype":"locality"
},
  "geometry": {"coordinates":[72.64215,40.80062],"type":"Point"}
}