{
  "type": "Feature",
  "properties": {
    "gn:admin1_code":"01",
    "gn:asciiname":"Labgardon",
    "gn:country_code":"UZ",
    "gn:dem":482,
    "gn:feature_class":"P",
    "gn:feature_code":"PPL",
    "gn:name":"Labgardon",
    "gn:population":0,
    "gn:timezone":"Asia/Tashkent",
    "iso:country":"UZ",
    "name:rus_x_preferred":[
        "\u041b\u0430\u0431\u0438\u0440\u0433\u0430\u0440\u0434\u0430\u043d"
    ],
    "name:und_x_variant":[
        "Labirgardan"
    ],
    "name:uzb_x_preferred":[
        "Labgardon"
    ],
    "wof:name":"Labgardon",
    "wof:placetype":"locality"
},
  "geometry": {"coordinates":[72.22884999999999,40.6851],"type":"Point"}
}