{
  "type": "Feature",
  "properties": {
    "gn:admin1_code":"09",
    "gn:asciiname":"Kantyubek",
    "gn:country_code":"UZ",
    "gn:dem":44,
    "gn:feature_class":"P",
    "gn:feature_code":"PPL",
    "gn:name":"Kantyubek",
    "gn:population":0,
    "gn:timezone":"Asia/Samarkand",
    "iso:country":"UZ",
    "wof:name":"Kantyubek",
    "wof:placetype":"locality"
},
  "geometry": {"coordinates":[59.25,45.06667],"type":"Point"}
}