{
  "type": "Feature",
  "properties": {
    "gn:admin1_code":"16",
    "gn:asciiname":"Mehnat",
    "gn:country_code":"UZ",
    "gn:dem":253,
    "gn:feature_class":"P",
    "gn:feature_code":"PPL",
    "gn:name":"Mehnat",
    "gn:population":0,
    "gn:timezone":"Asia/Tashkent",
    "iso:country":"UZ",
    "name:uzb_x_preferred":[
        "Mehnat"
    ],
    "wof:name":"Mehnat",
    "wof:placetype":"locality"
},
  "geometry": {"coordinates":[68.65871,40.90992],"type":"Point"}
}