{
  "type": "Feature",
  "properties": {
    "gn:admin1_code":"07",
    "gn:asciiname":"Gamxurd",
    "gn:country_code":"UZ",
    "gn:dem":280,
    "gn:feature_class":"P",
    "gn:feature_code":"PPL",
    "gn:name":"Gamxurd",
    "gn:population":0,
    "gn:timezone":"Asia/Samarkand",
    "iso:country":"UZ",
    "name:und_x_variant":[
        "Gamkhurd"
    ],
    "wof:name":"Gamxurd",
    "wof:placetype":"locality"
},
  "geometry": {"coordinates":[64.88673,40.20053],"type":"Point"}
}