{
  "type": "Feature",
  "properties": {
    "gn:admin1_code":"01",
    "gn:asciiname":"Bobochek",
    "gn:country_code":"UZ",
    "gn:dem":447,
    "gn:feature_class":"P",
    "gn:feature_code":"PPL",
    "gn:name":"Bobochek",
    "gn:population":0,
    "gn:timezone":"Asia/Tashkent",
    "iso:country":"UZ",
    "name:rus_x_preferred":[
        "\u0411\u0430\u0431\u0430\u0447\u0435\u043a"
    ],
    "name:und_x_variant":[
        "Babachek"
    ],
    "name:uzb_x_preferred":[
        "Bobochek"
    ],
    "wof:name":"Bobochek",
    "wof:placetype":"locality"
},
  "geometry": {"coordinates":[72.01682,40.66078],"type":"Point"}
}