{
  "type": "Feature",
  "properties": {
    "gn:admin1_code":"06",
    "gn:asciiname":"Go`rmiron",
    "gn:country_code":"UZ",
    "gn:dem":849,
    "gn:feature_class":"P",
    "gn:feature_code":"PPL",
    "gn:name":"Go\u2018rmiron",
    "gn:population":0,
    "gn:timezone":"Asia/Tashkent",
    "iso:country":"UZ",
    "name:eng_x_preferred":[
        "Gurmiran"
    ],
    "name:uzb_x_preferred":[
        "Go\u2018rmiron"
    ],
    "wof:name":"Go`rmiron",
    "wof:placetype":"locality"
},
  "geometry": {"coordinates":[71.53699,41.19058],"type":"Point"}
}