{
  "type": "Feature",
  "properties": {
    "gn:admin1_code":"06",
    "gn:asciiname":"Olish",
    "gn:country_code":"UZ",
    "gn:dem":635,
    "gn:feature_class":"P",
    "gn:feature_code":"PPL",
    "gn:name":"Olish",
    "gn:population":0,
    "gn:timezone":"Asia/Tashkent",
    "iso:country":"UZ",
    "name:eng_x_preferred":[
        "Olish"
    ],
    "wof:name":"Olish",
    "wof:placetype":"locality"
},
  "geometry": {"coordinates":[70.80468,40.83473],"type":"Point"}
}