{
  "type": "Feature",
  "properties": {
    "gn:admin1_code":"06",
    "gn:asciiname":"Ingichka",
    "gn:country_code":"UZ",
    "gn:dem":390,
    "gn:feature_class":"P",
    "gn:feature_code":"PPL",
    "gn:name":"Ingichka",
    "gn:population":0,
    "gn:timezone":"Asia/Tashkent",
    "iso:country":"UZ",
    "name:eng_x_preferred":[
        "Ingichka"
    ],
    "name:rus_x_preferred":[
        "\u0418\u043d\u0433\u0438\u0447\u043a\u0430"
    ],
    "name:uzb_x_preferred":[
        "Ingichka"
    ],
    "wof:name":"Ingichka",
    "wof:placetype":"locality"
},
  "geometry": {"coordinates":[71.50270999999999,40.86277000000001],"type":"Point"}
}