{
  "type": "Feature",
  "properties": {
    "gn:admin1_code":"08",
    "gn:asciiname":"Kurama",
    "gn:country_code":"UZ",
    "gn:dem":319,
    "gn:feature_class":"P",
    "gn:feature_code":"PPL",
    "gn:name":"Kurama",
    "gn:population":0,
    "gn:timezone":"Asia/Samarkand",
    "iso:country":"UZ",
    "name:ita_x_preferred":[
        "Kurama"
    ],
    "name:kaz_x_preferred":[
        "\u049a\u04b1\u0440\u0430\u043c\u0430"
    ],
    "name:msa_x_preferred":[
        "Kurama"
    ],
    "name:rus_x_preferred":[
        "\u041a\u0443\u0440\u0430\u043c\u0430"
    ],
    "name:spa_x_preferred":[
        "Kurama"
    ],
    "name:ukr_x_preferred":[
        "\u041a\u0443\u0440\u0430\u043c\u0430"
    ],
    "wof:name":"Kurama",
    "wof:placetype":"locality"
},
  "geometry": {"coordinates":[65.31667,38.98333],"type":"Point"}
}