{
  "type": "Feature",
  "properties": {
    "gn:admin1_code":"00",
    "gn:asciiname":"Nanay",
    "gn:cc2":"UZ",
    "gn:country_code":"UZ",
    "gn:dem":892,
    "gn:feature_class":"P",
    "gn:feature_code":"PPL",
    "gn:name":"Nanay",
    "gn:population":0,
    "gn:timezone":"Asia/Tashkent",
    "iso:country":"UZ",
    "name:und_x_variant":[
        "Nanai",
        "Nanay"
    ],
    "wof:name":"Nanay",
    "wof:placetype":"locality"
},
  "geometry": {"coordinates":[70.09999999999999,41.71667],"type":"Point"}
}