{
  "type": "Feature",
  "properties": {
    "gn:admin1_code":"06",
    "gn:asciiname":"Yangiyer",
    "gn:country_code":"UZ",
    "gn:dem":384,
    "gn:feature_class":"P",
    "gn:feature_code":"PPL",
    "gn:name":"Yangiyer",
    "gn:population":0,
    "gn:timezone":"Asia/Tashkent",
    "iso:country":"UZ",
    "name:azb_x_preferred":[
        "\u06cc\u0626\u0646\u06af\u06cc \u06cc\u0626\u0631"
    ],
    "name:ceb_x_preferred":[
        "Yangiyer"
    ],
    "name:ckb_x_preferred":[
        "\u06cc\u06d5\u0646\u06af\u06cc\u06ce\u0631"
    ],
    "name:deu_x_preferred":[
        "Yangiyer"
    ],
    "name:eng_x_preferred":[
        "Yangiyer"
    ],
    "name:fas_x_preferred":[
        "\u06cc\u0646\u06af\u06cc\u200c\u06cc\u0631"
    ],
    "name:hin_x_preferred":[
        "\u092f\u093e\u0902\u0917\u093f\u092f\u0947\u0930"
    ],
    "name:hsb_x_preferred":[
        "Yangiyer"
    ],
    "name:jpn_x_preferred":[
        "\u30e4\u30f3\u30ae\u30a4\u30a7\u30eb"
    ],
    "name:kik_x_preferred":[
        "Yangiyer"
    ],
    "name:pol_x_preferred":[
        "Yangiyer"
    ],
    "name:rus_x_preferred":[
        "\u042f\u043d\u0433\u0438\u0435\u0440"
    ],
    "name:spa_x_preferred":[
        "Yangiyer"
    ],
    "name:tat_x_preferred":[
        "\u042f\u04a3\u044b\u0439\u0438\u0440"
    ],
    "name:tgk_x_preferred":[
        "\u042f\u043d\u0433\u0438\u0435\u0440"
    ],
    "name:tur_x_preferred":[
        "Yangiyer"
    ],
    "name:ukr_x_preferred":[
        "\u042f\u043d\u0433\u0456\u0454\u0440"
    ],
    "name:urd_x_preferred":[
        "\u06cc\u0646\u06af\u06cc\u0631"
    ],
    "name:uzb_x_preferred":[
        "Yangiyer"
    ],
    "name:zho_x_preferred":[
        "\u63da\u5409\u8036\u723e"
    ],
    "wof:name":"Yangiyer",
    "wof:placetype":"locality"
},
  "geometry": {"coordinates":[70.97914,40.8167],"type":"Point"}
}