{
  "type": "Feature",
  "properties": {
    "gn:admin1_code":"06",
    "gn:asciiname":"Yangiyer",
    "gn:country_code":"UZ",
    "gn:dem":384,
    "gn:feature_class":"P",
    "gn:feature_code":"PPL",
    "gn:name":"Yangiyer",
    "gn:population":0,
    "gn:timezone":"Asia/Tashkent",
    "iso:country":"UZ",
    "name:eng_x_preferred":[
        "Yangiyer"
    ],
    "wof:name":"Yangiyer",
    "wof:placetype":"locality"
},
  "geometry": {"coordinates":[70.97914,40.8167],"type":"Point"}
}