{
  "type": "Feature",
  "properties": {
    "gn:admin1_code":"01",
    "gn:asciiname":"Shamsiko`l",
    "gn:country_code":"UZ",
    "gn:dem":422,
    "gn:feature_class":"P",
    "gn:feature_code":"PPL",
    "gn:name":"Shamsiko\u2018l",
    "gn:population":0,
    "gn:timezone":"Asia/Tashkent",
    "iso:country":"UZ",
    "name:rus_x_preferred":[
        "Shamshikul\u2019"
    ],
    "name:uzb_x_preferred":[
        "Shamsiko\u2018l"
    ],
    "wof:name":"Shamsiko`l",
    "wof:placetype":"locality"
},
  "geometry": {"coordinates":[71.85664,40.8123],"type":"Point"}
}