{
  "type": "Feature",
  "properties": {
    "gn:admin1_code":"06",
    "gn:asciiname":"Qumtepa",
    "gn:country_code":"UZ",
    "gn:dem":415,
    "gn:feature_class":"P",
    "gn:feature_code":"PPL",
    "gn:name":"Qumtepa",
    "gn:population":0,
    "gn:timezone":"Asia/Tashkent",
    "iso:country":"UZ",
    "name:uzb_x_preferred":[
        "Qumtepa"
    ],
    "wof:name":"Qumtepa",
    "wof:placetype":"locality"
},
  "geometry": {"coordinates":[71.80110999999999,40.95365],"type":"Point"}
}