{
  "type": "Feature",
  "properties": {
    "gn:admin1_code":"09",
    "gn:asciiname":"Turkmanovul",
    "gn:country_code":"UZ",
    "gn:dem":73,
    "gn:feature_class":"P",
    "gn:feature_code":"PPL",
    "gn:name":"Turkmanovul",
    "gn:population":0,
    "gn:timezone":"Asia/Samarkand",
    "iso:country":"UZ",
    "wof:name":"Turkmanovul",
    "wof:placetype":"locality"
},
  "geometry": {"coordinates":[59.52501,42.543],"type":"Point"}
}