{
  "type": "Feature",
  "properties": {
    "gn:admin1_code":"03",
    "gn:asciiname":"Kichik-Amirobod",
    "gn:country_code":"UZ",
    "gn:dem":388,
    "gn:feature_class":"P",
    "gn:feature_code":"PPL",
    "gn:name":"Kichik-Amirobod",
    "gn:population":0,
    "gn:timezone":"Asia/Tashkent",
    "iso:country":"UZ",
    "name:uzb_x_preferred":[
        "Kichik-Amirobod"
    ],
    "wof:name":"Kichik-Amirobod",
    "wof:placetype":"locality"
},
  "geometry": {"coordinates":[70.86274,40.58111],"type":"Point"}
}