{
  "type": "Feature",
  "properties": {
    "gn:admin1_code":"08",
    "gn:asciiname":"Chorvador",
    "gn:country_code":"UZ",
    "gn:dem":657,
    "gn:feature_class":"P",
    "gn:feature_code":"PPL",
    "gn:name":"Chorvador",
    "gn:population":0,
    "gn:timezone":"Asia/Samarkand",
    "iso:country":"UZ",
    "wof:name":"Chorvador",
    "wof:placetype":"locality"
},
  "geometry": {"coordinates":[66.67142,39.25717],"type":"Point"}
}