{
  "type": "Feature",
  "properties": {
    "gn:admin1_code":"14",
    "gn:asciiname":"Yaryk",
    "gn:country_code":"UZ",
    "gn:dem":371,
    "gn:feature_class":"P",
    "gn:feature_code":"PPL",
    "gn:name":"Yaryk",
    "gn:population":0,
    "gn:timezone":"Asia/Tashkent",
    "iso:country":"UZ",
    "wof:name":"Yaryk",
    "wof:placetype":"locality"
},
  "geometry": {"coordinates":[69.28869,41.02635],"type":"Point"}
}