{
  "type": "Feature",
  "properties": {
    "gn:admin1_code":"08",
    "gn:asciiname":"Ko`kdala",
    "gn:country_code":"UZ",
    "gn:dem":443,
    "gn:feature_class":"P",
    "gn:feature_code":"PPL",
    "gn:name":"Ko\u2018kdala",
    "gn:population":0,
    "gn:timezone":"Asia/Samarkand",
    "iso:country":"UZ",
    "name:und_x_variant":[
        "Kukdala",
        "Kokdala",
        "Ko\u2018kdala"
    ],
    "wof:name":"Ko`kdala",
    "wof:placetype":"locality"
},
  "geometry": {"coordinates":[66.16311999999999,39.22232],"type":"Point"}
}