{
  "type": "Feature",
  "properties": {
    "gn:admin1_code":"07",
    "gn:asciiname":"Shengeldi",
    "gn:country_code":"UZ",
    "gn:dem":137,
    "gn:feature_class":"P",
    "gn:feature_code":"PPL",
    "gn:name":"Shengeldi",
    "gn:population":0,
    "gn:timezone":"Asia/Samarkand",
    "iso:country":"UZ",
    "name:und_x_variant":[
        "Dzhingil\u2019dy",
        "Dzhengel\u2019dy",
        "Chingil\u2019dy",
        "Shengeldi"
    ],
    "wof:name":"Shengeldi",
    "wof:placetype":"locality"
},
  "geometry": {"coordinates":[64.35666999999999,40.96089],"type":"Point"}
}