{
  "type": "Feature",
  "properties": {
    "gn:admin1_code":"00",
    "gn:asciiname":"Sayat",
    "gn:country_code":"UZ",
    "gn:dem":327,
    "gn:feature_class":"P",
    "gn:feature_code":"PPL",
    "gn:name":"Sayat",
    "gn:population":0,
    "gn:timezone":"Asia/Samarkand",
    "iso:country":"UZ",
    "wof:name":"Sayat",
    "wof:placetype":"locality"
},
  "geometry": {"coordinates":[67.40000000000001,37.33333],"type":"Point"}
}