{
  "type": "Feature",
  "properties": {
    "gn:admin1_code":"00",
    "gn:asciiname":"Sayat",
    "gn:country_code":"UZ",
    "gn:dem":327,
    "gn:feature_class":"P",
    "gn:feature_code":"PPL",
    "gn:name":"Sayat",
    "gn:population":0,
    "gn:timezone":"Asia/Samarkand",
    "iso:country":"UZ",
    "name:cat_x_preferred":[
        "Saiac"
    ],
    "name:ceb_x_preferred":[
        "Sayat"
    ],
    "name:deu_x_preferred":[
        "Sayat"
    ],
    "name:eus_x_preferred":[
        "Sayat"
    ],
    "name:fra_x_preferred":[
        "Sayat"
    ],
    "name:hun_x_preferred":[
        "Sayat"
    ],
    "name:ita_x_preferred":[
        "Sayat"
    ],
    "name:lat_x_preferred":[
        "Sayat"
    ],
    "name:mlg_x_preferred":[
        "Sayat"
    ],
    "name:msa_x_preferred":[
        "Sayat"
    ],
    "name:nld_x_preferred":[
        "Sayat"
    ],
    "name:oci_x_preferred":[
        "Sayat"
    ],
    "name:pms_x_preferred":[
        "Sayat"
    ],
    "name:pol_x_preferred":[
        "Sayat"
    ],
    "name:por_x_preferred":[
        "Sayat"
    ],
    "name:ron_x_preferred":[
        "Sayat"
    ],
    "name:slk_x_preferred":[
        "Sayat"
    ],
    "name:spa_x_preferred":[
        "Sayat"
    ],
    "name:swe_x_preferred":[
        "Sayat"
    ],
    "name:ukr_x_preferred":[
        "\u0421\u0435\u044f"
    ],
    "name:uzb_x_preferred":[
        "Sayat"
    ],
    "name:vie_x_preferred":[
        "Sayat"
    ],
    "name:vol_x_preferred":[
        "Sayat"
    ],
    "name:war_x_preferred":[
        "Sayat"
    ],
    "name:zho_x_preferred":[
        "\u8d5b\u963f"
    ],
    "wof:name":"Sayat",
    "wof:placetype":"locality"
},
  "geometry": {"coordinates":[67.40000000000001,37.33333],"type":"Point"}
}