{
  "type": "Feature",
  "properties": {
    "gn:admin1_code":"12",
    "gn:asciiname":"Bakaty",
    "gn:country_code":"UZ",
    "gn:dem":470,
    "gn:feature_class":"P",
    "gn:feature_code":"PPL",
    "gn:name":"Bakaty",
    "gn:population":0,
    "gn:timezone":"Asia/Samarkand",
    "iso:country":"UZ",
    "wof:name":"Bakaty",
    "wof:placetype":"locality"
},
  "geometry": {"coordinates":[67.92888000000001,38.11815],"type":"Point"}
}