{
  "type": "Feature",
  "properties": {
    "gn:admin1_code":"03",
    "gn:asciiname":"Tiliming",
    "gn:country_code":"UZ",
    "gn:dem":384,
    "gn:feature_class":"P",
    "gn:feature_code":"PPL",
    "gn:name":"Tiliming",
    "gn:population":0,
    "gn:timezone":"Asia/Tashkent",
    "iso:country":"UZ",
    "name:uzb_x_preferred":[
        "Tiliming"
    ],
    "wof:name":"Tiliming",
    "wof:placetype":"locality"
},
  "geometry": {"coordinates":[70.96736999999997,40.62909000000001],"type":"Point"}
}