{
  "type": "Feature",
  "properties": {
    "gn:admin1_code":"06",
    "gn:asciiname":"Xafato`pi",
    "gn:country_code":"UZ",
    "gn:dem":441,
    "gn:feature_class":"P",
    "gn:feature_code":"PPL",
    "gn:name":"Xafato\u2018pi",
    "gn:population":0,
    "gn:timezone":"Asia/Tashkent",
    "iso:country":"UZ",
    "name:eng_x_preferred":[
        "Xafato\u2018pi"
    ],
    "name:kir_x_preferred":[
        "Xafato\u2018pi"
    ],
    "name:uzb_x_preferred":[
        "Xaltato\u2018pi"
    ],
    "wof:name":"Xafato`pi",
    "wof:placetype":"locality"
},
  "geometry": {"coordinates":[71.98002,40.98083],"type":"Point"}
}