{
  "type": "Feature",
  "properties": {
    "gn:admin1_code":"01",
    "gn:asciiname":"Buloqboshi",
    "gn:country_code":"UZ",
    "gn:dem":649,
    "gn:feature_class":"P",
    "gn:feature_code":"PPLA2",
    "gn:name":"Buloqboshi",
    "gn:population":0,
    "gn:timezone":"Asia/Tashkent",
    "iso:country":"UZ",
    "name:deu_x_preferred":[
        "Buloqboshi"
    ],
    "name:kik_x_preferred":[
        "Buloqboshi"
    ],
    "name:pnb_x_preferred":[
        "\u0628\u0648\u0644\u0627\u0642\u0628\u0627\u0634\u06cc"
    ],
    "name:rus_x_preferred":[
        "\u0411\u0443\u043b\u0430\u043a\u0431\u0430\u0448\u0438"
    ],
    "name:tur_x_preferred":[
        "Bulakba\u015f\u0131"
    ],
    "name:ukr_x_preferred":[
        "\u0411\u0443\u043b\u0430\u043a\u0431\u0430\u0448\u0456"
    ],
    "name:und_x_variant":[
        "Bulakbashi",
        "Buloqbashi"
    ],
    "name:urd_x_preferred":[
        "\u0628\u0648\u0644\u0627\u0642 \u0628\u0627\u0634\u06cc"
    ],
    "name:uzb_x_preferred":[
        "Buloqbashi"
    ],
    "name:uzb_x_variant":[
        "Buloqboshi"
    ],
    "wof:name":"Buloqboshi",
    "wof:placetype":"locality"
},
  "geometry": {"coordinates":[72.50211999999998,40.62907],"type":"Point"}
}