{
  "type": "Feature",
  "properties": {
    "gn:admin1_code":"09",
    "gn:asciiname":"Navoiy",
    "gn:country_code":"UZ",
    "gn:dem":98,
    "gn:feature_class":"P",
    "gn:feature_code":"PPL",
    "gn:name":"Navoiy",
    "gn:population":0,
    "gn:timezone":"Asia/Samarkand",
    "iso:country":"UZ",
    "name:ara_x_preferred":[
        "\u0646\u0648\u0627\u0648\u064a"
    ],
    "name:ast_x_preferred":[
        "Navoi"
    ],
    "name:azb_x_preferred":[
        "\u0646\u0648\u0627\u06cc\u06cc"
    ],
    "name:ceb_x_preferred":[
        "Navoiy"
    ],
    "name:ces_x_preferred":[
        "Navoiy"
    ],
    "name:ckb_x_preferred":[
        "\u0646\u06d5\u06a4\u0627\u06cc\u06cc"
    ],
    "name:dan_x_preferred":[
        "Navoi"
    ],
    "name:deu_x_preferred":[
        "Navoiy"
    ],
    "name:epo_x_preferred":[
        "Navojo"
    ],
    "name:fas_x_preferred":[
        "\u0646\u0648\u0627\u06cc\u06cc"
    ],
    "name:fin_x_preferred":[
        "Navoi"
    ],
    "name:fra_x_preferred":[
        "Navo\u00ef"
    ],
    "name:hin_x_preferred":[
        "\u0928\u0935\u094b\u0908"
    ],
    "name:hsb_x_preferred":[
        "Navoiy"
    ],
    "name:ita_x_preferred":[
        "Navoiy"
    ],
    "name:jpn_x_preferred":[
        "\u30ca\u30f4\u30a9\u30a4"
    ],
    "name:kaa_x_preferred":[
        "Naway\u0131"
    ],
    "name:kik_x_preferred":[
        "Navoiy"
    ],
    "name:kir_x_preferred":[
        "\u041d\u0430\u0432\u043e\u0438"
    ],
    "name:kor_x_preferred":[
        "\ub098\ubcf4\uc774"
    ],
    "name:lit_x_preferred":[
        "Navojis"
    ],
    "name:nld_x_preferred":[
        "Navoiy"
    ],
    "name:pan_x_preferred":[
        "\u0a28\u0a35\u0a4b\u0a08"
    ],
    "name:pol_x_preferred":[
        "Nawoi"
    ],
    "name:ron_x_preferred":[
        "Navoi"
    ],
    "name:rus_x_preferred":[
        "\u041d\u0430\u0432\u043e\u0438"
    ],
    "name:spa_x_preferred":[
        "Navoi"
    ],
    "name:swe_x_preferred":[
        "Navoi"
    ],
    "name:tat_x_preferred":[
        "\u041d\u04d9\u0432\u0430\u0439\u0438"
    ],
    "name:tgk_x_preferred":[
        "\u041d\u0430\u0432\u043e\u0438"
    ],
    "name:tur_x_preferred":[
        "Nevai"
    ],
    "name:ukr_x_preferred":[
        "\u041d\u0430\u0432\u043e\u0457"
    ],
    "name:urd_x_preferred":[
        "\u0646\u0648\u0627\u0626\u06cc"
    ],
    "name:uzb_x_preferred":[
        "Navoiy"
    ],
    "name:vie_x_preferred":[
        "Navoiy"
    ],
    "name:war_x_preferred":[
        "Navoiy"
    ],
    "name:zho_x_preferred":[
        "\u7eb3\u6c83\u4f0a"
    ],
    "wof:name":"Navoiy",
    "wof:placetype":"locality"
},
  "geometry": {"coordinates":[61.03357,41.69749],"type":"Point"}
}