{
  "type": "Feature",
  "properties": {
    "gn:admin1_code":"09",
    "gn:asciiname":"Navoiy",
    "gn:country_code":"UZ",
    "gn:dem":98,
    "gn:feature_class":"P",
    "gn:feature_code":"PPL",
    "gn:name":"Navoiy",
    "gn:population":0,
    "gn:timezone":"Asia/Samarkand",
    "iso:country":"UZ",
    "wof:name":"Navoiy",
    "wof:placetype":"locality"
},
  "geometry": {"coordinates":[61.03357,41.69749],"type":"Point"}
}