{
  "type": "Feature",
  "properties": {
    "gn:admin1_code":"00",
    "gn:asciiname":"Shurcha",
    "gn:country_code":"UZ",
    "gn:dem":545,
    "gn:feature_class":"P",
    "gn:feature_code":"PPL",
    "gn:name":"Shurcha",
    "gn:population":0,
    "gn:timezone":"Asia/Samarkand",
    "iso:country":"UZ",
    "wof:name":"Shurcha",
    "wof:placetype":"locality"
},
  "geometry": {"coordinates":[66.38333,39.88333],"type":"Point"}
}