{
  "type": "Feature",
  "properties": {
    "gn:admin1_code":"16",
    "gn:asciiname":"Sretenskoye",
    "gn:cc2":"UZ",
    "gn:country_code":"UZ",
    "gn:dem":294,
    "gn:feature_class":"P",
    "gn:feature_code":"PPL",
    "gn:name":"Sretenskoye",
    "gn:population":0,
    "gn:timezone":"Asia/Tashkent",
    "iso:country":"UZ",
    "name:und_x_variant":[
        "Sretenka",
        "Sretensnoye",
        "Sretenskoye"
    ],
    "wof:name":"Sretenskoye",
    "wof:placetype":"locality"
},
  "geometry": {"coordinates":[69.17,40.29861],"type":"Point"}
}