{
  "type": "Feature",
  "properties": {
    "gn:admin1_code":"08",
    "gn:admin2_code":"Beshkent",
    "gn:asciiname":"Kamandy",
    "gn:country_code":"UZ",
    "gn:dem":379,
    "gn:feature_class":"P",
    "gn:feature_code":"PPL",
    "gn:name":"Kamandy",
    "gn:population":0,
    "gn:timezone":"Asia/Samarkand",
    "iso:country":"UZ",
    "wof:name":"Kamandy",
    "wof:placetype":"locality"
},
  "geometry": {"coordinates":[65.76666999999999,38.85917],"type":"Point"}
}