{
  "type": "Feature",
  "properties": {
    "gn:admin1_code":"03",
    "gn:asciiname":"Qatortol",
    "gn:country_code":"UZ",
    "gn:dem":372,
    "gn:feature_class":"P",
    "gn:feature_code":"PPL",
    "gn:name":"Qatortol",
    "gn:population":0,
    "gn:timezone":"Asia/Tashkent",
    "iso:country":"UZ",
    "name:uzb_x_preferred":[
        "Qatortol"
    ],
    "wof:name":"Qatortol",
    "wof:placetype":"locality"
},
  "geometry": {"coordinates":[70.52500999999999,40.45675],"type":"Point"}
}