{
  "type": "Feature",
  "properties": {
    "gn:admin1_code":"00",
    "gn:asciiname":"Khodzha-Ismail",
    "gn:country_code":"UZ",
    "gn:dem":642,
    "gn:feature_class":"P",
    "gn:feature_code":"PPL",
    "gn:name":"Khodzha-Ismail",
    "gn:population":0,
    "gn:timezone":"Asia/Samarkand",
    "iso:country":"UZ",
    "wof:name":"Khodzha-Ismail",
    "wof:placetype":"locality"
},
  "geometry": {"coordinates":[66.95,39.81667],"type":"Point"}
}