{
  "type": "Feature",
  "properties": {
    "gn:admin1_code":"01",
    "gn:asciiname":"Oxunboboyev",
    "gn:country_code":"UZ",
    "gn:dem":682,
    "gn:feature_class":"P",
    "gn:feature_code":"PPLA2",
    "gn:name":"Oxunboboyev",
    "gn:population":0,
    "gn:timezone":"Asia/Tashkent",
    "iso:country":"UZ",
    "name:und_x_variant":[
        "Akhunbabayev",
        "Sufix",
        "Ologhjat",
        "Sufia",
        "Sufikishlak",
        "Sufi-Kashlak"
    ],
    "name:uzb_x_preferred":[
        "Okhunboboyew"
    ],
    "name:uzb_x_variant":[
        "Oxunboboyev"
    ],
    "wof:name":"Oxunboboyev",
    "wof:placetype":"locality"
},
  "geometry": {"coordinates":[72.64282,40.71984000000001],"type":"Point"}
}