{
  "type": "Feature",
  "properties": {
    "gn:admin1_code":"15",
    "gn:admin2_code":"Zomin",
    "gn:asciiname":"Chillamazar",
    "gn:cc2":"UZ",
    "gn:country_code":"UZ",
    "gn:dem":1194,
    "gn:feature_class":"P",
    "gn:feature_code":"PPL",
    "gn:name":"Chillamazar",
    "gn:population":0,
    "gn:timezone":"Asia/Samarkand",
    "iso:country":"UZ",
    "name:und_x_variant":[
        "Chillya-Mazar",
        "Chillamazar"
    ],
    "wof:name":"Chillamazar",
    "wof:placetype":"locality"
},
  "geometry": {"coordinates":[68.57805999999999,39.81611],"type":"Point"}
}