{
  "type": "Feature",
  "properties": {
    "gn:admin1_code":"01",
    "gn:asciiname":"Toshlok",
    "gn:country_code":"UZ",
    "gn:dem":551,
    "gn:feature_class":"P",
    "gn:feature_code":"PPL",
    "gn:name":"Toshlok",
    "gn:population":0,
    "gn:timezone":"Asia/Tashkent",
    "iso:country":"UZ",
    "name:rus_x_preferred":[
        "\u0422\u0430\u0448\u043b\u0430\u043a"
    ],
    "name:und_x_variant":[
        "Tashlak"
    ],
    "name:uzb_x_preferred":[
        "Toshlok"
    ],
    "wof:name":"Toshlok",
    "wof:placetype":"locality"
},
  "geometry": {"coordinates":[72.34583000000001,40.60913],"type":"Point"}
}