{
  "type": "Feature",
  "properties": {
    "gn:admin1_code":"03",
    "gn:asciiname":"Limbur",
    "gn:country_code":"UZ",
    "gn:dem":1005,
    "gn:feature_class":"P",
    "gn:feature_code":"PPL",
    "gn:name":"Limbur",
    "gn:population":0,
    "gn:timezone":"Asia/Bishkek",
    "iso:country":"UZ",
    "name:rus_x_preferred":[
        "\u041b\u0438\u043c\u0431\u0443\u0440"
    ],
    "name:und_x_variant":[
        "Apkan"
    ],
    "wof:name":"Limbur",
    "wof:placetype":"locality"
},
  "geometry": {"coordinates":[71.09787,40.08421],"type":"Point"}
}