{
  "type": "Feature",
  "properties": {
    "gn:admin1_code":"01",
    "gn:asciiname":"Yangichek",
    "gn:country_code":"UZ",
    "gn:dem":530,
    "gn:feature_class":"P",
    "gn:feature_code":"PPL",
    "gn:name":"Yangichek",
    "gn:population":0,
    "gn:timezone":"Asia/Tashkent",
    "iso:country":"UZ",
    "name:rus_x_preferred":[
        "\u042f\u043d\u0433\u0438\u0447\u0435\u043a"
    ],
    "name:uzb_x_preferred":[
        "Yangichek"
    ],
    "wof:name":"Yangichek",
    "wof:placetype":"locality"
},
  "geometry": {"coordinates":[72.52839,40.95413],"type":"Point"}
}