{
  "type": "Feature",
  "properties": {
    "gn:admin1_code":"12",
    "gn:asciiname":"Qattag`on",
    "gn:country_code":"UZ",
    "gn:dem":316,
    "gn:feature_class":"P",
    "gn:feature_code":"PPL",
    "gn:name":"Qattag\u2018on",
    "gn:population":0,
    "gn:timezone":"Asia/Samarkand",
    "iso:country":"UZ",
    "name:und_x_variant":[
        "Gilyambor",
        "Talashkan",
        "Zang",
        "Kyzyl-Yuldyuz"
    ],
    "name:uzb_x_preferred":[
        "Qattag\u2018on"
    ],
    "wof:name":"Qattag`on",
    "wof:placetype":"locality"
},
  "geometry": {"coordinates":[67.18416999999999,37.41528],"type":"Point"}
}