{
  "type": "Feature",
  "properties": {
    "gn:admin1_code":"08",
    "gn:asciiname":"Ayritom",
    "gn:country_code":"UZ",
    "gn:dem":489,
    "gn:feature_class":"P",
    "gn:feature_code":"PPL",
    "gn:name":"Ayritom",
    "gn:population":0,
    "gn:timezone":"Asia/Samarkand",
    "iso:country":"UZ",
    "name:und_x_variant":[
        "Airitam",
        "Air-Tam",
        "Ayrytam",
        "Ayritom"
    ],
    "wof:name":"Ayritom",
    "wof:placetype":"locality"
},
  "geometry": {"coordinates":[66.22315999999999,39.39242],"type":"Point"}
}