{
  "type": "Feature",
  "properties": {
    "gn:admin1_code":"03",
    "gn:asciiname":"Shahartepa",
    "gn:country_code":"UZ",
    "gn:dem":461,
    "gn:feature_class":"P",
    "gn:feature_code":"PPL",
    "gn:name":"Shahartepa",
    "gn:population":0,
    "gn:timezone":"Asia/Tashkent",
    "iso:country":"UZ",
    "name:und_x_variant":[
        "Shakhartepa"
    ],
    "name:uzb_x_preferred":[
        "Shahartepa"
    ],
    "wof:name":"Shahartepa",
    "wof:placetype":"locality"
},
  "geometry": {"coordinates":[71.72698000000003,40.52647],"type":"Point"}
}