{
  "type": "Feature",
  "properties": {
    "gn:admin1_code":"00",
    "gn:asciiname":"Say-Buye",
    "gn:country_code":"UZ",
    "gn:dem":477,
    "gn:feature_class":"P",
    "gn:feature_code":"PPL",
    "gn:name":"Say-Buye",
    "gn:population":0,
    "gn:timezone":"Asia/Tashkent",
    "iso:country":"UZ",
    "wof:name":"Say-Buye",
    "wof:placetype":"locality"
},
  "geometry": {"coordinates":[72.01666999999998,40.53333],"type":"Point"}
}