{
  "type": "Feature",
  "properties": {
    "gn:admin1_code":"01",
    "gn:asciiname":"Guliston",
    "gn:country_code":"UZ",
    "gn:dem":415,
    "gn:feature_class":"P",
    "gn:feature_code":"PPL",
    "gn:name":"Guliston",
    "gn:population":0,
    "gn:timezone":"Asia/Tashkent",
    "iso:country":"UZ",
    "name:uzb_x_preferred":[
        "Guliston"
    ],
    "wof:name":"Guliston",
    "wof:placetype":"locality"
},
  "geometry": {"coordinates":[71.78368,40.83222],"type":"Point"}
}