{
  "type": "Feature",
  "properties": {
    "gn:admin1_code":"06",
    "gn:asciiname":"Qahramon",
    "gn:country_code":"UZ",
    "gn:dem":464,
    "gn:feature_class":"P",
    "gn:feature_code":"PPL",
    "gn:name":"Qahramon",
    "gn:population":0,
    "gn:timezone":"Asia/Tashkent",
    "iso:country":"UZ",
    "name:eng_x_preferred":[
        "Qahramon"
    ],
    "name:kir_x_preferred":[
        "Qahramon"
    ],
    "name:und_x_variant":[
        "Kakhraman"
    ],
    "wof:name":"Qahramon",
    "wof:placetype":"locality"
},
  "geometry": {"coordinates":[71.95265999999999,41.06572],"type":"Point"}
}