{
  "type": "Feature",
  "properties": {
    "gn:admin1_code":"12",
    "gn:asciiname":"Jayilma",
    "gn:country_code":"UZ",
    "gn:dem":458,
    "gn:feature_class":"P",
    "gn:feature_code":"PPL",
    "gn:name":"Jayilma",
    "gn:population":0,
    "gn:timezone":"Asia/Samarkand",
    "iso:country":"UZ",
    "name:uzb_x_preferred":[
        "Jayilma"
    ],
    "wof:name":"Jayilma",
    "wof:placetype":"locality"
},
  "geometry": {"coordinates":[67.77361999999999,38.02139],"type":"Point"}
}