{
  "type": "Feature",
  "properties": {
    "gn:admin1_code":"06",
    "gn:asciiname":"Xo`jasho`rkent",
    "gn:country_code":"UZ",
    "gn:dem":797,
    "gn:feature_class":"P",
    "gn:feature_code":"PPL",
    "gn:name":"Xo\u2018jasho\u2018rkent",
    "gn:population":0,
    "gn:timezone":"Asia/Tashkent",
    "iso:country":"UZ",
    "name:und_x_variant":[
        "Khodzha-Shurkent",
        "Khodzhashirkent",
        "Xo\u2018jasho\u2018rkent"
    ],
    "wof:name":"Xo`jasho`rkent",
    "wof:placetype":"locality"
},
  "geometry": {"coordinates":[71.78369000000001,41.23013],"type":"Point"}
}