{
  "type": "Feature",
  "properties": {
    "gn:admin1_code":"00",
    "gn:asciiname":"Karaun",
    "gn:cc2":"UZ",
    "gn:country_code":"UZ",
    "gn:dem":191,
    "gn:feature_class":"P",
    "gn:feature_code":"PPL",
    "gn:name":"Karaun",
    "gn:population":0,
    "gn:timezone":"Asia/Samarkand",
    "iso:country":"UZ",
    "name:und_x_variant":[
        "Kulanchi",
        "Karaun"
    ],
    "wof:name":"Karaun",
    "wof:placetype":"locality"
},
  "geometry": {"coordinates":[63.65,39.51667],"type":"Point"}
}