{
  "type": "Feature",
  "properties": {
    "gn:admin1_code":"12",
    "gn:asciiname":"Hayrondara",
    "gn:country_code":"UZ",
    "gn:dem":660,
    "gn:feature_class":"P",
    "gn:feature_code":"PPL",
    "gn:name":"Hayrondara",
    "gn:population":0,
    "gn:timezone":"Asia/Samarkand",
    "iso:country":"UZ",
    "name:uzb_x_preferred":[
        "Hayrondara"
    ],
    "wof:name":"Hayrondara",
    "wof:placetype":"locality"
},
  "geometry": {"coordinates":[67.7633,38.28179],"type":"Point"}
}