{
  "type": "Feature",
  "properties": {
    "gn:admin1_code":"00",
    "gn:asciiname":"Katta-Suganchi",
    "gn:cc2":"UZ",
    "gn:country_code":"UZ",
    "gn:dem":536,
    "gn:feature_class":"P",
    "gn:feature_code":"PPL",
    "gn:name":"Katta-Suganchi",
    "gn:population":0,
    "gn:timezone":"Asia/Samarkand",
    "iso:country":"UZ",
    "name:und_x_variant":[
        "Suganchi",
        "Katta-Suganchi"
    ],
    "wof:name":"Katta-Suganchi",
    "wof:placetype":"locality"
},
  "geometry": {"coordinates":[66.61667,39.95],"type":"Point"}
}