{
  "type": "Feature",
  "properties": {
    "gn:admin1_code":"09",
    "gn:asciiname":"Shark Yulduz",
    "gn:country_code":"UZ",
    "gn:dem":94,
    "gn:feature_class":"P",
    "gn:feature_code":"PPL",
    "gn:name":"Shark Yulduz",
    "gn:population":0,
    "gn:timezone":"Asia/Samarkand",
    "iso:country":"UZ",
    "wof:name":"Shark Yulduz",
    "wof:placetype":"locality"
},
  "geometry": {"coordinates":[60.90106,41.91049],"type":"Point"}
}