{
  "type": "Feature",
  "properties": {
    "gn:admin1_code":"01",
    "gn:asciiname":"Teshiktosh",
    "gn:country_code":"UZ",
    "gn:dem":578,
    "gn:feature_class":"P",
    "gn:feature_code":"PPL",
    "gn:name":"Teshiktosh",
    "gn:population":0,
    "gn:timezone":"Asia/Tashkent",
    "iso:country":"UZ",
    "name:rus_x_preferred":[
        "\u0421\u0435\u0440\u0433\u043e-\u0422\u0435\u0448\u0438\u043a\u0442\u0430\u0448"
    ],
    "name:und_x_variant":[
        "Sergo-Teshiktash"
    ],
    "name:uzb_x_preferred":[
        "Teshiktosh"
    ],
    "wof:name":"Teshiktosh",
    "wof:placetype":"locality"
},
  "geometry": {"coordinates":[72.6037,40.84889],"type":"Point"}
}