{
  "type": "Feature",
  "properties": {
    "gn:admin1_code":"00",
    "gn:asciiname":"Zangibay",
    "gn:country_code":"UZ",
    "gn:dem":644,
    "gn:feature_class":"P",
    "gn:feature_code":"PPL",
    "gn:name":"Zangibay",
    "gn:population":0,
    "gn:timezone":"Asia/Samarkand",
    "iso:country":"UZ",
    "wof:name":"Zangibay",
    "wof:placetype":"locality"
},
  "geometry": {"coordinates":[66.71666999999999,39.68333],"type":"Point"}
}