{
  "type": "Feature",
  "properties": {
    "gn:admin1_code":"01",
    "gn:asciiname":"Kuyganyor",
    "gn:country_code":"UZ",
    "gn:dem":458,
    "gn:feature_class":"P",
    "gn:feature_code":"PPLA2",
    "gn:name":"Kuyganyor",
    "gn:population":0,
    "gn:timezone":"Asia/Tashkent",
    "iso:country":"UZ",
    "name:rus_x_preferred":[
        "\u041a\u0443\u0439\u0433\u0430\u043d\u044f\u0440"
    ],
    "name:rus_x_variant":[
        "\u041a\u0443\u0439\u0433\u0430\u043d-\u042f\u0440"
    ],
    "name:und_x_variant":[
        "Kuyganyar",
        "Kuyganyor",
        "Kuygan-Yar"
    ],
    "name:uzb_x_preferred":[
        "Kuyganyor"
    ],
    "wof:name":"Kuyganyor",
    "wof:placetype":"locality"
},
  "geometry": {"coordinates":[72.30734,40.85444],"type":"Point"}
}