{
  "type": "Feature",
  "properties": {
    "gn:admin1_code":"08",
    "gn:asciiname":"Tepetay",
    "gn:country_code":"UZ",
    "gn:dem":571,
    "gn:feature_class":"P",
    "gn:feature_code":"PPL",
    "gn:name":"Tepetay",
    "gn:population":0,
    "gn:timezone":"Asia/Samarkand",
    "iso:country":"UZ",
    "name:und_x_variant":[
        "Tepatay",
        "Tyube-Tay",
        "Tepetay"
    ],
    "wof:name":"Tepetay",
    "wof:placetype":"locality"
},
  "geometry": {"coordinates":[66.55,39.13333],"type":"Point"}
}