{
  "type": "Feature",
  "properties": {
    "gn:admin1_code":"06",
    "gn:asciiname":"Ijtimoiyot",
    "gn:country_code":"UZ",
    "gn:dem":905,
    "gn:feature_class":"P",
    "gn:feature_code":"PPL",
    "gn:name":"Ijtimoiyot",
    "gn:population":0,
    "gn:timezone":"Asia/Tashkent",
    "iso:country":"UZ",
    "name:eng_x_preferred":[
        "Ijtimoiyot"
    ],
    "wof:name":"Ijtimoiyot",
    "wof:placetype":"locality"
},
  "geometry": {"coordinates":[71.5594,41.25447],"type":"Point"}
}