{
  "type": "Feature",
  "properties": {
    "gn:admin1_code":"16",
    "gn:asciiname":"Tobor",
    "gn:country_code":"UZ",
    "gn:dem":282,
    "gn:feature_class":"P",
    "gn:feature_code":"PPL",
    "gn:name":"Tobor",
    "gn:population":0,
    "gn:timezone":"Asia/Tashkent",
    "iso:country":"UZ",
    "name:uzb_x_preferred":[
        "Tobor"
    ],
    "wof:name":"Tobor",
    "wof:placetype":"locality"
},
  "geometry": {"coordinates":[69.05327,40.4559],"type":"Point"}
}