{
  "type": "Feature",
  "properties": {
    "gn:admin1_code":"06",
    "gn:asciiname":"Sait-Bay",
    "gn:country_code":"UZ",
    "gn:dem":448,
    "gn:feature_class":"P",
    "gn:feature_code":"PPL",
    "gn:name":"Sait-Bay",
    "gn:population":0,
    "gn:timezone":"Asia/Tashkent",
    "iso:country":"UZ",
    "wof:name":"Sait-Bay",
    "wof:placetype":"locality"
},
  "geometry": {"coordinates":[72.09999999999999,40.96667],"type":"Point"}
}