{
  "type": "Feature",
  "properties": {
    "gn:admin1_code":"03",
    "gn:asciiname":"Mingchinor",
    "gn:country_code":"UZ",
    "gn:dem":442,
    "gn:feature_class":"P",
    "gn:feature_code":"PPL",
    "gn:name":"Mingchinor",
    "gn:population":0,
    "gn:timezone":"Asia/Tashkent",
    "iso:country":"UZ",
    "name:uzb_x_preferred":[
        "Mingchinor"
    ],
    "wof:name":"Mingchinor",
    "wof:placetype":"locality"
},
  "geometry": {"coordinates":[71.74226,40.60313],"type":"Point"}
}