{
  "type": "Feature",
  "properties": {
    "gn:admin1_code":"01",
    "gn:asciiname":"Kommuna",
    "gn:country_code":"UZ",
    "gn:dem":446,
    "gn:feature_class":"P",
    "gn:feature_code":"PPL",
    "gn:name":"Kommuna",
    "gn:population":0,
    "gn:timezone":"Asia/Tashkent",
    "iso:country":"UZ",
    "name:aze_x_preferred":[
        "Bala \u00c7ayl\u0131"
    ],
    "name:ita_x_preferred":[
        "Kommuna"
    ],
    "name:kat_x_preferred":[
        "\u10d9\u10dd\u10db\u10e3\u10dc\u10d0"
    ],
    "name:msa_x_preferred":[
        "Kommuna"
    ],
    "name:rus_x_preferred":[
        "\u041a\u043e\u043c\u043c\u0443\u043d\u0430"
    ],
    "wof:name":"Kommuna",
    "wof:placetype":"locality"
},
  "geometry": {"coordinates":[72.17339,40.79124],"type":"Point"}
}