{
  "type": "Feature",
  "properties": {
    "gn:admin1_code":"02",
    "gn:asciiname":"Marziya",
    "gn:cc2":"UZ",
    "gn:country_code":"UZ",
    "gn:dem":218,
    "gn:feature_class":"P",
    "gn:feature_code":"PPL",
    "gn:name":"Marziya",
    "gn:population":0,
    "gn:timezone":"Asia/Samarkand",
    "iso:country":"UZ",
    "name:und_x_variant":[
        "Mirzaya",
        "Marziya"
    ],
    "wof:name":"Marziya",
    "wof:placetype":"locality"
},
  "geometry": {"coordinates":[64.20471999999999,39.98944],"type":"Point"}
}