{
  "type": "Feature",
  "properties": {
    "gn:admin1_code":"14",
    "gn:asciiname":"Sulaymonov",
    "gn:country_code":"UZ",
    "gn:dem":319,
    "gn:feature_class":"P",
    "gn:feature_code":"PPL",
    "gn:name":"Sulaymonov",
    "gn:population":0,
    "gn:timezone":"Asia/Tashkent",
    "iso:country":"UZ",
    "name:uzb_x_preferred":[
        "Sulaymonov"
    ],
    "wof:name":"Sulaymonov",
    "wof:placetype":"locality"
},
  "geometry": {"coordinates":[69.06012,41.00762],"type":"Point"}
}