{
  "type": "Feature",
  "properties": {
    "gn:admin1_code":"08",
    "gn:asciiname":"Xummon",
    "gn:country_code":"UZ",
    "gn:dem":1671,
    "gn:feature_class":"P",
    "gn:feature_code":"PPL",
    "gn:name":"Xummon",
    "gn:population":0,
    "gn:timezone":"Asia/Samarkand",
    "iso:country":"UZ",
    "name:und_x_variant":[
        "Kuman"
    ],
    "wof:name":"Xummon",
    "wof:placetype":"locality"
},
  "geometry": {"coordinates":[67.15243000000001,38.88722],"type":"Point"}
}