{
  "type": "Feature",
  "properties": {
    "gn:admin1_code":"01",
    "gn:asciiname":"Zangkon",
    "gn:country_code":"UZ",
    "gn:dem":484,
    "gn:feature_class":"P",
    "gn:feature_code":"PPL",
    "gn:name":"Zangkon",
    "gn:population":0,
    "gn:timezone":"Asia/Tashkent",
    "iso:country":"UZ",
    "name:rus_x_preferred":[
        "\u0417\u0430\u043d\u043a\u0430\u043d"
    ],
    "name:und_x_variant":[
        "Zankan"
    ],
    "name:uzb_x_preferred":[
        "Zangkon"
    ],
    "wof:name":"Zangkon",
    "wof:placetype":"locality"
},
  "geometry": {"coordinates":[72.24256,40.69158],"type":"Point"}
}