{
  "type": "Feature",
  "properties": {
    "gn:admin1_code":"01",
    "gn:asciiname":"O`qchi",
    "gn:country_code":"UZ",
    "gn:dem":556,
    "gn:feature_class":"P",
    "gn:feature_code":"PPL",
    "gn:name":"O\u2018qchi",
    "gn:population":0,
    "gn:timezone":"Asia/Bishkek",
    "iso:country":"UZ",
    "name:rus_x_preferred":[
        "\u0423\u043a\u0447\u0438"
    ],
    "name:und_x_variant":[
        "Akchi",
        "Ukchi"
    ],
    "name:uzb_x_preferred":[
        "O\u2018qchi"
    ],
    "name:uzb_x_variant":[
        "Uqchi"
    ],
    "wof:name":"O`qchi",
    "wof:placetype":"locality"
},
  "geometry": {"coordinates":[72.35561,40.60452],"type":"Point"}
}