{
  "type": "Feature",
  "properties": {
    "gn:admin1_code":"00",
    "gn:asciiname":"Ak-Tyube",
    "gn:country_code":"UZ",
    "gn:dem":217,
    "gn:feature_class":"P",
    "gn:feature_code":"PPL",
    "gn:name":"Ak-Tyube",
    "gn:population":0,
    "gn:timezone":"Asia/Samarkand",
    "iso:country":"UZ",
    "wof:name":"Ak-Tyube",
    "wof:placetype":"locality"
},
  "geometry": {"coordinates":[64.23333000000001,39.86667],"type":"Point"}
}