{
  "type": "Feature",
  "properties": {
    "gn:admin1_code":"12",
    "gn:asciiname":"Dohibola",
    "gn:country_code":"UZ",
    "gn:dem":1753,
    "gn:feature_class":"P",
    "gn:feature_code":"PPL",
    "gn:name":"Dohibola",
    "gn:population":0,
    "gn:timezone":"Asia/Samarkand",
    "iso:country":"UZ",
    "name:und_x_variant":[
        "Diy-Bala",
        "Dii-Bala"
    ],
    "name:uzb_x_preferred":[
        "Dohibola"
    ],
    "wof:name":"Dohibola",
    "wof:placetype":"locality"
},
  "geometry": {"coordinates":[67.45848000000001,38.35303],"type":"Point"}
}