{
  "type": "Feature",
  "properties": {
    "gn:admin1_code":"08",
    "gn:asciiname":"Tezob",
    "gn:country_code":"UZ",
    "gn:dem":559,
    "gn:feature_class":"P",
    "gn:feature_code":"PPL",
    "gn:name":"Tezob",
    "gn:population":0,
    "gn:timezone":"Asia/Samarkand",
    "iso:country":"UZ",
    "wof:name":"Tezob",
    "wof:placetype":"locality"
},
  "geometry": {"coordinates":[66.68127,39.03398],"type":"Point"}
}