{
  "type": "Feature",
  "properties": {
    "gn:admin1_code":"07",
    "gn:asciiname":"Yangakly",
    "gn:country_code":"UZ",
    "gn:dem":879,
    "gn:feature_class":"P",
    "gn:feature_code":"PPL",
    "gn:name":"Yangakly",
    "gn:population":0,
    "gn:timezone":"Asia/Samarkand",
    "iso:country":"UZ",
    "name:und_x_variant":[
        "Dzhangak",
        "Yangakly"
    ],
    "wof:name":"Yangakly",
    "wof:placetype":"locality"
},
  "geometry": {"coordinates":[65.91667,40.31667],"type":"Point"}
}