{
  "type": "Feature",
  "properties": {
    "gn:admin1_code":"15",
    "gn:asciiname":"Navro`z",
    "gn:country_code":"UZ",
    "gn:dem":280,
    "gn:feature_class":"P",
    "gn:feature_code":"PPL",
    "gn:name":"Navro\u2018z",
    "gn:population":0,
    "gn:timezone":"Asia/Samarkand",
    "iso:country":"UZ",
    "name:uzb_x_preferred":[
        "Navro\u2018z"
    ],
    "wof:name":"Navro`z",
    "wof:placetype":"locality"
},
  "geometry": {"coordinates":[68.07252,40.45597],"type":"Point"}
}