{
  "type": "Feature",
  "properties": {
    "gn:admin1_code":"07",
    "gn:asciiname":"Ferma Nomer Dva Sovkhoza Imeni Kalinina",
    "gn:country_code":"UZ",
    "gn:dem":200,
    "gn:feature_class":"P",
    "gn:feature_code":"PPL",
    "gn:name":"Ferma Nomer Dva Sovkhoza Imeni Kalinina",
    "gn:population":0,
    "gn:timezone":"Asia/Tashkent",
    "iso:country":"UZ",
    "wof:name":"Ferma Nomer Dva Sovkhoza Imeni Kalinina",
    "wof:placetype":"locality"
},
  "geometry": {"coordinates":[66.03749999999999,42.44382],"type":"Point"}
}