{
  "type": "Feature",
  "properties": {
    "gn:admin1_code":"14",
    "gn:asciiname":"Chartak",
    "gn:country_code":"UZ",
    "gn:dem":310,
    "gn:feature_class":"P",
    "gn:feature_code":"PPL",
    "gn:name":"Chartak",
    "gn:population":0,
    "gn:timezone":"Asia/Tashkent",
    "iso:country":"UZ",
    "wof:name":"Chartak",
    "wof:placetype":"locality"
},
  "geometry": {"coordinates":[69.05,40.96667],"type":"Point"}
}