{
  "type": "Feature",
  "properties": {
    "gn:admin1_code":"14",
    "gn:asciiname":"Chartak",
    "gn:country_code":"UZ",
    "gn:dem":310,
    "gn:feature_class":"P",
    "gn:feature_code":"PPL",
    "gn:name":"Chartak",
    "gn:population":0,
    "gn:timezone":"Asia/Tashkent",
    "iso:country":"UZ",
    "name:azb_x_preferred":[
        "\u0686\u0627\u0631\u062a\u0627\u0642"
    ],
    "name:ceb_x_preferred":[
        "Chortoq"
    ],
    "name:ckb_x_preferred":[
        "\u0686\u0627\u0631\u062a\u0627\u0642"
    ],
    "name:deu_x_preferred":[
        "Chortoq"
    ],
    "name:fas_x_preferred":[
        "\u0686\u0627\u0631\u062a\u0627\u0642"
    ],
    "name:fra_x_preferred":[
        "Chortoq"
    ],
    "name:hsb_x_preferred":[
        "Chortoq"
    ],
    "name:jpn_x_preferred":[
        "\u30c1\u30e3\u30eb\u30bf\u30af"
    ],
    "name:kik_x_preferred":[
        "Chortoq"
    ],
    "name:lit_x_preferred":[
        "\u010cartakas"
    ],
    "name:pol_x_preferred":[
        "Chortoq"
    ],
    "name:rus_x_preferred":[
        "\u0427\u0430\u0440\u0442\u0430\u043a"
    ],
    "name:spa_x_preferred":[
        "\u00c7artak"
    ],
    "name:tat_x_preferred":[
        "\u0427\u0430\u0440\u0442\u0430\u043a"
    ],
    "name:tgk_x_preferred":[
        "\u0427\u043e\u0440\u0442\u043e\u049b"
    ],
    "name:tur_x_preferred":[
        "\u00c7artak"
    ],
    "name:urd_x_preferred":[
        "\u0686\u0627\u0631\u062a\u0627\u0642"
    ],
    "name:uzb_x_preferred":[
        "Chortoq"
    ],
    "wof:name":"Chartak",
    "wof:placetype":"locality"
},
  "geometry": {"coordinates":[69.05,40.96667],"type":"Point"}
}