{
  "type": "Feature",
  "properties": {
    "gn:admin1_code":"08",
    "gn:asciiname":"Qurama",
    "gn:country_code":"UZ",
    "gn:dem":717,
    "gn:feature_class":"P",
    "gn:feature_code":"PPL",
    "gn:name":"Qurama",
    "gn:population":0,
    "gn:timezone":"Asia/Samarkand",
    "iso:country":"UZ",
    "wof:name":"Qurama",
    "wof:placetype":"locality"
},
  "geometry": {"coordinates":[66.75806999999999,39.22788],"type":"Point"}
}