{
  "type": "Feature",
  "properties": {
    "gn:admin1_code":"15",
    "gn:asciiname":"Chilonzor",
    "gn:country_code":"UZ",
    "gn:dem":364,
    "gn:feature_class":"P",
    "gn:feature_code":"PPL",
    "gn:name":"Chilonzor",
    "gn:population":0,
    "gn:timezone":"Asia/Tashkent",
    "iso:country":"UZ",
    "name:uzb_x_preferred":[
        "Chilonzor"
    ],
    "wof:name":"Chilonzor",
    "wof:placetype":"locality"
},
  "geometry": {"coordinates":[68.59165,40.17621],"type":"Point"}
}