{
  "type": "Feature",
  "properties": {
    "gn:admin1_code":"12",
    "gn:asciiname":"Kaptugay",
    "gn:country_code":"UZ",
    "gn:dem":385,
    "gn:feature_class":"P",
    "gn:feature_code":"PPL",
    "gn:name":"Kaptugay",
    "gn:population":0,
    "gn:timezone":"Asia/Samarkand",
    "iso:country":"UZ",
    "wof:name":"Kaptugay",
    "wof:placetype":"locality"
},
  "geometry": {"coordinates":[67.51768,37.72081],"type":"Point"}
}