{
  "type": "Feature",
  "properties": {
    "gn:admin1_code":"16",
    "gn:asciiname":"Farhodobod",
    "gn:country_code":"UZ",
    "gn:dem":323,
    "gn:feature_class":"P",
    "gn:feature_code":"PPL",
    "gn:name":"Farhodobod",
    "gn:population":0,
    "gn:timezone":"Asia/Tashkent",
    "iso:country":"UZ",
    "name:uzb_x_preferred":[
        "Farhodobod"
    ],
    "wof:name":"Farhodobod",
    "wof:placetype":"locality"
},
  "geometry": {"coordinates":[69.01402,40.26279],"type":"Point"}
}