{
  "type": "Feature",
  "properties": {
    "gn:admin1_code":"00",
    "gn:asciiname":"Bulak",
    "gn:country_code":"UZ",
    "gn:dem":546,
    "gn:feature_class":"P",
    "gn:feature_code":"PPL",
    "gn:name":"Bulak",
    "gn:population":0,
    "gn:timezone":"Asia/Ashgabat",
    "iso:country":"UZ",
    "wof:name":"Bulak",
    "wof:placetype":"locality"
},
  "geometry": {"coordinates":[66.56667,37.55],"type":"Point"}
}