{
  "type": "Feature",
  "properties": {
    "gn:admin1_code":"00",
    "gn:asciiname":"Mazragan",
    "gn:country_code":"UZ",
    "gn:dem":260,
    "gn:feature_class":"P",
    "gn:feature_code":"PPL",
    "gn:name":"Mazragan",
    "gn:population":0,
    "gn:timezone":"Asia/Samarkand",
    "iso:country":"UZ",
    "wof:name":"Mazragan",
    "wof:placetype":"locality"
},
  "geometry": {"coordinates":[64.73333000000001,40.05],"type":"Point"}
}