{
  "type": "Feature",
  "properties": {
    "gn:admin1_code":"03",
    "gn:asciiname":"Ko`prikboshi",
    "gn:country_code":"UZ",
    "gn:dem":461,
    "gn:feature_class":"P",
    "gn:feature_code":"PPL",
    "gn:name":"Ko\u2018prikboshi",
    "gn:population":0,
    "gn:timezone":"Asia/Tashkent",
    "iso:country":"UZ",
    "name:uzb_x_preferred":[
        "Ko\u2018prikboshi"
    ],
    "wof:name":"Ko`prikboshi",
    "wof:placetype":"locality"
},
  "geometry": {"coordinates":[71.70291,40.52028],"type":"Point"}
}