{
  "type": "Feature",
  "properties": {
    "gn:admin1_code":"03",
    "gn:asciiname":"Oqshoqguzar",
    "gn:country_code":"UZ",
    "gn:dem":475,
    "gn:feature_class":"P",
    "gn:feature_code":"PPL",
    "gn:name":"Oqshoqguzar",
    "gn:population":0,
    "gn:timezone":"Asia/Tashkent",
    "iso:country":"UZ",
    "name:uzb_x_preferred":[
        "Oqshoqguzar"
    ],
    "wof:name":"Oqshoqguzar",
    "wof:placetype":"locality"
},
  "geometry": {"coordinates":[71.79054000000002,40.51149],"type":"Point"}
}