{
  "type": "Feature",
  "properties": {
    "gn:admin1_code":"08",
    "gn:asciiname":"Atakenty",
    "gn:country_code":"UZ",
    "gn:dem":858,
    "gn:feature_class":"P",
    "gn:feature_code":"PPL",
    "gn:name":"Atakenty",
    "gn:population":0,
    "gn:timezone":"Asia/Samarkand",
    "iso:country":"UZ",
    "name:und_x_variant":[
        "Ata-Kent",
        "Atakenty"
    ],
    "wof:name":"Atakenty",
    "wof:placetype":"locality"
},
  "geometry": {"coordinates":[66.78333000000001,39.25],"type":"Point"}
}