{
  "type": "Feature",
  "properties": {
    "gn:admin1_code":"03",
    "gn:asciiname":"Qiziltepa",
    "gn:country_code":"UZ",
    "gn:dem":413,
    "gn:feature_class":"P",
    "gn:feature_code":"PPL",
    "gn:name":"Qiziltepa",
    "gn:population":0,
    "gn:timezone":"Asia/Tashkent",
    "iso:country":"UZ",
    "name:und_x_variant":[
        "Kyzyltepa"
    ],
    "name:uzb_x_preferred":[
        "Qiziltepa"
    ],
    "wof:name":"Qiziltepa",
    "wof:placetype":"locality"
},
  "geometry": {"coordinates":[71.44029999999999,40.5025],"type":"Point"}
}