{
  "type": "Feature",
  "properties": {
    "gn:admin1_code":"09",
    "gn:asciiname":"Imeni Kirova",
    "gn:country_code":"UZ",
    "gn:dem":54,
    "gn:feature_class":"P",
    "gn:feature_code":"PPL",
    "gn:name":"Imeni Kirova",
    "gn:population":0,
    "gn:timezone":"Asia/Samarkand",
    "iso:country":"UZ",
    "name:ceb_x_preferred":[
        "Imeni Kirova"
    ],
    "name:swe_x_preferred":[
        "Imeni Kirova"
    ],
    "wof:name":"Imeni Kirova",
    "wof:placetype":"locality"
},
  "geometry": {"coordinates":[58.63333000000001,43.23333],"type":"Point"}
}