{
  "type": "Feature",
  "properties": {
    "gn:admin1_code":"00",
    "gn:asciiname":"Rastlyamak",
    "gn:country_code":"UZ",
    "gn:dem":875,
    "gn:feature_class":"P",
    "gn:feature_code":"PPL",
    "gn:name":"Rastlyamak",
    "gn:population":0,
    "gn:timezone":"Asia/Bishkek",
    "iso:country":"UZ",
    "wof:name":"Rastlyamak",
    "wof:placetype":"locality"
},
  "geometry": {"coordinates":[72.05,40.28333],"type":"Point"}
}