{
  "type": "Feature",
  "properties": {
    "gn:admin1_code":"10",
    "gn:asciiname":"Loyish",
    "gn:cc2":"UZ",
    "gn:country_code":"UZ",
    "gn:dem":580,
    "gn:feature_class":"P",
    "gn:feature_code":"PPL",
    "gn:name":"Loyish",
    "gn:population":0,
    "gn:timezone":"Asia/Samarkand",
    "iso:country":"UZ",
    "name:azb_x_preferred":[
        "\u0644\u0627\u06cc\u06cc\u0634"
    ],
    "name:fas_x_preferred":[
        "\u0644\u0627\u06cc\u0634"
    ],
    "name:rus_x_preferred":[
        "\u041b\u0430\u0438\u0448"
    ],
    "name:tur_x_preferred":[
        "Layi\u015f"
    ],
    "name:und_x_variant":[
        "Akdar\u2019ya",
        "Laish"
    ],
    "name:urd_x_preferred":[
        "\u0644\u0627\u06cc\u06cc\u0634"
    ],
    "name:uzb_x_preferred":[
        "Loyish"
    ],
    "wof:name":"Loyish",
    "wof:placetype":"locality"
},
  "geometry": {"coordinates":[66.74806,39.88389],"type":"Point"}
}