{
  "type": "Feature",
  "properties": {
    "gn:admin1_code":"10",
    "gn:asciiname":"Loyish",
    "gn:cc2":"UZ",
    "gn:country_code":"UZ",
    "gn:dem":580,
    "gn:feature_class":"P",
    "gn:feature_code":"PPL",
    "gn:name":"Loyish",
    "gn:population":0,
    "gn:timezone":"Asia/Samarkand",
    "iso:country":"UZ",
    "name:und_x_variant":[
        "Akdar\u2019ya",
        "Laish",
        "Loyish"
    ],
    "wof:name":"Loyish",
    "wof:placetype":"locality"
},
  "geometry": {"coordinates":[66.74806,39.88389],"type":"Point"}
}