{
  "type": "Feature",
  "properties": {
    "gn:admin1_code":"00",
    "gn:asciiname":"Tupadas",
    "gn:cc2":"UZ",
    "gn:country_code":"UZ",
    "gn:dem":628,
    "gn:feature_class":"P",
    "gn:feature_code":"PPL",
    "gn:name":"Tupadas",
    "gn:population":0,
    "gn:timezone":"Asia/Samarkand",
    "iso:country":"UZ",
    "name:und_x_variant":[
        "Tupalas",
        "Tupadas"
    ],
    "wof:name":"Tupadas",
    "wof:placetype":"locality"
},
  "geometry": {"coordinates":[66.95,39.86667],"type":"Point"}
}