{
  "type": "Feature",
  "properties": {
    "gn:admin1_code":"01",
    "gn:asciiname":"Arabqishloq",
    "gn:country_code":"UZ",
    "gn:dem":498,
    "gn:feature_class":"P",
    "gn:feature_code":"PPL",
    "gn:name":"Arabqishloq",
    "gn:population":0,
    "gn:timezone":"Asia/Tashkent",
    "iso:country":"UZ",
    "name:uzb_x_preferred":[
        "Arabqishloq"
    ],
    "wof:name":"Arabqishloq",
    "wof:placetype":"locality"
},
  "geometry": {"coordinates":[72.23549,40.99264],"type":"Point"}
}