{
  "type": "Feature",
  "properties": {
    "gn:admin1_code":"08",
    "gn:asciiname":"Lag`mon",
    "gn:country_code":"UZ",
    "gn:dem":376,
    "gn:feature_class":"P",
    "gn:feature_code":"PPL",
    "gn:name":"Lag\u2018mon",
    "gn:population":0,
    "gn:timezone":"Asia/Samarkand",
    "iso:country":"UZ",
    "name:eng_x_preferred":[
        "Lag\u2018mon"
    ],
    "wof:name":"Lag`mon",
    "wof:placetype":"locality"
},
  "geometry": {"coordinates":[65.79346,38.88798],"type":"Point"}
}