{
  "type": "Feature",
  "properties": {
    "gn:admin1_code":"00",
    "gn:asciiname":"Baglydara",
    "gn:country_code":"UZ",
    "gn:dem":1519,
    "gn:feature_class":"P",
    "gn:feature_code":"PPL",
    "gn:name":"Baglydara",
    "gn:population":0,
    "gn:timezone":"Asia/Samarkand",
    "iso:country":"UZ",
    "wof:name":"Baglydara",
    "wof:placetype":"locality"
},
  "geometry": {"coordinates":[66.78333000000001,37.96667],"type":"Point"}
}