{
  "type": "Feature",
  "properties": {
    "gn:admin1_code":"06",
    "gn:asciiname":"Qizilyozi",
    "gn:country_code":"UZ",
    "gn:dem":1223,
    "gn:feature_class":"P",
    "gn:feature_code":"PPL",
    "gn:name":"Qizilyozi",
    "gn:population":0,
    "gn:timezone":"Asia/Tashkent",
    "iso:country":"UZ",
    "name:eng_x_preferred":[
        "Qizilyazi"
    ],
    "name:uzb_x_preferred":[
        "Qizilyozi"
    ],
    "wof:name":"Qizilyozi",
    "wof:placetype":"locality"
},
  "geometry": {"coordinates":[71.67803000000001,41.44297],"type":"Point"}
}