{
  "type": "Feature",
  "properties": {
    "gn:admin1_code":"14",
    "gn:asciiname":"Shampan",
    "gn:cc2":"UZ",
    "gn:country_code":"UZ",
    "gn:dem":907,
    "gn:feature_class":"P",
    "gn:feature_code":"PPL",
    "gn:name":"Shampan",
    "gn:population":0,
    "gn:timezone":"Asia/Tashkent",
    "iso:country":"UZ",
    "name:und_x_variant":[
        "Sovkhoz Parkent"
    ],
    "wof:name":"Shampan",
    "wof:placetype":"locality"
},
  "geometry": {"coordinates":[69.71944000000001,41.21278],"type":"Point"}
}