{
  "type": "Feature",
  "properties": {
    "gn:admin1_code":"01",
    "gn:asciiname":"Janubiy Olamushuk",
    "gn:country_code":"UZ",
    "gn:dem":679,
    "gn:feature_class":"P",
    "gn:feature_code":"PPL",
    "gn:name":"Janubiy Olamushuk",
    "gn:population":0,
    "gn:timezone":"Asia/Tashkent",
    "iso:country":"UZ",
    "name:und_x_variant":[
        "Yuzhnyj-Alamyshik",
        "Yuzhnyy Alamyshik",
        "Janubiy Olamushuk"
    ],
    "wof:name":"Janubiy Olamushuk",
    "wof:placetype":"locality"
},
  "geometry": {"coordinates":[72.61273,40.75611],"type":"Point"}
}