{
  "type": "Feature",
  "properties": {
    "gn:admin1_code":"01",
    "gn:asciiname":"Tovuldi",
    "gn:country_code":"UZ",
    "gn:dem":439,
    "gn:feature_class":"P",
    "gn:feature_code":"PPL",
    "gn:name":"Tovuldi",
    "gn:population":0,
    "gn:timezone":"Asia/Tashkent",
    "iso:country":"UZ",
    "name:rus_x_preferred":[
        "\u0422\u0430\u0432\u0443\u043b\u0434\u0438"
    ],
    "name:und_x_variant":[
        "Tavuldi"
    ],
    "name:uzb_x_preferred":[
        "Tovuldi"
    ],
    "wof:name":"Tovuldi",
    "wof:placetype":"locality"
},
  "geometry": {"coordinates":[72.16079000000001,40.84769],"type":"Point"}
}