{
  "type": "Feature",
  "properties": {
    "gn:admin1_code":"08",
    "gn:asciiname":"Beshkazak",
    "gn:country_code":"UZ",
    "gn:dem":655,
    "gn:feature_class":"P",
    "gn:feature_code":"PPL",
    "gn:name":"Beshkazak",
    "gn:population":0,
    "gn:timezone":"Asia/Samarkand",
    "iso:country":"UZ",
    "wof:name":"Beshkazak",
    "wof:placetype":"locality"
},
  "geometry": {"coordinates":[66.88333,39.11667],"type":"Point"}
}