{
  "type": "Feature",
  "properties": {
    "gn:admin1_code":"00",
    "gn:asciiname":"Kyzyl-Kala",
    "gn:country_code":"UZ",
    "gn:dem":190,
    "gn:feature_class":"P",
    "gn:feature_code":"PPL",
    "gn:name":"Kyzyl-Kala",
    "gn:population":0,
    "gn:timezone":"Asia/Samarkand",
    "iso:country":"UZ",
    "wof:name":"Kyzyl-Kala",
    "wof:placetype":"locality"
},
  "geometry": {"coordinates":[63.93333000000001,39.36667],"type":"Point"}
}