{
  "type": "Feature",
  "properties": {
    "gn:admin1_code":"03",
    "gn:asciiname":"Xamraobod",
    "gn:country_code":"UZ",
    "gn:dem":394,
    "gn:feature_class":"P",
    "gn:feature_code":"PPL",
    "gn:name":"Xamraobod",
    "gn:population":0,
    "gn:timezone":"Asia/Tashkent",
    "iso:country":"UZ",
    "name:uzb_x_preferred":[
        "Xamraobod"
    ],
    "name:uzb_x_variant":[
        "Xamrabod"
    ],
    "wof:name":"Xamraobod",
    "wof:placetype":"locality"
},
  "geometry": {"coordinates":[70.76881,40.49089],"type":"Point"}
}