{
  "type": "Feature",
  "properties": {
    "gn:admin1_code":"01",
    "gn:asciiname":"Mirzaboshichek",
    "gn:country_code":"UZ",
    "gn:dem":421,
    "gn:feature_class":"P",
    "gn:feature_code":"PPL",
    "gn:name":"Mirzaboshichek",
    "gn:population":0,
    "gn:timezone":"Asia/Tashkent",
    "iso:country":"UZ",
    "name:eng_x_preferred":[
        "Mirzaboshichek"
    ],
    "name:uzb_x_preferred":[
        "Mirzaboshlik"
    ],
    "wof:name":"Mirzaboshichek",
    "wof:placetype":"locality"
},
  "geometry": {"coordinates":[71.87838000000001,40.89118],"type":"Point"}
}