{
  "type": "Feature",
  "properties": {
    "gn:admin1_code":"01",
    "gn:asciiname":"Dalvarzin",
    "gn:country_code":"UZ",
    "gn:dem":473,
    "gn:feature_class":"P",
    "gn:feature_code":"PPL",
    "gn:name":"Dalvarzin",
    "gn:population":0,
    "gn:timezone":"Asia/Tashkent",
    "iso:country":"UZ",
    "name:rus_x_preferred":[
        "Dal\u2019verzin"
    ],
    "name:rus_x_variant":[
        "\u0414\u0430\u043b\u044c\u0432\u0435\u0440\u0437\u0438\u043d",
        "Tel\u2019man",
        "\u0422\u0435\u043b\u044c\u043c\u0430\u043d"
    ],
    "name:uzb_x_preferred":[
        "Dalvarzin"
    ],
    "name:uzb_x_variant":[
        "Mexnat"
    ],
    "wof:name":"Dalvarzin",
    "wof:placetype":"locality"
},
  "geometry": {"coordinates":[72.29734999999999,40.77186],"type":"Point"}
}