{
  "type": "Feature",
  "properties": {
    "gn:admin1_code":"03",
    "gn:asciiname":"Loyson",
    "gn:country_code":"UZ",
    "gn:dem":443,
    "gn:feature_class":"P",
    "gn:feature_code":"PPL",
    "gn:name":"Loyson",
    "gn:population":0,
    "gn:timezone":"Asia/Tashkent",
    "iso:country":"UZ",
    "name:uzb_x_preferred":[
        "Loyson"
    ],
    "wof:name":"Loyson",
    "wof:placetype":"locality"
},
  "geometry": {"coordinates":[71.67305,40.54794],"type":"Point"}
}