{
  "type": "Feature",
  "properties": {
    "gn:admin1_code":"07",
    "gn:asciiname":"Oqsoch",
    "gn:country_code":"UZ",
    "gn:dem":253,
    "gn:feature_class":"P",
    "gn:feature_code":"PPL",
    "gn:name":"Oqsoch",
    "gn:population":0,
    "gn:timezone":"Asia/Samarkand",
    "iso:country":"UZ",
    "wof:name":"Oqsoch",
    "wof:placetype":"locality"
},
  "geometry": {"coordinates":[64.78601999999999,39.97602],"type":"Point"}
}