{
  "type": "Feature",
  "properties": {
    "gn:admin1_code":"12",
    "gn:asciiname":"Tarakli",
    "gn:country_code":"UZ",
    "gn:dem":646,
    "gn:feature_class":"P",
    "gn:feature_code":"PPL",
    "gn:name":"Tarakli",
    "gn:population":0,
    "gn:timezone":"Asia/Samarkand",
    "iso:country":"UZ",
    "name:und_x_variant":[
        "Tarakly"
    ],
    "name:uzb_x_preferred":[
        "Tarakli"
    ],
    "wof:name":"Tarakli",
    "wof:placetype":"locality"
},
  "geometry": {"coordinates":[67.84192,38.38588],"type":"Point"}
}