{
  "type": "Feature",
  "properties": {
    "gn:admin1_code":"06",
    "gn:asciiname":"Chagall",
    "gn:country_code":"UZ",
    "gn:dem":367,
    "gn:feature_class":"P",
    "gn:feature_code":"PPL",
    "gn:name":"Chagall",
    "gn:population":0,
    "gn:timezone":"Asia/Tashkent",
    "iso:country":"UZ",
    "name:eng_x_preferred":[
        "Chagall"
    ],
    "wof:name":"Chagall",
    "wof:placetype":"locality"
},
  "geometry": {"coordinates":[70.83599,40.70975],"type":"Point"}
}