{
  "type": "Feature",
  "properties": {
    "gn:admin1_code":"08",
    "gn:asciiname":"Obikanda",
    "gn:country_code":"UZ",
    "gn:dem":1109,
    "gn:feature_class":"P",
    "gn:feature_code":"PPL",
    "gn:name":"Obikanda",
    "gn:population":0,
    "gn:timezone":"Asia/Samarkand",
    "iso:country":"UZ",
    "name:und_x_variant":[
        "Obikandy",
        "Obikanda"
    ],
    "wof:name":"Obikanda",
    "wof:placetype":"locality"
},
  "geometry": {"coordinates":[67.15764,39.16869000000001],"type":"Point"}
}