{
  "type": "Feature",
  "properties": {
    "gn:admin1_code":"08",
    "gn:asciiname":"Igizak",
    "gn:country_code":"UZ",
    "gn:dem":578,
    "gn:feature_class":"P",
    "gn:feature_code":"PPL",
    "gn:name":"\u0130gizak",
    "gn:population":0,
    "gn:timezone":"Asia/Samarkand",
    "iso:country":"UZ",
    "wof:name":"Igizak",
    "wof:placetype":"locality"
},
  "geometry": {"coordinates":[66.56667,39.11667],"type":"Point"}
}