{
  "type": "Feature",
  "properties": {
    "gn:admin1_code":"00",
    "gn:asciiname":"Orday-Moynak",
    "gn:cc2":"UZ",
    "gn:country_code":"UZ",
    "gn:dem":678,
    "gn:feature_class":"P",
    "gn:feature_code":"PPL",
    "gn:name":"Orday-Moynak",
    "gn:population":0,
    "gn:timezone":"Asia/Tashkent",
    "iso:country":"UZ",
    "name:und_x_variant":[
        "Orday"
    ],
    "wof:name":"Orday-Moynak",
    "wof:placetype":"locality"
},
  "geometry": {"coordinates":[72.55,40.58333],"type":"Point"}
}