{
  "type": "Feature",
  "properties": {
    "gn:admin1_code":"16",
    "gn:asciiname":"Sultonhovuz",
    "gn:country_code":"UZ",
    "gn:dem":301,
    "gn:feature_class":"P",
    "gn:feature_code":"PPL",
    "gn:name":"Sultonhovuz",
    "gn:population":0,
    "gn:timezone":"Asia/Tashkent",
    "iso:country":"UZ",
    "name:uzb_x_preferred":[
        "Sultonhovuz"
    ],
    "wof:name":"Sultonhovuz",
    "wof:placetype":"locality"
},
  "geometry": {"coordinates":[69.06948,40.31538],"type":"Point"}
}