{
  "type": "Feature",
  "properties": {
    "gn:admin1_code":"01",
    "gn:asciiname":"Qoziqo`rg`on",
    "gn:country_code":"UZ",
    "gn:dem":434,
    "gn:feature_class":"P",
    "gn:feature_code":"PPL",
    "gn:name":"Qoziqo\u2018rg\u2018on",
    "gn:population":0,
    "gn:timezone":"Asia/Tashkent",
    "iso:country":"UZ",
    "name:uzb_x_preferred":[
        "Qoziqo\u2018rg\u2018on"
    ],
    "wof:name":"Qoziqo`rg`on",
    "wof:placetype":"locality"
},
  "geometry": {"coordinates":[71.9371,40.65975],"type":"Point"}
}