{
  "type": "Feature",
  "properties": {
    "gn:admin1_code":"03",
    "gn:asciiname":"Kirqiboldi",
    "gn:country_code":"UZ",
    "gn:dem":419,
    "gn:feature_class":"P",
    "gn:feature_code":"PPL",
    "gn:name":"Kirqiboldi",
    "gn:population":0,
    "gn:timezone":"Asia/Tashkent",
    "iso:country":"UZ",
    "name:und_x_variant":[
        "Kyrkepaldy"
    ],
    "name:uzb_x_preferred":[
        "Kirqiboldi"
    ],
    "wof:name":"Kirqiboldi",
    "wof:placetype":"locality"
},
  "geometry": {"coordinates":[71.20036999999998,40.47352],"type":"Point"}
}