{
  "type": "Feature",
  "properties": {
    "gn:admin1_code":"03",
    "gn:asciiname":"Qo`rg`onobod",
    "gn:country_code":"UZ",
    "gn:dem":391,
    "gn:feature_class":"P",
    "gn:feature_code":"PPL",
    "gn:name":"Qo\u2018rg\u2018onobod",
    "gn:population":0,
    "gn:timezone":"Asia/Tashkent",
    "iso:country":"UZ",
    "name:und_x_variant":[
        "Kurganabad"
    ],
    "name:uzb_x_preferred":[
        "Qo\u2018rg\u2018onobod"
    ],
    "wof:name":"Qo`rg`onobod",
    "wof:placetype":"locality"
},
  "geometry": {"coordinates":[71.20723000000002,40.60236],"type":"Point"}
}