{
  "type": "Feature",
  "properties": {
    "gn:admin1_code":"03",
    "gn:asciiname":"Belariq",
    "gn:country_code":"UZ",
    "gn:dem":418,
    "gn:feature_class":"P",
    "gn:feature_code":"PPL",
    "gn:name":"Belariq",
    "gn:population":0,
    "gn:timezone":"Asia/Tashkent",
    "iso:country":"UZ",
    "name:rus_x_preferred":[
        "Bel\u2019aryk"
    ],
    "name:uzb_x_preferred":[
        "Belariq"
    ],
    "wof:name":"Belariq",
    "wof:placetype":"locality"
},
  "geometry": {"coordinates":[71.43682,40.4691],"type":"Point"}
}