{
  "type": "Feature",
  "properties": {
    "gn:admin1_code":"01",
    "gn:asciiname":"Paxtaobod",
    "gn:country_code":"UZ",
    "gn:dem":687,
    "gn:feature_class":"P",
    "gn:feature_code":"PPL",
    "gn:name":"Paxtaobod",
    "gn:population":0,
    "gn:timezone":"Asia/Tashkent",
    "iso:country":"UZ",
    "name:rus_x_preferred":[
        "\u041f\u0430\u0445\u0442\u0430\u0430\u0431\u0430\u0434"
    ],
    "name:und_x_variant":[
        "Pakhtaabad"
    ],
    "name:uzb_x_preferred":[
        "Paxtaobod"
    ],
    "wof:name":"Paxtaobod",
    "wof:placetype":"locality"
},
  "geometry": {"coordinates":[72.55754,40.57804],"type":"Point"}
}