{
  "type": "Feature",
  "properties": {
    "gn:admin1_code":"06",
    "gn:asciiname":"O`zgarish",
    "gn:country_code":"UZ",
    "gn:dem":390,
    "gn:feature_class":"P",
    "gn:feature_code":"PPL",
    "gn:name":"O\u2018zgarish",
    "gn:population":0,
    "gn:timezone":"Asia/Tashkent",
    "iso:country":"UZ",
    "name:eng_x_preferred":[
        "O\u2018zgarish"
    ],
    "wof:name":"O`zgarish",
    "wof:placetype":"locality"
},
  "geometry": {"coordinates":[71.49285999999999,40.83623],"type":"Point"}
}