{
  "type": "Feature",
  "properties": {
    "gn:admin1_code":"02",
    "gn:asciiname":"Bazarchi",
    "gn:country_code":"UZ",
    "gn:dem":260,
    "gn:feature_class":"P",
    "gn:feature_code":"PPL",
    "gn:name":"Bazarchi",
    "gn:population":0,
    "gn:timezone":"Asia/Samarkand",
    "iso:country":"UZ",
    "wof:name":"Bazarchi",
    "wof:placetype":"locality"
},
  "geometry": {"coordinates":[64.95,39.43333],"type":"Point"}
}