{
  "type": "Feature",
  "properties": {
    "gn:admin1_code":"03",
    "gn:asciiname":"Chimyon",
    "gn:country_code":"UZ",
    "gn:dem":684,
    "gn:feature_class":"P",
    "gn:feature_code":"PPL",
    "gn:name":"Chimyon",
    "gn:population":0,
    "gn:timezone":"Asia/Tashkent",
    "iso:country":"UZ",
    "name:und_x_variant":[
        "Chimion",
        "Chimyon"
    ],
    "wof:name":"Chimyon",
    "wof:placetype":"locality"
},
  "geometry": {"coordinates":[71.55804000000001,40.24502],"type":"Point"}
}