{
  "type": "Feature",
  "properties": {
    "gn:admin1_code":"12",
    "gn:asciiname":"Qizil Qishloq",
    "gn:country_code":"UZ",
    "gn:dem":558,
    "gn:feature_class":"P",
    "gn:feature_code":"PPL",
    "gn:name":"Qizil Qishloq",
    "gn:population":0,
    "gn:timezone":"Asia/Samarkand",
    "iso:country":"UZ",
    "name:uzb_x_preferred":[
        "Qizil Qishloq"
    ],
    "wof:name":"Qizil Qishloq",
    "wof:placetype":"locality"
},
  "geometry": {"coordinates":[68.078,38.35614],"type":"Point"}
}