{
  "type": "Feature",
  "properties": {
    "gn:admin1_code":"14",
    "gn:asciiname":"Changi",
    "gn:cc2":"UZ",
    "gn:country_code":"UZ",
    "gn:dem":955,
    "gn:feature_class":"P",
    "gn:feature_code":"PPL",
    "gn:name":"Changi",
    "gn:population":0,
    "gn:timezone":"Asia/Tashkent",
    "iso:country":"UZ",
    "name:und_x_variant":[
        "Changir",
        "Changi"
    ],
    "wof:name":"Changi",
    "wof:placetype":"locality"
},
  "geometry": {"coordinates":[69.73971999999999,41.30806],"type":"Point"}
}