{
  "type": "Feature",
  "properties": {
    "gn:admin1_code":"00",
    "gn:asciiname":"Dukchigi",
    "gn:country_code":"UZ",
    "gn:dem":736,
    "gn:feature_class":"P",
    "gn:feature_code":"PPL",
    "gn:name":"Dukchigi",
    "gn:population":0,
    "gn:timezone":"Asia/Samarkand",
    "iso:country":"UZ",
    "wof:name":"Dukchigi",
    "wof:placetype":"locality"
},
  "geometry": {"coordinates":[66.95,39.63333],"type":"Point"}
}