{
  "type": "Feature",
  "properties": {
    "gn:admin1_code":"00",
    "gn:asciiname":"Kok",
    "gn:cc2":"UZ",
    "gn:country_code":"UZ",
    "gn:dem":544,
    "gn:feature_class":"P",
    "gn:feature_code":"PPL",
    "gn:name":"Kok",
    "gn:population":0,
    "gn:timezone":"Asia/Samarkand",
    "iso:country":"UZ",
    "name:ceb_x_preferred":[
        "Kok"
    ],
    "name:ces_x_preferred":[
        "Kok"
    ],
    "name:dan_x_preferred":[
        "Kok"
    ],
    "name:fin_x_preferred":[
        "Kok"
    ],
    "name:fry_x_preferred":[
        "Kok"
    ],
    "name:nld_x_preferred":[
        "Kok"
    ],
    "name:pol_x_preferred":[
        "Kok"
    ],
    "name:slk_x_preferred":[
        "Kok"
    ],
    "name:swe_x_preferred":[
        "Kok"
    ],
    "name:und_x_variant":[
        "Kuk"
    ],
    "wof:name":"Kok",
    "wof:placetype":"locality"
},
  "geometry": {"coordinates":[66.31667,40.08333],"type":"Point"}
}