{
  "type": "Feature",
  "properties": {
    "gn:admin1_code":"06",
    "gn:asciiname":"Qaznoq",
    "gn:country_code":"UZ",
    "gn:dem":372,
    "gn:feature_class":"P",
    "gn:feature_code":"PPL",
    "gn:name":"Qaznoq",
    "gn:population":0,
    "gn:timezone":"Asia/Tashkent",
    "iso:country":"UZ",
    "name:eng_x_preferred":[
        "Qaznoq"
    ],
    "wof:name":"Qaznoq",
    "wof:placetype":"locality"
},
  "geometry": {"coordinates":[71.01468,40.79093],"type":"Point"}
}