{
  "type": "Feature",
  "properties": {
    "gn:admin1_code":"08",
    "gn:asciiname":"Kaany",
    "gn:country_code":"UZ",
    "gn:dem":877,
    "gn:feature_class":"P",
    "gn:feature_code":"PPL",
    "gn:name":"Kaany",
    "gn:population":0,
    "gn:timezone":"Asia/Samarkand",
    "iso:country":"UZ",
    "wof:name":"Kaany",
    "wof:placetype":"locality"
},
  "geometry": {"coordinates":[67.06667,39.03333],"type":"Point"}
}