{
  "type": "Feature",
  "properties": {
    "gn:admin1_code":"03",
    "gn:asciiname":"Sho`r",
    "gn:country_code":"UZ",
    "gn:dem":435,
    "gn:feature_class":"P",
    "gn:feature_code":"PPL",
    "gn:name":"Sho\u2018r",
    "gn:population":0,
    "gn:timezone":"Asia/Tashkent",
    "iso:country":"UZ",
    "name:uzb_x_preferred":[
        "Sho\u2018r"
    ],
    "wof:name":"Sho`r",
    "wof:placetype":"locality"
},
  "geometry": {"coordinates":[70.76519,40.37242],"type":"Point"}
}