{
  "type": "Feature",
  "properties": {
    "gn:admin1_code":"06",
    "gn:asciiname":"Qiziltepa",
    "gn:country_code":"UZ",
    "gn:dem":743,
    "gn:feature_class":"P",
    "gn:feature_code":"PPL",
    "gn:name":"Qiziltepa",
    "gn:population":0,
    "gn:timezone":"Asia/Tashkent",
    "iso:country":"UZ",
    "name:azb_x_preferred":[
        "\u0642\u06cc\u0632\u06cc\u0644\u200c\u062a\u067e\u0647"
    ],
    "name:ceb_x_preferred":[
        "Qiziltepa"
    ],
    "name:eng_x_preferred":[
        "Qiziltepa"
    ],
    "name:hsb_x_preferred":[
        "Qiziltepa"
    ],
    "name:ita_x_preferred":[
        "Qiziltepa"
    ],
    "name:jpn_x_preferred":[
        "\u30ad\u30ba\u30a3\u30eb\u30c6\u30d1"
    ],
    "name:kik_x_preferred":[
        "Qiziltepa"
    ],
    "name:pol_x_preferred":[
        "Qiziltepa"
    ],
    "name:rus_x_preferred":[
        "\u041a\u044b\u0437\u044b\u043b\u0442\u0435\u043f\u0430"
    ],
    "name:spa_x_preferred":[
        "Qiziltepa"
    ],
    "name:tat_x_preferred":[
        "\u041a\u044b\u0437\u044b\u043b\u0442\u04af\u0431\u04d9"
    ],
    "name:tur_x_preferred":[
        "K\u0131z\u0131ltepe"
    ],
    "name:ukr_x_preferred":[
        "\u041a\u0438\u0437\u0438\u043b\u0442\u0435\u043f\u0430"
    ],
    "name:urd_x_preferred":[
        "\u0642\u06cc\u0632\u06cc\u0644 \u062a\u067e\u06c1"
    ],
    "name:uzb_x_preferred":[
        "Qiziltepa"
    ],
    "wof:name":"Qiziltepa",
    "wof:placetype":"locality"
},
  "geometry": {"coordinates":[71.30515,41.05764],"type":"Point"}
}