{
  "type": "Feature",
  "properties": {
    "gn:admin1_code":"06",
    "gn:asciiname":"Qiziltepa",
    "gn:country_code":"UZ",
    "gn:dem":743,
    "gn:feature_class":"P",
    "gn:feature_code":"PPL",
    "gn:name":"Qiziltepa",
    "gn:population":0,
    "gn:timezone":"Asia/Tashkent",
    "iso:country":"UZ",
    "name:eng_x_preferred":[
        "Qiziltepa"
    ],
    "wof:name":"Qiziltepa",
    "wof:placetype":"locality"
},
  "geometry": {"coordinates":[71.30515,41.05764],"type":"Point"}
}