{
  "type": "Feature",
  "properties": {
    "gn:admin1_code":"08",
    "gn:asciiname":"Gallabuloq",
    "gn:country_code":"UZ",
    "gn:dem":1107,
    "gn:feature_class":"P",
    "gn:feature_code":"PPL",
    "gn:name":"Gallabuloq",
    "gn:population":0,
    "gn:timezone":"Asia/Samarkand",
    "iso:country":"UZ",
    "name:und_x_variant":[
        "Galla"
    ],
    "name:uzb_x_preferred":[
        "Galabuloq"
    ],
    "wof:name":"Gallabuloq",
    "wof:placetype":"locality"
},
  "geometry": {"coordinates":[66.45856999999999,38.18335],"type":"Point"}
}