{
  "type": "Feature",
  "properties": {
    "gn:admin1_code":"07",
    "gn:asciiname":"Boltasovdir",
    "gn:country_code":"UZ",
    "gn:dem":261,
    "gn:feature_class":"P",
    "gn:feature_code":"PPL",
    "gn:name":"Boltasovdir",
    "gn:population":0,
    "gn:timezone":"Asia/Samarkand",
    "iso:country":"UZ",
    "name:und_x_variant":[
        "Baltasaudyr",
        "Boltasowdir",
        "Boltasovdir"
    ],
    "wof:name":"Boltasovdir",
    "wof:placetype":"locality"
},
  "geometry": {"coordinates":[66.18172,40.84972],"type":"Point"}
}