{
  "type": "Feature",
  "properties": {
    "gn:admin1_code":"08",
    "gn:asciiname":"Yangiobod",
    "gn:country_code":"UZ",
    "gn:dem":500,
    "gn:feature_class":"P",
    "gn:feature_code":"PPL",
    "gn:name":"Yangiobod",
    "gn:population":0,
    "gn:timezone":"Asia/Samarkand",
    "iso:country":"UZ",
    "wof:name":"Yangiobod",
    "wof:placetype":"locality"
},
  "geometry": {"coordinates":[66.3395,38.67058],"type":"Point"}
}