{
  "type": "Feature",
  "properties": {
    "gn:admin1_code":"14",
    "gn:asciiname":"O`rtabo`z",
    "gn:country_code":"UZ",
    "gn:dem":283,
    "gn:feature_class":"P",
    "gn:feature_code":"PPL",
    "gn:name":"O\u2018rtabo\u2018z",
    "gn:population":0,
    "gn:timezone":"Asia/Tashkent",
    "iso:country":"UZ",
    "name:uzb_x_preferred":[
        "O\u2018rtabo\u2018z"
    ],
    "wof:name":"O`rtabo`z",
    "wof:placetype":"locality"
},
  "geometry": {"coordinates":[69.1065,40.35998],"type":"Point"}
}