{
  "type": "Feature",
  "properties": {
    "gn:admin1_code":"03",
    "gn:asciiname":"Valik",
    "gn:country_code":"UZ",
    "gn:dem":671,
    "gn:feature_class":"P",
    "gn:feature_code":"PPL",
    "gn:name":"Valik",
    "gn:population":0,
    "gn:timezone":"Asia/Tashkent",
    "iso:country":"UZ",
    "name:fas_x_preferred":[
        "\u0648\u0644\u06cc\u06a9"
    ],
    "name:mzn_x_preferred":[
        "\u0648\u0644\u06cc\u06a9"
    ],
    "name:und_x_variant":[
        "Ualik",
        "Valik",
        "Pastki-Valik"
    ],
    "wof:name":"Valik",
    "wof:placetype":"locality"
},
  "geometry": {"coordinates":[71.99593,40.37769],"type":"Point"}
}