{
  "type": "Feature",
  "properties": {
    "gn:admin1_code":"16",
    "gn:asciiname":"Navqiron",
    "gn:country_code":"UZ",
    "gn:dem":271,
    "gn:feature_class":"P",
    "gn:feature_code":"PPL",
    "gn:name":"Navqiron",
    "gn:population":0,
    "gn:timezone":"Asia/Tashkent",
    "iso:country":"UZ",
    "name:uzb_x_preferred":[
        "Navqiron"
    ],
    "wof:name":"Navqiron",
    "wof:placetype":"locality"
},
  "geometry": {"coordinates":[68.96810000000001,40.62234],"type":"Point"}
}