{
  "type": "Feature",
  "properties": {
    "gn:admin1_code":"03",
    "gn:asciiname":"Chinor",
    "gn:country_code":"UZ",
    "gn:dem":435,
    "gn:feature_class":"P",
    "gn:feature_code":"PPL",
    "gn:name":"Chinor",
    "gn:population":0,
    "gn:timezone":"Asia/Tashkent",
    "iso:country":"UZ",
    "name:fas_x_preferred":[
        "\u0686\u0646\u0627\u0631"
    ],
    "name:msa_x_preferred":[
        "Chinor"
    ],
    "name:tgk_x_preferred":[
        "\u0427\u0438\u043d\u043e\u0440"
    ],
    "name:urd_x_preferred":[
        "\u0686\u0646\u0627\u0631"
    ],
    "name:uzb_x_preferred":[
        "Chinor"
    ],
    "wof:name":"Chinor",
    "wof:placetype":"locality"
},
  "geometry": {"coordinates":[70.85773,40.45227],"type":"Point"}
}