{
  "type": "Feature",
  "properties": {
    "gn:admin1_code":"09",
    "gn:asciiname":"Dovqora",
    "gn:country_code":"UZ",
    "gn:dem":54,
    "gn:feature_class":"P",
    "gn:feature_code":"PPL",
    "gn:name":"Dovqora",
    "gn:population":0,
    "gn:timezone":"Asia/Samarkand",
    "iso:country":"UZ",
    "name:und_x_variant":[
        "Urkendy",
        "Daukara",
        "Dovqora"
    ],
    "wof:name":"Dovqora",
    "wof:placetype":"locality"
},
  "geometry": {"coordinates":[60.36811,43.1418],"type":"Point"}
}