{
  "type": "Feature",
  "properties": {
    "gn:admin1_code":"06",
    "gn:asciiname":"Kemaboshi",
    "gn:country_code":"UZ",
    "gn:dem":425,
    "gn:feature_class":"P",
    "gn:feature_code":"PPL",
    "gn:name":"Kemaboshi",
    "gn:population":0,
    "gn:timezone":"Asia/Tashkent",
    "iso:country":"UZ",
    "name:eng_x_preferred":[
        "Kemaboshi"
    ],
    "name:kir_x_preferred":[
        "Kemaboshi"
    ],
    "name:und_x_variant":[
        "Kamabashi"
    ],
    "wof:name":"Kemaboshi",
    "wof:placetype":"locality"
},
  "geometry": {"coordinates":[71.97799000000001,40.90343],"type":"Point"}
}