{
  "type": "Feature",
  "properties": {
    "gn:admin1_code":"09",
    "gn:asciiname":"To`rtgul",
    "gn:country_code":"UZ",
    "gn:dem":101,
    "gn:feature_class":"P",
    "gn:feature_code":"PPL",
    "gn:name":"To\u2018rtgul",
    "gn:population":0,
    "gn:timezone":"Asia/Samarkand",
    "iso:country":"UZ",
    "name:uzb_x_preferred":[
        "To\u2018rtgul"
    ],
    "wof:name":"To`rtgul",
    "wof:placetype":"locality"
},
  "geometry": {"coordinates":[61.10949,41.58326],"type":"Point"}
}