{
  "type": "Feature",
  "properties": {
    "gn:admin1_code":"01",
    "gn:asciiname":"Maslahat",
    "gn:country_code":"UZ",
    "gn:dem":452,
    "gn:feature_class":"P",
    "gn:feature_code":"PPL",
    "gn:name":"Maslahat",
    "gn:population":0,
    "gn:timezone":"Asia/Tashkent",
    "iso:country":"UZ",
    "name:uzb_x_preferred":[
        "Maslahat"
    ],
    "wof:name":"Maslahat",
    "wof:placetype":"locality"
},
  "geometry": {"coordinates":[72.23345999999999,40.81314],"type":"Point"}
}