{
  "type": "Feature",
  "properties": {
    "gn:admin1_code":"03",
    "gn:asciiname":"Qirqlar",
    "gn:country_code":"UZ",
    "gn:dem":393,
    "gn:feature_class":"P",
    "gn:feature_code":"PPL",
    "gn:name":"Qirqlar",
    "gn:population":0,
    "gn:timezone":"Asia/Tashkent",
    "iso:country":"UZ",
    "name:uzb_x_preferred":[
        "Qirqlar"
    ],
    "wof:name":"Qirqlar",
    "wof:placetype":"locality"
},
  "geometry": {"coordinates":[70.87414,40.57223],"type":"Point"}
}