{
  "type": "Feature",
  "properties": {
    "gn:admin1_code":"08",
    "gn:asciiname":"Yangikent",
    "gn:country_code":"UZ",
    "gn:dem":439,
    "gn:feature_class":"P",
    "gn:feature_code":"PPL",
    "gn:name":"Yangikent",
    "gn:population":0,
    "gn:timezone":"Asia/Samarkand",
    "iso:country":"UZ",
    "wof:name":"Yangikent",
    "wof:placetype":"locality"
},
  "geometry": {"coordinates":[66.06052,38.70265],"type":"Point"}
}