{
  "type": "Feature",
  "properties": {
    "gn:admin1_code":"09",
    "gn:asciiname":"Chimboy Shahri",
    "gn:country_code":"UZ",
    "gn:dem":65,
    "gn:feature_class":"P",
    "gn:feature_code":"PPLA2",
    "gn:name":"Chimboy Shahri",
    "gn:population":0,
    "gn:timezone":"Asia/Samarkand",
    "iso:country":"UZ",
    "name:und_x_variant":[
        "Gorod Chimbay",
        "Chimboy Shahri"
    ],
    "wof:name":"Chimboy Shahri",
    "wof:placetype":"locality"
},
  "geometry": {"coordinates":[59.78199,42.92952],"type":"Point"}
}