{
  "type": "Feature",
  "properties": {
    "gn:admin1_code":"00",
    "gn:asciiname":"Karakalpak",
    "gn:country_code":"UZ",
    "gn:dem":762,
    "gn:feature_class":"P",
    "gn:feature_code":"PPL",
    "gn:name":"Karakalpak",
    "gn:population":0,
    "gn:timezone":"Asia/Samarkand",
    "iso:country":"UZ",
    "wof:name":"Karakalpak",
    "wof:placetype":"locality"
},
  "geometry": {"coordinates":[67.33333,39.78333],"type":"Point"}
}