{
  "type": "Feature",
  "properties": {
    "gn:admin1_code":"12",
    "gn:asciiname":"Manguzar",
    "gn:country_code":"UZ",
    "gn:dem":310,
    "gn:feature_class":"P",
    "gn:feature_code":"PPL",
    "gn:name":"Manguzar",
    "gn:population":0,
    "gn:timezone":"Asia/Samarkand",
    "iso:country":"UZ",
    "name:rus_x_preferred":[
        "\u041c\u0430\u043d\u0433\u0443\u0437\u0430\u0440"
    ],
    "name:uzb_x_preferred":[
        "Manguzar"
    ],
    "wof:name":"Manguzar",
    "wof:placetype":"locality"
},
  "geometry": {"coordinates":[67.322,37.2523],"type":"Point"}
}