{
  "type": "Feature",
  "properties": {
    "gn:admin1_code":"03",
    "gn:asciiname":"Xo`jaxasan",
    "gn:country_code":"UZ",
    "gn:dem":473,
    "gn:feature_class":"P",
    "gn:feature_code":"PPL",
    "gn:name":"Xo\u2018jaxasan",
    "gn:population":0,
    "gn:timezone":"Asia/Tashkent",
    "iso:country":"UZ",
    "name:rus_x_preferred":[
        "\u041f\u0430\u0441\u0442\u043a\u0438 \u0425\u043e\u0434\u0436\u0430\u0445\u0430\u0441\u0430\u043d"
    ],
    "name:und_x_variant":[
        "Pastki Khodzhakhasan",
        "Khodzya-Kasan"
    ],
    "name:uzb_x_preferred":[
        "Xo\u2018jaxasan"
    ],
    "wof:name":"Xo`jaxasan",
    "wof:placetype":"locality"
},
  "geometry": {"coordinates":[72.05225,40.56372],"type":"Point"}
}