{
  "type": "Feature",
  "properties": {
    "gn:admin1_code":"06",
    "gn:asciiname":"Ziyokor",
    "gn:country_code":"UZ",
    "gn:dem":467,
    "gn:feature_class":"P",
    "gn:feature_code":"PPL",
    "gn:name":"Ziyokor",
    "gn:population":0,
    "gn:timezone":"Asia/Tashkent",
    "iso:country":"UZ",
    "name:eng_x_preferred":[
        "Ziyokor"
    ],
    "name:kir_x_preferred":[
        "Ziyokor"
    ],
    "name:und_x_variant":[
        "Ziyakar"
    ],
    "wof:name":"Ziyokor",
    "wof:placetype":"locality"
},
  "geometry": {"coordinates":[72.00423000000001,41.07588],"type":"Point"}
}