{
  "type": "Feature",
  "properties": {
    "gn:admin1_code":"08",
    "gn:asciiname":"Sariq",
    "gn:country_code":"UZ",
    "gn:dem":294,
    "gn:feature_class":"P",
    "gn:feature_code":"PPL",
    "gn:name":"Sariq",
    "gn:population":0,
    "gn:timezone":"Asia/Samarkand",
    "iso:country":"UZ",
    "name:und_x_variant":[
        "Saarak",
        "Saryk",
        "Sariq"
    ],
    "wof:name":"Sariq",
    "wof:placetype":"locality"
},
  "geometry": {"coordinates":[65.16582,39.21242],"type":"Point"}
}