{
  "type": "Feature",
  "properties": {
    "gn:admin1_code":"08",
    "gn:asciiname":"Sariq",
    "gn:country_code":"UZ",
    "gn:dem":294,
    "gn:feature_class":"P",
    "gn:feature_code":"PPL",
    "gn:name":"Sariq",
    "gn:population":0,
    "gn:timezone":"Asia/Samarkand",
    "iso:country":"UZ",
    "name:azb_x_preferred":[
        "\u0633\u0627\u0631\u06cc\u0642"
    ],
    "name:kik_x_preferred":[
        "Sariq"
    ],
    "name:rus_x_preferred":[
        "\u0421\u0430\u0440\u044b\u0445"
    ],
    "name:tur_x_preferred":[
        "Sar\u0131"
    ],
    "name:und_x_variant":[
        "Saarak",
        "Saryk"
    ],
    "name:urd_x_preferred":[
        "\u0633\u0627\u0631\u06cc\u0642"
    ],
    "name:uzb_x_preferred":[
        "Sariq"
    ],
    "wof:name":"Sariq",
    "wof:placetype":"locality"
},
  "geometry": {"coordinates":[65.16582,39.21242],"type":"Point"}
}