{
  "type": "Feature",
  "properties": {
    "gn:admin1_code":"03",
    "gn:asciiname":"Yangi",
    "gn:country_code":"UZ",
    "gn:dem":408,
    "gn:feature_class":"P",
    "gn:feature_code":"PPL",
    "gn:name":"Yangi",
    "gn:population":0,
    "gn:timezone":"Asia/Tashkent",
    "iso:country":"UZ",
    "name:ara_x_preferred":[
        "\u064a\u0627\u0646\u063a\u064a"
    ],
    "name:cat_x_preferred":[
        "Yangi"
    ],
    "name:fin_x_preferred":[
        "Yangi"
    ],
    "name:ind_x_preferred":[
        "Yangi"
    ],
    "wof:name":"Yangi",
    "wof:placetype":"locality"
},
  "geometry": {"coordinates":[70.71666999999999,40.38333],"type":"Point"}
}