{
  "type": "Feature",
  "properties": {
    "gn:admin1_code":"01",
    "gn:asciiname":"Kalinin",
    "gn:country_code":"UZ",
    "gn:dem":676,
    "gn:feature_class":"P",
    "gn:feature_code":"PPL",
    "gn:name":"Kalinin",
    "gn:population":0,
    "gn:timezone":"Asia/Tashkent",
    "iso:country":"UZ",
    "name:bel_x_preferred":[
        "\u041a\u0430\u043b\u0456\u043d\u0456\u043d"
    ],
    "name:ceb_x_preferred":[
        "Kalinin"
    ],
    "name:deu_x_preferred":[
        "Kalinin"
    ],
    "name:est_x_preferred":[
        "Kalinin"
    ],
    "name:fas_x_preferred":[
        "\u06a9\u0627\u0644\u06cc\u0646\u06cc\u0646"
    ],
    "name:fin_x_preferred":[
        "Kalinin"
    ],
    "name:hye_x_preferred":[
        "\u053f\u0561\u056c\u056b\u0576\u056b\u0576"
    ],
    "name:ita_x_preferred":[
        "Kalinin"
    ],
    "name:jpn_x_preferred":[
        "\u30ab\u30ea\u30fc\u30cb\u30f3"
    ],
    "name:kir_x_preferred":[
        "\u041a\u0430\u043b\u0438\u043d\u0438\u043d"
    ],
    "name:lit_x_preferred":[
        "Kalininas"
    ],
    "name:nld_x_preferred":[
        "Kalinin"
    ],
    "name:pol_x_preferred":[
        "Kalinin"
    ],
    "name:por_x_preferred":[
        "Kalinin"
    ],
    "name:ron_x_preferred":[
        "Kalinin"
    ],
    "name:rus_x_preferred":[
        "\u041a\u0430\u043b\u0438\u043d\u0438\u043d"
    ],
    "name:slk_x_preferred":[
        "Kalinin"
    ],
    "name:slv_x_preferred":[
        "Kalinin"
    ],
    "name:spa_x_preferred":[
        "Kalinin"
    ],
    "name:swe_x_preferred":[
        "Kalinin"
    ],
    "name:ukr_x_preferred":[
        "\u041a\u0430\u043b\u0456\u043d\u0456\u043d"
    ],
    "name:zho_x_preferred":[
        "\u52a0\u91cc\u5b81"
    ],
    "wof:name":"Kalinin",
    "wof:placetype":"locality"
},
  "geometry": {"coordinates":[72.81978000000002,40.79552],"type":"Point"}
}