{
  "type": "Feature",
  "properties": {
    "gn:admin1_code":"07",
    "gn:asciiname":"Debaland",
    "gn:country_code":"UZ",
    "gn:dem":549,
    "gn:feature_class":"P",
    "gn:feature_code":"PPL",
    "gn:name":"Debaland",
    "gn:population":0,
    "gn:timezone":"Asia/Samarkand",
    "iso:country":"UZ",
    "name:und_x_variant":[
        "Degay-Balyand",
        "Degan-Balyand",
        "Di-Balyand",
        "Dekhibalyand",
        "Debaland"
    ],
    "wof:name":"Debaland",
    "wof:placetype":"locality"
},
  "geometry": {"coordinates":[65.56792,40.50805],"type":"Point"}
}