{
  "type": "Feature",
  "properties": {
    "gn:admin1_code":"00",
    "gn:asciiname":"Donkara",
    "gn:country_code":"UZ",
    "gn:dem":480,
    "gn:feature_class":"P",
    "gn:feature_code":"PPL",
    "gn:name":"Donkara",
    "gn:population":0,
    "gn:timezone":"Asia/Samarkand",
    "iso:country":"UZ",
    "wof:name":"Donkara",
    "wof:placetype":"locality"
},
  "geometry": {"coordinates":[66.34999999999999,39.98333],"type":"Point"}
}