{
  "type": "Feature",
  "properties": {
    "gn:admin1_code":"07",
    "gn:asciiname":"Kulankok",
    "gn:country_code":"UZ",
    "gn:dem":183,
    "gn:feature_class":"P",
    "gn:feature_code":"PPL",
    "gn:name":"Kulankok",
    "gn:population":0,
    "gn:timezone":"Asia/Samarkand",
    "iso:country":"UZ",
    "name:und_x_variant":[
        "Kolodtsy Kulan-Kak",
        "Kulak-Kak",
        "Kulankok"
    ],
    "wof:name":"Kulankok",
    "wof:placetype":"locality"
},
  "geometry": {"coordinates":[62.96073000000001,41.19563],"type":"Point"}
}