{
  "type": "Feature",
  "properties": {
    "gn:admin1_code":"10",
    "gn:asciiname":"Kutan-Tyube",
    "gn:country_code":"UZ",
    "gn:dem":829,
    "gn:feature_class":"P",
    "gn:feature_code":"PPL",
    "gn:name":"Kutan-Tyube",
    "gn:population":0,
    "gn:timezone":"Asia/Samarkand",
    "iso:country":"UZ",
    "wof:name":"Kutan-Tyube",
    "wof:placetype":"locality"
},
  "geometry": {"coordinates":[67.05972,39.49333],"type":"Point"}
}