{
  "type": "Feature",
  "properties": {
    "gn:admin1_code":"14",
    "gn:asciiname":"Kerayit",
    "gn:country_code":"UZ",
    "gn:dem":313,
    "gn:feature_class":"P",
    "gn:feature_code":"PPL",
    "gn:name":"Kerayit",
    "gn:population":0,
    "gn:timezone":"Asia/Tashkent",
    "iso:country":"UZ",
    "name:uzb_x_preferred":[
        "Kerayit"
    ],
    "wof:name":"Kerayit",
    "wof:placetype":"locality"
},
  "geometry": {"coordinates":[69.06256999999999,40.86489],"type":"Point"}
}