{
  "type": "Feature",
  "properties": {
    "gn:admin1_code":"01",
    "gn:asciiname":"Guliston",
    "gn:country_code":"UZ",
    "gn:dem":446,
    "gn:feature_class":"P",
    "gn:feature_code":"PPL",
    "gn:name":"Guliston",
    "gn:population":0,
    "gn:timezone":"Asia/Tashkent",
    "iso:country":"UZ",
    "name:rus_x_preferred":[
        "\u0413\u0443\u043b\u0438\u0441\u0442\u0430\u043d"
    ],
    "name:und_x_variant":[
        "Gulistan"
    ],
    "name:uzb_x_preferred":[
        "Guliston"
    ],
    "wof:name":"Guliston",
    "wof:placetype":"locality"
},
  "geometry": {"coordinates":[72.12885,40.77686],"type":"Point"}
}