{
  "type": "Feature",
  "properties": {
    "gn:admin1_code":"10",
    "gn:asciiname":"Gulobod",
    "gn:cc2":"UZ",
    "gn:country_code":"UZ",
    "gn:dem":786,
    "gn:feature_class":"P",
    "gn:feature_code":"PPL",
    "gn:name":"Gulobod",
    "gn:population":0,
    "gn:timezone":"Asia/Samarkand",
    "iso:country":"UZ",
    "name:und_x_variant":[
        "Yangiaryk Pervyy",
        "Gul\u2019abad",
        "Gulobod"
    ],
    "wof:name":"Gulobod",
    "wof:placetype":"locality"
},
  "geometry": {"coordinates":[66.92028000000001,39.57833],"type":"Point"}
}