{
  "type": "Feature",
  "properties": {
    "gn:admin1_code":"09",
    "gn:asciiname":"Bo`stanliq",
    "gn:country_code":"UZ",
    "gn:dem":57,
    "gn:feature_class":"P",
    "gn:feature_code":"PPL",
    "gn:name":"Bo\u2018stanliq",
    "gn:population":0,
    "gn:timezone":"Asia/Samarkand",
    "iso:country":"UZ",
    "name:uzb_x_preferred":[
        "Bo\u2018stanliq"
    ],
    "wof:name":"Bo`stanliq",
    "wof:placetype":"locality"
},
  "geometry": {"coordinates":[58.76606,43.01775],"type":"Point"}
}