{
  "type": "Feature",
  "properties": {
    "gn:admin1_code":"01",
    "gn:asciiname":"Xoldevonbek",
    "gn:country_code":"UZ",
    "gn:dem":443,
    "gn:feature_class":"P",
    "gn:feature_code":"PPL",
    "gn:name":"Xoldevonbek",
    "gn:population":0,
    "gn:timezone":"Asia/Tashkent",
    "iso:country":"UZ",
    "name:und_x_variant":[
        "Khaldyvanbek"
    ],
    "name:uzb_x_preferred":[
        "Holdevonbek"
    ],
    "name:uzb_x_variant":[
        "Xoldevonbek"
    ],
    "wof:name":"Xoldevonbek",
    "wof:placetype":"locality"
},
  "geometry": {"coordinates":[71.98980999999998,40.67064],"type":"Point"}
}