{
  "type": "Feature",
  "properties": {
    "gn:admin1_code":"12",
    "gn:asciiname":"Xo`jamulki",
    "gn:country_code":"UZ",
    "gn:dem":423,
    "gn:feature_class":"P",
    "gn:feature_code":"PPL",
    "gn:name":"Xo\u2018jamulki",
    "gn:population":0,
    "gn:timezone":"Asia/Samarkand",
    "iso:country":"UZ",
    "name:und_x_variant":[
        "Khoja-Mil\u2019ki",
        "Khodzha-Mil\u2019ki"
    ],
    "name:uzb_x_preferred":[
        "Xo\u2018jamulki"
    ],
    "wof:name":"Xo`jamulki",
    "wof:placetype":"locality"
},
  "geometry": {"coordinates":[67.72235000000001,37.90926],"type":"Point"}
}