{
  "type": "Feature",
  "properties": {
    "gn:admin1_code":"14",
    "gn:asciiname":"Paxtaobod",
    "gn:country_code":"UZ",
    "gn:dem":281,
    "gn:feature_class":"P",
    "gn:feature_code":"PPL",
    "gn:name":"Paxtaobod",
    "gn:population":0,
    "gn:timezone":"Asia/Tashkent",
    "iso:country":"UZ",
    "name:uzb_x_preferred":[
        "Paxtaobod"
    ],
    "wof:name":"Paxtaobod",
    "wof:placetype":"locality"
},
  "geometry": {"coordinates":[68.96236,40.86097],"type":"Point"}
}