{
  "type": "Feature",
  "properties": {
    "gn:admin1_code":"12",
    "gn:asciiname":"Pyatiletka",
    "gn:country_code":"UZ",
    "gn:dem":421,
    "gn:feature_class":"P",
    "gn:feature_code":"PPL",
    "gn:name":"Pyatiletka",
    "gn:population":0,
    "gn:timezone":"Asia/Samarkand",
    "iso:country":"UZ",
    "wof:name":"Pyatiletka",
    "wof:placetype":"locality"
},
  "geometry": {"coordinates":[67.80556,37.94028],"type":"Point"}
}