{
  "type": "Feature",
  "properties": {
    "gn:admin1_code":"12",
    "gn:asciiname":"Kampirtepa",
    "gn:country_code":"UZ",
    "gn:dem":1214,
    "gn:feature_class":"P",
    "gn:feature_code":"PPL",
    "gn:name":"Kampirtepa",
    "gn:population":0,
    "gn:timezone":"Asia/Samarkand",
    "iso:country":"UZ",
    "name:und_x_variant":[
        "Kempir-Tyube"
    ],
    "name:uzb_x_preferred":[
        "Kampirtepa"
    ],
    "wof:name":"Kampirtepa",
    "wof:placetype":"locality"
},
  "geometry": {"coordinates":[66.68855000000001,37.78416],"type":"Point"}
}