{
  "type": "Feature",
  "properties": {
    "gn:asciiname":"Tayake Vtoroy",
    "gn:country_code":"UZ",
    "gn:dem":675,
    "gn:feature_class":"P",
    "gn:feature_code":"PPL",
    "gn:name":"Tayake Vtoroy",
    "gn:population":0,
    "gn:timezone":"Asia/Bishkek",
    "iso:country":"UZ",
    "name:kir_x_preferred":[
        "\u0422\u0430\u044f\u043a\u0435 \u0412\u0442\u043e\u0440\u043e\u0439"
    ],
    "name:rus_x_preferred":[
        "\u0422\u0430\u044f\u043a\u0435 \u0412\u0442\u043e\u0440\u043e\u0439"
    ],
    "wof:name":"Tayake Vtoroy",
    "wof:placetype":"locality"
},
  "geometry": {"coordinates":[72.55351,40.60195],"type":"Point"}
}