{
  "type": "Feature",
  "properties": {
    "gn:admin1_code":"14",
    "gn:asciiname":"Urtasaroy",
    "gn:country_code":"UZ",
    "gn:dem":423,
    "gn:feature_class":"P",
    "gn:feature_code":"PPL",
    "gn:name":"\u016crtasaroy",
    "gn:population":0,
    "gn:timezone":"Asia/Tashkent",
    "iso:country":"UZ",
    "name:und_x_variant":[
        "Urtasaray",
        "Ortasaray",
        "\u016crtasaroy"
    ],
    "wof:name":"Urtasaroy",
    "wof:placetype":"locality"
},
  "geometry": {"coordinates":[69.41944000000001,41.12694000000001],"type":"Point"}
}