{
  "type": "Feature",
  "properties": {
    "gn:admin1_code":"10",
    "gn:asciiname":"Ukrach",
    "gn:country_code":"UZ",
    "gn:dem":434,
    "gn:feature_class":"P",
    "gn:feature_code":"PPL",
    "gn:name":"Ukrach",
    "gn:population":0,
    "gn:timezone":"Asia/Samarkand",
    "iso:country":"UZ",
    "wof:name":"Ukrach",
    "wof:placetype":"locality"
},
  "geometry": {"coordinates":[65.76805999999999,39.96833],"type":"Point"}
}