{
  "type": "Feature",
  "properties": {
    "gn:admin1_code":"00",
    "gn:asciiname":"Gandum-Tash",
    "gn:country_code":"UZ",
    "gn:dem":340,
    "gn:feature_class":"P",
    "gn:feature_code":"PPL",
    "gn:name":"Gandum-Tash",
    "gn:population":0,
    "gn:timezone":"Asia/Samarkand",
    "iso:country":"UZ",
    "wof:name":"Gandum-Tash",
    "wof:placetype":"locality"
},
  "geometry": {"coordinates":[67.78333000000001,40.15],"type":"Point"}
}