{
  "type": "Feature",
  "properties": {
    "gn:admin1_code":"07",
    "gn:asciiname":"Ashitobelik",
    "gn:country_code":"UZ",
    "gn:dem":148,
    "gn:feature_class":"P",
    "gn:feature_code":"PPL",
    "gn:name":"Ashitobelik",
    "gn:population":0,
    "gn:timezone":"Asia/Samarkand",
    "iso:country":"UZ",
    "wof:name":"Ashitobelik",
    "wof:placetype":"locality"
},
  "geometry": {"coordinates":[63.55,41.71667],"type":"Point"}
}