{
  "type": "Feature",
  "properties": {
    "gn:admin1_code":"08",
    "gn:admin2_code":"Beshkent",
    "gn:asciiname":"Kerait",
    "gn:country_code":"UZ",
    "gn:dem":402,
    "gn:feature_class":"P",
    "gn:feature_code":"PPL",
    "gn:name":"Kerait",
    "gn:population":0,
    "gn:timezone":"Asia/Samarkand",
    "iso:country":"UZ",
    "wof:name":"Kerait",
    "wof:placetype":"locality"
},
  "geometry": {"coordinates":[65.91168,38.88073],"type":"Point"}
}