{
  "type": "Feature",
  "properties": {
    "gn:admin1_code":"14",
    "gn:asciiname":"Niyazbash",
    "gn:cc2":"UZ",
    "gn:country_code":"UZ",
    "gn:dem":355,
    "gn:feature_class":"P",
    "gn:feature_code":"PPL",
    "gn:name":"Niyazbash",
    "gn:population":0,
    "gn:timezone":"Asia/Tashkent",
    "iso:country":"UZ",
    "name:und_x_variant":[
        "Kolkhoz Imeni Lenina",
        "Niyazbashi",
        "Niyazbay",
        "Niyazbash"
    ],
    "wof:name":"Niyazbash",
    "wof:placetype":"locality"
},
  "geometry": {"coordinates":[69.09166999999999,41.10472],"type":"Point"}
}