{
  "type": "Feature",
  "properties": {
    "gn:admin1_code":"01",
    "gn:asciiname":"Shavruq",
    "gn:country_code":"UZ",
    "gn:dem":529,
    "gn:feature_class":"P",
    "gn:feature_code":"PPL",
    "gn:name":"Shavruq",
    "gn:population":0,
    "gn:timezone":"Asia/Tashkent",
    "iso:country":"UZ",
    "name:rus_x_preferred":[
        "\u0428\u0430\u0432\u0440\u0443\u043a"
    ],
    "name:und_x_variant":[
        "Shavruk"
    ],
    "name:uzb_x_preferred":[
        "Shavruq"
    ],
    "wof:name":"Shavruq",
    "wof:placetype":"locality"
},
  "geometry": {"coordinates":[72.53695999999999,40.91673],"type":"Point"}
}