{
  "type": "Feature",
  "properties": {
    "gn:admin1_code":"09",
    "gn:asciiname":"Sarytungul'",
    "gn:country_code":"UZ",
    "gn:dem":70,
    "gn:feature_class":"P",
    "gn:feature_code":"PPL",
    "gn:name":"Sarytungul\u2019",
    "gn:population":0,
    "gn:timezone":"Asia/Samarkand",
    "iso:country":"UZ",
    "name:rus_x_preferred":[
        "Sarytungul\u2019"
    ],
    "wof:name":"Sarytungul'",
    "wof:placetype":"locality"
},
  "geometry": {"coordinates":[59.41667,42.65],"type":"Point"}
}