{
  "type": "Feature",
  "properties": {
    "gn:admin1_code":"00",
    "gn:asciiname":"Guliston",
    "gn:country_code":"UZ",
    "gn:dem":613,
    "gn:feature_class":"P",
    "gn:feature_code":"PPL",
    "gn:name":"Guliston",
    "gn:population":0,
    "gn:timezone":"Asia/Samarkand",
    "iso:country":"UZ",
    "name:und_x_variant":[
        "Gulistan"
    ],
    "name:uzb_x_preferred":[
        "Guliston"
    ],
    "wof:name":"Guliston",
    "wof:placetype":"locality"
},
  "geometry": {"coordinates":[67.04883000000001,37.84222000000001],"type":"Point"}
}