{
  "type": "Feature",
  "properties": {
    "gn:admin1_code":"03",
    "gn:asciiname":"Kurash",
    "gn:country_code":"UZ",
    "gn:dem":586,
    "gn:feature_class":"P",
    "gn:feature_code":"PPL",
    "gn:name":"Kurash",
    "gn:population":0,
    "gn:timezone":"Asia/Tashkent",
    "iso:country":"UZ",
    "name:bak_x_preferred":[
        "\u041a\u04e9\u0440\u04d9\u0448"
    ],
    "name:bul_x_preferred":[
        "\u041a\u0443\u0440\u0430\u0448"
    ],
    "name:ces_x_preferred":[
        "Kura\u0161"
    ],
    "name:dan_x_preferred":[
        "Kurash"
    ],
    "name:ell_x_preferred":[
        "\u039a\u03bf\u03c5\u03c1\u03ac\u03c2"
    ],
    "name:fas_x_preferred":[
        "\u06a9\u0648\u0631\u0627\u0634"
    ],
    "name:fra_x_preferred":[
        "Kourach"
    ],
    "name:ind_x_preferred":[
        "Kurash"
    ],
    "name:ita_x_preferred":[
        "Kurash"
    ],
    "name:jpn_x_preferred":[
        "\u30af\u30e9\u30c3\u30b7\u30e5"
    ],
    "name:kaz_x_preferred":[
        "\u041a\u04af\u0440\u0435\u0441"
    ],
    "name:kir_x_preferred":[
        "\u041a\u04af\u0440\u04e9\u0448"
    ],
    "name:kor_x_preferred":[
        "\ucfe0\ub77c\uc2dc"
    ],
    "name:lit_x_preferred":[
        "Kura\u0161as"
    ],
    "name:rus_x_preferred":[
        "\u041a\u0443\u0440\u0435\u0448"
    ],
    "name:spa_x_preferred":[
        "Kurash"
    ],
    "name:tat_x_preferred":[
        "\u041c\u0438\u043b\u043b\u0438 \u043a\u04e9\u0440\u04d9\u0448"
    ],
    "name:tha_x_preferred":[
        "\u0e04\u0e39\u0e23\u0e32\u0e0a"
    ],
    "name:uig_x_preferred":[
        "\u0643\u06c8\u0631\u06d5\u0634"
    ],
    "name:ukr_x_preferred":[
        "\u041a\u0443\u0440\u0435\u0448"
    ],
    "name:und_x_variant":[
        "Kurgantepa"
    ],
    "name:uzb_x_preferred":[
        "Kurash"
    ],
    "name:zho_x_preferred":[
        "\u514b\u62c9\u8853"
    ],
    "wof:name":"Kurash",
    "wof:placetype":"locality"
},
  "geometry": {"coordinates":[71.43643,40.29071],"type":"Point"}
}