{
  "type": "Feature",
  "properties": {
    "gn:admin1_code":"03",
    "gn:asciiname":"Kurash",
    "gn:country_code":"UZ",
    "gn:dem":586,
    "gn:feature_class":"P",
    "gn:feature_code":"PPL",
    "gn:name":"Kurash",
    "gn:population":0,
    "gn:timezone":"Asia/Tashkent",
    "iso:country":"UZ",
    "name:und_x_variant":[
        "Kurgantepa"
    ],
    "name:uzb_x_preferred":[
        "Kurash"
    ],
    "wof:name":"Kurash",
    "wof:placetype":"locality"
},
  "geometry": {"coordinates":[71.43643,40.29071],"type":"Point"}
}