{
  "type": "Feature",
  "properties": {
    "gn:admin1_code":"07",
    "gn:asciiname":"Kattaich",
    "gn:country_code":"UZ",
    "gn:dem":595,
    "gn:feature_class":"P",
    "gn:feature_code":"PPL",
    "gn:name":"Kattaich",
    "gn:population":0,
    "gn:timezone":"Asia/Samarkand",
    "iso:country":"UZ",
    "name:und_x_variant":[
        "Simbulak",
        "Kattauch",
        "Kattaich"
    ],
    "wof:name":"Kattaich",
    "wof:placetype":"locality"
},
  "geometry": {"coordinates":[66.57694000000001,40.66889000000001],"type":"Point"}
}