{
  "type": "Feature",
  "properties": {
    "gn:admin1_code":"00",
    "gn:asciiname":"Kichkina-Bulak",
    "gn:country_code":"UZ",
    "gn:dem":878,
    "gn:feature_class":"P",
    "gn:feature_code":"PPL",
    "gn:name":"Kichkina-Bulak",
    "gn:population":0,
    "gn:timezone":"Asia/Samarkand",
    "iso:country":"UZ",
    "wof:name":"Kichkina-Bulak",
    "wof:placetype":"locality"
},
  "geometry": {"coordinates":[67.38333,39.93333],"type":"Point"}
}