{
  "type": "Feature",
  "properties": {
    "gn:admin1_code":"10",
    "gn:asciiname":"Qarnob Ikkinchi Bo`lim",
    "gn:country_code":"UZ",
    "gn:dem":468,
    "gn:feature_class":"P",
    "gn:feature_code":"PPL",
    "gn:name":"Qarnob Ikkinchi Bo\u2018lim",
    "gn:population":0,
    "gn:timezone":"Asia/Samarkand",
    "iso:country":"UZ",
    "name:eng_x_preferred":[
        "Qarnob #2 bo\u2018lim"
    ],
    "name:und_x_variant":[
        "Qarnob Ikkinchi Bo\u2018lim"
    ],
    "wof:name":"Qarnob Ikkinchi Bo`lim",
    "wof:placetype":"locality"
},
  "geometry": {"coordinates":[65.89738,39.63204],"type":"Point"}
}