{
  "type": "Feature",
  "properties": {
    "gn:admin1_code":"01",
    "gn:asciiname":"Beshgul",
    "gn:country_code":"UZ",
    "gn:dem":436,
    "gn:feature_class":"P",
    "gn:feature_code":"PPL",
    "gn:name":"Beshgul",
    "gn:population":0,
    "gn:timezone":"Asia/Tashkent",
    "iso:country":"UZ",
    "name:rus_x_preferred":[
        "Beshgul\u2019"
    ],
    "name:uzb_x_preferred":[
        "Beshgul"
    ],
    "wof:name":"Beshgul",
    "wof:placetype":"locality"
},
  "geometry": {"coordinates":[71.92179,40.65071],"type":"Point"}
}