{
  "type": "Feature",
  "properties": {
    "gn:admin1_code":"03",
    "gn:asciiname":"Barzangi",
    "gn:country_code":"UZ",
    "gn:dem":407,
    "gn:feature_class":"P",
    "gn:feature_code":"PPL",
    "gn:name":"Barzangi",
    "gn:population":0,
    "gn:timezone":"Asia/Tashkent",
    "iso:country":"UZ",
    "name:uzb_x_preferred":[
        "Barzangi"
    ],
    "wof:name":"Barzangi",
    "wof:placetype":"locality"
},
  "geometry": {"coordinates":[70.87260000000001,40.52423],"type":"Point"}
}