{
  "type": "Feature",
  "properties": {
    "gn:admin1_code":"08",
    "gn:asciiname":"Ashir-Buka",
    "gn:country_code":"UZ",
    "gn:dem":406,
    "gn:feature_class":"P",
    "gn:feature_code":"PPL",
    "gn:name":"Ashir-Buka",
    "gn:population":0,
    "gn:timezone":"Asia/Samarkand",
    "iso:country":"UZ",
    "wof:name":"Ashir-Buka",
    "wof:placetype":"locality"
},
  "geometry": {"coordinates":[66.05015999999999,39.28273],"type":"Point"}
}