{
  "type": "Feature",
  "properties": {
    "gn:admin1_code":"14",
    "gn:asciiname":"Ruzayevka",
    "gn:country_code":"UZ",
    "gn:dem":497,
    "gn:feature_class":"P",
    "gn:feature_code":"PPL",
    "gn:name":"Ruzayevka",
    "gn:population":0,
    "gn:timezone":"Asia/Tashkent",
    "iso:country":"UZ",
    "name:und_x_variant":[
        "Leninchi"
    ],
    "wof:name":"Ruzayevka",
    "wof:placetype":"locality"
},
  "geometry": {"coordinates":[69.54637,40.92848],"type":"Point"}
}