{
  "type": "Feature",
  "properties": {
    "gn:admin1_code":"14",
    "gn:asciiname":"Ruzayevka",
    "gn:country_code":"UZ",
    "gn:dem":497,
    "gn:feature_class":"P",
    "gn:feature_code":"PPL",
    "gn:name":"Ruzayevka",
    "gn:population":0,
    "gn:timezone":"Asia/Tashkent",
    "iso:country":"UZ",
    "name:ara_x_preferred":[
        "\u0631\u0648\u0632\u0627\u064a\u0627\u0641\u0643\u0627"
    ],
    "name:azb_x_preferred":[
        "\u0631\u0648\u0632\u0627\u06cc\u0641\u06a9\u0627"
    ],
    "name:bel_x_preferred":[
        "\u0420\u0443\u0437\u0430\u0435\u045e\u043a\u0430"
    ],
    "name:bul_x_preferred":[
        "\u0420\u0443\u0437\u0430\u0435\u0432\u043a\u0430"
    ],
    "name:ceb_x_preferred":[
        "Ruzayevka"
    ],
    "name:ces_x_preferred":[
        "Ruzajevka"
    ],
    "name:che_x_preferred":[
        "\u0420\u0443\u0437\u0430\u0435\u0432\u043a\u0430"
    ],
    "name:chv_x_preferred":[
        "\u0420\u0443\u0437\u0430\u0435\u0432\u043a\u0430"
    ],
    "name:deu_x_preferred":[
        "Rusajewka"
    ],
    "name:epo_x_preferred":[
        "Ruzajevka"
    ],
    "name:est_x_preferred":[
        "Ruzajevka"
    ],
    "name:fas_x_preferred":[
        "\u0631\u0648\u0632\u0627\u06cc\u0641\u06a9\u0627"
    ],
    "name:fin_x_preferred":[
        "Ruzajevka"
    ],
    "name:fra_x_preferred":[
        "Rouza\u00efevka"
    ],
    "name:hsb_x_preferred":[
        "Ruzajewka"
    ],
    "name:hun_x_preferred":[
        "Ruzajevka"
    ],
    "name:ita_x_preferred":[
        "Ruzaevka"
    ],
    "name:kom_x_preferred":[
        "\u0420\u0443\u0437\u0430\u0435\u0432\u043a\u0430"
    ],
    "name:lav_x_preferred":[
        "Ruzajevka"
    ],
    "name:lit_x_preferred":[
        "Ruzajevka"
    ],
    "name:mdf_x_preferred":[
        "\u041e\u0440\u043e\u0437\u0430\u0439"
    ],
    "name:myv_x_preferred":[
        "\u041e\u0440\u0430\u0437\u0430\u0439 \u043e\u0448"
    ],
    "name:nld_x_preferred":[
        "Roezajevka"
    ],
    "name:nno_x_preferred":[
        "Ruzajevka"
    ],
    "name:nor_x_preferred":[
        "Ruzajevka"
    ],
    "name:pol_x_preferred":[
        "Ruzajewka"
    ],
    "name:rus_x_preferred":[
        "\u0420\u0443\u0437\u0430\u0435\u0432\u043a\u0430"
    ],
    "name:spa_x_preferred":[
        "Ruz\u00e1yevka"
    ],
    "name:srp_x_preferred":[
        "\u0420\u0443\u0437\u0430\u0458\u0435\u0432\u043a\u0430"
    ],
    "name:tat_x_preferred":[
        "\u0420\u0443\u0437\u0430\u0439"
    ],
    "name:tgk_x_preferred":[
        "\u0420\u0443\u0437\u0430\u0435\u0432\u043a\u0430"
    ],
    "name:tgl_x_preferred":[
        "Ruzayevka"
    ],
    "name:tur_x_preferred":[
        "Ruzayevka"
    ],
    "name:ukr_x_preferred":[
        "\u0420\u0443\u0437\u0430\u0454\u0432\u043a\u0430"
    ],
    "name:und_x_variant":[
        "Leninchi"
    ],
    "name:vep_x_preferred":[
        "Ruzajevk"
    ],
    "name:war_x_preferred":[
        "Ruzayevka"
    ],
    "name:xal_x_preferred":[
        "\u0420\u0443\u0437\u0430\u0435\u0432\u043a\u0430 \u0431\u0430\u043b\u04bb\u0441\u043d"
    ],
    "name:zho_x_preferred":[
        "\u9b6f\u624e\u8036\u592b\u5361"
    ],
    "wof:name":"Ruzayevka",
    "wof:placetype":"locality"
},
  "geometry": {"coordinates":[69.54637,40.92848],"type":"Point"}
}