{
  "type": "Feature",
  "properties": {
    "gn:admin1_code":"08",
    "gn:asciiname":"Kaochin",
    "gn:country_code":"UZ",
    "gn:dem":339,
    "gn:feature_class":"P",
    "gn:feature_code":"PPL",
    "gn:name":"Kaochin",
    "gn:population":0,
    "gn:timezone":"Asia/Samarkand",
    "iso:country":"UZ",
    "name:und_x_variant":[
        "Kauchin"
    ],
    "wof:name":"Kaochin",
    "wof:placetype":"locality"
},
  "geometry": {"coordinates":[65.55965,38.79011],"type":"Point"}
}