{
  "type": "Feature",
  "properties": {
    "gn:admin1_code":"00",
    "gn:asciiname":"Bostan",
    "gn:country_code":"UZ",
    "gn:dem":514,
    "gn:feature_class":"P",
    "gn:feature_code":"PPL",
    "gn:name":"Bostan",
    "gn:population":0,
    "gn:timezone":"Asia/Tashkent",
    "iso:country":"UZ",
    "name:bul_x_preferred":[
        "\u0411\u043e\u0441\u0442\u0430\u043d"
    ],
    "name:ceb_x_preferred":[
        "Bostan"
    ],
    "name:deu_x_preferred":[
        "Bostan"
    ],
    "name:fas_x_preferred":[
        "\u0628\u0633\u062a\u0627\u0646"
    ],
    "name:mkd_x_preferred":[
        "\u0411\u043e\u0441\u0442\u0430\u043d"
    ],
    "name:ron_x_preferred":[
        "Bostan"
    ],
    "name:rus_x_preferred":[
        "\u0411\u043e\u0441\u0442\u0430\u043d"
    ],
    "name:srp_x_preferred":[
        "\u0411\u043e\u0441\u0442\u0430\u043d"
    ],
    "name:swe_x_preferred":[
        "Bostan"
    ],
    "name:tur_x_preferred":[
        "Bostan"
    ],
    "name:ukr_x_preferred":[
        "\u0411\u043e\u0441\u0442\u0430\u043d"
    ],
    "name:urd_x_preferred":[
        "\u0628\u0648\u0633\u062a\u0627\u0646"
    ],
    "wof:name":"Bostan",
    "wof:placetype":"locality"
},
  "geometry": {"coordinates":[72.13333,40.53333],"type":"Point"}
}