{
  "type": "Feature",
  "properties": {
    "gn:admin1_code":"00",
    "gn:asciiname":"Bostan",
    "gn:country_code":"UZ",
    "gn:dem":514,
    "gn:feature_class":"P",
    "gn:feature_code":"PPL",
    "gn:name":"Bostan",
    "gn:population":0,
    "gn:timezone":"Asia/Tashkent",
    "iso:country":"UZ",
    "wof:name":"Bostan",
    "wof:placetype":"locality"
},
  "geometry": {"coordinates":[72.13333,40.53333],"type":"Point"}
}