{
  "type": "Feature",
  "properties": {
    "gn:admin1_code":"00",
    "gn:asciiname":"Losha",
    "gn:country_code":"UZ",
    "gn:dem":221,
    "gn:feature_class":"P",
    "gn:feature_code":"PPL",
    "gn:name":"Losha",
    "gn:population":0,
    "gn:timezone":"Asia/Samarkand",
    "iso:country":"UZ",
    "name:ceb_x_preferred":[
        "Losha"
    ],
    "name:swe_x_preferred":[
        "Losha"
    ],
    "wof:name":"Losha",
    "wof:placetype":"locality"
},
  "geometry": {"coordinates":[64.43333,39.71667],"type":"Point"}
}