{
  "type": "Feature",
  "properties": {
    "gn:admin1_code":"01",
    "gn:asciiname":"Bekmakhalla",
    "gn:country_code":"UZ",
    "gn:dem":554,
    "gn:feature_class":"P",
    "gn:feature_code":"PPL",
    "gn:name":"Bekmakhalla",
    "gn:population":0,
    "gn:timezone":"Asia/Tashkent",
    "iso:country":"UZ",
    "name:rus_x_preferred":[
        "\u0411\u0435\u043a\u043c\u0430\u0445\u0430\u043b\u043b\u0430"
    ],
    "wof:name":"Bekmakhalla",
    "wof:placetype":"locality"
},
  "geometry": {"coordinates":[72.56131999999999,40.88452],"type":"Point"}
}