{
  "type": "Feature",
  "properties": {
    "gn:admin1_code":"08",
    "gn:asciiname":"Xitoy",
    "gn:country_code":"UZ",
    "gn:dem":318,
    "gn:feature_class":"P",
    "gn:feature_code":"PPL",
    "gn:name":"Xitoy",
    "gn:population":0,
    "gn:timezone":"Asia/Samarkand",
    "iso:country":"UZ",
    "name:und_x_variant":[
        "Khtay"
    ],
    "wof:name":"Xitoy",
    "wof:placetype":"locality"
},
  "geometry": {"coordinates":[65.37854,39.09317],"type":"Point"}
}