{
  "type": "Feature",
  "properties": {
    "gn:admin1_code":"00",
    "gn:asciiname":"Saray",
    "gn:country_code":"UZ",
    "gn:dem":451,
    "gn:feature_class":"P",
    "gn:feature_code":"PPL",
    "gn:name":"Saray",
    "gn:population":0,
    "gn:timezone":"Asia/Samarkand",
    "iso:country":"UZ",
    "wof:name":"Saray",
    "wof:placetype":"locality"
},
  "geometry": {"coordinates":[66.18333,39.96667],"type":"Point"}
}