{
  "type": "Feature",
  "properties": {
    "gn:admin1_code":"07",
    "gn:asciiname":"Jizlon",
    "gn:country_code":"UZ",
    "gn:dem":519,
    "gn:feature_class":"P",
    "gn:feature_code":"PPL",
    "gn:name":"Jizlon",
    "gn:population":0,
    "gn:timezone":"Asia/Samarkand",
    "iso:country":"UZ",
    "wof:name":"Jizlon",
    "wof:placetype":"locality"
},
  "geometry": {"coordinates":[65.40137,40.33944],"type":"Point"}
}