{
  "type": "Feature",
  "properties": {
    "gn:admin1_code":"07",
    "gn:asciiname":"Bazar-Dzhay",
    "gn:country_code":"UZ",
    "gn:dem":389,
    "gn:feature_class":"P",
    "gn:feature_code":"PPL",
    "gn:name":"Bazar-Dzhay",
    "gn:population":0,
    "gn:timezone":"Asia/Samarkand",
    "iso:country":"UZ",
    "wof:name":"Bazar-Dzhay",
    "wof:placetype":"locality"
},
  "geometry": {"coordinates":[65.75,40.06667],"type":"Point"}
}