{
  "type": "Feature",
  "properties": {
    "gn:admin1_code":"03",
    "gn:asciiname":"Mehnatobod",
    "gn:country_code":"UZ",
    "gn:dem":388,
    "gn:feature_class":"P",
    "gn:feature_code":"PPL",
    "gn:name":"Mehnatobod",
    "gn:population":0,
    "gn:timezone":"Asia/Tashkent",
    "iso:country":"UZ",
    "name:und_x_variant":[
        "Mekhnatabad"
    ],
    "name:uzb_x_preferred":[
        "Mehnatobod"
    ],
    "wof:name":"Mehnatobod",
    "wof:placetype":"locality"
},
  "geometry": {"coordinates":[71.32521,40.58134],"type":"Point"}
}