{
  "type": "Feature",
  "properties": {
    "gn:admin1_code":"08",
    "gn:asciiname":"Kattaqishloq",
    "gn:country_code":"UZ",
    "gn:dem":452,
    "gn:feature_class":"P",
    "gn:feature_code":"PPL",
    "gn:name":"Kattaqishloq",
    "gn:population":0,
    "gn:timezone":"Asia/Samarkand",
    "iso:country":"UZ",
    "name:und_x_variant":[
        "Kattakishlak"
    ],
    "wof:name":"Kattaqishloq",
    "wof:placetype":"locality"
},
  "geometry": {"coordinates":[66.16413,39.1275],"type":"Point"}
}