{
  "type": "Feature",
  "properties": {
    "gn:admin1_code":"03",
    "gn:asciiname":"Katta-Qashg`ar",
    "gn:country_code":"UZ",
    "gn:dem":448,
    "gn:feature_class":"P",
    "gn:feature_code":"PPL",
    "gn:name":"Katta-Qashg\u2018ar",
    "gn:population":0,
    "gn:timezone":"Asia/Tashkent",
    "iso:country":"UZ",
    "name:und_x_variant":[
        "Katta-Kashgar"
    ],
    "name:uzb_x_preferred":[
        "Katta-Qashg\u2018ar"
    ],
    "wof:name":"Katta-Qashg`ar",
    "wof:placetype":"locality"
},
  "geometry": {"coordinates":[71.08629999999999,40.483],"type":"Point"}
}