{
  "type": "Feature",
  "properties": {
    "gn:admin1_code":"01",
    "gn:asciiname":"Qo`shko`prik",
    "gn:country_code":"UZ",
    "gn:dem":451,
    "gn:feature_class":"P",
    "gn:feature_code":"PPL",
    "gn:name":"Qo\u2018shko\u2018prik",
    "gn:population":0,
    "gn:timezone":"Asia/Tashkent",
    "iso:country":"UZ",
    "name:eng_x_preferred":[
        "Qo\u2018shko\u2018prik"
    ],
    "name:und_x_variant":[
        "Koshkuprik"
    ],
    "name:uzb_x_preferred":[
        "Qo\u2018shko\u2018prik"
    ],
    "wof:name":"Qo`shko`prik",
    "wof:placetype":"locality"
},
  "geometry": {"coordinates":[72.22865999999998,40.87472],"type":"Point"}
}