{
  "type": "Feature",
  "properties": {
    "gn:country":"UZ",
    "gn:fcode":"PPL",
    "gn:pop":16524,
    "iso:country":"UZ",
    "name:azb_x_preferred":[
        "\u062f\u0648\u0633\u062a\u0644\u06cc\u06a9"
    ],
    "name:eng_x_preferred":[
        "Dustlik"
    ],
    "name:hsb_x_preferred":[
        "Do\u2018stlik"
    ],
    "name:jpn_x_preferred":[
        "\u30c9\u30a5\u30b9\u30c8\u30ea\u30af"
    ],
    "name:kik_x_preferred":[
        "Do\u02bbstlik"
    ],
    "name:nld_x_preferred":[
        "Dustlik"
    ],
    "name:pol_x_preferred":[
        "Do\u02bbstlik"
    ],
    "name:rus_x_preferred":[
        "\u0414\u0443\u0441\u0442\u043b\u0438\u043a"
    ],
    "name:spa_x_preferred":[
        "Dustlik"
    ],
    "name:tat_x_preferred":[
        "\u0414\u0443\u0441\u043b\u044b\u043a"
    ],
    "name:tur_x_preferred":[
        "Dostluk"
    ],
    "name:ukr_x_preferred":[
        "\u0414\u0443\u0441\u0442\u043b\u0456\u043a"
    ],
    "name:unk_x_variant":[
        "Dustlik"
    ],
    "name:urd_x_preferred":[
        "\u062f\u0648\u0633\u062a\u0644\u06cc\u06a9"
    ],
    "name:uzb_x_preferred":[
        "Do\u02bbstlik"
    ],
    "qs:name":"D\u016dstlik",
    "qs:photos_9r":0,
    "qs:photos_sr":0,
    "qs:pop_sr":"6",
    "wd:wordcount":37,
    "wof:name":"D\u016dstlik",
    "wof:placetype":"locality",
    "wof:population":16524
},
  "geometry": {"coordinates":[68.03583,40.52472],"type":"Point"}
}