{
  "type": "Feature",
  "properties": {
    "gn:admin1_code":"00",
    "gn:asciiname":"Tashkent",
    "gn:cc2":"UZ",
    "gn:country_code":"UZ",
    "gn:dem":396,
    "gn:feature_class":"P",
    "gn:feature_code":"PPL",
    "gn:name":"Tashkent",
    "gn:population":0,
    "gn:timezone":"Asia/Samarkand",
    "iso:country":"UZ",
    "name:rus_x_preferred":[
        "\u0422\u0430\u0448\u043a\u0435\u043d\u0442"
    ],
    "name:und_x_variant":[
        "Tash-Kisken",
        "Tashkent"
    ],
    "wof:name":"Tashkent",
    "wof:placetype":"locality"
},
  "geometry": {"coordinates":[68.36667,40.13333],"type":"Point"}
}