{
  "type": "Feature",
  "properties": {
    "gn:admin1_code":"09",
    "gn:asciiname":"Kichik Guldursun",
    "gn:country_code":"UZ",
    "gn:dem":102,
    "gn:feature_class":"P",
    "gn:feature_code":"PPL",
    "gn:name":"Kichik Guldursun",
    "gn:population":0,
    "gn:timezone":"Asia/Samarkand",
    "iso:country":"UZ",
    "wof:name":"Kichik Guldursun",
    "wof:placetype":"locality"
},
  "geometry": {"coordinates":[61.05606,41.68343],"type":"Point"}
}