{
  "type": "Feature",
  "properties": {
    "iso:country":"UZ",
    "name:eng_x_preferred":[
        "Uch-Korgon"
    ],
    "name:fas_x_preferred":[
        "\u0627\u0648\u0686 \u06a9\u0631\u06af\u0646"
    ],
    "name:kir_x_preferred":[
        "\u04ae\u0447-\u041a\u043e\u0440\u0433\u043e\u043d"
    ],
    "name:nld_x_preferred":[
        "Uch-Korgon"
    ],
    "name:rup_x_preferred":[
        "Uch-Kurgan"
    ],
    "name:rus_x_preferred":[
        "\u0423\u0447-\u041a\u043e\u0440\u0433\u043e\u043d"
    ],
    "name:unk_x_variant":[
        "Uchq\u016drghon"
    ],
    "name:urd_x_preferred":[
        "\u0627\u0686-\u06a9\u0648\u0631\u06af\u0648\u0646"
    ],
    "name:uzb_x_preferred":[
        "Uchq\u016drghon Shahri"
    ],
    "qs:gn_country":"UZ",
    "qs:gn_fcode":"PPLA2",
    "qs:gn_pop":33323,
    "qs:name":"Uchkurgan",
    "qs:name_adm0":"Uzbekistan",
    "qs:name_adm1":"Namangan",
    "qs:photos":0,
    "qs:photos_1k":0,
    "qs:photos_9k":1,
    "qs:photos_9r":1,
    "qs:photos_all":1,
    "qs:photos_sr":0,
    "qs:placetype":"Town",
    "qs:pop_sr":"7",
    "qs:woe_adm0":23424980,
    "wd:wordcount":14,
    "wof:name":"Uchkurgan",
    "wof:placetype":"locality",
    "wof:population":33323
},
  "geometry": {"coordinates":[72.07915,41.11371],"type":"Point"}
}