{
  "type": "Feature",
  "properties": {
    "iso:country":"UZ",
    "name:und_x_variant":[
        "Chartak"
    ],
    "qs:gn_country":"UZ",
    "qs:gn_fcode":"PPL",
    "qs:gn_pop":49844,
    "qs:name":"Chertak",
    "qs:name_adm0":"Uzbekistan",
    "qs:name_adm1":"Namangan",
    "qs:photos":0,
    "qs:photos_1k":0,
    "qs:photos_9k":0,
    "qs:photos_9r":0,
    "qs:photos_all":0,
    "qs:photos_sr":0,
    "qs:placetype":"Town",
    "qs:pop_sr":"7",
    "qs:woe_adm0":23424980,
    "wof:name":"Chertak",
    "wof:placetype":"locality",
    "wof:population":49844
},
  "geometry": {"coordinates":[71.85527,41.06656],"type":"Point"}
}