{
  "type": "Feature",
  "properties": {
    "gn:admin1_code":"00",
    "gn:asciiname":"Dzhail'ma",
    "gn:country_code":"UZ",
    "gn:dem":867,
    "gn:feature_class":"P",
    "gn:feature_code":"PPL",
    "gn:name":"Dzhail\u2019ma",
    "gn:population":0,
    "gn:timezone":"Asia/Samarkand",
    "iso:country":"UZ",
    "name:rus_x_preferred":[
        "Dzhail\u2019ma"
    ],
    "wof:name":"Dzhail'ma",
    "wof:placetype":"locality"
},
  "geometry": {"coordinates":[66.40000000000001,40.36667],"type":"Point"}
}