{
  "type": "Feature",
  "properties": {
    "gn:admin1_code":"00",
    "gn:asciiname":"Zenakhas",
    "gn:cc2":"UZ",
    "gn:country_code":"UZ",
    "gn:dem":100,
    "gn:feature_class":"P",
    "gn:feature_code":"PPL",
    "gn:name":"Zenakhas",
    "gn:population":0,
    "gn:timezone":"Asia/Samarkand",
    "iso:country":"UZ",
    "name:und_x_variant":[
        "Zenankhas",
        "Zenakhas"
    ],
    "wof:name":"Zenakhas",
    "wof:placetype":"locality"
},
  "geometry": {"coordinates":[60.65,41.46667],"type":"Point"}
}