{
  "type": "Feature",
  "properties": {
    "gn:admin1_code":"03",
    "gn:asciiname":"O`rikzor",
    "gn:country_code":"UZ",
    "gn:dem":688,
    "gn:feature_class":"P",
    "gn:feature_code":"PPL",
    "gn:name":"O\u2018rikzor",
    "gn:population":0,
    "gn:timezone":"Asia/Tashkent",
    "iso:country":"UZ",
    "name:und_x_variant":[
        "Uryukzar"
    ],
    "name:uzb_x_preferred":[
        "O\u2018rikzor"
    ],
    "wof:name":"O`rikzor",
    "wof:placetype":"locality"
},
  "geometry": {"coordinates":[71.87170999999999,40.30725],"type":"Point"}
}