{
  "type": "Feature",
  "properties": {
    "gn:admin1_code":"03",
    "gn:asciiname":"Ilg`or",
    "gn:country_code":"UZ",
    "gn:dem":560,
    "gn:feature_class":"P",
    "gn:feature_code":"PPL",
    "gn:name":"Ilg\u2018or",
    "gn:population":0,
    "gn:timezone":"Asia/Tashkent",
    "iso:country":"UZ",
    "name:und_x_variant":[
        "Kyrgyzshura"
    ],
    "name:uzb_x_preferred":[
        "Qirgizsho\u2018ra"
    ],
    "name:uzb_x_variant":[
        "Ilg\u2018or"
    ],
    "wof:name":"Ilg`or",
    "wof:placetype":"locality"
},
  "geometry": {"coordinates":[71.72054,40.39936],"type":"Point"}
}