{
  "type": "Feature",
  "properties": {
    "gn:admin1_code":"03",
    "gn:asciiname":"Sanam",
    "gn:country_code":"UZ",
    "gn:dem":393,
    "gn:feature_class":"P",
    "gn:feature_code":"PPL",
    "gn:name":"Sanam",
    "gn:population":0,
    "gn:timezone":"Asia/Tashkent",
    "iso:country":"UZ",
    "name:uzb_x_preferred":[
        "Sanam"
    ],
    "wof:name":"Sanam",
    "wof:placetype":"locality"
},
  "geometry": {"coordinates":[70.94238,40.59469],"type":"Point"}
}