{
  "type": "Feature",
  "properties": {
    "gn:admin1_code":"12",
    "gn:asciiname":"Kara-Tyube",
    "gn:country_code":"UZ",
    "gn:dem":516,
    "gn:feature_class":"P",
    "gn:feature_code":"PPL",
    "gn:name":"Kara-Tyube",
    "gn:population":0,
    "gn:timezone":"Asia/Samarkand",
    "iso:country":"UZ",
    "wof:name":"Kara-Tyube",
    "wof:placetype":"locality"
},
  "geometry": {"coordinates":[67.77672,38.1616],"type":"Point"}
}