{
  "type": "Feature",
  "properties": {
    "gn:admin1_code":"00",
    "gn:asciiname":"Parcha-Kara",
    "gn:country_code":"UZ",
    "gn:dem":653,
    "gn:feature_class":"P",
    "gn:feature_code":"PPL",
    "gn:name":"Parcha-Kara",
    "gn:population":0,
    "gn:timezone":"Asia/Samarkand",
    "iso:country":"UZ",
    "wof:name":"Parcha-Kara",
    "wof:placetype":"locality"
},
  "geometry": {"coordinates":[66.65000000000001,39.66667],"type":"Point"}
}