{
  "type": "Feature",
  "properties": {
    "gn:admin1_code":"12",
    "gn:asciiname":"Kiprich",
    "gn:country_code":"UZ",
    "gn:dem":354,
    "gn:feature_class":"P",
    "gn:feature_code":"PPL",
    "gn:name":"Kiprich",
    "gn:population":0,
    "gn:timezone":"Asia/Samarkand",
    "iso:country":"UZ",
    "name:deu_x_preferred":[
        "Kiprich"
    ],
    "name:hat_x_preferred":[
        "Kiprich"
    ],
    "wof:name":"Kiprich",
    "wof:placetype":"locality"
},
  "geometry": {"coordinates":[67.44667,37.43083],"type":"Point"}
}