{
  "type": "Feature",
  "properties": {
    "gn:admin1_code":"14",
    "gn:asciiname":"Bessarabskiy",
    "gn:country_code":"UZ",
    "gn:dem":286,
    "gn:feature_class":"P",
    "gn:feature_code":"PPL",
    "gn:name":"Bessarabskiy",
    "gn:population":0,
    "gn:timezone":"Asia/Tashkent",
    "iso:country":"UZ",
    "wof:name":"Bessarabskiy",
    "wof:placetype":"locality"
},
  "geometry": {"coordinates":[68.96666999999999,40.76667],"type":"Point"}
}