{
  "type": "Feature",
  "properties": {
    "gn:admin1_code":"14",
    "gn:asciiname":"Novo-Dmitriyevskiy",
    "gn:country_code":"UZ",
    "gn:dem":287,
    "gn:feature_class":"P",
    "gn:feature_code":"PPL",
    "gn:name":"Novo-Dmitriyevskiy",
    "gn:population":0,
    "gn:timezone":"Asia/Tashkent",
    "iso:country":"UZ",
    "wof:name":"Novo-Dmitriyevskiy",
    "wof:placetype":"locality"
},
  "geometry": {"coordinates":[69.05,40.71667],"type":"Point"}
}