{
  "type": "Feature",
  "properties": {
    "gn:admin1_code":"12",
    "gn:asciiname":"Kakaydi",
    "gn:country_code":"UZ",
    "gn:dem":383,
    "gn:feature_class":"P",
    "gn:feature_code":"PPL",
    "gn:name":"Kakaydi",
    "gn:population":0,
    "gn:timezone":"Asia/Samarkand",
    "iso:country":"UZ",
    "name:und_x_variant":[
        "Kokayty",
        "Kakaydy"
    ],
    "name:uzb_x_preferred":[
        "Kakaydi"
    ],
    "wof:name":"Kakaydi",
    "wof:placetype":"locality"
},
  "geometry": {"coordinates":[67.51459,37.56773],"type":"Point"}
}