{
  "type": "Feature",
  "properties": {
    "gn:admin1_code":"03",
    "gn:asciiname":"Qo`rg`onariq",
    "gn:country_code":"UZ",
    "gn:dem":465,
    "gn:feature_class":"P",
    "gn:feature_code":"PPL",
    "gn:name":"Qo\u2018rg\u2018onariq",
    "gn:population":0,
    "gn:timezone":"Asia/Tashkent",
    "iso:country":"UZ",
    "name:uzb_x_preferred":[
        "Qo\u2018rg\u2018onariq"
    ],
    "wof:name":"Qo`rg`onariq",
    "wof:placetype":"locality"
},
  "geometry": {"coordinates":[71.60715999999999,40.42071],"type":"Point"}
}