{
  "type": "Feature",
  "properties": {
    "gn:admin1_code":"06",
    "gn:asciiname":"Eshaobod",
    "gn:country_code":"UZ",
    "gn:dem":413,
    "gn:feature_class":"P",
    "gn:feature_code":"PPL",
    "gn:name":"Eshaobod",
    "gn:population":0,
    "gn:timezone":"Asia/Tashkent",
    "iso:country":"UZ",
    "name:eng_x_preferred":[
        "Eshaobod"
    ],
    "name:und_x_variant":[
        "Ishavat"
    ],
    "name:uzb_x_preferred":[
        "Eshobod"
    ],
    "wof:name":"Eshaobod",
    "wof:placetype":"locality"
},
  "geometry": {"coordinates":[71.72063,40.97405],"type":"Point"}
}