{
  "type": "Feature",
  "properties": {
    "gn:admin1_code":"03",
    "gn:asciiname":"Paxtakor",
    "gn:country_code":"UZ",
    "gn:dem":432,
    "gn:feature_class":"P",
    "gn:feature_code":"PPL",
    "gn:name":"Paxtakor",
    "gn:population":0,
    "gn:timezone":"Asia/Tashkent",
    "iso:country":"UZ",
    "name:und_x_variant":[
        "Pakhtakor"
    ],
    "name:uzb_x_preferred":[
        "Paxtakor"
    ],
    "wof:name":"Paxtakor",
    "wof:placetype":"locality"
},
  "geometry": {"coordinates":[71.67814,40.60254000000001],"type":"Point"}
}