{
  "type": "Feature",
  "properties": {
    "gn:admin1_code":"03",
    "gn:asciiname":"Uzunqishloq",
    "gn:country_code":"UZ",
    "gn:dem":392,
    "gn:feature_class":"P",
    "gn:feature_code":"PPL",
    "gn:name":"Uzunqishloq",
    "gn:population":0,
    "gn:timezone":"Asia/Tashkent",
    "iso:country":"UZ",
    "name:uzb_x_preferred":[
        "Uzunqishloq"
    ],
    "wof:name":"Uzunqishloq",
    "wof:placetype":"locality"
},
  "geometry": {"coordinates":[70.55781,40.41812],"type":"Point"}
}