{
  "type": "Feature",
  "properties": {
    "gn:admin1_code":"14",
    "gn:asciiname":"Telav",
    "gn:cc2":"UZ",
    "gn:country_code":"UZ",
    "gn:dem":648,
    "gn:feature_class":"P",
    "gn:feature_code":"PPL",
    "gn:name":"Telav",
    "gn:population":0,
    "gn:timezone":"Asia/Tashkent",
    "iso:country":"UZ",
    "name:und_x_variant":[
        "Telyau",
        "Telav"
    ],
    "wof:name":"Telav",
    "wof:placetype":"locality"
},
  "geometry": {"coordinates":[69.80611,40.88389],"type":"Point"}
}