{
  "type": "Feature",
  "properties": {
    "gn:admin1_code":"00",
    "gn:asciiname":"Kara-Khana",
    "gn:cc2":"UZ",
    "gn:country_code":"UZ",
    "gn:dem":225,
    "gn:feature_class":"P",
    "gn:feature_code":"PPL",
    "gn:name":"Kara-Khana",
    "gn:population":0,
    "gn:timezone":"Asia/Samarkand",
    "iso:country":"UZ",
    "name:und_x_variant":[
        "Tuganchi",
        "Arab-Khana",
        "Kara-Khana"
    ],
    "wof:name":"Kara-Khana",
    "wof:placetype":"locality"
},
  "geometry": {"coordinates":[64.28333000000001,39.93333],"type":"Point"}
}