{
  "type": "Feature",
  "properties": {
    "gn:admin1_code":"12",
    "gn:asciiname":"Salavat",
    "gn:country_code":"UZ",
    "gn:dem":314,
    "gn:feature_class":"P",
    "gn:feature_code":"PPL",
    "gn:name":"Salavat",
    "gn:population":0,
    "gn:timezone":"Asia/Samarkand",
    "iso:country":"UZ",
    "name:rus_x_preferred":[
        "\u0421\u0430\u043b\u0430\u0432\u0430\u0442"
    ],
    "wof:name":"Salavat",
    "wof:placetype":"locality"
},
  "geometry": {"coordinates":[67.33694,37.28361],"type":"Point"}
}