{
  "type": "Feature",
  "properties": {
    "gn:admin1_code":"12",
    "gn:asciiname":"Salavat",
    "gn:country_code":"UZ",
    "gn:dem":314,
    "gn:feature_class":"P",
    "gn:feature_code":"PPL",
    "gn:name":"Salavat",
    "gn:population":0,
    "gn:timezone":"Asia/Samarkand",
    "iso:country":"UZ",
    "name:aze_x_preferred":[
        "Salavat"
    ],
    "name:bak_x_preferred":[
        "\u0421\u0430\u043b\u0430\u0443\u0430\u0442"
    ],
    "name:bos_x_preferred":[
        "Salavat"
    ],
    "name:ceb_x_preferred":[
        "Salawat"
    ],
    "name:ces_x_preferred":[
        "Salavat"
    ],
    "name:deu_x_preferred":[
        "Salawat"
    ],
    "name:hye_x_preferred":[
        "\u054d\u0561\u056c\u0561\u057e\u0561\u0569"
    ],
    "name:rus_x_preferred":[
        "\u0421\u0430\u043b\u0430\u0432\u0430\u0442"
    ],
    "name:swe_x_preferred":[
        "Salawat"
    ],
    "name:tgl_x_preferred":[
        "Salavat"
    ],
    "name:ukr_x_preferred":[
        "\u0421\u0430\u043b\u0430\u0432\u0430\u0442"
    ],
    "wof:name":"Salavat",
    "wof:placetype":"locality"
},
  "geometry": {"coordinates":[67.33694,37.28361],"type":"Point"}
}