{
  "type": "Feature",
  "properties": {
    "gn:admin1_code":"08",
    "gn:asciiname":"Yakkabog`",
    "gn:country_code":"UZ",
    "gn:dem":580,
    "gn:feature_class":"P",
    "gn:feature_code":"PPL",
    "gn:name":"Yakkabog\u2018",
    "gn:population":0,
    "gn:timezone":"Asia/Samarkand",
    "iso:country":"UZ",
    "name:und_x_variant":[
        "Yakkabag",
        "Yakkabogh",
        "Stantsiya Yakkabag"
    ],
    "name:uzb_x_preferred":[
        "Yakkabog\u2018"
    ],
    "wof:name":"Yakkabog`",
    "wof:placetype":"locality"
},
  "geometry": {"coordinates":[66.67639,38.98083],"type":"Point"}
}