{
  "type": "Feature",
  "properties": {
    "gn:admin1_code":"08",
    "gn:asciiname":"Yakkabog`",
    "gn:country_code":"UZ",
    "gn:dem":580,
    "gn:feature_class":"P",
    "gn:feature_code":"PPL",
    "gn:name":"Yakkabog\u2018",
    "gn:population":0,
    "gn:timezone":"Asia/Samarkand",
    "iso:country":"UZ",
    "name:azb_x_preferred":[
        "\u06cc\u0626\u06a9\u06a9\u0647\u200c\u0628\u0627\u063a"
    ],
    "name:hsb_x_preferred":[
        "Yakkabog\u2018"
    ],
    "name:kik_x_preferred":[
        "Yakkabog\u02bb"
    ],
    "name:pol_x_preferred":[
        "Yakkabog\u02bb"
    ],
    "name:rus_x_preferred":[
        "\u042f\u043a\u043a\u0430\u0431\u0430\u0433"
    ],
    "name:tat_x_preferred":[
        "\u042f\u043a\u043a\u04d9\u0431\u0430\u0433"
    ],
    "name:tur_x_preferred":[
        "Yakkaba\u011f"
    ],
    "name:und_x_variant":[
        "Yakkabag",
        "Yakkabogh",
        "Stantsiya Yakkabag"
    ],
    "name:urd_x_preferred":[
        "\u06cc\u0626\u06a9\u06c1 \u0628\u0627\u063a"
    ],
    "name:uzb_x_preferred":[
        "Yakkabog\u2018"
    ],
    "name:uzb_x_variant":[
        "Yakkabog\u02bb"
    ],
    "wof:name":"Yakkabog`",
    "wof:placetype":"locality"
},
  "geometry": {"coordinates":[66.67639,38.98083],"type":"Point"}
}