{
  "type": "Feature",
  "properties": {
    "gn:admin1_code":"01",
    "gn:asciiname":"G`anchiyuz",
    "gn:country_code":"UZ",
    "gn:dem":481,
    "gn:feature_class":"P",
    "gn:feature_code":"PPL",
    "gn:name":"G\u2018anchiyuz",
    "gn:population":0,
    "gn:timezone":"Asia/Tashkent",
    "iso:country":"UZ",
    "name:rus_x_preferred":[
        "\u0413\u0430\u043d\u0447\u0438\u044e\u0437"
    ],
    "name:und_x_variant":[
        "Ganchiyuz"
    ],
    "name:uzb_x_preferred":[
        "G\u2018anchiyuz"
    ],
    "wof:name":"G`anchiyuz",
    "wof:placetype":"locality"
},
  "geometry": {"coordinates":[72.13330999999999,40.5957],"type":"Point"}
}