{
  "type": "Feature",
  "properties": {
    "gn:admin1_code":"01",
    "gn:asciiname":"Qoraqalpoq",
    "gn:country_code":"UZ",
    "gn:dem":436,
    "gn:feature_class":"P",
    "gn:feature_code":"PPL",
    "gn:name":"Qoraqalpoq",
    "gn:population":0,
    "gn:timezone":"Asia/Tashkent",
    "iso:country":"UZ",
    "name:rus_x_preferred":[
        "\u041a\u0430\u0440\u0430\u043a\u0430\u043b\u043f\u0430\u043a"
    ],
    "name:und_x_variant":[
        "Karakalpak"
    ],
    "name:uzb_x_preferred":[
        "Qoraqalpoq"
    ],
    "wof:name":"Qoraqalpoq",
    "wof:placetype":"locality"
},
  "geometry": {"coordinates":[72.1373,40.8961],"type":"Point"}
}