{
  "type": "Feature",
  "properties": {
    "iso:country":"UZ",
    "name:azb_x_preferred":[
        "\u063a\u0632\u0644\u200c\u06a9\u0646\u062f"
    ],
    "name:deu_x_historical":[
        "Gasalkent"
    ],
    "name:deu_x_preferred":[
        "G\u02bbazalkent"
    ],
    "name:deu_x_variant":[
        "Gasalkent"
    ],
    "name:eng_x_preferred":[
        "Gazalkent"
    ],
    "name:fas_x_preferred":[
        "\u06af\u0632\u0644\u06a9\u0646\u062a"
    ],
    "name:fra_x_preferred":[
        "Gazalkent"
    ],
    "name:hsb_x_preferred":[
        "Ga\u2018zalkent"
    ],
    "name:hun_x_preferred":[
        "G\u02bbazalkent"
    ],
    "name:jpn_x_preferred":[
        "\u30ac\u30b6\u30eb\u30b1\u30f3\u30c8"
    ],
    "name:kik_x_preferred":[
        "Gazalkent"
    ],
    "name:lit_x_preferred":[
        "Gazalkentas"
    ],
    "name:nld_x_preferred":[
        "Gazalkent"
    ],
    "name:pnb_x_preferred":[
        "\u063a\u0632\u0627\u0644 \u06a9\u0646\u062a"
    ],
    "name:pol_x_preferred":[
        "G\u02bbazalkent"
    ],
    "name:rus_x_preferred":[
        "\u0413\u0430\u0437\u0430\u043b\u043a\u0435\u043d\u0442"
    ],
    "name:spa_x_preferred":[
        "Gazalkent"
    ],
    "name:tat_x_preferred":[
        "\u0413\u0430\u0437\u04d9\u043b\u043a\u04d9\u043d\u0442"
    ],
    "name:tur_x_preferred":[
        "Gazalkent"
    ],
    "name:ukr_x_preferred":[
        "\u0413\u0430\u0437\u0430\u043b\u043a\u0435\u043d\u0442"
    ],
    "name:unk_x_variant":[
        "Ghazalkent"
    ],
    "name:urd_x_preferred":[
        "\u063a\u0632\u0644 \u0642\u0646\u062f"
    ],
    "name:uzb_x_preferred":[
        "G\u02bbazalkent"
    ],
    "qs:gn_country":"UZ",
    "qs:gn_fcode":"PPL",
    "qs:gn_pop":24700,
    "qs:name":"Gazalkent",
    "qs:name_adm0":"Uzbekistan",
    "qs:name_adm1":"Toshkent",
    "qs:photos":0,
    "qs:photos_1k":0,
    "qs:photos_9k":1,
    "qs:photos_9r":1,
    "qs:photos_all":5,
    "qs:photos_sr":0,
    "qs:placetype":"Town",
    "qs:pop_sr":"7",
    "qs:woe_adm0":23424980,
    "wd:wordcount":23,
    "wof:name":"Gazalkent",
    "wof:placetype":"locality",
    "wof:population":24700
},
  "geometry": {"coordinates":[69.77083,41.55806],"type":"Point"}
}