{
  "type": "Feature",
  "properties": {
    "gn:admin1_code":"00",
    "gn:asciiname":"Mukhtar",
    "gn:country_code":"UZ",
    "gn:dem":193,
    "gn:feature_class":"P",
    "gn:feature_code":"PPL",
    "gn:name":"Mukhtar",
    "gn:population":0,
    "gn:timezone":"Asia/Samarkand",
    "iso:country":"UZ",
    "wof:name":"Mukhtar",
    "wof:placetype":"locality"
},
  "geometry": {"coordinates":[63.88333000000001,39.43333],"type":"Point"}
}