{
  "type": "Feature",
  "properties": {
    "gn:admin1_code":"12",
    "gn:asciiname":"Xo`jaqiya",
    "gn:country_code":"UZ",
    "gn:dem":397,
    "gn:feature_class":"P",
    "gn:feature_code":"PPL",
    "gn:name":"Xo\u2018jaqiya",
    "gn:population":0,
    "gn:timezone":"Asia/Samarkand",
    "iso:country":"UZ",
    "name:und_x_variant":[
        "Khodzha-Kiya"
    ],
    "name:uzb_x_preferred":[
        "Xo\u2018jaqiya"
    ],
    "wof:name":"Xo`jaqiya",
    "wof:placetype":"locality"
},
  "geometry": {"coordinates":[66.9431,37.65128],"type":"Point"}
}