{
  "type": "Feature",
  "properties": {
    "gn:admin1_code":"08",
    "gn:asciiname":"Jarqum",
    "gn:country_code":"UZ",
    "gn:dem":342,
    "gn:feature_class":"P",
    "gn:feature_code":"PPL",
    "gn:name":"Jarqum",
    "gn:population":0,
    "gn:timezone":"Asia/Samarkand",
    "iso:country":"UZ",
    "name:und_x_variant":[
        "Dzharkum",
        "Jarqum"
    ],
    "wof:name":"Jarqum",
    "wof:placetype":"locality"
},
  "geometry": {"coordinates":[65.71826999999999,39.34701],"type":"Point"}
}