{
  "type": "Feature",
  "properties": {
    "gn:admin1_code":"03",
    "gn:asciiname":"Yangiqo`rg`on",
    "gn:country_code":"UZ",
    "gn:dem":466,
    "gn:feature_class":"P",
    "gn:feature_code":"PPL",
    "gn:name":"Yangiqo\u2018rg\u2018on",
    "gn:population":0,
    "gn:timezone":"Asia/Tashkent",
    "iso:country":"UZ",
    "name:und_x_variant":[
        "Yangikurgan",
        "Yangiqurghon"
    ],
    "name:uzb_x_preferred":[
        "Yangiqo\u2018rg\u2018on"
    ],
    "wof:name":"Yangiqo`rg`on",
    "wof:placetype":"locality"
},
  "geometry": {"coordinates":[71.46165000000001,40.37805],"type":"Point"}
}