{
  "type": "Feature",
  "properties": {
    "gn:admin1_code":"06",
    "gn:asciiname":"Damko`l",
    "gn:country_code":"UZ",
    "gn:dem":388,
    "gn:feature_class":"P",
    "gn:feature_code":"PPL",
    "gn:name":"Damko\u2018l",
    "gn:population":0,
    "gn:timezone":"Asia/Tashkent",
    "iso:country":"UZ",
    "name:eng_x_preferred":[
        "Damko\u2018l"
    ],
    "wof:name":"Damko`l",
    "wof:placetype":"locality"
},
  "geometry": {"coordinates":[71.48661,40.78157],"type":"Point"}
}