{
  "type": "Feature",
  "properties": {
    "gn:admin1_code":"12",
    "gn:asciiname":"Bocharo",
    "gn:country_code":"UZ",
    "gn:dem":454,
    "gn:feature_class":"P",
    "gn:feature_code":"PPL",
    "gn:name":"Bocharo",
    "gn:population":0,
    "gn:timezone":"Asia/Samarkand",
    "iso:country":"UZ",
    "name:uzb_x_preferred":[
        "Bocharo"
    ],
    "wof:name":"Bocharo",
    "wof:placetype":"locality"
},
  "geometry": {"coordinates":[67.53919,37.87407],"type":"Point"}
}