{
  "type": "Feature",
  "properties": {
    "gn:admin1_code":"07",
    "gn:asciiname":"Nayman",
    "gn:country_code":"UZ",
    "gn:dem":402,
    "gn:feature_class":"P",
    "gn:feature_code":"PPL",
    "gn:name":"Nayman",
    "gn:population":0,
    "gn:timezone":"Asia/Samarkand",
    "iso:country":"UZ",
    "name:ceb_x_preferred":[
        "Nayman"
    ],
    "name:kir_x_preferred":[
        "\u041d\u0430\u0439\u043c\u0430\u043d"
    ],
    "name:rus_x_preferred":[
        "\u041d\u0430\u0439\u043c\u0430\u043d"
    ],
    "name:swe_x_preferred":[
        "Nayman"
    ],
    "name:ukr_x_preferred":[
        "\u041d\u0430\u0439\u043c\u0430\u043d"
    ],
    "name:uzb_x_preferred":[
        "Nayman"
    ],
    "wof:name":"Nayman",
    "wof:placetype":"locality"
},
  "geometry": {"coordinates":[65.84999999999999,40.05],"type":"Point"}
}