{
  "type": "Feature",
  "properties": {
    "gn:admin1_code":"12",
    "gn:asciiname":"Qo`shchinor",
    "gn:country_code":"UZ",
    "gn:dem":375,
    "gn:feature_class":"P",
    "gn:feature_code":"PPL",
    "gn:name":"Qo\u2018shchinor",
    "gn:population":0,
    "gn:timezone":"Asia/Samarkand",
    "iso:country":"UZ",
    "name:uzb_x_preferred":[
        "Qo\u2018shchinor"
    ],
    "wof:name":"Qo`shchinor",
    "wof:placetype":"locality"
},
  "geometry": {"coordinates":[67.26819,37.62679],"type":"Point"}
}