{
  "type": "Feature",
  "properties": {
    "gn:admin1_code":"03",
    "gn:asciiname":"Tolhovuz",
    "gn:country_code":"UZ",
    "gn:dem":427,
    "gn:feature_class":"P",
    "gn:feature_code":"PPL",
    "gn:name":"Tolhovuz",
    "gn:population":0,
    "gn:timezone":"Asia/Tashkent",
    "iso:country":"UZ",
    "name:und_x_variant":[
        "Tashauz",
        "Talkhavuz"
    ],
    "name:uzb_x_preferred":[
        "Tolhovuz"
    ],
    "name:uzb_x_variant":[
        "Toshhovuz"
    ],
    "wof:name":"Tolhovuz",
    "wof:placetype":"locality"
},
  "geometry": {"coordinates":[71.72031,40.66039],"type":"Point"}
}