{
  "type": "Feature",
  "properties": {
    "gn:admin1_code":"06",
    "gn:asciiname":"Olmos",
    "gn:country_code":"UZ",
    "gn:dem":698,
    "gn:feature_class":"P",
    "gn:feature_code":"PPL",
    "gn:name":"Olmos",
    "gn:population":0,
    "gn:timezone":"Asia/Tashkent",
    "iso:country":"UZ",
    "name:arg_x_preferred":[
        "Olmos"
    ],
    "name:ceb_x_preferred":[
        "Olmos"
    ],
    "name:deu_x_preferred":[
        "Olmos"
    ],
    "name:ita_x_preferred":[
        "Olmos"
    ],
    "name:por_x_preferred":[
        "Olmos"
    ],
    "name:swe_x_preferred":[
        "Olmos"
    ],
    "name:und_x_variant":[
        "Kum-Almas",
        "Kuy-Almas",
        "Kui-Almas",
        "Kuyu-Almas",
        "Almas",
        "Olmos"
    ],
    "wof:name":"Olmos",
    "wof:placetype":"locality"
},
  "geometry": {"coordinates":[71.09764,41.0096],"type":"Point"}
}