{
  "type": "Feature",
  "properties": {
    "gn:admin1_code":"06",
    "gn:asciiname":"Olmos",
    "gn:country_code":"UZ",
    "gn:dem":698,
    "gn:feature_class":"P",
    "gn:feature_code":"PPL",
    "gn:name":"Olmos",
    "gn:population":0,
    "gn:timezone":"Asia/Tashkent",
    "iso:country":"UZ",
    "name:ara_x_preferred":[
        "\u0623\u0648\u0644\u0645\u0648\u0633"
    ],
    "name:arg_x_preferred":[
        "Olmos"
    ],
    "name:ben_x_preferred":[
        "\u0993\u09b2\u09ae\u09b8"
    ],
    "name:ceb_x_preferred":[
        "Olmos"
    ],
    "name:deu_x_preferred":[
        "Olmos"
    ],
    "name:ell_x_preferred":[
        "\u038c\u03bb\u03bc\u03bf\u03c2"
    ],
    "name:fas_x_preferred":[
        "\u0627\u0648\u0644\u0645\u0648\u0633"
    ],
    "name:fra_x_preferred":[
        "Olmos"
    ],
    "name:heb_x_preferred":[
        "\u05d0\u05d5\u05dc\u05de\u05d5\u05e1"
    ],
    "name:hin_x_preferred":[
        "\u0913\u0932\u094d\u092e\u094b\u0938"
    ],
    "name:hun_x_preferred":[
        "Olmos"
    ],
    "name:ind_x_preferred":[
        "Olmos"
    ],
    "name:ita_x_preferred":[
        "Olmos"
    ],
    "name:jpn_x_preferred":[
        "\u30aa\u30eb\u30e2\u30b9"
    ],
    "name:kor_x_preferred":[
        "\uc62c\ubaa8\uc2a4"
    ],
    "name:nld_x_preferred":[
        "Olmos"
    ],
    "name:pol_x_preferred":[
        "Olmos"
    ],
    "name:por_x_preferred":[
        "Olmos"
    ],
    "name:rus_x_preferred":[
        "\u041e\u043b\u044c\u043c\u043e\u0441"
    ],
    "name:swe_x_preferred":[
        "Olmos"
    ],
    "name:tur_x_preferred":[
        "Olmos"
    ],
    "name:ukr_x_preferred":[
        "\u041e\u043b\u043c\u043e\u0441"
    ],
    "name:und_x_variant":[
        "Kum-Almas",
        "Kuy-Almas",
        "Kui-Almas",
        "Kuyu-Almas",
        "Almas"
    ],
    "name:urd_x_preferred":[
        "\u0627\u0648\u0644\u0645\u0648\u0633"
    ],
    "name:vie_x_preferred":[
        "Olmos"
    ],
    "name:zho_cn_x_preferred":[
        "\u5965\u5c14\u83ab\u65af"
    ],
    "name:zho_tw_x_preferred":[
        "\u5967\u723e\u83ab\u65af"
    ],
    "wof:name":"Olmos",
    "wof:placetype":"locality"
},
  "geometry": {"coordinates":[71.09764,41.0096],"type":"Point"}
}