{
  "type": "Feature",
  "properties": {
    "gn:admin1_code":"09",
    "gn:asciiname":"Tobekol'",
    "gn:country_code":"UZ",
    "gn:dem":55,
    "gn:feature_class":"P",
    "gn:feature_code":"PPL",
    "gn:name":"Tobekol\u2019",
    "gn:population":0,
    "gn:timezone":"Asia/Samarkand",
    "iso:country":"UZ",
    "name:und_x_variant":[
        "Imeni Maksima Gor\u2019kogo",
        "Tobekol\u2019"
    ],
    "wof:name":"Tobekol'",
    "wof:placetype":"locality"
},
  "geometry": {"coordinates":[60.33333,43.16667],"type":"Point"}
}