{
  "type": "Feature",
  "properties": {
    "gn:admin1_code":"08",
    "gn:asciiname":"Obihayot",
    "gn:country_code":"UZ",
    "gn:dem":626,
    "gn:feature_class":"P",
    "gn:feature_code":"PPL",
    "gn:name":"Obihayot",
    "gn:population":0,
    "gn:timezone":"Asia/Samarkand",
    "iso:country":"UZ",
    "wof:name":"Obihayot",
    "wof:placetype":"locality"
},
  "geometry": {"coordinates":[66.39100999999999,38.5405],"type":"Point"}
}