{
  "type": "Feature",
  "properties": {
    "gn:admin1_code":"07",
    "gn:asciiname":"Usen-Kuduk",
    "gn:country_code":"UZ",
    "gn:dem":255,
    "gn:feature_class":"P",
    "gn:feature_code":"PPL",
    "gn:name":"Usen-Kuduk",
    "gn:population":0,
    "gn:timezone":"Asia/Samarkand",
    "iso:country":"UZ",
    "wof:name":"Usen-Kuduk",
    "wof:placetype":"locality"
},
  "geometry": {"coordinates":[65.88333,41.11667],"type":"Point"}
}