{
  "type": "Feature",
  "properties": {
    "gn:admin1_code":"00",
    "gn:asciiname":"Orta-Aul",
    "gn:country_code":"UZ",
    "gn:dem":754,
    "gn:feature_class":"P",
    "gn:feature_code":"PPL",
    "gn:name":"Orta-Aul",
    "gn:population":0,
    "gn:timezone":"Asia/Samarkand",
    "iso:country":"UZ",
    "wof:name":"Orta-Aul",
    "wof:placetype":"locality"
},
  "geometry": {"coordinates":[66.56667,40.18333],"type":"Point"}
}