{
  "type": "Feature",
  "properties": {
    "gn:admin1_code":"01",
    "gn:asciiname":"Sho`rqishloq",
    "gn:country_code":"UZ",
    "gn:dem":461,
    "gn:feature_class":"P",
    "gn:feature_code":"PPL",
    "gn:name":"Sho\u2018rqishloq",
    "gn:population":0,
    "gn:timezone":"Asia/Tashkent",
    "iso:country":"UZ",
    "name:uzb_x_preferred":[
        "Sho\u2018rqishloq"
    ],
    "wof:name":"Sho`rqishloq",
    "wof:placetype":"locality"
},
  "geometry": {"coordinates":[72.1773,40.73496],"type":"Point"}
}