{
  "type": "Feature",
  "properties": {
    "gn:admin1_code":"01",
    "gn:asciiname":"Haqiqat",
    "gn:country_code":"UZ",
    "gn:dem":704,
    "gn:feature_class":"P",
    "gn:feature_code":"PPL",
    "gn:name":"Haqiqat",
    "gn:population":0,
    "gn:timezone":"Asia/Tashkent",
    "iso:country":"UZ",
    "name:uzb_x_preferred":[
        "Haqiqat"
    ],
    "wof:name":"Haqiqat",
    "wof:placetype":"locality"
},
  "geometry": {"coordinates":[72.67273,40.70786],"type":"Point"}
}