{
  "type": "Feature",
  "properties": {
    "gn:admin1_code":"08",
    "gn:asciiname":"Olmazor",
    "gn:country_code":"UZ",
    "gn:dem":468,
    "gn:feature_class":"P",
    "gn:feature_code":"PPL",
    "gn:name":"Olmazor",
    "gn:population":0,
    "gn:timezone":"Asia/Samarkand",
    "iso:country":"UZ",
    "name:und_x_variant":[
        "Ul\u2019mas"
    ],
    "wof:name":"Olmazor",
    "wof:placetype":"locality"
},
  "geometry": {"coordinates":[66.34191,38.83429],"type":"Point"}
}