{
  "type": "Feature",
  "properties": {
    "gn:admin1_code":"01",
    "gn:asciiname":"Gulistan",
    "gn:country_code":"UZ",
    "gn:dem":573,
    "gn:feature_class":"P",
    "gn:feature_code":"PPL",
    "gn:name":"Gulistan",
    "gn:population":0,
    "gn:timezone":"Asia/Tashkent",
    "iso:country":"UZ",
    "name:ara_x_preferred":[
        "\u0643\u0644\u0633\u062a\u0627\u0646"
    ],
    "name:cat_x_preferred":[
        "Gulistan"
    ],
    "name:ceb_x_preferred":[
        "Gulistan"
    ],
    "name:epo_x_preferred":[
        "Golestano"
    ],
    "name:fas_x_preferred":[
        "\u06af\u0644\u0633\u062a\u0627\u0646"
    ],
    "name:ita_x_preferred":[
        "Gulistan"
    ],
    "name:jpn_x_preferred":[
        "\u30b4\u30ec\u30b9\u30bf\u30fc\u30f3"
    ],
    "name:mzn_x_preferred":[
        "\u06af\u0644\u0633\u062a\u0627\u0646"
    ],
    "name:pol_x_preferred":[
        "Gulistan"
    ],
    "name:rus_x_preferred":[
        "\u0413\u0443\u043b\u0438\u0441\u0442\u0430\u043d"
    ],
    "name:swe_x_preferred":[
        "Gulistan"
    ],
    "name:tur_x_preferred":[
        "G\u00fclistan"
    ],
    "name:ukr_x_preferred":[
        "\u0490\u0443\u043b\u0456\u0441\u0442\u0430\u043d"
    ],
    "wof:name":"Gulistan",
    "wof:placetype":"locality"
},
  "geometry": {"coordinates":[72.46519000000001,40.75948],"type":"Point"}
}