{
  "type": "Feature",
  "properties": {
    "gn:admin1_code":"01",
    "gn:asciiname":"Gulistan",
    "gn:country_code":"UZ",
    "gn:dem":573,
    "gn:feature_class":"P",
    "gn:feature_code":"PPL",
    "gn:name":"Gulistan",
    "gn:population":0,
    "gn:timezone":"Asia/Tashkent",
    "iso:country":"UZ",
    "name:rus_x_preferred":[
        "\u0413\u0443\u043b\u0438\u0441\u0442\u0430\u043d"
    ],
    "wof:name":"Gulistan",
    "wof:placetype":"locality"
},
  "geometry": {"coordinates":[72.46519000000001,40.75948],"type":"Point"}
}