{
  "type": "Feature",
  "properties": {
    "gn:admin1_code":"09",
    "gn:asciiname":"Janajap",
    "gn:country_code":"UZ",
    "gn:dem":74,
    "gn:feature_class":"P",
    "gn:feature_code":"PPL",
    "gn:name":"Janajap",
    "gn:population":0,
    "gn:timezone":"Asia/Samarkand",
    "iso:country":"UZ",
    "wof:name":"Janajap",
    "wof:placetype":"locality"
},
  "geometry": {"coordinates":[59.43135,42.33539],"type":"Point"}
}