{
  "type": "Feature",
  "properties": {
    "gn:admin1_code":"01",
    "gn:asciiname":"Shamuradov",
    "gn:country_code":"UZ",
    "gn:dem":424,
    "gn:feature_class":"P",
    "gn:feature_code":"PPL",
    "gn:name":"Shamuradov",
    "gn:population":0,
    "gn:timezone":"Asia/Tashkent",
    "iso:country":"UZ",
    "name:uzb_x_preferred":[
        "Shamuradov"
    ],
    "wof:name":"Shamuradov",
    "wof:placetype":"locality"
},
  "geometry": {"coordinates":[71.88961,40.74362],"type":"Point"}
}