{
  "type": "Feature",
  "properties": {
    "gn:admin1_code":"06",
    "gn:asciiname":"Qoraqo`rg`on",
    "gn:country_code":"UZ",
    "gn:dem":1025,
    "gn:feature_class":"P",
    "gn:feature_code":"PPL",
    "gn:name":"Qoraqo\u2018rg\u2018on",
    "gn:population":0,
    "gn:timezone":"Asia/Tashkent",
    "iso:country":"UZ",
    "name:eng_x_preferred":[
        "Qoraqo\u2018rg\u2018on"
    ],
    "wof:name":"Qoraqo`rg`on",
    "wof:placetype":"locality"
},
  "geometry": {"coordinates":[71.23846999999998,41.17117],"type":"Point"}
}