{
  "type": "Feature",
  "properties": {
    "gn:admin1_code":"01",
    "gn:asciiname":"Guliston",
    "gn:country_code":"UZ",
    "gn:dem":417,
    "gn:feature_class":"P",
    "gn:feature_code":"PPL",
    "gn:name":"Guliston",
    "gn:population":0,
    "gn:timezone":"Asia/Tashkent",
    "iso:country":"UZ",
    "name:eng_x_preferred":[
        "Guliston"
    ],
    "name:und_x_variant":[
        "Gulistan"
    ],
    "wof:name":"Guliston",
    "wof:placetype":"locality"
},
  "geometry": {"coordinates":[71.87034,40.91042],"type":"Point"}
}