{
  "type": "Feature",
  "properties": {
    "gn:admin1_code":"06",
    "gn:asciiname":"Sherbuloq",
    "gn:country_code":"UZ",
    "gn:dem":544,
    "gn:feature_class":"P",
    "gn:feature_code":"PPL",
    "gn:name":"Sherbuloq",
    "gn:population":0,
    "gn:timezone":"Asia/Tashkent",
    "iso:country":"UZ",
    "name:uzb_x_preferred":[
        "Sherbuloq"
    ],
    "wof:name":"Sherbuloq",
    "wof:placetype":"locality"
},
  "geometry": {"coordinates":[71.70039,41.05697],"type":"Point"}
}