{
  "type": "Feature",
  "properties": {
    "gn:admin1_code":"03",
    "gn:asciiname":"Qo`rg`oncha",
    "gn:country_code":"UZ",
    "gn:dem":475,
    "gn:feature_class":"P",
    "gn:feature_code":"PPL",
    "gn:name":"Qo\u2018rg\u2018oncha",
    "gn:population":0,
    "gn:timezone":"Asia/Tashkent",
    "iso:country":"UZ",
    "name:uzb_x_preferred":[
        "Qo\u2018rg\u2018oncha"
    ],
    "wof:name":"Qo`rg`oncha",
    "wof:placetype":"locality"
},
  "geometry": {"coordinates":[71.74214000000001,40.50165],"type":"Point"}
}