{
  "type": "Feature",
  "properties": {
    "gn:admin1_code":"08",
    "gn:asciiname":"Kara-Tepe",
    "gn:country_code":"UZ",
    "gn:dem":1896,
    "gn:feature_class":"P",
    "gn:feature_code":"PPL",
    "gn:name":"Kara-Tepe",
    "gn:population":0,
    "gn:timezone":"Asia/Samarkand",
    "iso:country":"UZ",
    "wof:name":"Kara-Tepe",
    "wof:placetype":"locality"
},
  "geometry": {"coordinates":[66.91667,38.53333],"type":"Point"}
}