{
  "type": "Feature",
  "properties": {
    "gn:admin1_code":"00",
    "gn:asciiname":"Sulyukurgan",
    "gn:country_code":"UZ",
    "gn:dem":390,
    "gn:feature_class":"P",
    "gn:feature_code":"PPL",
    "gn:name":"Sulyukurgan",
    "gn:population":0,
    "gn:timezone":"Asia/Samarkand",
    "iso:country":"UZ",
    "wof:name":"Sulyukurgan",
    "wof:placetype":"locality"
},
  "geometry": {"coordinates":[65.65000000000001,40.08333],"type":"Point"}
}