{
  "type": "Feature",
  "properties": {
    "gn:admin1_code":"01",
    "gn:asciiname":"Xonbogi",
    "gn:country_code":"UZ",
    "gn:dem":455,
    "gn:feature_class":"P",
    "gn:feature_code":"PPL",
    "gn:name":"Xonbogi",
    "gn:population":0,
    "gn:timezone":"Asia/Tashkent",
    "iso:country":"UZ",
    "name:rus_x_preferred":[
        "\u0425\u0430\u043d\u0431\u0430\u0433\u0438"
    ],
    "name:und_x_variant":[
        "Khanbagi"
    ],
    "name:uzb_x_preferred":[
        "Xonbogi"
    ],
    "name:uzb_x_variant":[
        "Hindibogi"
    ],
    "wof:name":"Xonbogi",
    "wof:placetype":"locality"
},
  "geometry": {"coordinates":[72.21946,40.7686],"type":"Point"}
}