{
  "type": "Feature",
  "properties": {
    "gn:admin1_code":"01",
    "gn:asciiname":"Olchalik",
    "gn:country_code":"UZ",
    "gn:dem":1029,
    "gn:feature_class":"P",
    "gn:feature_code":"PPL",
    "gn:name":"Olchalik",
    "gn:population":0,
    "gn:timezone":"Asia/Tashkent",
    "iso:country":"UZ",
    "name:rus_x_preferred":[
        "\u0410\u043b\u043c\u0430\u043b\u044b\u043a"
    ],
    "name:und_x_variant":[
        "Almalyk"
    ],
    "name:uzb_x_preferred":[
        "Olchalik"
    ],
    "wof:name":"Olchalik",
    "wof:placetype":"locality"
},
  "geometry": {"coordinates":[73.08088000000002,40.81097000000001],"type":"Point"}
}