{
  "type": "Feature",
  "properties": {
    "gn:admin1_code":"00",
    "gn:asciiname":"Davry-Kurgan",
    "gn:country_code":"UZ",
    "gn:dem":929,
    "gn:feature_class":"P",
    "gn:feature_code":"PPL",
    "gn:name":"Davry-Kurgan",
    "gn:population":0,
    "gn:timezone":"Asia/Samarkand",
    "iso:country":"UZ",
    "wof:name":"Davry-Kurgan",
    "wof:placetype":"locality"
},
  "geometry": {"coordinates":[66.51666999999999,40.35],"type":"Point"}
}