{
  "type": "Feature",
  "properties": {
    "gn:admin1_code":"01",
    "gn:asciiname":"Ko`tarma",
    "gn:country_code":"UZ",
    "gn:dem":645,
    "gn:feature_class":"P",
    "gn:feature_code":"PPL",
    "gn:name":"Ko\u2018tarma",
    "gn:population":0,
    "gn:timezone":"Asia/Tashkent",
    "iso:country":"UZ",
    "name:rus_x_preferred":[
        "\u041a\u0443\u0442\u0430\u0440\u043c\u0430"
    ],
    "name:und_x_variant":[
        "Kutarma"
    ],
    "name:uzb_x_preferred":[
        "Ko\u2018tarma"
    ],
    "wof:name":"Ko`tarma",
    "wof:placetype":"locality"
},
  "geometry": {"coordinates":[72.54434999999999,40.69357],"type":"Point"}
}