{
  "type": "Feature",
  "properties": {
    "gn:admin1_code":"09",
    "gn:asciiname":"Oqterak",
    "gn:country_code":"UZ",
    "gn:dem":73,
    "gn:feature_class":"P",
    "gn:feature_code":"PPL",
    "gn:name":"Oqterak",
    "gn:population":0,
    "gn:timezone":"Asia/Samarkand",
    "iso:country":"UZ",
    "name:und_x_variant":[
        "Nurtambay"
    ],
    "wof:name":"Oqterak",
    "wof:placetype":"locality"
},
  "geometry": {"coordinates":[59.40715,42.58419],"type":"Point"}
}