{
  "type": "Feature",
  "properties": {
    "gn:admin1_code":"03",
    "gn:asciiname":"Dasht",
    "gn:country_code":"UZ",
    "gn:dem":432,
    "gn:feature_class":"P",
    "gn:feature_code":"PPL",
    "gn:name":"Dasht",
    "gn:population":0,
    "gn:timezone":"Asia/Tashkent",
    "iso:country":"UZ",
    "name:uzb_x_preferred":[
        "Dasht"
    ],
    "wof:name":"Dasht",
    "wof:placetype":"locality"
},
  "geometry": {"coordinates":[70.65564000000001,40.33529],"type":"Point"}
}