{
  "type": "Feature",
  "properties": {
    "gn:admin1_code":"01",
    "gn:asciiname":"Terakzor",
    "gn:country_code":"UZ",
    "gn:dem":411,
    "gn:feature_class":"P",
    "gn:feature_code":"PPL",
    "gn:name":"Terakzor",
    "gn:population":0,
    "gn:timezone":"Asia/Tashkent",
    "iso:country":"UZ",
    "name:uzb_x_preferred":[
        "Terakzor"
    ],
    "wof:name":"Terakzor",
    "wof:placetype":"locality"
},
  "geometry": {"coordinates":[71.69824,40.84482],"type":"Point"}
}