{
  "type": "Feature",
  "properties": {
    "gn:admin1_code":"06",
    "gn:asciiname":"Obodon",
    "gn:country_code":"UZ",
    "gn:dem":850,
    "gn:feature_class":"P",
    "gn:feature_code":"PPL",
    "gn:name":"Obodon",
    "gn:population":0,
    "gn:timezone":"Asia/Bishkek",
    "iso:country":"UZ",
    "name:eng_x_preferred":[
        "Obodon"
    ],
    "wof:name":"Obodon",
    "wof:placetype":"locality"
},
  "geometry": {"coordinates":[71.45350999999999,41.1979],"type":"Point"}
}