{
  "type": "Feature",
  "properties": {
    "gn:admin1_code":"12",
    "gn:asciiname":"Xo`jakulusun",
    "gn:country_code":"UZ",
    "gn:dem":1231,
    "gn:feature_class":"P",
    "gn:feature_code":"PPL",
    "gn:name":"Xo\u2018jakulusun",
    "gn:population":0,
    "gn:timezone":"Asia/Samarkand",
    "iso:country":"UZ",
    "name:und_x_variant":[
        "Khodzhakulusun"
    ],
    "name:uzb_x_preferred":[
        "Xo\u2018jakulusun"
    ],
    "wof:name":"Xo`jakulusun",
    "wof:placetype":"locality"
},
  "geometry": {"coordinates":[68.34139,38.22917],"type":"Point"}
}