{
  "type": "Feature",
  "properties": {
    "gn:admin1_code":"00",
    "gn:asciiname":"Kairma",
    "gn:country_code":"UZ",
    "gn:dem":637,
    "gn:feature_class":"P",
    "gn:feature_code":"PPL",
    "gn:name":"Kairma",
    "gn:population":0,
    "gn:timezone":"Asia/Samarkand",
    "iso:country":"UZ",
    "wof:name":"Kairma",
    "wof:placetype":"locality"
},
  "geometry": {"coordinates":[68.40000000000001,39.96667],"type":"Point"}
}