{
  "type": "Feature",
  "properties": {
    "gn:admin1_code":"01",
    "gn:asciiname":"Tashkechik",
    "gn:country_code":"UZ",
    "gn:dem":479,
    "gn:feature_class":"P",
    "gn:feature_code":"PPL",
    "gn:name":"Tashkechik",
    "gn:population":0,
    "gn:timezone":"Asia/Tashkent",
    "iso:country":"UZ",
    "name:uzb_x_preferred":[
        "Tashkechik"
    ],
    "wof:name":"Tashkechik",
    "wof:placetype":"locality"
},
  "geometry": {"coordinates":[72.37333000000002,40.91352],"type":"Point"}
}