{
  "type": "Feature",
  "properties": {
    "gn:admin1_code":"12",
    "gn:asciiname":"Ishan",
    "gn:country_code":"UZ",
    "gn:dem":528,
    "gn:feature_class":"P",
    "gn:feature_code":"PPL",
    "gn:name":"Ishan",
    "gn:population":0,
    "gn:timezone":"Asia/Samarkand",
    "iso:country":"UZ",
    "wof:name":"Ishan",
    "wof:placetype":"locality"
},
  "geometry": {"coordinates":[67.928,38.30555],"type":"Point"}
}