{
  "type": "Feature",
  "properties": {
    "gn:admin1_code":"14",
    "gn:asciiname":"Konka",
    "gn:country_code":"UZ",
    "gn:dem":292,
    "gn:feature_class":"P",
    "gn:feature_code":"PPL",
    "gn:name":"Konka",
    "gn:population":0,
    "gn:timezone":"Asia/Tashkent",
    "iso:country":"UZ",
    "name:ceb_x_preferred":[
        "Konka"
    ],
    "name:swe_x_preferred":[
        "Konka"
    ],
    "name:urd_x_preferred":[
        "\u06a9\u0631\u06cc\u06af \u062f\u0631\u06cc\u0627"
    ],
    "name:uzb_x_preferred":[
        "Konka"
    ],
    "wof:name":"Konka",
    "wof:placetype":"locality"
},
  "geometry": {"coordinates":[68.97275999999999,40.80749],"type":"Point"}
}