{
  "type": "Feature",
  "properties": {
    "gn:admin1_code":"00",
    "gn:asciiname":"Mitan",
    "gn:country_code":"UZ",
    "gn:dem":106,
    "gn:feature_class":"P",
    "gn:feature_code":"PPL",
    "gn:name":"Mitan",
    "gn:population":0,
    "gn:timezone":"Asia/Samarkand",
    "iso:country":"UZ",
    "wof:name":"Mitan",
    "wof:placetype":"locality"
},
  "geometry": {"coordinates":[60.93333000000001,41.35],"type":"Point"}
}