{
  "type": "Feature",
  "properties": {
    "gn:admin1_code":"07",
    "gn:asciiname":"Manamdzhan",
    "gn:country_code":"UZ",
    "gn:dem":133,
    "gn:feature_class":"P",
    "gn:feature_code":"PPL",
    "gn:name":"Manamdzhan",
    "gn:population":0,
    "gn:timezone":"Asia/Samarkand",
    "iso:country":"UZ",
    "wof:name":"Manamdzhan",
    "wof:placetype":"locality"
},
  "geometry": {"coordinates":[64.71666999999999,41.11667],"type":"Point"}
}