{
  "type": "Feature",
  "properties": {
    "gn:admin1_code":"08",
    "gn:asciiname":"Supa",
    "gn:country_code":"UZ",
    "gn:dem":1787,
    "gn:feature_class":"P",
    "gn:feature_code":"PPL",
    "gn:name":"Supa",
    "gn:population":0,
    "gn:timezone":"Asia/Samarkand",
    "iso:country":"UZ",
    "name:ceb_x_preferred":[
        "Supa"
    ],
    "name:swe_x_preferred":[
        "Supa"
    ],
    "wof:name":"Supa",
    "wof:placetype":"locality"
},
  "geometry": {"coordinates":[67.07333,38.64139],"type":"Point"}
}