{
  "type": "Feature",
  "properties": {
    "gn:admin1_code":"00",
    "gn:asciiname":"Nauruz-Tepe",
    "gn:country_code":"UZ",
    "gn:dem":716,
    "gn:feature_class":"P",
    "gn:feature_code":"PPL",
    "gn:name":"Nauruz-Tepe",
    "gn:population":0,
    "gn:timezone":"Asia/Samarkand",
    "iso:country":"UZ",
    "wof:name":"Nauruz-Tepe",
    "wof:placetype":"locality"
},
  "geometry": {"coordinates":[67.13333,39.83333],"type":"Point"}
}