{
  "type": "Feature",
  "properties": {
    "gn:admin1_code":"01",
    "gn:asciiname":"Olaqanot",
    "gn:country_code":"UZ",
    "gn:dem":487,
    "gn:feature_class":"P",
    "gn:feature_code":"PPL",
    "gn:name":"Olaqanot",
    "gn:population":0,
    "gn:timezone":"Asia/Tashkent",
    "iso:country":"UZ",
    "name:rus_x_preferred":[
        "\u0410\u043b\u0430\u043a\u0430\u043d\u0430\u0442"
    ],
    "name:und_x_variant":[
        "Alakanat"
    ],
    "name:uzb_x_preferred":[
        "Olaqanot"
    ],
    "wof:name":"Olaqanot",
    "wof:placetype":"locality"
},
  "geometry": {"coordinates":[72.25021,40.67987],"type":"Point"}
}