{
  "type": "Feature",
  "properties": {
    "gn:admin1_code":"03",
    "gn:asciiname":"Chamanzor",
    "gn:country_code":"UZ",
    "gn:dem":367,
    "gn:feature_class":"P",
    "gn:feature_code":"PPL",
    "gn:name":"Chamanzor",
    "gn:population":0,
    "gn:timezone":"Asia/Tashkent",
    "iso:country":"UZ",
    "name:uzb_x_preferred":[
        "Chamanzor"
    ],
    "wof:name":"Chamanzor",
    "wof:placetype":"locality"
},
  "geometry": {"coordinates":[70.74538000000003,40.62758],"type":"Point"}
}