{
  "type": "Feature",
  "properties": {
    "gn:admin1_code":"15",
    "gn:asciiname":"G`allaorol",
    "gn:country_code":"UZ",
    "gn:dem":572,
    "gn:feature_class":"P",
    "gn:feature_code":"PPL",
    "gn:name":"G\u2018allaorol",
    "gn:population":0,
    "gn:timezone":"Asia/Samarkand",
    "iso:country":"UZ",
    "name:und_x_variant":[
        "Gallyaaral",
        "Gallia-Aral",
        "Ghallaorol",
        "G\u2018allaorol"
    ],
    "wof:name":"G`allaorol",
    "wof:placetype":"locality"
},
  "geometry": {"coordinates":[67.5975,40.02139],"type":"Point"}
}