{
  "type": "Feature",
  "properties": {
    "gn:admin1_code":"02",
    "gn:asciiname":"Miyonsaroy",
    "gn:cc2":"UZ",
    "gn:country_code":"UZ",
    "gn:dem":224,
    "gn:feature_class":"P",
    "gn:feature_code":"PPL",
    "gn:name":"Miyonsaroy",
    "gn:population":0,
    "gn:timezone":"Asia/Samarkand",
    "iso:country":"UZ",
    "name:und_x_variant":[
        "Mian-Saray",
        "Miyansaraj",
        "Miyonsaroy"
    ],
    "wof:name":"Miyonsaroy",
    "wof:placetype":"locality"
},
  "geometry": {"coordinates":[64.23555999999999,39.91917],"type":"Point"}
}