{
  "type": "Feature",
  "properties": {
    "gn:admin1_code":"06",
    "gn:asciiname":"Katta-Toshloq",
    "gn:country_code":"UZ",
    "gn:dem":414,
    "gn:feature_class":"P",
    "gn:feature_code":"PPL",
    "gn:name":"Katta-Toshloq",
    "gn:population":0,
    "gn:timezone":"Asia/Tashkent",
    "iso:country":"UZ",
    "name:eng_x_preferred":[
        "Katta-Toshloq"
    ],
    "wof:name":"Katta-Toshloq",
    "wof:placetype":"locality"
},
  "geometry": {"coordinates":[71.80145999999998,40.94792],"type":"Point"}
}