{
  "type": "Feature",
  "properties": {
    "gn:admin1_code":"12",
    "gn:asciiname":"Surnaytepa",
    "gn:country_code":"UZ",
    "gn:dem":494,
    "gn:feature_class":"P",
    "gn:feature_code":"PPL",
    "gn:name":"Surnaytepa",
    "gn:population":0,
    "gn:timezone":"Asia/Samarkand",
    "iso:country":"UZ",
    "name:uzb_x_preferred":[
        "Surnaytepa"
    ],
    "wof:name":"Surnaytepa",
    "wof:placetype":"locality"
},
  "geometry": {"coordinates":[67.94268000000001,38.21517],"type":"Point"}
}