{
  "type": "Feature",
  "properties": {
    "gn:admin1_code":"03",
    "gn:asciiname":"Hoshimdasht",
    "gn:country_code":"UZ",
    "gn:dem":469,
    "gn:feature_class":"P",
    "gn:feature_code":"PPL",
    "gn:name":"Hoshimdasht",
    "gn:population":0,
    "gn:timezone":"Asia/Tashkent",
    "iso:country":"UZ",
    "name:und_x_variant":[
        "Khashimdasht"
    ],
    "name:uzb_x_preferred":[
        "Hoshimdasht"
    ],
    "wof:name":"Hoshimdasht",
    "wof:placetype":"locality"
},
  "geometry": {"coordinates":[71.06323,40.46816],"type":"Point"}
}