{
  "type": "Feature",
  "properties": {
    "gn:admin1_code":"00",
    "gn:asciiname":"Kiyovsu",
    "gn:country_code":"UZ",
    "gn:dem":1536,
    "gn:feature_class":"P",
    "gn:feature_code":"PPL",
    "gn:name":"Kiyovsu",
    "gn:population":0,
    "gn:timezone":"Asia/Samarkand",
    "iso:country":"UZ",
    "name:und_x_variant":[
        "Kiyau-Su"
    ],
    "name:uzb_x_preferred":[
        "Kiyovsu"
    ],
    "wof:name":"Kiyovsu",
    "wof:placetype":"locality"
},
  "geometry": {"coordinates":[67.65389,38.3591],"type":"Point"}
}