{
  "type": "Feature",
  "properties": {
    "gn:admin1_code":"12",
    "gn:asciiname":"Gagarin",
    "gn:country_code":"UZ",
    "gn:dem":294,
    "gn:feature_class":"P",
    "gn:feature_code":"PPL",
    "gn:name":"Gagarin",
    "gn:population":0,
    "gn:timezone":"Asia/Samarkand",
    "iso:country":"UZ",
    "name:und_x_variant":[
        "Gagarino"
    ],
    "name:uzb_x_preferred":[
        "Gagarin"
    ],
    "wof:name":"Gagarin",
    "wof:placetype":"locality"
},
  "geometry": {"coordinates":[66.98889,37.41917],"type":"Point"}
}