{
  "type": "Feature",
  "properties": {
    "gn:admin1_code":"14",
    "gn:asciiname":"Qirsadoq",
    "gn:country_code":"UZ",
    "gn:dem":321,
    "gn:feature_class":"P",
    "gn:feature_code":"PPL",
    "gn:name":"Qirsadoq",
    "gn:population":0,
    "gn:timezone":"Asia/Tashkent",
    "iso:country":"UZ",
    "name:uzb_x_preferred":[
        "Qirsadoq"
    ],
    "wof:name":"Qirsadoq",
    "wof:placetype":"locality"
},
  "geometry": {"coordinates":[69.13705999999999,40.96685],"type":"Point"}
}