{
  "type": "Feature",
  "properties": {
    "gn:admin1_code":"08",
    "gn:asciiname":"Chim",
    "gn:country_code":"UZ",
    "gn:dem":454,
    "gn:feature_class":"P",
    "gn:feature_code":"PPL",
    "gn:name":"Chim",
    "gn:population":0,
    "gn:timezone":"Asia/Samarkand",
    "iso:country":"UZ",
    "name:ceb_x_preferred":[
        "Chim"
    ],
    "name:deu_x_preferred":[
        "Chim"
    ],
    "name:swe_x_preferred":[
        "Chim"
    ],
    "wof:name":"Chim",
    "wof:placetype":"locality"
},
  "geometry": {"coordinates":[66.25753,38.85753],"type":"Point"}
}