{
  "type": "Feature",
  "properties": {
    "gn:admin1_code":"03",
    "gn:asciiname":"Qorakuyli",
    "gn:country_code":"UZ",
    "gn:dem":394,
    "gn:feature_class":"P",
    "gn:feature_code":"PPL",
    "gn:name":"Qorakuyli",
    "gn:population":0,
    "gn:timezone":"Asia/Tashkent",
    "iso:country":"UZ",
    "name:uzb_x_preferred":[
        "Qorakuyli"
    ],
    "wof:name":"Qorakuyli",
    "wof:placetype":"locality"
},
  "geometry": {"coordinates":[70.54415999999998,40.41419000000001],"type":"Point"}
}