{
  "type": "Feature",
  "properties": {
    "gn:admin1_code":"01",
    "gn:asciiname":"Tait",
    "gn:country_code":"UZ",
    "gn:dem":451,
    "gn:feature_class":"P",
    "gn:feature_code":"PPL",
    "gn:name":"Tait",
    "gn:population":0,
    "gn:timezone":"Asia/Tashkent",
    "iso:country":"UZ",
    "name:deu_x_preferred":[
        "Tait"
    ],
    "name:fra_x_preferred":[
        "Tait"
    ],
    "name:jpn_x_preferred":[
        "\u30c6\u30a4\u30c8"
    ],
    "name:pol_x_preferred":[
        "Tait"
    ],
    "name:rus_x_preferred":[
        "\u0422\u0430\u0438\u0442"
    ],
    "name:spa_x_preferred":[
        "Tait"
    ],
    "name:swe_x_preferred":[
        "Tait"
    ],
    "name:uzb_x_preferred":[
        "Tait"
    ],
    "wof:name":"Tait",
    "wof:placetype":"locality"
},
  "geometry": {"coordinates":[72.02542,40.63832],"type":"Point"}
}